Workbook

Sheet 地域区分
D1: 売上単価 (支払単価） 【≒粗利】 | E1: 4月 | F1: 5月 | G1: 6月 | H1: 7月 | I1: 8月 | J1: 9月 | K1: 10月 | L1: 11月 | M1: 12月 | N1: 1月 | O1: 2月 | P1: 3月 | Q1: 合計
A2: UAL 総計 | D2: 売上 | E2: =E5+E8 -> 56058811 | F2: =F5+F8 -> 55056008 | G2: =G5+G8 -> 56149143 | H2: =H5+H8 -> 58799277 | I2: =I5+I8 -> 55632341 | J2: =J5+J8 -> 57287363 | K2: =K5+K8 -> 61911924 | L2: =L5+L8 -> 55318343 | ... Q2: =Q5+Q8 -> 6.913759e+08
D3: 仕入 | E3: =E6+E9 -> 45001579 | F3: =F6+F9 -> 44303397 | G3: =G6+G9 -> 45633632 | H3: =H6+H9 -> 46036102 | I3: =I6+I9 -> 45651219 | J3: =J6+J9 -> 46511418 | K3: =K6+K9 -> 47468200 | L3: =L6+L9 -> 45353471 | ... Q3: =Q6+Q9 -> 5.5377074e+08
D4: 粗利 | E4: =E2-E3 -> 11057232 | F4: =F2-F3 -> 10752611 | G4: =G2-G3 -> 10515511 | H4: =H2-H3 -> 12763175 | I4: =I2-I3 -> 9981122 | J4: =J2-J3 -> 10775945 | K4: =K2-K3 -> 14443724 | L4: =L2-L3 -> 9964871.8 | ... Q4: =Q2-Q3 -> 1.3760516e+08
A5: 首都圏 | D5: 売上 | E5: =まとめ!E61 -> 45780631 | F5: =まとめ!F61 -> 45006457 | G5: =まとめ!G61 -> 46132538 | H5: =まとめ!H61 -> 47813057 | I5: =まとめ!I61 -> 45095786 | J5: =まとめ!J61 -> 45964337 | K5: =まとめ!K61 -> 48641845 | L5: =まとめ!L61 -> 44714137 | ... P5: =まとめ!P61 -> 47818949 | Q5: =SUM(E5:P5) -> 5.5698764e+08
D6: 仕入 | E6: =まとめ!E62 -> 36598064 | F6: =まとめ!F62 -> 36175956 | G6: =まとめ!G62 -> 37289937 | H6: =まとめ!H62 -> 37229902 | I6: =まとめ!I62 -> 36754194 | J6: =まとめ!J62 -> 36999218 | K6: =まとめ!K62 -> 38087958 | L6: =まとめ!L62 -> 36819954 | ... P6: =まとめ!P62 -> 37961867 | Q6: =SUM(E6:P6) -> 4.4666338e+08
D7: 粗利 | E7: =E5-E6 -> 9182566.8 | F7: =F5-F6 -> 8830501 | G7: =G5-G6 -> 8842601 | H7: =H5-H6 -> 10583155 | I7: =I5-I6 -> 8341592 | J7: =J5-J6 -> 8965119.2 | K7: =K5-K6 -> 10553887 | L7: =L5-L6 -> 7894182.8 | ... P7: =P5-P6 -> 9857082 | Q7: =SUM(E7:P7) -> 1.1032426e+08
A8: 地方 | D8: 売上 | E8: =まとめ!E64 -> 10278180 | F8: =まとめ!F64 -> 10049551 | G8: =まとめ!G64 -> 10016605 | H8: =まとめ!H64 -> 10986220 | I8: =まとめ!I64 -> 10536555 | J8: =まとめ!J64 -> 11323026 | K8: =まとめ!K64 -> 13270079 | L8: =まとめ!L64 -> 10604206 | ... P8: =まとめ!P64 -> 12429324 | Q8: =SUM(E8:P8) -> 1.3438826e+08
D9: 仕入 | E9: =まとめ!E65 -> 8403515 | F9: =まとめ!F65 -> 8127441 | G9: =まとめ!G65 -> 8343695 | H9: =まとめ!H65 -> 8806200 | I9: =まとめ!I65 -> 8897025 | J9: =まとめ!J65 -> 9512200 | K9: =まとめ!K65 -> 9380242 | L9: =まとめ!L65 -> 8533517 | ... P9: =まとめ!P65 -> 9645872.9 | Q9: =SUM(E9:P9) -> 1.0710736e+08
D10: 粗利 | E10: =E8-E9 -> 1874665 | F10: =F8-F9 -> 1922110 | G10: =G8-G9 -> 1672910 | H10: =H8-H9 -> 2180020 | I10: =I8-I9 -> 1639530 | J10: =J8-J9 -> 1810826 | K10: =K8-K9 -> 3889837 | L10: =L8-L9 -> 2070689 | ... P10: =P8-P9 -> 2783450.9 | Q10: =SUM(E10:P10) -> 27280903
D11: 売上 | E11: =E2 -> 56058811 | F11: =F2 -> 55056008 | G11: =G2 -> 56149143 | H11: =H2 -> 58799277 | I11: =I2 -> 55632341 | J11: =J2 -> 57287363 | K11: =K2 -> 61911924 | L11: =L2 -> 55318343 | ... Q11: =Q2 -> 6.913759e+08
D12: 仕入 | E12: =E3 -> 45001579 | F12: =F3 -> 44303397 | G12: =G3 -> 45633632 | H12: =H3 -> 46036102 | I12: =I3 -> 45651219 | J12: =J3 -> 46511418 | K12: =K3 -> 47468200 | L12: =L3 -> 45353471 | ... Q12: =Q3 -> 5.5377074e+08
D13: 粗利 | E13: =E4 -> 11057232 | F13: =F4 -> 10752611 | G13: =G4 -> 10515511 | H13: =H4 -> 12763175 | I13: =I4 -> 9981122 | J13: =J4 -> 10775945 | K13: =K4 -> 14443724 | L13: =L4 -> 9964871.8 | ... Q13: =Q4 -> 1.3760516e+08
D14: Q売上 | E14: =SUM(E11:G11) -> 167263962 | H14: =SUM(H11:J11) -> 171718981 | K14: =SUM(K11:M11) -> 175875073 | N14: =SUM(N11:P11) -> 1.7651789e+08 | Q14: =SUM(E14:P14) -> 6.913759e+08
D15: Q仕入 | E15: =SUM(E12:G12) -> 1.3493861e+08 | H15: =SUM(H12:J12) -> 1.3819874e+08 | K15: =SUM(K12:M12) -> 1.3969585e+08 | N15: =SUM(N12:P12) -> 1.4093755e+08 | Q15: =SUM(E15:P15) -> 5.5377074e+08
D16: Q粗利 | E16: =SUM(E13:G13) -> 32325354 | H16: =SUM(H13:J13) -> 33520242 | K16: =SUM(K13:M13) -> 36179226 | N16: =SUM(N13:P13) -> 35580336 | Q16: =SUM(E16:P16) -> 1.3760516e+08

Sheet 地域区分 (2)
D1: 売上単価 (支払単価） 【≒粗利】 | E1: 4月 | F1: 5月 | G1: 6月 | H1: 7月 | I1: 8月 | J1: 9月 | K1: 10月 | L1: 11月 | M1: 12月 | N1: 1月 | O1: 2月 | P1: 3月 | Q1: 合計
A2: UAL 総計 | D2: 売上 | E2: =E5+E8 -> 56058811 | F2: =F5+F8 -> 55056008 | G2: =G5+G8 -> 56149143 | H2: =H5+H8 -> 58799277 | I2: =I5+I8 -> 55632341 | J2: =J5+J8 -> 57287363 | K2: =K5+K8 -> 61911924 | L2: =L5+L8 -> 55318343 | ... Q2: =Q5+Q8 -> 6.913759e+08
D3: 仕入 | E3: =E6+E9 -> 45001579 | F3: =F6+F9 -> 44303397 | G3: =G6+G9 -> 45633632 | H3: =H6+H9 -> 46036102 | I3: =I6+I9 -> 45651219 | J3: =J6+J9 -> 46511418 | K3: =K6+K9 -> 47468200 | L3: =L6+L9 -> 45353471 | ... Q3: =Q6+Q9 -> 5.5377074e+08
D4: 粗利 | E4: =E2-E3 -> 11057232 | F4: =F2-F3 -> 10752611 | G4: =G2-G3 -> 10515511 | H4: =H2-H3 -> 12763175 | I4: =I2-I3 -> 9981122 | J4: =J2-J3 -> 10775945 | K4: =K2-K3 -> 14443724 | L4: =L2-L3 -> 9964871.8 | ... Q4: =Q2-Q3 -> 1.3760516e+08
A5: 首都圏 | D5: 売上 | E5: =まとめ!E61 -> 45780631 | F5: =まとめ!F61 -> 45006457 | G5: =まとめ!G61 -> 46132538 | H5: =まとめ!H61 -> 47813057 | I5: =まとめ!I61 -> 45095786 | J5: =まとめ!J61 -> 45964337 | K5: =まとめ!K61 -> 48641845 | L5: =まとめ!L61 -> 44714137 | ... P5: =まとめ!P61 -> 47818949 | Q5: =SUM(E5:P5) -> 5.5698764e+08
D6: 仕入 | E6: =まとめ!E62 -> 36598064 | F6: =まとめ!F62 -> 36175956 | G6: =まとめ!G62 -> 37289937 | H6: =まとめ!H62 -> 37229902 | I6: =まとめ!I62 -> 36754194 | J6: =まとめ!J62 -> 36999218 | K6: =まとめ!K62 -> 38087958 | L6: =まとめ!L62 -> 36819954 | ... P6: =まとめ!P62 -> 37961867 | Q6: =SUM(E6:P6) -> 4.4666338e+08
D7: 粗利 | E7: =E5-E6 -> 9182566.8 | F7: =F5-F6 -> 8830501 | G7: =G5-G6 -> 8842601 | H7: =H5-H6 -> 10583155 | I7: =I5-I6 -> 8341592 | J7: =J5-J6 -> 8965119.2 | K7: =K5-K6 -> 10553887 | L7: =L5-L6 -> 7894182.8 | ... P7: =P5-P6 -> 9857082 | Q7: =SUM(E7:P7) -> 1.1032426e+08
A8: 地方 | D8: 売上 | E8: =まとめ!E64 -> 10278180 | F8: =まとめ!F64 -> 10049551 | G8: =まとめ!G64 -> 10016605 | H8: =まとめ!H64 -> 10986220 | I8: =まとめ!I64 -> 10536555 | J8: =まとめ!J64 -> 11323026 | K8: =まとめ!K64 -> 13270079 | L8: =まとめ!L64 -> 10604206 | ... P8: =まとめ!P64 -> 12429324 | Q8: =SUM(E8:P8) -> 1.3438826e+08
D9: 仕入 | E9: =まとめ!E65 -> 8403515 | F9: =まとめ!F65 -> 8127441 | G9: =まとめ!G65 -> 8343695 | H9: =まとめ!H65 -> 8806200 | I9: =まとめ!I65 -> 8897025 | J9: =まとめ!J65 -> 9512200 | K9: =まとめ!K65 -> 9380242 | L9: =まとめ!L65 -> 8533517 | ... P9: =まとめ!P65 -> 9645872.9 | Q9: =SUM(E9:P9) -> 1.0710736e+08
D10: 粗利 | E10: =E8-E9 -> 1874665 | F10: =F8-F9 -> 1922110 | G10: =G8-G9 -> 1672910 | H10: =H8-H9 -> 2180020 | I10: =I8-I9 -> 1639530 | J10: =J8-J9 -> 1810826 | K10: =K8-K9 -> 3889837 | L10: =L8-L9 -> 2070689 | ... P10: =P8-P9 -> 2783450.9 | Q10: =SUM(E10:P10) -> 27280903
D11: 売上 | E11: =E2 -> 56058811 | F11: =F2 -> 55056008 | G11: =G2 -> 56149143 | H11: =H2 -> 58799277 | I11: =I2 -> 55632341 | J11: =J2 -> 57287363 | K11: =K2 -> 61911924 | L11: =L2 -> 55318343 | ... Q11: =Q2 -> 6.913759e+08
D12: 仕入 | E12: =E3 -> 45001579 | F12: =F3 -> 44303397 | G12: =G3 -> 45633632 | H12: =H3 -> 46036102 | I12: =I3 -> 45651219 | J12: =J3 -> 46511418 | K12: =K3 -> 47468200 | L12: =L3 -> 45353471 | ... Q12: =Q3 -> 5.5377074e+08
D13: 粗利 | E13: =E4 -> 11057232 | F13: =F4 -> 10752611 | G13: =G4 -> 10515511 | H13: =H4 -> 12763175 | I13: =I4 -> 9981122 | J13: =J4 -> 10775945 | K13: =K4 -> 14443724 | L13: =L4 -> 9964871.8 | ... Q13: =Q4 -> 1.3760516e+08
D14: Q売上 | E14: =SUM(E11:G11) -> 167263962 | H14: =SUM(H11:J11) -> 171718981 | K14: =SUM(K11:M11) -> 175875073 | N14: =SUM(N11:P11) -> 1.7651789e+08 | Q14: =SUM(E14:P14) -> 6.913759e+08
D15: Q仕入 | E15: =SUM(E12:G12) -> 1.3493861e+08 | H15: =SUM(H12:J12) -> 1.3819874e+08 | K15: =SUM(K12:M12) -> 1.3969585e+08 | N15: =SUM(N12:P12) -> 1.4093755e+08 | Q15: =SUM(E15:P15) -> 5.5377074e+08
D16: Q粗利 | E16: =SUM(E13:G13) -> 32325354 | H16: =SUM(H13:J13) -> 33520242 | K16: =SUM(K13:M13) -> 36179226 | N16: =SUM(N13:P13) -> 35580336 | Q16: =SUM(E16:P16) -> 1.3760516e+08
B18: 契約単価上昇係数
B19: 賃上げ上昇係数

Sheet まとめ
D1: 売上単価 (支払単価） 【≒粗利】 | E1: 4月 | F1: 5月 | G1: 6月 | H1: 7月 | I1: 8月 | J1: 9月 | K1: 10月 | L1: 11月 | M1: 12月 | N1: 1月 | O1: 2月 | P1: 3月 | Q1: 合計
A2: UAL 総計 | D2: 売上 | E2: =E5+E8+E11+E14+E17+E20+E23+E26+E29+E32+E35+E38+E41+E44+E47+E50 -> 56058811 | F2: =F5+F8+F11+F14+F17+F20+F23+F26+F29+F32+F35+F38+F41+F44+F47+F50 -> 55056008 | G2: =G5+G8+G11+G14+G17+G20+G23+G26+G29+G32+G35+G38+G41+G44+G47+G50 -> 56149143 | H2: =H5+H8+H11+H14+H17+H20+H23+H26+H29+H32+H35+H38+H41+H44+H47+H50 -> 58799277 | I2: =I5+I8+I11+I14+I17+I20+I23+I26+I29+I32+I35+I38+I41+I44+I47+I50 -> 55632341 | J2: =J5+J8+J11+J14+J17+J20+J23+J26+J29+J32+J35+J38+J41+J44+J47+J50 -> 57287363 | K2: =K5+K8+K11+K14+K17+K20+K23+K26+K29+K32+K35+K38+K41+K44+K47+K50 -> 61911924 | L2: =L5+L8+L11+L14+L17+L20+L23+L26+L29+L32+L35+L38+L41+L44+L47+L50 -> 55318343 | ... Q2: =Q5+Q8+Q11+Q14+Q17+Q20+Q23+Q26+Q29+Q32+Q35+Q38+Q41+Q44+Q47+Q50 -> 6.913759e+08
D3: 仕入 | E3: =E6+E9+E12+E15+E18+E21+E24+E27+E30+E33+E36+E39+E42+E45+E48+E51 -> 45001579 | F3: =F6+F9+F12+F15+F18+F21+F24+F27+F30+F33+F36+F39+F42+F45+F48+F51 -> 44303397 | G3: =G6+G9+G12+G15+G18+G21+G24+G27+G30+G33+G36+G39+G42+G45+G48+G51 -> 45633632 | H3: =H6+H9+H12+H15+H18+H21+H24+H27+H30+H33+H36+H39+H42+H45+H48+H51 -> 46036102 | I3: =I6+I9+I12+I15+I18+I21+I24+I27+I30+I33+I36+I39+I42+I45+I48+I51 -> 45651219 | J3: =J6+J9+J12+J15+J18+J21+J24+J27+J30+J33+J36+J39+J42+J45+J48+J51 -> 46511418 | K3: =K6+K9+K12+K15+K18+K21+K24+K27+K30+K33+K36+K39+K42+K45+K48+K51 -> 47468200 | L3: =L6+L9+L12+L15+L18+L21+L24+L27+L30+L33+L36+L39+L42+L45+L48+L51 -> 45353471 | ... Q3: =Q6+Q9+Q12+Q15+Q18+Q21+Q24+Q27+Q30+Q33+Q36+Q39+Q42+Q45+Q48+Q51 -> 5.5377074e+08
D4: 粗利 | E4: =E2-E3 -> 11057232 | F4: =F2-F3 -> 10752611 | G4: =G2-G3 -> 10515511 | H4: =H2-H3 -> 12763175 | I4: =I2-I3 -> 9981122 | J4: =J2-J3 -> 10775945 | K4: =K2-K3 -> 14443724 | L4: =L2-L3 -> 9964871.8 | ... Q4: =Q2-Q3 -> 1.3760516e+08
A5: =本社営業本部!C2 -> UAL本社営業本部 | D5: 売上 | E5: =本社営業本部!L2 -> 2549025 | F5: =本社営業本部!M2 -> 2359392 | G5: =本社営業本部!N2 -> 2554986 | H5: =本社営業本部!O2 -> 2686325 | I5: =本社営業本部!P2 -> 2331236 | J5: =本社営業本部!Q2 -> 2606247 | K5: =本社営業本部!R2 -> 3284610 | L5: =本社営業本部!S2 -> 2793312 | ... P5: =本社営業本部!W2 -> 2943025 | Q5: =SUM(E5:P5) -> 32055727
D6: 仕入 | E6: =本社営業本部!L3 -> 2082365 | F6: =本社営業本部!M3 -> 1950886 | G6: =本社営業本部!N3 -> 2112324 | H6: =本社営業本部!O3 -> 2215362 | I6: =本社営業本部!P3 -> 1995210 | J6: =本社営業本部!Q3 -> 2157501.5 | K6: =本社営業本部!R3 -> 2572616 | L6: =本社営業本部!S3 -> 2446945.3 | ... P6: =本社営業本部!W3 -> 2288929 | Q6: =SUM(E6:P6) -> 26549033
D7: 粗利 | E7: =E5-E6 -> 466660 | F7: =F5-F6 -> 408506 | G7: =G5-G6 -> 442662 | H7: =H5-H6 -> 470963 | I7: =I5-I6 -> 336026 | J7: =J5-J6 -> 448745.5 | K7: =K5-K6 -> 711994 | L7: =L5-L6 -> 346366.67 | ... P7: =P5-P6 -> 654096 | Q7: =SUM(E7:P7) -> 5506694.2
A8: =パートナー営業本部!C2 -> パートナー営業本部 | D8: 売上 | E8: =パートナー営業本部!L2 -> 1855900 | F8: =パートナー営業本部!M2 -> 1858000 | G8: =パートナー営業本部!N2 -> 1865700 | H8: =パートナー営業本部!O2 -> 1967800 | I8: =パートナー営業本部!P2 -> 1750000 | J8: =パートナー営業本部!Q2 -> 1915300 | K8: =パートナー営業本部!R2 -> 1958200 | L8: =パートナー営業本部!S2 -> 1573900 | ... P8: =パートナー営業本部!W2 -> 1855900 | Q8: =SUM(E8:P8) -> 21767880
D9: 仕入 | E9: =パートナー営業本部!L3 -> 1391699 | F9: =パートナー営業本部!M3 -> 1394797 | G9: =パートナー営業本部!N3 -> 1402483 | H9: =パートナー営業本部!O3 -> 1466639 | I9: =パートナー営業本部!P3 -> 1364900 | J9: =パートナー営業本部!Q3 -> 1435484 | K9: =パートナー営業本部!R3 -> 1480269 | L9: =パートナー営業本部!S3 -> 1289606 | ... P9: =パートナー営業本部!W3 -> 1391699 | Q9: =SUM(E9:P9) -> 16653242
D10: 粗利 | E10: =E8-E9 -> 464201 | F10: =F8-F9 -> 463203 | G10: =G8-G9 -> 463217 | H10: =H8-H9 -> 501161 | I10: =I8-I9 -> 385100 | J10: =J8-J9 -> 479816 | K10: =K8-K9 -> 477931 | L10: =L8-L9 -> 284294 | ... P10: =P8-P9 -> 464201 | Q10: =SUM(E10:P10) -> 5114638
A11: =ビジネス推進本部!C2 -> ビジネス推進本部 | D11: 売上 | E11: =ビジネス推進本部!L2 -> 4590421 | F11: =ビジネス推進本部!M2 -> 4432220 | G11: =ビジネス推進本部!N2 -> 4564802 | H11: =ビジネス推進本部!O2 -> 5724727 | I11: =ビジネス推進本部!P2 -> 3878290 | J11: =ビジネス推進本部!Q2 -> 4078855 | K11: =ビジネス推進本部!R2 -> 4483980 | L11: =ビジネス推進本部!S2 -> 3711735 | ... P11: =ビジネス推進本部!W2 -> 3052331 | Q11: =SUM(E11:P11) -> 49426752
D12: 仕入 | E12: =ビジネス推進本部!L3 -> 3931343 | F12: =ビジネス推進本部!M3 -> 3797773 | G12: =ビジネス推進本部!N3 -> 3936678 | H12: =ビジネス推進本部!O3 -> 3817336 | I12: =ビジネス推進本部!P3 -> 3507998 | J12: =ビジネス推進本部!Q3 -> 3583399 | K12: =ビジネス推進本部!R3 -> 3820972 | L12: =ビジネス推進本部!S3 -> 3290280 | ... P12: =ビジネス推進本部!W3 -> 2960001 | Q12: =SUM(E12:P12) -> 42207179
D13: 粗利 | E13: =E11-E12 -> 659078 | F13: =F11-F12 -> 634447 | G13: =G11-G12 -> 628124 | H13: =H11-H12 -> 1907391 | I13: =I11-I12 -> 370292 | J13: =J11-J12 -> 495456 | K13: =K11-K12 -> 663008 | L13: =L11-L12 -> 421455 | ... P13: =P11-P12 -> 92330 | Q13: =SUM(E13:P13) -> 7219573
A14: =DXシステム本部!C2 -> DXシステム本部 | D14: 売上 | E14: =DXシステム本部!L2 -> 2493700 | F14: =DXシステム本部!M2 -> 2299200 | G14: =DXシステム本部!N2 -> 2549200 | H14: =DXシステム本部!O2 -> 2549200 | I14: =DXシステム本部!P2 -> 3285160 | J14: =DXシステム本部!Q2 -> 3139830 | K14: =DXシステム本部!R2 -> 3299200 | L14: =DXシステム本部!S2 -> 3247650 | ... P14: =DXシステム本部!W2 -> 3899200 | Q14: =SUM(E14:P14) -> 37150670
D15: 仕入 | E15: =DXシステム本部!L3 -> 1960995.5 | F15: =DXシステム本部!M3 -> 1946020 | G15: =DXシステム本部!N3 -> 1974776 | H15: =DXシステム本部!O3 -> 2013459 | I15: =DXシステム本部!P3 -> 2547631 | J15: =DXシステム本部!Q3 -> 2550410 | K15: =DXシステム本部!R3 -> 2540711 | L15: =DXシステム本部!S3 -> 2539305 | ... P15: =DXシステム本部!W3 -> 3038749 | Q15: =SUM(E15:P15) -> 29242126
D16: 粗利 | E16: =E14-E15 -> 532704.48 | F16: =F14-F15 -> 353180 | G16: =G14-G15 -> 574424 | H16: =H14-H15 -> 535741 | I16: =I14-I15 -> 737529 | J16: =J14-J15 -> 589420 | K16: =K14-K15 -> 758489 | L16: =L14-L15 -> 708345 | ... P16: =P14-P15 -> 860451 | Q16: =SUM(E16:P16) -> 7908544.5
A17: =マーケティングコミュニケーション本部!C$2 -> マーケティングコミュニケーション本部 | D17: 売上 | E17: =マーケティングコミュニケーション本部!L2 -> 1497500 | F17: =マーケティングコミュニケーション本部!M2 -> 1692200 | G17: =マーケティングコミュニケーション本部!N2 -> 1674800 | H17: =マーケティングコミュニケーション本部!O2 -> 1923740 | I17: =マーケティングコミュニケーション本部!P2 -> 1709080 | J17: =マーケティングコミュニケーション本部!Q2 -> 1741555 | K17: =マーケティングコミュニケーション本部!R2 -> 1784720 | L17: =マーケティングコミュニケーション本部!S2 -> 1738930 | ... P17: =マーケティングコミュニケーション本部!W2 -> 2106500 | Q17: =SUM(E17:P17) -> 21731455
D18: 仕入 | E18: =マーケティングコミュニケーション本部!L3 -> 1238221.7 | F18: =マーケティングコミュニケーション本部!M3 -> 1460165 | G18: =マーケティングコミュニケーション本部!N3 -> 1671530 | H18: =マーケティングコミュニケーション本部!O3 -> 1628669 | I18: =マーケティングコミュニケーション本部!P3 -> 1428100 | J18: =マーケティングコミュニケーション本部!Q3 -> 1423623.3 | K18: =マーケティングコミュニケーション本部!R3 -> 1318886 | L18: =マーケティングコミュニケーション本部!S3 -> 1510767.9 | ... P18: =マーケティングコミュニケーション本部!W3 -> 1621088 | Q18: =SUM(E18:P18) -> 17586253
D19: 粗利 | E19: =マーケティングコミュニケーション本部!L4 -> 259278.33 | F19: =マーケティングコミュニケーション本部!M4 -> 232035 | G19: =マーケティングコミュニケーション本部!N4 -> 3270 | H19: =マーケティングコミュニケーション本部!O4 -> 295071 | I19: =マーケティングコミュニケーション本部!P4 -> 280980.03 | J19: =マーケティングコミュニケーション本部!Q4 -> 317931.66 | K19: =マーケティングコミュニケーション本部!R4 -> 465834.04 | L19: =マーケティングコミュニケーション本部!S4 -> 228162.09 | ... P19: =マーケティングコミュニケーション本部!W4 -> 485412 | Q19: =SUM(E19:P19) -> 4145202.1
A20: =ネットワークサービス本部!C$2 -> ネットワークサービス本部 | D20: 売上 | E20: =ネットワークサービス本部!L2 -> 1150000 | F20: =ネットワークサービス本部!M2 -> 1127150 | G20: =ネットワークサービス本部!N2 -> 1150000 | H20: =ネットワークサービス本部!O2 -> 1150000 | I20: =ネットワークサービス本部!P2 -> 1150000 | J20: =ネットワークサービス本部!Q2 -> 1150000 | K20: =ネットワークサービス本部!R2 -> 1150000 | L20: =ネットワークサービス本部!S2 -> 1062805 | ... P20: =ネットワークサービス本部!W2 -> 1150000 | Q20: =SUM(E20:P20) -> 13482055
D21: 仕入 | E21: =ネットワークサービス本部!L3 -> 866552 | F21: =ネットワークサービス本部!M3 -> 863755 | G21: =ネットワークサービス本部!N3 -> 869534 | H21: =ネットワークサービス本部!O3 -> 867547 | I21: =ネットワークサービス本部!P3 -> 862003 | J21: =ネットワークサービス本部!Q3 -> 864804 | K21: =ネットワークサービス本部!R3 -> 866337 | L21: =ネットワークサービス本部!S3 -> 852634 | ... P21: =ネットワークサービス本部!W3 -> 866552 | Q21: =SUM(E21:P21) -> 10360502
D22: 粗利 | E22: =E20-E21 -> 283448 | F22: =F20-F21 -> 263395 | G22: =G20-G21 -> 280466 | H22: =H20-H21 -> 282453 | I22: =I20-I21 -> 287997 | J22: =J20-J21 -> 285196 | K22: =K20-K21 -> 283663 | L22: =L20-L21 -> 210171 | ... P22: =P20-P21 -> 283448 | Q22: =SUM(E22:P22) -> 3121553
A23: =アカウントサービス第一本部!C2 -> アカウントサービス第一本部 | D23: 売上 | E23: =アカウントサービス第一本部!L2 -> 7233400 | F23: =アカウントサービス第一本部!M2 -> 7381230 | G23: =アカウントサービス第一本部!N2 -> 7754925 | H23: =アカウントサービス第一本部!O2 -> 7945385 | I23: =アカウントサービス第一本部!P2 -> 7255870 | J23: =アカウントサービス第一本部!Q2 -> 7501850 | K23: =アカウントサービス第一本部!R2 -> 7944685 | L23: =アカウントサービス第一本部!S2 -> 7497605 | ... P23: =アカウントサービス第一本部!W2 -> 7247882.8 | Q23: =SUM(E23:P23) -> 90010903
D24: 仕入 | E24: =アカウントサービス第一本部!L3 -> 5961660 | F24: =アカウントサービス第一本部!M3 -> 5817622 | G24: =アカウントサービス第一本部!N3 -> 6261808 | H24: =アカウントサービス第一本部!O3 -> 6454475 | I24: =アカウントサービス第一本部!P3 -> 5955003 | J24: =アカウントサービス第一本部!Q3 -> 5994003 | K24: =アカウントサービス第一本部!R3 -> 6284881 | L24: =アカウントサービス第一本部!S3 -> 6005666 | ... P24: =アカウントサービス第一本部!W3 -> 5939386.1 | Q24: =SUM(E24:P24) -> 72953630
D25: 粗利 | E25: =E23-E24 -> 1271740 | F25: =F23-F24 -> 1563608 | G25: =G23-G24 -> 1493117 | H25: =H23-H24 -> 1490910 | I25: =I23-I24 -> 1300867 | J25: =J23-J24 -> 1507847 | K25: =K23-K24 -> 1659804 | L25: =L23-L24 -> 1491939 | ... P25: =P23-P24 -> 1308496.7 | Q25: =SUM(E25:P25) -> 17057273
A26: =アカウントサービス第二本部!C2 -> アカウントサービス第二本部 | D26: 売上 | E26: =アカウントサービス第二本部!L2 -> 760000 | F26: =アカウントサービス第二本部!M2 -> 1051235 | G26: =アカウントサービス第二本部!N2 -> 1070905 | H26: =アカウントサービス第二本部!O2 -> 1450000 | I26: =アカウントサービス第二本部!P2 -> 1454060 | J26: =アカウントサービス第二本部!Q2 -> 1450000 | K26: =アカウントサービス第二本部!R2 -> 1614020 | L26: =アカウントサービス第二本部!S2 -> 1450000 | ... P26: =アカウントサービス第二本部!W2 -> 1410000 | Q26: =SUM(E26:P26) -> 15985220
D27: 仕入 | E27: =アカウントサービス第二本部!L3 -> 612134 | F27: =アカウントサービス第二本部!M3 -> 910091 | G27: =アカウントサービス第二本部!N3 -> 865244 | H27: =アカウントサービス第二本部!O3 -> 1017483 | I27: =アカウントサービス第二本部!P3 -> 1013218 | J27: =アカウントサービス第二本部!Q3 -> 999652 | K27: =アカウントサービス第二本部!R3 -> 1142236 | L27: =アカウントサービス第二本部!S3 -> 1020062 | ... P27: =アカウントサービス第二本部!W3 -> 976783 | Q27: =SUM(E27:P27) -> 11642566
D28: 粗利 | E28: =E26-E27 -> 147866 | F28: =F26-F27 -> 141144 | G28: =G26-G27 -> 205661 | H28: =H26-H27 -> 432517 | I28: =I26-I27 -> 440842 | J28: =J26-J27 -> 450348 | K28: =K26-K27 -> 471784 | L28: =L26-L27 -> 429938 | ... P28: =P26-P27 -> 433217 | Q28: =SUM(E28:P28) -> 4342654
A29: =アカウントサービス第五本部!C2 -> アカウントサービス第五本部 | D29: 売上 | E29: =アカウントサービス第五本部!L2 -> 5097600 | F29: =アカウントサービス第五本部!M2 -> 4924750 | G29: =アカウントサービス第五本部!N2 -> 4957050 | H29: =アカウントサービス第五本部!O2 -> 5049400 | I29: =アカウントサービス第五本部!P2 -> 4693700 | J29: =アカウントサービス第五本部!Q2 -> 4794295 | K29: =アカウントサービス第五本部!R2 -> 4373550 | L29: =アカウントサービス第五本部!S2 -> 4130180 | ... P29: =アカウントサービス第五本部!W2 -> 6412600 | Q29: =SUM(E29:P29) -> 61402520
D30: 仕入 | E30: =アカウントサービス第五本部!L3 -> 3846091 | F30: =アカウントサービス第五本部!M3 -> 3740385 | G30: =アカウントサービス第五本部!N3 -> 3815448 | H30: =アカウントサービス第五本部!O3 -> 3977832 | I30: =アカウントサービス第五本部!P3 -> 3788701 | J30: =アカウントサービス第五本部!Q3 -> 3631814 | K30: =アカウントサービス第五本部!R3 -> 3207288 | L30: =アカウントサービス第五本部!S3 -> 3338455 | ... P30: =アカウントサービス第五本部!W3 -> 4605472 | Q30: =SUM(E30:P30) -> 46730823
D31: 粗利 | E31: =E29-E30 -> 1251509 | F31: =F29-F30 -> 1184365 | G31: =G29-G30 -> 1141602 | H31: =H29-H30 -> 1071568 | I31: =I29-I30 -> 904999 | J31: =J29-J30 -> 1162481 | K31: =K29-K30 -> 1166262 | L31: =L29-L30 -> 791725 | ... P31: =P29-P30 -> 1807128 | Q31: =SUM(E31:P31) -> 14671697
A32: =マネージドサービス第一本部!C2 -> マネージドサービス第一本部 | D32: 売上 | E32: =マネージドサービス第一本部!L2 -> 9019005 | F32: =マネージドサービス第一本部!M2 -> 8517400 | G32: =マネージドサービス第一本部!N2 -> 8553300 | H32: =マネージドサービス第一本部!O2 -> 8728550 | I32: =マネージドサービス第一本部!P2 -> 8362195 | J32: =マネージドサービス第一本部!Q2 -> 8137740 | K32: =マネージドサービス第一本部!R2 -> 9029510 | L32: =マネージドサービス第一本部!S2 -> 8574705 | ... P32: =マネージドサービス第一本部!W2 -> 8615508.3 | Q32: =SUM(E32:P32) -> 1.0363969e+08
D33: 仕入 | E33: =マネージドサービス第一本部!L3 -> 7421278 | F33: =マネージドサービス第一本部!M3 -> 7091978 | G33: =マネージドサービス第一本部!N3 -> 7112189 | H33: =マネージドサービス第一本部!O3 -> 7197283 | I33: =マネージドサービス第一本部!P3 -> 7091566 | J33: =マネージドサービス第一本部!Q3 -> 7109635 | K33: =マネージドサービス第一本部!R3 -> 7364005.5 | L33: =マネージドサービス第一本部!S3 -> 7404708 | ... P33: =マネージドサービス第一本部!W3 -> 7251849.2 | Q33: =SUM(E33:P33) -> 87186306
D34: 粗利 | E34: =E32-E33 -> 1597727 | F34: =F32-F33 -> 1425422 | G34: =G32-G33 -> 1441111 | H34: =H32-H33 -> 1531267 | I34: =I32-I33 -> 1270629 | J34: =J32-J33 -> 1028105 | K34: =K32-K33 -> 1665504.5 | L34: =L32-L33 -> 1169997 | ... P34: =P32-P33 -> 1363659.1 | Q34: =SUM(E34:P34) -> 16453383
A35: =マネージドサービス第二本部!C2 -> マネージドサービス第二本部 | D35: 売上 | E35: =マネージドサービス第二本部!K2 -> 4758625 | F35: =マネージドサービス第二本部!L2 -> 4539760 | G35: =マネージドサービス第二本部!M2 -> 4685890 | H35: =マネージドサービス第二本部!N2 -> 4235550 | I35: =マネージドサービス第二本部!O2 -> 4232000 | J35: =マネージドサービス第二本部!P2 -> 4305625 | K35: =マネージドサービス第二本部!Q2 -> 4286630 | L35: =マネージドサービス第二本部!R2 -> 4035400 | ... P35: =マネージドサービス第二本部!V2 -> 3789575 | Q35: =SUM(E35:P35) -> 50536465
D36: 仕入 | E36: =マネージドサービス第二本部!K3 -> 3409115 | F36: =マネージドサービス第二本部!L3 -> 3360925 | G36: =マネージドサービス第二本部!M3 -> 3405027 | H36: =マネージドサービス第二本部!N3 -> 2977481 | I36: =マネージドサービス第二本部!O3 -> 2953730 | J36: =マネージドサービス第二本部!P3 -> 2930924 | K36: =マネージドサービス第二本部!Q3 -> 3114891 | L36: =マネージドサービス第二本部!R3 -> 2919826 | ... P36: =マネージドサービス第二本部!V3 -> 2676301 | Q36: =SUM(E36:P36) -> 36038836
D37: 粗利 | E37: =E35-E36 -> 1349510 | F37: =F35-F36 -> 1178835 | G37: =G35-G36 -> 1280863 | H37: =H35-H36 -> 1258069 | I37: =I35-I36 -> 1278270 | J37: =J35-J36 -> 1374701 | K37: =K35-K36 -> 1171739 | L37: =L35-L36 -> 1115574 | ... P37: =P35-P36 -> 1113274 | Q37: =SUM(E37:P37) -> 14497629
A38: =セキュリティサービス本部!C2 -> セキュリティサービス本部 | D38: 売上 | E38: =セキュリティサービス本部!L2 -> 600000 | F38: =セキュリティサービス本部!M2 -> 625250 | G38: =セキュリティサービス本部!N2 -> 590400 | H38: =セキュリティサービス本部!O2 -> 606800 | I38: =セキュリティサービス本部!P2 -> 1265200 | J38: =セキュリティサービス本部!Q2 -> 1389350 | K38: =セキュリティサービス本部!R2 -> 1634100 | L38: =セキュリティサービス本部!S2 -> 1353450 | ... P38: =セキュリティサービス本部!W2 -> 1545000 | Q38: =SUM(E38:P38) -> 13954800
D39: 仕入 | E39: =セキュリティサービス本部!L3 -> 523561 | F39: =セキュリティサービス本部!M3 -> 492359 | G39: =セキュリティサービス本部!N3 -> 510393 | H39: =セキュリティサービス本部!O3 -> 518204 | I39: =セキュリティサービス本部!P3 -> 1212862 | J39: =セキュリティサービス本部!Q3 -> 1231190 | K39: =セキュリティサービス本部!R3 -> 1280192 | L39: =セキュリティサービス本部!S3 -> 1172634 | ... P39: =セキュリティサービス本部!W3 -> 1283957 | Q39: =SUM(E39:P39) -> 11929369
D40: 粗利 | E40: =E38-E39 -> 76439 | F40: =F38-F39 -> 132891 | G40: =G38-G39 -> 80007 | H40: =H38-H39 -> 88596 | I40: =I38-I39 -> 52338 | J40: =J38-J39 -> 158160 | K40: =K38-K39 -> 353908 | L40: =L38-L39 -> 180816 | ... P40: =P38-P39 -> 261043 | Q40: =SUM(E40:P40) -> 2025431
A41: =カスタマーリレーション本部!C2 -> カスタマーリレーション本部 | D41: 売上 | E41: =カスタマーリレーション本部!L2 -> 4175455 | F41: =カスタマーリレーション本部!M2 -> 4198670 | G41: =カスタマーリレーション本部!N2 -> 4160580 | H41: =カスタマーリレーション本部!O2 -> 3795580 | I41: =カスタマーリレーション本部!P2 -> 3728995 | J41: =カスタマーリレーション本部!Q2 -> 3753690 | K41: =カスタマーリレーション本部!R2 -> 3798640 | L41: =カスタマーリレーション本部!S2 -> 3544465 | ... P41: =カスタマーリレーション本部!W2 -> 3791427.2 | Q41: =SUM(E41:P41) -> 45843502
D42: 仕入 | E42: =カスタマーリレーション本部!L3 -> 3353049 | F42: =カスタマーリレーション本部!M3 -> 3349200 | G42: =カスタマーリレーション本部!N3 -> 3352503 | H42: =カスタマーリレーション本部!O3 -> 3078132 | I42: =カスタマーリレーション本部!P3 -> 3033272 | J42: =カスタマーリレーション本部!Q3 -> 3086778 | K42: =カスタマーリレーション本部!R3 -> 3094674 | L42: =カスタマーリレーション本部!S3 -> 3029065 | ... P42: =カスタマーリレーション本部!W3 -> 3061101 | Q42: =SUM(E42:P42) -> 37583518
D43: 粗利 | E43: =E41-E42 -> 822406 | F43: =F41-F42 -> 849470 | G43: =G41-G42 -> 808077 | H43: =H41-H42 -> 717448 | I43: =I41-I42 -> 695723 | J43: =J41-J42 -> 666912 | K43: =K41-K42 -> 703966 | L43: =L41-L42 -> 515400 | ... P43: =P41-P42 -> 730326.22 | Q43: =SUM(E43:P43) -> 8259984.2
A44: =中部支店!C2 -> 中部支店 | D44: 売上 | E44: =中部支店!L2 -> 1698395 | F44: =中部支店!M2 -> 1685881 | G44: =中部支店!N2 -> 1455725 | H44: =中部支店!O2 -> 1459990 | I44: =中部支店!P2 -> 1491335 | J44: =中部支店!Q2 -> 1675136 | K44: =中部支店!R2 -> 1792152 | L44: =中部支店!S2 -> 1446616 | ... P44: =中部支店!W2 -> 1672645 | Q44: =SUM(E44:P44) -> 18609548
D45: 仕入 | E45: =中部支店!L3 -> 1446665 | F45: =中部支店!M3 -> 1376574 | G45: =中部支店!N3 -> 1396151 | H45: =中部支店!O3 -> 1256122 | I45: =中部支店!P3 -> 1320368 | J45: =中部支店!Q3 -> 1381883 | K45: =中部支店!R3 -> 1487191 | L45: =中部支店!S3 -> 1288499 | ... P45: =中部支店!W3 -> 1410043 | Q45: =SUM(E45:P45) -> 16020425
D46: 粗利 | E46: =E44-E45 -> 251730 | F46: =F44-F45 -> 309307 | G46: =G44-G45 -> 59574 | H46: =H44-H45 -> 203868 | I46: =I44-I45 -> 170967 | J46: =J44-J45 -> 293253 | K46: =K44-K45 -> 304961 | L46: =L44-L45 -> 158117 | ... P46: =P44-P45 -> 262602 | Q46: =SUM(E46:P46) -> 2589123
A47: =関西支店!C2 -> 関西支店 | D47: 売上 | E47: =関西支店!L2 -> 5889090 | F47: =関西支店!M2 -> 5730205 | G47: =関西支店!N2 -> 5873915 | H47: =関西支店!O2 -> 6739310 | I47: =関西支店!P2 -> 6687320 | J47: =関西支店!Q2 -> 6848325 | K47: =関西支店!R2 -> 7151175 | L47: =関西支店!S2 -> 6571715 | ... P47: =関西支店!W2 -> 6652111.7 | Q47: =SUM(E47:P47) -> 78125902
D48: 仕入 | E48: =関西支店!L3 -> 4783382 | F48: =関西支店!M3 -> 4635866 | G48: =関西支店!N3 -> 4798011 | H48: =関西支店!O3 -> 5344646 | I48: =関西支店!P3 -> 5503766 | J48: =関西支店!Q3 -> 5638676 | K48: =関西支店!R3 -> 5549070 | L48: =関西支店!S3 -> 5218175 | ... P48: =関西支店!W3 -> 5202936.3 | Q48: =SUM(E48:P48) -> 62172259
D49: 粗利 | E49: =E47-E48 -> 1105708 | F49: =F47-F48 -> 1094339 | G49: =G47-G48 -> 1075904 | H49: =H47-H48 -> 1394664 | I49: =I47-I48 -> 1183554 | J49: =J47-J48 -> 1209649 | K49: =K47-K48 -> 1602105 | L49: =L47-L48 -> 1353540 | ... P49: =P47-P48 -> 1449175.4 | Q49: =SUM(E49:P49) -> 15953642
A50: =地方!C2 -> 地方 | D50: 売上 | E50: =地方!L2 -> 2690695 | F50: =地方!M2 -> 2633465 | G50: =地方!N2 -> 2686965 | H50: =地方!O2 -> 2786920 | I50: =地方!P2 -> 2357900 | J50: =地方!Q2 -> 2799565 | K50: =地方!R2 -> 4326752 | L50: =地方!S2 -> 2585875 | ... P50: =地方!W2 -> 4104567.2 | Q50: =SUM(E50:P50) -> 37652814
D51: 仕入 | E51: =地方!L3 -> 2173468 | F51: =地方!M3 -> 2115001 | G51: =地方!N3 -> 2149533 | H51: =地方!O3 -> 2205432 | I51: =地方!P3 -> 2072891 | J51: =地方!Q3 -> 2491641 | K51: =地方!R3 -> 2343981 | L51: =地方!S3 -> 2026843 | ... P51: =地方!W3 -> 3032893.7 | Q51: =SUM(E51:P51) -> 28914677
D52: 粗利 | E52: =E50-E51 -> 517227 | F52: =F50-F51 -> 518464 | G52: =G50-G51 -> 537432 | H52: =H50-H51 -> 581488 | I52: =I50-I51 -> 285009 | J52: =J50-J51 -> 307924 | K52: =K50-K51 -> 1982771 | L52: =L50-L51 -> 559032 | ... P52: =P50-P51 -> 1071673.6 | Q52: =SUM(E52:P52) -> 8738137.6
D53: 売上 | E53: =E2 -> 56058811 | F53: =F2 -> 55056008 | G53: =G2 -> 56149143 | H53: =H2 -> 58799277 | I53: =I2 -> 55632341 | J53: =J2 -> 57287363 | K53: =K2 -> 61911924 | L53: =L2 -> 55318343 | ... Q53: =Q2 -> 6.913759e+08
D54: 仕入 | E54: =E3 -> 45001579 | F54: =F3 -> 44303397 | G54: =G3 -> 45633632 | H54: =H3 -> 46036102 | I54: =I3 -> 45651219 | J54: =J3 -> 46511418 | K54: =K3 -> 47468200 | L54: =L3 -> 45353471 | ... Q54: =Q3 -> 5.5377074e+08
D55: 粗利 | E55: =E4 -> 11057232 | F55: =F4 -> 10752611 | G55: =G4 -> 10515511 | H55: =H4 -> 12763175 | I55: =I4 -> 9981122 | J55: =J4 -> 10775945 | K55: =K4 -> 14443724 | L55: =L4 -> 9964871.8 | ... Q55: =Q4 -> 1.3760516e+08
D56: Q売上 | E56: =SUM(E53:G53) -> 167263962 | H56: =SUM(H53:J53) -> 171718981 | K56: =SUM(K53:M53) -> 175875073 | N56: =SUM(N53:P53) -> 1.7651789e+08 | Q56: =SUM(E56:P56) -> 6.913759e+08
D57: Q仕入 | E57: =SUM(E54:G54) -> 1.3493861e+08 | H57: =SUM(H54:J54) -> 1.3819874e+08 | K57: =SUM(K54:M54) -> 1.3969585e+08 | N57: =SUM(N54:P54) -> 1.4093755e+08 | Q57: =SUM(E57:P57) -> 5.5377074e+08
D58: Q粗利 | E58: =SUM(E55:G55) -> 32325354 | H58: =SUM(H55:J55) -> 33520242 | K58: =SUM(K55:M55) -> 36179226 | N58: =SUM(N55:P55) -> 35580336 | Q58: =SUM(E58:P58) -> 1.3760516e+08
A61: 首都圏 | D61: 売上 | E61: =E2-E64 -> 45780631 | F61: =F2-F64 -> 45006457 | G61: =G2-G64 -> 46132538 | H61: =H2-H64 -> 47813057 | I61: =I2-I64 -> 45095786 | J61: =J2-J64 -> 45964337 | K61: =K2-K64 -> 48641845 | L61: =L2-L64 -> 44714137 | ... Q61: =Q2-Q64 -> 5.5698764e+08
D62: 仕入 | E62: =E3-E65 -> 36598064 | F62: =F3-F65 -> 36175956 | G62: =G3-G65 -> 37289937 | H62: =H3-H65 -> 37229902 | I62: =I3-I65 -> 36754194 | J62: =J3-J65 -> 36999218 | K62: =K3-K65 -> 38087958 | L62: =L3-L65 -> 36819954 | ... Q62: =Q3-Q65 -> 4.4666338e+08
D63: 粗利 | E63: =E61-E62 -> 9182566.8 | F63: =F61-F62 -> 8830501 | G63: =G61-G62 -> 8842601 | H63: =H61-H62 -> 10583155 | I63: =I61-I62 -> 8341592 | J63: =J61-J62 -> 8965119.2 | K63: =K61-K62 -> 10553887 | L63: =L61-L62 -> 7894182.8 | ... Q63: =Q61-Q62 -> 1.1032426e+08
A64: 地方全体 | D64: 売上 | E64: =E44+E47+E50 -> 10278180 | F64: =F44+F47+F50 -> 10049551 | G64: =G44+G47+G50 -> 10016605 | H64: =H44+H47+H50 -> 10986220 | I64: =I44+I47+I50 -> 10536555 | J64: =J44+J47+J50 -> 11323026 | K64: =K44+K47+K50 -> 13270079 | L64: =L44+L47+L50 -> 10604206 | ... P64: =P44+P47+P50 -> 12429324 | Q64: =SUM(E64:P64) -> 1.3438826e+08
D65: 仕入 | E65: =E45+E48+E51 -> 8403515 | F65: =F45+F48+F51 -> 8127441 | G65: =G45+G48+G51 -> 8343695 | H65: =H45+H48+H51 -> 8806200 | I65: =I45+I48+I51 -> 8897025 | J65: =J45+J48+J51 -> 9512200 | K65: =K45+K48+K51 -> 9380242 | L65: =L45+L48+L51 -> 8533517 | ... P65: =P45+P48+P51 -> 9645872.9 | Q65: =SUM(E65:P65) -> 1.0710736e+08
D66: 粗利 | E66: =E64-E65 -> 1874665 | F66: =F64-F65 -> 1922110 | G66: =G64-G65 -> 1672910 | H66: =H64-H65 -> 2180020 | I66: =I64-I65 -> 1639530 | J66: =J64-J65 -> 1810826 | K66: =K64-K65 -> 3889837 | L66: =L64-L65 -> 2070689 | ... P66: =P64-P65 -> 2783450.9 | Q66: =SUM(E66:P66) -> 27280903

Sheet グラフ

Sheet 本社営業本部
A1: 社員番号 | B1: 氏名 | C1: No | D1: 派遣/請負 | E1: 担当 | F1: 氏名 | G1: 派遣先部署 | H1: 作業名 | I1: 契約先 | J1: 外注会社 | K1: 売上単価 (支払単価） 【≒粗利】 | L1: 4月 | M1: 5月 | N1: 6月 | O1: 7月 | P1: 8月 | Q1: 9月 | R1: 10月 | S1: 11月 | T1: 12月 | U1: 1月 | V1: 2月 | W1: 3月 | X1: 合計
C2: UAL本社営業本部 | K2: 売上 | L2: =L89 -> 2549025 | M2: =M89 -> 2359392 | N2: =N89 -> 2554986 | O2: =O89 -> 2686325 | P2: =P89 -> 2331236 | Q2: =Q89 -> 2606247 | R2: =R89 -> 3284610 | S2: =S89 -> 2793312 | ... W2: =W89 -> 2943025 | X2: =SUM(L2:W2) -> 32055727
K3: 仕入 | L3: =L90 -> 2082365 | M3: =M90 -> 1950886 | N3: =N90 -> 2112324 | O3: =O90 -> 2215362 | P3: =P90 -> 1995210 | Q3: =Q90 -> 2157501.5 | R3: =R90 -> 2572616 | S3: =S90 -> 2446945.3 | ... W3: =W90 -> 2288929 | X3: =SUM(L3:W3) -> 26549033
K4: 粗利 | L4: =L91 -> 466660 | M4: =M91 -> 408506 | N4: =N91 -> 442662 | O4: =O91 -> 470963 | P4: =P91 -> 336026 | Q4: =Q91 -> 448745.5 | R4: =R91 -> 711994 | S4: =S91 -> 346366.67 | ... W4: =W91 -> 654096 | X4: =SUM(L4:W4) -> 5506694.2
A5: 2017034 | C5: 1 | D5: 派遣 | G5: サービスプロバイダ営業本部サービスプロバイダ第二営業部 | I5: 本社営業 | J5: 社員 | K5: 総受注金額 | L5: =L6+L7 -> 450450 | M5: =M6+M7 -> 413000 | N5: =N6+N7 -> 439250 | O5: =O6+O7 -> 481600 | P5: =P6+P7 -> 364350 | Q5: =Q6+Q7 -> 408100 | R5: =R6+R7 -> 438900 | S5: =S6+S7 -> 389550 | ... W5: =W6+W7 -> 450450 | X5: =SUM(L5:W5) -> 4922750
A6: =+A5 -> 2017034 | K6: 派遣金額 | L6: 450450 | M6: 413000 | N6: 439250 | O6: 481600 | P6: 364350 | Q6: 408100 | R6: 438900 | S6: 389550 | T6: 336700 | U6: 400400 | V6: 350000 | W6: 450450 | X6: =SUM(L6:W6) -> 4922750
A7: =+A6 -> 2017034 | X7: =SUM(L7:W7) -> 0
A8: =+A7 -> 2017034 | K8: 総経費 | L8: =SUM(L9:L15) -> 363860 | M8: =SUM(M9:M15) -> 338704 | N8: =SUM(N9:N15) -> 373712 | O8: =SUM(O9:O15) -> 391714 | P8: =SUM(P9:P15) -> 355504 | Q8: =SUM(Q9:Q15) -> 341497 | R8: =SUM(R9:R15) -> 375652 | S8: =SUM(S9:S15) -> 330015 | ... W8: =SUM(W9:W15) -> 363860 | X8: =SUM(L8:W8) -> 4216660
A9: =+A8 -> 2017034 | K9: 賃金 | L9: 303075 | M9: 279113 | N9: 314775 | O9: 330920 | P9: 288738 | Q9: 275800 | R9: 309600 | S9: 264438 | T9: 287100 | U9: 258250 | V9: 239963 | W9: 303075 | X9: =SUM(L9:W9) -> 3454847
A10: =+A9 -> 2017034 | K10: 交通費その他 | X10: =SUM(L10:W10) -> 0
A11: =+A10 -> 2017034 | K11: 通勤定期代 | L11: 18488 | M11: 17556 | N11: 16538 | O11: 18208 | P11: 19054 | Q11: 18130 | R11: 18130 | S11: 18130 | T11: 18130 | U11: 18130 | V11: 18130 | W11: 18488 | X11: =SUM(L11:W11) -> 217112
A12: =+A11 -> 2017034 | K12: 健康保険 | L12: 13300 | M12: 13300 | N12: 13300 | O12: 13300 | P12: 15200 | Q12: 15200 | R12: 15200 | S12: 15200 | T12: 15200 | U12: 15200 | V12: 15200 | W12: 13300 | X12: =SUM(L12:W12) -> 172900
A13: =+A12 -> 2017034 | K13: 厚生年金 | L13: 25620 | M13: 25620 | N13: 25620 | O13: 25620 | P13: 29280 | Q13: 29280 | R13: 29280 | S13: 29280 | T13: 29280 | U13: 29280 | V13: 29280 | W13: 25620 | X13: =SUM(L13:W13) -> 333060
A14: =+A13 -> 2017034 | K14: 労災保険 | L14: 1608 | M14: 1483 | N14: 1657 | O14: 1746 | P14: 1539 | Q14: 1470 | R14: 1639 | S14: 1413 | T14: 1526 | U14: 1382 | V14: 1377 | W14: 1608 | X14: =SUM(L14:W14) -> 18448
A15: =+A14 -> 2017034 | K15: 雇用保険 | L15: 1769 | M15: 1632 | N15: 1822 | O15: 1920 | P15: 1693 | Q15: 1617 | R15: 1803 | S15: 1554 | T15: 1679 | U15: 1520 | V15: 1515 | W15: 1769 | X15: =SUM(L15:W15) -> 20293
A16: =+A15 -> 2017034 | K16: 粗利 | L16: =L5-L8 -> 86590 | M16: =M5-M8 -> 74296 | N16: =N5-N8 -> 65538 | O16: =O5-O8 -> 89886 | P16: =P5-P8 -> 8846 | Q16: =Q5-Q8 -> 66603 | R16: =R5-R8 -> 63248 | S16: =S5-S8 -> 59535 | ... X16: =X5-X8 -> 706090
A17: 2023018 | C17: =C5+1 -> 2 | D17: 派遣 | G17: サービスプロバイダ営業本部サービスプロバイダ第二営業部 | I17: 本社営業 | J17: 社員 | K17: 総受注金額 | L17: =L18+L19 -> 448700 | M17: =M18+M19 -> 421050 | N17: =N18+N19 -> 443800 | O17: =O18+O19 -> 460950 | P17: =P18+P19 -> 354900 | Q17: =Q18+Q19 -> 393050 | R17: =R18+R19 -> 439250 | S17: =S18+S19 -> 351050 | ... W17: =W18+W19 -> 448700 | X17: =SUM(L17:W17) -> 4870950
A18: =+A17 -> 2023018 | K18: 派遣金額 | L18: 448700 | M18: 421050 | N18: 443800 | O18: 460950 | P18: 354900 | Q18: 393050 | R18: 439250 | S18: 351050 | T18: 333550 | U18: 373100 | V18: 402850 | W18: 448700 | X18: =SUM(L18:W18) -> 4870950
A19: =+A18 -> 2023018 | K19: 交通費 | X19: =SUM(L19:W19) -> 0
A20: =+A19 -> 2023018 | K20: 総経費 | L20: =SUM(L21:L27) -> 361049 | M20: =SUM(M21:M27) -> 338825 | N20: =SUM(N21:N27) -> 372044 | O20: =SUM(O21:O27) -> 391065 | P20: =SUM(P21:P27) -> 324284 | Q20: =SUM(Q21:Q27) -> 327393 | R20: =SUM(R21:R27) -> 375229 | S20: =SUM(S21:S27) -> 325982 | ... W20: =SUM(W21:W27) -> 361049 | X20: =SUM(L20:W20) -> 4174172
A21: =+A20 -> 2023018 | K21: 賃金 | L21: 313280 | M21: 284567 | N21: 316600 | O21: 336684 | P21: 271017 | Q21: 275164 | R21: 321664 | S21: 275448 | T21: 313759 | U21: 259173 | V21: 269817 | W21: 313280 | X21: =SUM(L21:W21) -> 3550453
A22: =+A21 -> 2023018 | K22: 交通費その他 | X22: =SUM(L22:W22) -> 0
A23: =+A22 -> 2023018 | K23: 通勤定期代 | L23: 0 | M23: 6720 | N23: 7560 | O23: 6300 | P23: 5880 | Q23: 7560 | R23: 8400 | S23: 5880 | T23: 6720 | U23: 6300 | V23: 7140 | W23: 0 | X23: =SUM(L23:W23) -> 68460
A24: =+A23 -> 2023018 | K24: 健康保険 | L24: 15200 | M24: 15200 | N24: 15200 | O24: 15200 | P24: 15200 | Q24: 14250 | R24: 14250 | S24: 14250 | T24: 14250 | U24: 14250 | V24: 14250 | W24: 15200 | X24: =SUM(L24:W24) -> 176700
A25: =+A24 -> 2023018 | K25: 厚生年金 | L25: 29280 | M25: 29280 | N25: 29280 | O25: 29280 | P25: 29280 | Q25: 27450 | R25: 27450 | S25: 27450 | T25: 27450 | U25: 27450 | V25: 27450 | W25: 29280 | X25: =SUM(L25:W25) -> 340380
A26: =+A25 -> 2023018 | K26: 労災保険 | L26: 1566 | M26: 1456 | N26: 1621 | O26: 1715 | P26: 1384 | Q26: 1414 | R26: 1650 | S26: 1407 | T26: 1602 | U26: 1327 | V26: 1472 | W26: 1566 | X26: =SUM(L26:W26) -> 18180
A27: =+A26 -> 2023018 | K27: 雇用保険 | L27: 1723 | M27: 1602 | N27: 1783 | O27: 1886 | P27: 1523 | Q27: 1555 | R27: 1815 | S27: 1547 | T27: 1763 | U27: 1460 | V27: 1619 | W27: 1723 | X27: =SUM(L27:W27) -> 19999
A28: =+A27 -> 2023018 | K28: 粗利 | L28: =L17-L20 -> 87651 | M28: =M17-M20 -> 82225 | N28: =N17-N20 -> 71756 | O28: =O17-O20 -> 69885 | P28: =P17-P20 -> 30616 | Q28: =Q17-Q20 -> 65657 | R28: =R17-R20 -> 64021 | S28: =S17-S20 -> 25068 | ... X28: =X17-X20 -> 696778
A29: 2017037 | C29: =C17+1 -> 3 | D29: 派遣 | E29: 転出 | G29: サービスプロバイダ営業本部サービスプロバイダ第二営業部 | I29: 本社営業 | J29: 社員 | K29: 総受注金額 | L29: =L30+L31 -> 476000 | M29: =M30+M31 -> 451500 | N29: =N30+N31 -> 517650 | O29: =O30+O31 -> 511350 | P29: =P30+P31 -> 473200 | Q29: =Q30+Q31 -> 439600 | R29: =R30+R31 -> 490700 | S29: =S30+S31 -> 344750 | T29: 0 | U29: 0 | V29: 0 | W29: 0 | X29: =SUM(L29:W29) -> 3704750
A30: =+A29 -> 2017037 | K30: 派遣金額 | L30: 476000 | M30: 451500 | N30: 517650 | O30: 511350 | P30: 473200 | Q30: 439600 | R30: 490700 | S30: 344750 | X30: =SUM(L30:W30) -> 3704750
A31: =+A30 -> 2017037 | K31: 交通費 | X31: =SUM(L31:W31) -> 0
A32: =+A31 -> 2017037 | K32: 総経費 | L32: =SUM(L33:L39) -> 391803 | M32: =SUM(M33:M39) -> 378121 | N32: =SUM(N33:N39) -> 409837 | O32: =SUM(O33:O39) -> 406460 | P32: =SUM(P33:P39) -> 374789 | Q32: =SUM(Q33:Q39) -> 358626 | R32: =SUM(R33:R39) -> 382696 | S32: =SUM(S33:S39) -> 334100 | T32: 0 | U32: 0 | V32: 0 | W32: =SUM(W33:W39) -> 0 | X32: =SUM(L32:W32) -> 3036432
A33: =+A32 -> 2017037 | K33: 賃金 | L33: 329163 | M33: 319163 | N33: 350550 | O33: 354288 | P33: 324125 | Q33: 306950 | R33: 331950 | S33: 281500 | X33: =SUM(L33:W33) -> 2597689
A34: =+A33 -> 2017037 | K34: 交通費その他 | X34: =SUM(L34:W34) -> 0
A35: =+A34 -> 2017037 | K35: 通勤定期代 | L35: 11800 | M35: 8260 | N35: 8260 | O35: 1180 | P35: 0 | Q35: 1180 | R35: 0 | S35: 2360 | X35: =SUM(L35:W35) -> 33040
A36: =+A35 -> 2017037 | K36: 健康保険 | L36: 16150 | M36: 16150 | N36: 16150 | O36: 16150 | P36: 16150 | Q36: 16150 | R36: 16150 | S36: 16150 | X36: =SUM(L36:W36) -> 129200
A37: =+A36 -> 2017037 | K37: 厚生年金 | L37: 31110 | M37: 31110 | N37: 31110 | O37: 31110 | P37: 31110 | Q37: 31110 | R37: 31110 | S37: 31110 | X37: =SUM(L37:W37) -> 248880
A38: =+A37 -> 2017037 | K38: 労災保険 | L38: 1705 | M38: 1637 | N38: 1794 | O38: 1777 | P38: 1621 | Q38: 1541 | R38: 1660 | S38: 1419 | X38: =SUM(L38:W38) -> 13154
A39: =+A38 -> 2017037 | K39: 雇用保険 | L39: 1875 | M39: 1801 | N39: 1973 | O39: 1955 | P39: 1783 | Q39: 1695 | R39: 1826 | S39: 1561 | X39: =SUM(L39:W39) -> 14469
A40: =+A39 -> 2017037 | K40: 粗利 | L40: =L29-L32 -> 84197 | M40: =M29-M32 -> 73379 | N40: =N29-N32 -> 107813 | O40: =O29-O32 -> 104890 | P40: =P29-P32 -> 98411 | Q40: =Q29-Q32 -> 80974 | R40: =R29-R32 -> 108004 | S40: =S29-S32 -> 10650 | ... X40: =X29-X32 -> 668318
A41: 2016012 | C41: =C29+1 -> 4 | D41: 派遣 | G41: サービスプロバイダ営業本部サービスプロバイダ第二営業部 | I41: 本社営業 | J41: 社員 | K41: 総受注金額 | L41: =L42+L43 -> 597200 | M41: =M42+M43 -> 568530 | N41: =N42+N43 -> 600300 | O41: =O42+O43 -> 565000 | P41: =P42+P43 -> 565000 | Q41: =Q42+Q43 -> 580885 | R41: =R42+R43 -> 783860 | S41: =S42+S43 -> 582650 | ... W41: =W42+W43 -> 597200 | X41: =SUM(L41:W41) -> 7292710
A42: =+A41 -> 2016012 | K42: 派遣金額 | L42: 597200 | M42: 568530 | N42: 600300 | O42: 565000 | P42: 565000 | Q42: 580885 | R42: 783860 | S42: 582650 | T42: 660310 | U42: 626775 | V42: 565000 | W42: 597200 | X42: =SUM(L42:W42) -> 7292710
A43: =+A42 -> 2016012 | K43: 交通費 | X43: =SUM(L43:W43) -> 0
A44: =+A43 -> 2016012 | K44: 総経費 | L44: =SUM(L45:L51) -> 516375 | M44: =SUM(M45:M51) -> 491590 | N44: =SUM(N45:N51) -> 487205 | O44: =SUM(O45:O51) -> 509546 | P44: =SUM(P45:P51) -> 480638 | Q44: =SUM(Q45:Q51) -> 514272 | R44: =SUM(R45:R51) -> 610877 | S44: =SUM(S45:S51) -> 495545 | ... W44: =SUM(W45:W51) -> 516375 | X44: =SUM(L44:W44) -> 6145962
A45: =+A44 -> 2016012 | K45: 賃金 | L45: 441250 | M45: 418200 | N45: 417700 | O45: 437150 | P45: 411200 | Q45: 423700 | R45: 532659 | S45: 418900 | T45: 489450 | U45: 427200 | V45: 375950 | W45: 441250 | X45: =SUM(L45:W45) -> 5234609
A46: =+A45 -> 2016012 | K46: 交通費その他 | X46: =SUM(L46:W46) -> 0
A47: =+A46 -> 2016012 | K47: 通勤定期代 | L47: 5316 | M47: 3879 | N47: 0 | O47: 2658 | P47: 0 | Q47: 16391 | R47: 3034 | S47: 2658 | T47: 2215 | U47: 2658 | V47: 3544 | W47: 5316 | X47: =SUM(L47:W47) -> 47669
A48: =+A47 -> 2016012 | K48: 健康保険 | L48: 24860 | M48: 24860 | N48: 24860 | O48: 24860 | P48: 24860 | Q48: 26555 | R48: 26555 | S48: 26555 | T48: 26555 | U48: 26555 | V48: 26555 | W48: 24860 | X48: =SUM(L48:W48) -> 308490
A49: =+A48 -> 2016012 | K49: 厚生年金 | L49: 40260 | M49: 40260 | N49: 40260 | O49: 40260 | P49: 40260 | Q49: 43005 | R49: 43005 | S49: 43005 | T49: 43005 | U49: 43005 | V49: 43005 | W49: 40260 | X49: =SUM(L49:W49) -> 499590
A50: =+A49 -> 2016012 | K50: 労災保険 | L50: 2233 | M50: 2091 | N50: 2088 | O50: 2199 | P50: 2056 | Q50: 2200 | R50: 2678 | S50: 2108 | T50: 2458 | U50: 2149 | V50: 1984 | W50: 2233 | X50: =SUM(L50:W50) -> 26477
A51: =+A50 -> 2016012 | K51: 雇用保険 | L51: 2456 | M51: 2300 | N51: 2297 | O51: 2419 | P51: 2262 | Q51: 2421 | R51: 2946 | S51: 2319 | T51: 2704 | U51: 2364 | V51: 2183 | W51: 2456 | X51: =SUM(L51:W51) -> 29127
A52: =+A51 -> 2016012 | K52: 粗利 | L52: =L41-L44 -> 80825 | M52: =M41-M44 -> 76940 | N52: =N41-N44 -> 113095 | O52: =O41-O44 -> 55454 | P52: =P41-P44 -> 84362 | Q52: =Q41-Q44 -> 66613 | R52: =R41-R44 -> 172983 | S52: =S41-S44 -> 87105 | ... X52: =X41-X44 -> 1146748
A53: 2018043 | C53: =C41+1 -> 5 | D53: 派遣 | G53: エンタープライズ営業本部エンタープライズ第二営業部 | I53: 本社営業 | J53: 社員 | K53: 総受注金額 | L53: =L54+L55 -> 576675 | M53: =M54+M55 -> 505312 | N53: =N54+N55 -> 553986 | O53: =O54+O55 -> 667425 | P53: =P54+P55 -> 573786 | Q53: =Q54+Q55 -> 574612 | R53: =R54+R55 -> 669900 | S53: =S54+S55 -> 485512 | ... W53: =W54+W55 -> 576675 | X53: =SUM(L53:W53) -> 6783967
A54: =+A53 -> 2018043 | K54: 派遣金額 | L54: 576675 | M54: 505312 | N54: 553986 | O54: 667425 | P54: 573786 | Q54: 574612 | R54: 669900 | S54: 485512 | T54: 566362 | U54: 492936 | V54: 540786 | W54: 576675 | X54: =SUM(L54:W54) -> 6783967
A55: =+A54 -> 2018043 | K55: 交通費 | X55: =SUM(L55:W55) -> 0
A56: =+A55 -> 2018043 | K56: 総経費 | L56: =SUM(L57:L63) -> 449278 | M56: =SUM(M57:M63) -> 403646 | N56: =SUM(N57:N63) -> 469526 | O56: =SUM(O57:O63) -> 516577 | P56: =SUM(P57:P63) -> 459995 | Q56: =SUM(Q57:Q63) -> 467223 | R56: =SUM(R57:R63) -> 531181 | S56: =SUM(S57:S63) -> 428147 | ... W56: =SUM(W57:W63) -> 449278 | X56: =SUM(L56:W56) -> 5545121
A57: =+A56 -> 2018043 | K57: 賃金 | L57: 390450 | M57: 344363 | N57: 406775 | O57: 453338 | P57: 399200 | Q57: 407313 | R57: 468750 | S57: 363075 | T57: 430438 | U57: 379563 | V57: 377900 | W57: 390450 | X57: =SUM(L57:W57) -> 4811615
A58: =+A57 -> 2018043 | K58: 交通費その他 | X58: =SUM(L58:W58) -> 0
A59: =+A58 -> 2018043 | K59: 通勤定期代 | L59: 4640 | M59: 5568 | N59: 8352 | O59: 8352 | P59: 6496 | Q59: 2784 | R59: 4640 | S59: 8352 | T59: 928 | U59: 4640 | V59: 5568 | W59: 4640 | X59: =SUM(L59:W59) -> 64960
A60: =+A59 -> 2018043 | K60: 健康保険 | L60: 17100 | M60: 17100 | N60: 17100 | O60: 17100 | P60: 17100 | Q60: 18050 | R60: 18050 | S60: 18050 | T60: 18050 | U60: 18050 | V60: 18050 | W60: 17100 | X60: =SUM(L60:W60) -> 210900
A61: =+A60 -> 2018043 | K61: 厚生年金 | L61: 32940 | M61: 32940 | N61: 32940 | O61: 32940 | P61: 32940 | Q61: 34770 | R61: 34770 | S61: 34770 | T61: 34770 | U61: 34770 | V61: 34770 | W61: 32940 | X61: =SUM(L61:W61) -> 406260
A62: =+A61 -> 2018043 | K62: 労災保険 | L62: 1975 | M62: 1750 | N62: 2076 | O62: 2308 | P62: 2028 | Q62: 2050 | R62: 2367 | S62: 1857 | T62: 2157 | U62: 1921 | V62: 2004 | W62: 1975 | X62: =SUM(L62:W62) -> 24468
A63: =+A62 -> 2018043 | K63: 雇用保険 | L63: 2173 | M63: 1925 | N63: 2283 | O63: 2539 | P63: 2231 | Q63: 2256 | R63: 2604 | S63: 2043 | T63: 2373 | U63: 2113 | V63: 2205 | W63: 2173 | X63: =SUM(L63:W63) -> 26918
A64: =+A63 -> 2018043 | K64: 粗利 | L64: =L53-L56 -> 127397 | M64: =M53-M56 -> 101666 | N64: =N53-N56 -> 84460 | O64: =O53-O56 -> 150848 | P64: =P53-P56 -> 113791 | Q64: =Q53-Q56 -> 107389 | R64: =R53-R56 -> 138719 | S64: =S53-S56 -> 57365 | ... X64: =X53-X56 -> 1238846
A65: 2025014 | C65: 6 | D65: 派遣 | G65: サービスプロバイダ営業本部サービスプロバイダ第二営業部 | I65: 本社営業 | J65: 社員 | K65: 総受注金額 | L65: =L66+L67 -> 0 | M65: =M66+M67 -> 0 | N65: =N66+N67 -> 0 | O65: =O66+O67 -> 0 | P65: =P66+P67 -> 0 | Q65: =Q66+Q67 -> 210000 | R65: =R66+R67 -> 462000 | S65: =S66+S67 -> 357000 | ... W65: =W66+W67 -> 450000 | X65: =SUM(L65:W65) -> 2663400
A66: =+A65 -> 2025014 | K66: 派遣金額 | Q66: 210000 | R66: 462000 | S66: 357000 | T66: 420000 | U66: 386400 | V66: 378000 | W66: 450000 | X66: =SUM(L66:W66) -> 2663400
A67: =+A66 -> 2025014 | K67: 交通費 | X67: =SUM(L67:W67) -> 0
A68: =+A67 -> 2025014 | K68: 総経費 | L68: =SUM(L69:L75) -> 0 | M68: =SUM(M69:M75) -> 0 | N68: =SUM(N69:N75) -> 0 | O68: =SUM(O69:O75) -> 0 | P68: =SUM(P69:P75) -> 0 | Q68: =SUM(Q69:Q75) -> 148490.5 | R68: =SUM(R69:R75) -> 296981 | S68: =SUM(S69:S75) -> 296981 | ... W68: =SUM(W69:W75) -> 298130 | X68: =SUM(L68:W68) -> 1990839.5
A69: =+A68 -> 2025014 | K69: 賃金 | Q69: =250000/2 -> 125000 | R69: 250000 | S69: 250000 | T69: 270000 | U69: 270400 | V69: 264160 | W69: 248000 | X69: =SUM(L69:W69) -> 1677560
A70: =+A69 -> 2025014 | K70: 交通費その他 | X70: =SUM(L70:W70) -> 0
A71: =+A70 -> 2025014 | K71: 通勤定期代 | Q71: =8130/2 -> 4065 | R71: 8130 | S71: 8130 | T71: 9450 | U71: 9450 | V71: 9450 | W71: 10000 | X71: =SUM(L71:W71) -> 58675
A72: =+A71 -> 2025014 | K72: 健康保険 | Q72: =12350/2 -> 6175 | R72: 12350 | S72: 12350 | T72: 12350 | U72: 12350 | V72: 12350 | W72: 11900 | X72: =SUM(L72:W72) -> 79825
A73: =+A72 -> 2025014 | K73: 厚生年金 | Q73: =23790/2 -> 11895 | R73: 23790 | S73: 23790 | T73: 23790 | U73: 23790 | V73: 23790 | W73: 25620 | X73: =SUM(L73:W73) -> 156465
A74: =+A73 -> 2025014 | K74: 労災保険 | Q74: =1291/2 -> 645.5 | R74: 1291 | S74: 1291 | T74: 1397 | U74: 1399 | V74: 1455 | W74: 870 | X74: =SUM(L74:W74) -> 8348.5
A75: =+A74 -> 2025014 | K75: 雇用保険 | Q75: =1420/2 -> 710 | R75: 1420 | S75: 1420 | T75: 1537 | U75: 1539 | V75: 1600 | W75: 1740 | X75: =SUM(L75:W75) -> 9966
A76: =+A75 -> 2025014 | K76: 粗利 | L76: =L65-L68 -> 0 | M76: =M65-M68 -> 0 | N76: =N65-N68 -> 0 | O76: =O65-O68 -> 0 | P76: =P65-P68 -> 0 | Q76: =Q65-Q68 -> 61509.5 | R76: =R65-R68 -> 165019 | S76: =S65-S68 -> 60019 | ... X76: =X65-X68 -> 672560.5
A77: 2023033 | C77: 7 | D77: 派遣 | G77: サービスプロバイダ営業本部サービスプロバイダ第二営業部 | I77: 本社営業 | J77: 社員 | K77: 総受注金額 | L77: =L78+L79 -> 0 | M77: =M78+M79 -> 0 | N77: =N78+N79 -> 0 | O77: =O78+O79 -> 0 | P77: =P78+P79 -> 0 | Q77: 0 | R77: =R78+R79 -> 0 | S77: =S78+S79 -> 282800 | T77: =T78+T79 -> 400400 | U77: =U78+U79 -> 357000 | V77: =V78+V79 -> 357000 | W77: =W78+W79 -> 420000 | X77: =SUM(L77:W77) -> 1817200
A78: =+A77 -> 2023033 | B78: =+B77 -> 0 | K78: 派遣金額 | S78: 282800 | T78: 400400 | U78: 357000 | V78: 357000 | W78: 420000 | X78: =SUM(L78:W78) -> 1817200
A79: =+A78 -> 2023033 | B79: =+B78 -> 0 | K79: 交通費 | X79: =SUM(L79:W79) -> 0
A80: =+A79 -> 2023033 | B80: =+B79 -> 0 | K80: 総経費 | L80: =SUM(L81:L87) -> 0 | M80: =SUM(M81:M87) -> 0 | N80: =SUM(N81:N87) -> 0 | O80: =SUM(O81:O87) -> 0 | P80: =SUM(P81:P87) -> 0 | Q80: 0 | R80: 0 | S80: =SUM(S81:S87) -> 236175.33 | T80: =SUM(T81:T87) -> 300629 | U80: =SUM(U81:U87) -> 300629 | V80: =SUM(V81:V87) -> 302176 | W80: =SUM(W81:W87) -> 300237 | X80: =SUM(L80:W80) -> 1439846.3
A81: =+A80 -> 2023033 | B81: =+B80 -> 0 | K81: 賃金 | S81: =245000/18*14 -> 190555.56 | T81: 245000 | U81: 245000 | V81: 246351 | W81: 245000 | X81: =SUM(L81:W81) -> 1171906.6
A82: =+A81 -> 2023033 | B82: =+B81 -> 0 | K82: 交通費その他 | X82: =SUM(L82:W82) -> 0
A83: =+A82 -> 2023033 | B83: =+B82 -> 0 | K83: 通勤定期代 | S83: =19734/18*14 -> 15348.667 | T83: 16740 | U83: 16740 | V83: 16740 | W83: 16740 | X83: =SUM(L83:W83) -> 82308.667
A84: =+A83 -> 2023033 | B84: =+B83 -> 0 | K84: 健康保険 | S84: =12350/18*14 -> 9605.5556 | T84: 12350 | U84: 12350 | V84: 12350 | W84: 12350 | X84: =SUM(L84:W84) -> 59005.556
A85: =+A84 -> 2023033 | B85: =+B84 -> 0 | K85: 厚生年金 | S85: =23790/18*14 -> 18503.333 | T85: 23790 | U85: 23790 | V85: 23790 | W85: 23790 | X85: =SUM(L85:W85) -> 113663.33
A86: =+A85 -> 2023033 | B86: =+B85 -> 0 | K86: 労災保険 | S86: =1324/18*14 -> 1029.7778 | T86: 1309 | U86: 1309 | V86: 1402 | W86: 786 | X86: =SUM(L86:W86) -> 5835.7778
A87: =+A86 -> 2023033 | B87: =+B86 -> 0 | K87: 雇用保険 | S87: =1456/18*14 -> 1132.4444 | T87: 1440 | U87: 1440 | V87: 1543 | W87: 1571 | X87: =SUM(L87:W87) -> 7126.4444
A88: =+A87 -> 2023033 | B88: =+B87 -> 0 | K88: 粗利 | L88: =L77-L80 -> 0 | M88: =M77-M80 -> 0 | N88: =N77-N80 -> 0 | O88: =O77-O80 -> 0 | P88: =P77-P80 -> 0 | Q88: =Q77-Q80 -> 0 | R88: =R77-R80 -> 0 | S88: =S77-S80 -> 46624.667 | ... X88: =X77-X80 -> 377353.67
C89: =C2 -> UAL本社営業本部 | K89: 売上 | L89: =L5+L17+L29+L41+L53+L65+L77 -> 2549025 | M89: =M5+M17+M29+M41+M53+M65+M77 -> 2359392 | N89: =N5+N17+N29+N41+N53+N65+N77 -> 2554986 | O89: =O5+O17+O29+O41+O53+O65+O77 -> 2686325 | P89: =P5+P17+P29+P41+P53+P65+P77 -> 2331236 | Q89: =Q5+Q17+Q29+Q41+Q53+Q65+Q77 -> 2606247 | R89: =R5+R17+R29+R41+R53+R65+R77 -> 3284610 | S89: =S5+S17+S29+S41+S53+S65+S77 -> 2793312 | ... W89: =W5+W17+W29+W41+W53+W65+W77 -> 2943025 | X89: =SUM(L89:W89) -> 32055727
K90: 仕入 | L90: =L8+L20+L32+L44+L56+L68+L80 -> 2082365 | M90: =M8+M20+M32+M44+M56+M68+M80 -> 1950886 | N90: =N8+N20+N32+N44+N56+N68+N80 -> 2112324 | O90: =O8+O20+O32+O44+O56+O68+O80 -> 2215362 | P90: =P8+P20+P32+P44+P56+P68+P80 -> 1995210 | Q90: =Q8+Q20+Q32+Q44+Q56+Q68+Q80 -> 2157501.5 | R90: =R8+R20+R32+R44+R56+R68+R80 -> 2572616 | S90: =S8+S20+S32+S44+S56+S68+S80 -> 2446945.3 | ... W90: =W8+W20+W32+W44+W56+W68+W80 -> 2288929 | X90: =SUM(L90:W90) -> 26549033
K91: 粗利 | L91: =L89-L90 -> 466660 | M91: =M89-M90 -> 408506 | N91: =N89-N90 -> 442662 | O91: =O89-O90 -> 470963 | P91: =P89-P90 -> 336026 | Q91: =Q89-Q90 -> 448745.5 | R91: =R89-R90 -> 711994 | S91: =S89-S90 -> 346366.67 | ... W91: =W89-W90 -> 654096 | X91: =SUM(L91:W91) -> 5506694.2
K92: Q売上 | L92: =SUM(L89:N89) -> 7463403 | O92: =SUM(O89:Q89) -> 7623808 | R92: =SUM(R89:T89) -> 8795244 | U92: =SUM(U89:W89) -> 8173272 | X92: =X89 -> 32055727
K93: Q仕入 | L93: =SUM(L90:N90) -> 6145575 | O93: =SUM(O90:Q90) -> 6368073.5 | R93: =SUM(R90:T90) -> 7412276.3 | U93: =SUM(U90:W90) -> 6623108 | X93: =X90 -> 26549033
K94: Q粗利 | L94: =SUM(L91:N91) -> 1317828 | O94: =SUM(O91:Q91) -> 1255734.5 | R94: =SUM(R91:T91) -> 1382967.7 | U94: =SUM(U91:W91) -> 1550164 | X94: =X91 -> 5506694.2
G106: =COUNTA(F5:F64) -> 0

Sheet パートナー営業本部
A1: 社員番号 | B1: 氏名 | C1: No | D1: 派遣/請負 | E1: 担当 | F1: 氏名 | G1: 派遣先部署 | H1: 作業名 | I1: 契約先 | J1: 外注会社 | K1: 売上単価 (支払単価） 【≒粗利】 | L1: 4月 | M1: 5月 | N1: 6月 | O1: 7月 | P1: 8月 | Q1: 9月 | R1: 10月 | S1: 11月 | T1: 12月 | U1: 1月 | V1: 2月 | W1: 3月 | X1: 合計
C2: パートナー営業本部 | K2: 売上 | L2: =L53 -> 1855900 | M2: =M53 -> 1858000 | N2: =N53 -> 1865700 | O2: =O53 -> 1967800 | P2: =P53 -> 1750000 | Q2: =Q53 -> 1915300 | R2: =R53 -> 1958200 | S2: =S53 -> 1573900 | ... W2: =W53 -> 1855900 | X2: =SUM(L2:W2) -> 21767880
K3: 仕入 | L3: =L54 -> 1391699 | M3: =M54 -> 1394797 | N3: =N54 -> 1402483 | O3: =O54 -> 1466639 | P3: =P54 -> 1364900 | Q3: =Q54 -> 1435484 | R3: =R54 -> 1480269 | S3: =S54 -> 1289606 | ... W3: =W54 -> 1391699 | X3: =SUM(L3:W3) -> 16653242
K4: 粗利 | L4: =L55 -> 464201 | M4: =M55 -> 463203 | N4: =N55 -> 463217 | O4: =O55 -> 501161 | P4: =P55 -> 385100 | Q4: =Q55 -> 479816 | R4: =R55 -> 477931 | S4: =S55 -> 284294 | ... W4: =W55 -> 464201 | X4: =SUM(L4:W4) -> 5114638
A5: 2024038 | C5: 1 | D5: 派遣 | G5: パートナー営業本部第三営業部 | H5: 週３勤務 | J5: 社員 | K5: 総受注金額 | L5: =L6+L7 -> 354900 | M5: =M6+M7 -> 382200 | N5: =N6+N7 -> 359100 | O5: =O6+O7 -> 352800 | P5: =P6+P7 -> 289800 | Q5: =Q6+Q7 -> 359100 | R5: =R6+R7 -> 378000 | S5: =S6+S7 -> 327600 | ... W5: =W6+W7 -> 354900 | X5: =SUM(L5:W5) -> 4109700
A6: =+A5 -> 2024038 | K6: 派遣金額 | L6: 354900 | M6: 382200 | N6: 359100 | O6: 352800 | P6: 289800 | Q6: 359100 | R6: 378000 | S6: 327600 | T6: 327600 | U6: 327600 | V6: 296100 | W6: 354900 | X6: =SUM(L6:W6) -> 4109700
A7: =+A6 -> 2024038 | X7: =SUM(L7:W7) -> 0
A8: =+A7 -> 2024038 | K8: 総経費 | L8: =SUM(L9:L15) -> 261142 | M8: =SUM(M9:M15) -> 282373 | N8: =SUM(N9:N15) -> 266305 | O8: =SUM(O9:O15) -> 261782 | P8: =SUM(P9:P15) -> 259660 | Q8: =SUM(Q9:Q15) -> 265646 | R8: =SUM(R9:R15) -> 278699 | S8: =SUM(S9:S15) -> 242631 | ... W8: =SUM(W9:W15) -> 261142 | X8: =SUM(L8:W8) -> 3128655
A9: =+A8 -> 2024038 | K9: 賃金 | L9: 256675 | M9: 277800 | N9: 259700 | O9: 255200 | P9: 255200 | Q9: 260100 | R9: 275200 | S9: 237200 | T9: 259700 | U9: 238000 | V9: 237200 | W9: 256675 | X9: =SUM(L9:W9) -> 3068650
A10: =+A9 -> 2024038 | K10: 紹介費用 | X10: =SUM(L10:W10) -> 0
A11: =+A10 -> 2024038 | K11: 通勤定期代 | L11: 3168 | M11: 3168 | N11: 5280 | O11: 5280 | P11: 3168 | Q11: 4224 | R11: 2112 | S11: 4224 | T11: 4224 | U11: 2112 | V11: 4224 | W11: 3168 | X11: =SUM(L11:W11) -> 44352
A12: =+A11 -> 2024038 | K12: 健康保険 | X12: =SUM(L12:W12) -> 0
A13: =+A12 -> 2024038 | K13: 厚生年金 | X13: =SUM(L13:W13) -> 0
A14: =+A13 -> 2024038 | K14: 労災保険 | L14: 1299 | M14: 1405 | N14: 1325 | O14: 1302 | P14: 1292 | Q14: 1322 | R14: 1387 | S14: 1207 | T14: 1320 | U14: 1201 | V14: 1294 | W14: 1299 | X14: =SUM(L14:W14) -> 15653
A15: =+A14 -> 2024038 | K15: 雇用保険 | X15: =SUM(L15:W15) -> 0
A16: =+A15 -> 2024038 | K16: 粗利 | L16: =L5-L8 -> 93758 | M16: =M5-M8 -> 99827 | N16: =N5-N8 -> 92795 | O16: =O5-O8 -> 91018 | P16: =P5-P8 -> 30140 | Q16: =Q5-Q8 -> 93454 | R16: =R5-R8 -> 99301 | S16: =S5-S8 -> 84969 | ... X16: =X5-X8 -> 981045
A17: 2023028 | C17: =C5+1 -> 2 | D17: 派遣 | G17: パートナー営業本部第三営業部 | H17: 内勤営業 | J17: 社員 | K17: 総受注金額 | L17: =L18+L19 -> 445000 | M17: =M18+M19 -> 445000 | N17: =N18+N19 -> 445000 | O17: =O18+O19 -> 445000 | P17: =P18+P19 -> 445000 | Q17: =Q18+Q19 -> 445000 | R17: =R18+R19 -> 445000 | S17: =S18+S19 -> 431100 | ... W17: =W18+W19 -> 445000 | X17: =SUM(L17:W17) -> 5314980
A18: =+A17 -> 2023028 | K18: 派遣金額 | L18: 445000 | M18: 445000 | N18: 445000 | O18: 445000 | P18: 445000 | Q18: 445000 | R18: 445000 | S18: 431100 | T18: 445000 | U18: 445000 | V18: 433880 | W18: 445000 | X18: =SUM(L18:W18) -> 5314980
A19: =+A18 -> 2023028 | X19: =SUM(L19:W19) -> 0
A20: =+A19 -> 2023028 | K20: 総経費 | L20: =SUM(L21:L27) -> 300281 | M20: =SUM(M21:M27) -> 299876 | N20: =SUM(N21:N27) -> 300281 | O20: =SUM(O21:O27) -> 297993 | P20: =SUM(P21:P27) -> 298732 | Q20: =SUM(Q21:Q27) -> 299876 | R20: =SUM(R21:R27) -> 298651 | S20: =SUM(S21:S27) -> 298328 | ... W20: =SUM(W21:W27) -> 300281 | X20: =SUM(L20:W20) -> 3589767
A21: =+A20 -> 2023028 | K21: 賃金 | L21: 256800 | M21: 256400 | N21: 256800 | O21: 257600 | P21: 256800 | Q21: 256400 | R21: 257200 | S21: 256400 | T21: 256400 | U21: 256400 | V21: 253634 | W21: 256800 | X21: =SUM(L21:W21) -> 3077634
A22: =+A21 -> 2023028 | K22: 紹介費用 | X22: =SUM(L22:W22) -> 0
A23: =+A22 -> 2023028 | K23: 通勤定期代 | L23: 4596 | M23: 4596 | N23: 4596 | O23: 1532 | P23: 3064 | Q23: 4596 | R23: 2583 | S23: 3064 | T23: 4596 | U23: 3064 | V23: 4596 | W23: 4596 | X23: =SUM(L23:W23) -> 45479
A24: =+A23 -> 2023028 | K24: 健康保険 | L24: 12350 | M24: 12350 | N24: 12350 | O24: 12350 | P24: 12350 | Q24: 12350 | R24: 12350 | S24: 12350 | T24: 12350 | U24: 12350 | V24: 12350 | W24: 12350 | X24: =SUM(L24:W24) -> 148200
A25: =+A24 -> 2023028 | K25: 厚生年金 | L25: 23790 | M25: 23790 | N25: 23790 | O25: 23790 | P25: 23790 | Q25: 23790 | R25: 23790 | S25: 23790 | T25: 23790 | U25: 23790 | V25: 23790 | W25: 23790 | X25: =SUM(L25:W25) -> 285480
A26: =+A25 -> 2023028 | K26: 労災保険 | L26: 1307 | M26: 1305 | N26: 1307 | O26: 1296 | P26: 1299 | Q26: 1305 | R26: 1299 | S26: 1297 | T26: 1305 | U26: 1297 | V26: 1378 | W26: 1307 | X26: =SUM(L26:W26) -> 15702
A27: =+A26 -> 2023028 | K27: 雇用保険 | L27: 1438 | M27: 1435 | N27: 1438 | O27: 1425 | P27: 1429 | Q27: 1435 | R27: 1429 | S27: 1427 | T27: 1435 | U27: 1427 | V27: 1516 | W27: 1438 | X27: =SUM(L27:W27) -> 17272
A28: =+A27 -> 2023028 | K28: 粗利 | L28: =L17-L20 -> 144719 | M28: =M17-M20 -> 145124 | N28: =N17-N20 -> 144719 | O28: =O17-O20 -> 147007 | P28: =P17-P20 -> 146268 | Q28: =Q17-Q20 -> 145124 | R28: =R17-R20 -> 146349 | S28: =S17-S20 -> 132772 | ... X28: =X17-X20 -> 1725213
A29: 2018015 | C29: =C17+1 -> 3 | D29: 派遣 | G29: パートナー営業本部第三営業部 | J29: 社員 | K29: 総受注金額 | L29: =L30+L31 -> 552000 | M29: =M30+M31 -> 537600 | N29: =N30+N31 -> 556000 | O29: =O30+O31 -> 624000 | P29: =P30+P31 -> 518400 | Q29: =Q30+Q31 -> 603200 | R29: =R30+R31 -> 629600 | S29: =S30+S31 -> 383200 | ... W29: =W30+W31 -> 552000 | X29: =SUM(L29:W29) -> 6524800
A30: =+A29 -> 2018015 | K30: 派遣金額 | L30: 552000 | M30: 537600 | N30: 556000 | O30: 624000 | P30: 518400 | Q30: 603200 | R30: 629600 | S30: 383200 | T30: 545600 | U30: 494400 | V30: 528800 | W30: 552000 | X30: =SUM(L30:W30) -> 6524800
A31: =+A30 -> 2018015 | X31: =SUM(L31:W31) -> 0
A32: =+A31 -> 2018015 | K32: 総経費 | L32: =SUM(L33:L39) -> 410462 | M32: =SUM(M33:M39) -> 400879 | N32: =SUM(N33:N39) -> 414937 | O32: =SUM(O33:O39) -> 456942 | P32: =SUM(P33:P39) -> 392258 | Q32: =SUM(Q33:Q39) -> 448087 | R32: =SUM(R33:R39) -> 465901 | S32: =SUM(S33:S39) -> 380445 | ... W32: =SUM(W33:W39) -> 410462 | X32: =SUM(L32:W32) -> 4981334
A33: =+A32 -> 2018015 | K33: 賃金 | L33: 358700 | M33: 348720 | N33: 359650 | O33: 404200 | P33: 335680 | Q33: 388940 | R33: 406570 | S33: 323990 | T33: 369920 | U33: 319580 | V33: 342310 | W33: 358700 | X33: =SUM(L33:W33) -> 4316960
A34: =+A33 -> 2018015 | K34: 紹介費用 | X34: =SUM(L34:W34) -> 0
A35: =+A34 -> 2018015 | K35: 通勤定期代 | L35: 3479 | M35: 3976 | N35: 6958 | O35: 3976 | P35: 2982 | Q35: 4970 | R35: 4970 | S35: 2982 | T35: 1988 | U35: 3976 | V35: 1988 | W35: 3479 | X35: =SUM(L35:W35) -> 45724
A36: =+A35 -> 2018015 | K36: 健康保険 | L36: 15200 | M36: 15200 | N36: 15200 | O36: 15200 | P36: 17100 | Q36: 17100 | R36: 17100 | S36: 17100 | T36: 17100 | U36: 17100 | V36: 17100 | W36: 15200 | X36: =SUM(L36:W36) -> 195700
A37: =+A36 -> 2018015 | K37: 厚生年金 | L37: 29280 | M37: 29280 | N37: 29280 | O37: 29280 | P37: 32940 | Q37: 32940 | R37: 32940 | S37: 32940 | T37: 32940 | U37: 32940 | V37: 32940 | W37: 29280 | X37: =SUM(L37:W37) -> 376980
A38: =+A37 -> 2018015 | K38: 労災保険 | L38: 1811 | M38: 1763 | N38: 1833 | O38: 2041 | P38: 1693 | Q38: 1970 | R38: 2058 | S38: 1635 | T38: 1860 | U38: 1618 | V38: 1798 | W38: 1811 | X38: =SUM(L38:W38) -> 21891
A39: =+A38 -> 2018015 | K39: 雇用保険 | L39: 1992 | M39: 1940 | N39: 2016 | O39: 2245 | P39: 1863 | Q39: 2167 | R39: 2263 | S39: 1798 | T39: 2045 | U39: 1780 | V39: 1978 | W39: 1992 | X39: =SUM(L39:W39) -> 24079
A40: =+A39 -> 2018015 | K40: 粗利 | L40: =L29-L32 -> 141538 | M40: =M29-M32 -> 136721 | N40: =N29-N32 -> 141063 | O40: =O29-O32 -> 167058 | P40: =P29-P32 -> 126142 | Q40: =Q29-Q32 -> 155113 | R40: =R29-R32 -> 163699 | S40: =S29-S32 -> 2755 | ... X40: =X29-X32 -> 1543466
A41: 2018003 | C41: =C29+1 -> 4 | D41: 派遣 | G41: パートナー営業本部第四営業部 | J41: 社員 | K41: 総受注金額 | L41: =L42+L43 -> 504000 | M41: =M42+M43 -> 493200 | N41: =N42+N43 -> 505600 | O41: =O42+O43 -> 546000 | P41: =P42+P43 -> 496800 | Q41: =Q42+Q43 -> 508000 | R41: =R42+R43 -> 505600 | S41: =S42+S43 -> 432000 | ... W41: =W42+W43 -> 504000 | X41: =SUM(L41:W41) -> 5818400
A42: =+A41 -> 2018003 | B42: =+B41 -> 0 | K42: 派遣金額 | L42: 504000 | M42: 493200 | N42: 505600 | O42: 546000 | P42: 496800 | Q42: 508000 | R42: 505600 | S42: 432000 | T42: 457600 | U42: 433600 | V42: 432000 | W42: 504000 | X42: =SUM(L42:W42) -> 5818400
A43: =+A42 -> 2018003 | B43: =+B42 -> 0 | X43: =SUM(L43:W43) -> 0
A44: =+A43 -> 2018003 | B44: =+B43 -> 0 | K44: 総経費 | L44: =SUM(L45:L51) -> 419814 | M44: =SUM(M45:M51) -> 411669 | N44: =SUM(N45:N51) -> 420960 | O44: =SUM(O45:O51) -> 449922 | P44: =SUM(P45:P51) -> 414250 | Q44: =SUM(Q45:Q51) -> 421875 | R44: =SUM(R45:R51) -> 437018 | S44: =SUM(S45:S51) -> 368202 | ... W44: =SUM(W45:W51) -> 419814 | X44: =SUM(L44:W44) -> 4953486
A45: =+A44 -> 2018003 | B45: =+B44 -> 0 | K45: 賃金 | L45: 362725 | M45: 354665 | N45: 363860 | O45: 392520 | P45: 357219 | Q45: 364765 | R45: 379750 | S45: 311650 | T45: 373005 | U45: 334983 | V45: 311250 | W45: 362725 | X45: =SUM(L45:W45) -> 4269117
A46: =+A45 -> 2018003 | B46: =+B45 -> 0 | K46: 紹介費用 | X46: =SUM(L46:W46) -> 0
A47: =+A46 -> 2018003 | B47: =+B46 -> 0 | K47: 通勤定期代 | L47: 0 | M47: 0 | N47: 0 | O47: 0 | P47: 0 | Q47: 0 | R47: 0 | S47: 0 | T47: 0 | U47: 0 | V47: 0 | W47: 0 | X47: =SUM(L47:W47) -> 0
A48: =+A47 -> 2018003 | B48: =+B47 -> 0 | K48: 健康保険 | L48: 20340 | M48: 20340 | N48: 20340 | O48: 20340 | P48: 20340 | Q48: 20340 | R48: 20340 | S48: 20340 | T48: 20340 | U48: 20340 | V48: 20340 | W48: 20340 | X48: =SUM(L48:W48) -> 244080
A49: =+A48 -> 2018003 | B49: =+B48 -> 0 | K49: 厚生年金 | L49: 32940 | M49: 32940 | N49: 32940 | O49: 32940 | P49: 32940 | Q49: 32940 | R49: 32940 | S49: 32940 | T49: 32940 | U49: 32940 | V49: 32940 | W49: 32940 | X49: =SUM(L49:W49) -> 395280
A50: =+A49 -> 2018003 | B50: =+B49 -> 0 | K50: 労災保険 | L50: 1814 | M50: 1773 | N50: 1819 | O50: 1963 | P50: 1786 | Q50: 1824 | R50: 1899 | S50: 1558 | T50: 1865 | U50: 1675 | V50: 1643 | W50: 1814 | X50: =SUM(L50:W50) -> 21433
A51: =+A50 -> 2018003 | B51: =+B50 -> 0 | K51: 雇用保険 | L51: 1995 | M51: 1951 | N51: 2001 | O51: 2159 | P51: 1965 | Q51: 2006 | R51: 2089 | S51: 1714 | T51: 2052 | U51: 1842 | V51: 1807 | W51: 1995 | X51: =SUM(L51:W51) -> 23576
A52: =+A51 -> 2018003 | B52: =+B51 -> 0 | K52: 粗利 | L52: =L41-L44 -> 84186 | M52: =M41-M44 -> 81531 | N52: =N41-N44 -> 84640 | O52: =O41-O44 -> 96078 | P52: =P41-P44 -> 82550 | Q52: =Q41-Q44 -> 86125 | R52: =R41-R44 -> 68582 | S52: =S41-S44 -> 63798 | ... X52: =X41-X44 -> 864914
C53: =C2 -> パートナー営業本部 | K53: 売上 | L53: =L5+L17+L29+L41 -> 1855900 | M53: =M5+M17+M29+M41 -> 1858000 | N53: =N5+N17+N29+N41 -> 1865700 | O53: =O5+O17+O29+O41 -> 1967800 | P53: =P5+P17+P29+P41 -> 1750000 | Q53: =Q5+Q17+Q29+Q41 -> 1915300 | R53: =R5+R17+R29+R41 -> 1958200 | S53: =S5+S17+S29+S41 -> 1573900 | ... W53: =W5+W17+W29+W41 -> 1855900 | X53: =SUM(L53:W53) -> 21767880
K54: 仕入 | L54: =L8+L20+L32+L44 -> 1391699 | M54: =M8+M20+M32+M44 -> 1394797 | N54: =N8+N20+N32+N44 -> 1402483 | O54: =O8+O20+O32+O44 -> 1466639 | P54: =P8+P20+P32+P44 -> 1364900 | Q54: =Q8+Q20+Q32+Q44 -> 1435484 | R54: =R8+R20+R32+R44 -> 1480269 | S54: =S8+S20+S32+S44 -> 1289606 | ... W54: =W8+W20+W32+W44 -> 1391699 | X54: =SUM(L54:W54) -> 16653242
K55: 粗利 | L55: =L53-L54 -> 464201 | M55: =M53-M54 -> 463203 | N55: =N53-N54 -> 463217 | O55: =O53-O54 -> 501161 | P55: =P53-P54 -> 385100 | Q55: =Q53-Q54 -> 479816 | R55: =R53-R54 -> 477931 | S55: =S53-S54 -> 284294 | ... W55: =W53-W54 -> 464201 | X55: =SUM(L55:W55) -> 5114638
K56: Q売上 | L56: =SUM(L53:N53) -> 5579600 | O56: =SUM(O53:Q53) -> 5633100 | R56: =SUM(R53:T53) -> 5307900 | U56: =SUM(U53:W53) -> 5247280 | X56: =SUM(X53) -> 21767880
K57: Q仕入 | L57: =SUM(L54:N54) -> 4188979 | O57: =SUM(O54:Q54) -> 4267023 | R57: =SUM(R54:T54) -> 4191050 | U57: =SUM(U54:W54) -> 4006190 | X57: =SUM(X54) -> 16653242
K58: Q粗利 | L58: =SUM(L55:N55) -> 1390621 | O58: =SUM(O55:Q55) -> 1366077 | R58: =SUM(R55:T55) -> 1116850 | U58: =SUM(U55:W55) -> 1241090 | X58: =SUM(X55) -> 5114638
F63: =COUNTA(F5:F52) -> 0

Sheet ビジネス推進本部
A1: 社員番号 | B1: 氏名 | C1: No | D1: 派遣/請負 | E1: 担当 | F1: 氏名 | G1: 派遣先部署 | H1: 作業名 | I1: 契約先 | J1: 外注会社 | K1: 売上単価 (支払単価） 【≒粗利】 | L1: 4月 | M1: 5月 | N1: 6月 | O1: 7月 | P1: 8月 | Q1: 9月 | R1: 10月 | S1: 11月 | T1: 12月 | U1: 1月 | V1: 2月 | W1: 3月 | X1: 合計
C2: ビジネス推進本部 | K2: 売上 | L2: =L137 -> 4590421 | M2: =M137 -> 4432220 | N2: =N137 -> 4564802 | O2: =O137 -> 5724727 | P2: =P137 -> 3878290 | Q2: =Q137 -> 4078855 | R2: =R137 -> 4483980 | S2: =S137 -> 3711735 | ... W2: =W137 -> 3052331 | X2: =SUM(L2:W2) -> 49426752
K3: 仕入 | L3: =L138 -> 3931343 | M3: =M138 -> 3797773 | N3: =N138 -> 3936678 | O3: =O138 -> 3817336 | P3: =P138 -> 3507998 | Q3: =Q138 -> 3583399 | R3: =R138 -> 3820972 | S3: =S138 -> 3290280 | ... W3: =W138 -> 2960001 | X3: =SUM(L3:W3) -> 42207179
K4: 粗利 | L4: =L2-L3 -> 659078 | M4: =M2-M3 -> 634447 | N4: =N2-N3 -> 628124 | O4: =O2-O3 -> 1907391 | P4: =P2-P3 -> 370292 | Q4: =Q2-Q3 -> 495456 | R4: =R2-R3 -> 663008 | S4: =S2-S3 -> 421455 | ... W4: =W2-W3 -> 92330 | X4: =SUM(L4:W4) -> 7219573
A5: 2019006 | C5: 1 | D5: 派遣 | G5: ビジネス推進本部ビジネス企画推進部ビジネス企画推進二室 | J5: 社員 | K5: 総受注金額 | L5: =L6+L7 -> 388080 | M5: =M6+M7 -> 359100 | N5: =N6+N7 -> 363510 | O5: =O6+O7 -> 383670 | P5: =P6+P7 -> 309960 | Q5: =Q6+Q7 -> 309960 | R5: =R6+R7 -> 369180 | S5: =S6+S7 -> 315630 | ... W5: =W6+W7 -> 388080 | X5: =SUM(L5:W5) -> 4224780
A6: =+A5 -> 2019006 | K6: 派遣金額 | L6: 388080 | M6: 359100 | N6: 363510 | O6: 383670 | P6: 309960 | Q6: 309960 | R6: 369180 | S6: 315630 | T6: 332640 | U6: 359100 | V6: 345870 | W6: 388080 | X6: =SUM(L6:W6) -> 4224780
A7: =+A6 -> 2019006 | K7: 交通費 | X7: 0
A8: =+A7 -> 2019006 | K8: 総経費 | L8: =SUM(L9:L15) -> 303474 | M8: =SUM(M9:M15) -> 289570 | N8: =SUM(N9:N15) -> 304712 | O8: =SUM(O9:O15) -> 315343 | P8: =SUM(P9:P15) -> 284679 | Q8: =SUM(Q9:Q15) -> 290913 | R8: =SUM(R9:R15) -> 317695 | S8: =SUM(S9:S15) -> 282308 | ... W8: =SUM(W9:W15) -> 303474 | X8: =SUM(L8:W8) -> 3551129
A9: =+A8 -> 2019006 | K9: 賃金 | L9: 262750 | M9: 250200 | N9: 265185 | O9: 275705 | P9: 245360 | Q9: 248600 | R9: 275103 | S9: 240085 | T9: 249810 | U9: 238050 | V9: 240495 | W9: 262750 | X9: =SUM(L9:W9) -> 3054093
A10: =+A9 -> 2019006 | K10: 交通費その他 | X10: =SUM(L10:W10) -> 0
A11: =+A10 -> 2019006 | K11: 通勤定期代 | L11: 2420 | M11: 1210 | N11: 1210 | O11: 1210 | P11: 1210 | Q11: 1210 | R11: 1210 | S11: 1210 | T11: 3630 | U11: 1210 | V11: 2420 | W11: 2420 | X11: =SUM(L11:W11) -> 20570
A12: =+A11 -> 2019006 | K12: 健康保険 | L12: 13560 | M12: 13560 | N12: 13560 | O12: 13560 | P12: 13560 | Q12: 14690 | R12: 14690 | S12: 14690 | T12: 14690 | U12: 14690 | V12: 14690 | W12: 13560 | X12: =SUM(L12:W12) -> 169500
A13: =+A12 -> 2019006 | K13: 厚生年金 | L13: 21960 | M13: 21960 | N13: 21960 | O13: 21960 | P13: 21960 | Q13: 23790 | R13: 23790 | S13: 23790 | T13: 23790 | U13: 23790 | V13: 23790 | W13: 21960 | X13: =SUM(L13:W13) -> 274500
A14: =+A13 -> 2019006 | K14: 労災保険 | L14: 1326 | M14: 1257 | N14: 1332 | O14: 1385 | P14: 1233 | Q14: 1249 | R14: 1382 | S14: 1206 | T14: 1267 | U14: 1196 | V14: 1301 | W14: 1326 | X14: =SUM(L14:W14) -> 15460
A15: =+A14 -> 2019006 | K15: 雇用保険 | L15: 1458 | M15: 1383 | N15: 1465 | O15: 1523 | P15: 1356 | Q15: 1374 | R15: 1520 | S15: 1327 | T15: 1394 | U15: 1316 | V15: 1432 | W15: 1458 | X15: =SUM(L15:W15) -> 17006
A16: =+A15 -> 2019006 | K16: 粗利 | L16: =L5-L8 -> 84606 | M16: =M5-M8 -> 69530 | N16: =N5-N8 -> 58798 | O16: =O5-O8 -> 68327 | P16: =P5-P8 -> 25281 | Q16: =Q5-Q8 -> 19047 | R16: =R5-R8 -> 51485 | S16: =S5-S8 -> 33322 | ... X16: =X5-X8 -> 673651
A17: 2020007 | C17: =C5+1 -> 2 | D17: 派遣 | E17: 転出 | G17: ビジネス推進本部ビジネス企画推進部ビジネス企画推進二室 | I17: 営業事務 | J17: 社員 | K17: 総受注金額 | L17: =L18+L19 -> 366660 | M17: =M18+M19 -> 322560 | N17: =N18+N19 -> 350280 | O17: =O18+O19 -> 408240 | P17: =P18+P19 -> 315000 | Q17: =Q18+Q19 -> 365715 | R17: =R18+R19 -> 349650 | S17: =S18+S19 -> 292320 | T17: =T18+T19 -> 287595 | X17: =SUM(L17:W17) -> 3058020
A18: =+A17 -> 2020007 | K18: 派遣金額 | L18: 366660 | M18: 322560 | N18: 350280 | O18: 408240 | P18: 315000 | Q18: 365715 | R18: 349650 | S18: 292320 | T18: 287595 | X18: =SUM(L18:W18) -> 3058020
A19: =+A18 -> 2020007 | K19: 交通費 | X19: =SUM(L19:W19) -> 0
A20: =+A19 -> 2020007 | K20: 総経費 | L20: =SUM(L21:L27) -> 339931 | M20: =SUM(M21:M27) -> 325986 | N20: =SUM(N21:N27) -> 341363 | O20: =SUM(O21:O27) -> 348943 | P20: =SUM(P21:P27) -> 336513 | Q20: =SUM(Q21:Q27) -> 335903 | R20: =SUM(R21:R27) -> 353935 | S20: =SUM(S21:S27) -> 304324 | T20: =SUM(T21:T27) -> 335572 | X20: =SUM(L20:W20) -> 3022470
A21: =+A20 -> 2020007 | K21: 賃金 | L21: 291100 | M21: 277300 | N21: 292500 | O21: 300000 | P21: 287700 | Q21: 290025 | R21: 307850 | S21: 257200 | T21: 274125 | X21: =SUM(L21:W21) -> 2577800
A22: =+A21 -> 2020007 | K22: 紹介料 | X22: =SUM(L22:W22) -> 0
A23: =+A22 -> 2020007 | K23: 通勤定期代 | L23: 1360 | M23: 1360 | N23: 1378 | O23: 1378 | P23: 1378 | Q23: 1378 | R23: 1398 | S23: 2952 | T23: 17712 | X23: =SUM(L23:W23) -> 30294
A24: =+A23 -> 2020007 | K24: 健康保険 | L24: 16950 | M24: 16950 | N24: 16950 | O24: 16950 | P24: 16950 | Q24: 15820 | R24: 15820 | S24: 15820 | T24: 15820 | X24: =SUM(L24:W24) -> 148030
A25: =+A24 -> 2020007 | K25: 厚生年金 | L25: 27450 | M25: 27450 | N25: 27450 | O25: 27450 | P25: 27450 | Q25: 25620 | R25: 25620 | S25: 25620 | T25: 25620 | X25: =SUM(L25:W25) -> 239730
A26: =+A25 -> 2020007 | K26: 労災保険 | L26: 1462 | M26: 1393 | N26: 1469 | O26: 1507 | P26: 1445 | Q26: 1457 | R26: 1546 | S26: 1301 | T26: 1350 | X26: =SUM(L26:W26) -> 12930
A27: =+A26 -> 2020007 | K27: 雇用保険 | L27: 1609 | M27: 1533 | N27: 1616 | O27: 1658 | P27: 1590 | Q27: 1603 | R27: 1701 | S27: 1431 | T27: 945 | X27: =SUM(L27:W27) -> 13686
A28: =+A27 -> 2020007 | K28: 粗利 | L28: =L17-L20 -> 26729 | M28: =M17-M20 -> -3426 | N28: =N17-N20 -> 8917 | O28: =O17-O20 -> 59297 | P28: =P17-P20 -> -21513 | Q28: =Q17-Q20 -> 29812 | R28: =R17-R20 -> -4285 | S28: =S17-S20 -> -12004 | T28: =T17-T20 -> -47977 | X28: =X17-X20 -> 35550
A29: 2021012 | C29: =C17+1 -> 3 | D29: 派遣 | G29: ビジネス推進本部ビジネス企画推進部ビジネス企画推進二室 | I29: 営業事務 | J29: 社員 | K29: 総受注金額 | L29: =L30+L31 -> 360360 | M29: =M30+M31 -> 370440 | N29: =N30+N31 -> 374220 | O29: =O30+O31 -> 384300 | P29: =P30+P31 -> 307440 | Q29: =Q30+Q31 -> 361620 | R29: =R30+R31 -> 366660 | S29: =S30+S31 -> 312480 | ... W29: =W30+W31 -> 360360 | X29: =SUM(L29:W29) -> 4186980
A30: =+A29 -> 2021012 | K30: 派遣金額 | L30: 360360 | M30: 370440 | N30: 374220 | O30: 384300 | P30: 307440 | Q30: 361620 | R30: 366660 | S30: 312480 | T30: 352800 | U30: 328860 | V30: 307440 | W30: 360360 | X30: =SUM(L30:W30) -> 4186980
A31: =+A30 -> 2021012 | K31: 交通費 | X31: =SUM(L31:W31) -> 0
A32: =+A31 -> 2021012 | K32: 総経費 | L32: =SUM(L33:L39) -> 301427 | M32: =SUM(M33:M39) -> 295925 | N32: =SUM(N33:N39) -> 310482 | O32: =SUM(O33:O39) -> 326514 | P32: =SUM(P33:P39) -> 288158 | Q32: =SUM(Q33:Q39) -> 296397 | R32: =SUM(R33:R39) -> 318739 | S32: =SUM(S33:S39) -> 267925 | ... W32: =SUM(W33:W39) -> 301427 | X32: =SUM(L32:W32) -> 3574022
A33: =+A32 -> 2021012 | K33: 賃金 | L33: 258135 | M33: 252690 | N33: 268120 | O33: 283985 | P33: 246028 | Q33: 253125 | R33: 275235 | S33: 226005 | T33: 266485 | U33: 236860 | V33: 236025 | W33: 258135 | X33: =SUM(L33:W33) -> 3060828
A34: =+A33 -> 2021012 | K34: 紹介料 | X34: =SUM(L34:W34) -> 0
A35: =+A34 -> 2021012 | K35: 通勤定期代 | L35: 2080 | M35: 2080 | N35: 1056 | O35: 1056 | P35: 1056 | Q35: 2112 | R35: 2112 | S35: 1056 | T35: 1056 | U35: 2116 | V35: 1056 | W35: 2080 | X35: =SUM(L35:W35) -> 18916
A36: =+A35 -> 2021012 | K36: 健康保険 | L36: 14690 | M36: 14690 | N36: 14690 | O36: 14690 | P36: 14690 | Q36: 14690 | R36: 14690 | S36: 14690 | T36: 14690 | U36: 14690 | V36: 14690 | W36: 14690 | X36: =SUM(L36:W36) -> 176280
A37: =+A36 -> 2021012 | K37: 厚生年金 | L37: 23790 | M37: 23790 | N37: 23790 | O37: 23790 | P37: 23790 | Q37: 23790 | R37: 23790 | S37: 23790 | T37: 23790 | U37: 23790 | V37: 23790 | W37: 23790 | X37: =SUM(L37:W37) -> 285480
A38: =+A37 -> 2021012 | K38: 労災保険 | L38: 1301 | M38: 1274 | N38: 1346 | O38: 1425 | P38: 1235 | Q38: 1276 | R38: 1387 | S38: 1135 | T38: 1338 | U38: 1195 | V38: 1272 | W38: 1301 | X38: =SUM(L38:W38) -> 15485
A39: =+A38 -> 2021012 | K39: 雇用保険 | L39: 1431 | M39: 1401 | N39: 1480 | O39: 1568 | P39: 1359 | Q39: 1404 | R39: 1525 | S39: 1249 | T39: 1471 | U39: 1314 | V39: 1400 | W39: 1431 | X39: =SUM(L39:W39) -> 17033
A40: =+A39 -> 2021012 | K40: 粗利 | L40: =L29-L32 -> 58933 | M40: =M29-M32 -> 74515 | N40: =N29-N32 -> 63738 | O40: =O29-O32 -> 57786 | P40: =P29-P32 -> 19282 | Q40: =Q29-Q32 -> 65223 | R40: =R29-R32 -> 47921 | S40: =S29-S32 -> 44555 | ... X40: =X29-X32 -> 612958
A41: 2019053 | C41: =C29+1 -> 4 | D41: 派遣 | G41: ビジネス推進本部ビジネス企画推進部ビジネス企画推進二室 | I41: 営業事務 | J41: 社員 | K41: 総受注金額 | L41: =L42+L43 -> 513135 | M41: =M42+M43 -> 458010 | N41: =N42+N43 -> 440685 | O41: =O42+O43 -> 453915 | P41: =P42+P43 -> 449505 | Q41: =Q42+Q43 -> 471870 | R41: =R42+R43 -> 513765 | S41: =S42+S43 -> 405090 | ... W41: =W42+W43 -> 513135 | X41: =SUM(L41:W41) -> 5447610
A42: =+A41 -> 2019053 | K42: 派遣金額 | L42: 513135 | M42: 458010 | N42: 440685 | O42: 453915 | P42: 449505 | Q42: 471870 | R42: 513765 | S42: 405090 | T42: 474390 | U42: 404460 | V42: 349650 | W42: 513135 | X42: =SUM(L42:W42) -> 5447610
A43: =+A42 -> 2019053 | K43: 交通費 | X43: =SUM(L43:W43) -> 0
A44: =+A43 -> 2019053 | K44: 総経費 | L44: =SUM(L45:L51) -> 436703 | M44: =SUM(M45:M51) -> 406534 | N44: =SUM(N45:N51) -> 383396 | O44: =SUM(O45:O51) -> 406296 | P44: =SUM(P45:P51) -> 393916 | Q44: =SUM(Q45:Q51) -> 414889 | R44: =SUM(R45:R51) -> 434262 | S44: =SUM(S45:S51) -> 372486 | ... W44: =SUM(W45:W51) -> 436703 | X44: =SUM(L44:W44) -> 4828866
A45: =+A44 -> 2019053 | K45: 賃金 | L45: 372283 | M45: 356970 | N45: 331428 | O45: 355413 | P45: 337658 | Q45: 355770 | R45: 378908 | S45: 318435 | T45: 369430 | U45: 318790 | V45: 293515 | W45: 372283 | X45: =SUM(L45:W45) -> 4160883
A46: =+A45 -> 2019053 | K46: 紹介料 | X46: =SUM(L46:W46) -> 0
A47: =+A46 -> 2019053 | K47: 通勤定期代 | L47: 15864 | M47: 1322 | N47: 3966 | O47: 2644 | P47: 2644 | Q47: 5288 | R47: 1322 | S47: 661 | T47: 1322 | U47: 0 | V47: 0 | W47: 15864 | X47: =SUM(L47:W47) -> 50897
A48: =+A47 -> 2019053 | K48: 健康保険 | L48: 15200 | M48: 15200 | N48: 15200 | O48: 15200 | P48: 17100 | Q48: 17100 | R48: 17100 | S48: 17100 | T48: 17100 | U48: 17100 | V48: 17100 | W48: 15200 | X48: =SUM(L48:W48) -> 195700
A49: =+A48 -> 2019053 | K49: 厚生年金 | L49: 29280 | M49: 29280 | N49: 29280 | O49: 29280 | P49: 32940 | Q49: 32940 | R49: 32940 | S49: 32940 | T49: 32940 | U49: 32940 | V49: 32940 | W49: 29280 | X49: =SUM(L49:W49) -> 376980
A50: =+A49 -> 2019053 | K50: 労災保険 | L50: 1941 | M50: 1791 | N50: 1677 | O50: 1790 | P50: 1702 | Q50: 1805 | R50: 1901 | S50: 1595 | T50: 1854 | U50: 1594 | V50: 1554 | W50: 1941 | X50: =SUM(L50:W50) -> 21145
A51: =+A50 -> 2019053 | K51: 雇用保険 | L51: 2135 | M51: 1971 | N51: 1845 | O51: 1969 | P51: 1872 | Q51: 1986 | R51: 2091 | S51: 1755 | T51: 2039 | U51: 1753 | V51: 1710 | W51: 2135 | X51: =SUM(L51:W51) -> 23261
A52: =+A51 -> 2019053 | K52: 粗利 | L52: =L41-L44 -> 76432 | M52: =M41-M44 -> 51476 | N52: =N41-N44 -> 57289 | O52: =O41-O44 -> 47619 | P52: =P41-P44 -> 55589 | Q52: =Q41-Q44 -> 56981 | R52: =R41-R44 -> 79503 | S52: =S41-S44 -> 32604 | ... X52: =X41-X44 -> 618744
A53: 2018048 | C53: =C41+1 -> 5 | D53: 派遣 | G53: ビジネス推進本部ビジネス企画推進部ビジネス企画推進二室 | I53: 営業事務 | J53: 社員 | K53: 総受注金額 | L53: =L54+L55 -> 378630 | M53: =M54+M55 -> 370125 | N53: =N54+N55 -> 406350 | O53: =O54+O55 -> 445725 | P53: =P54+P55 -> 298620 | Q53: =Q54+Q55 -> 399105 | R53: =R54+R55 -> 416430 | S53: =S54+S55 -> 367290 | ... W53: =W54+W55 -> 378630 | X53: =SUM(L53:W53) -> 4755870
A54: =+A53 -> 2018048 | K54: 派遣金額 | L54: 378630 | M54: 370125 | N54: 406350 | O54: 445725 | P54: 298620 | Q54: 399105 | R54: 416430 | S54: 367290 | T54: 420525 | U54: 434070 | V54: 440370 | W54: 378630 | X54: =SUM(L54:W54) -> 4755870
A55: =+A54 -> 2018048 | K55: 交通費 | X55: =SUM(L55:W55) -> 0
A56: =+A55 -> 2018048 | K56: 総経費 | L56: =SUM(L57:L63) -> 323479 | M56: =SUM(M57:M63) -> 308331 | N56: =SUM(N57:N63) -> 331143 | O56: =SUM(O57:O63) -> 355517 | P56: =SUM(P57:P63) -> 304869 | Q56: =SUM(Q57:Q63) -> 317028 | R56: =SUM(R57:R63) -> 322956 | S56: =SUM(S57:S63) -> 302500 | ... W56: =SUM(W57:W63) -> 323479 | X56: =SUM(L56:W56) -> 3917221
A57: =+A56 -> 2018048 | K57: 賃金 | L57: 276338 | M57: 261348 | N57: 285238 | O57: 301463 | P57: 260553 | Q57: 271270 | R57: 274505 | S57: 259525 | T57: 305488 | U57: 298430 | V57: 281800 | W57: 276338 | X57: =SUM(L57:W57) -> 3352296
A58: =+A57 -> 2018048 | K58: 交通費その他 | X58: =SUM(L58:W58) -> 0
A59: =+A58 -> 2018048 | K59: 通勤定期代 | L59: 5264 | M59: 5264 | N59: 3948 | O59: 11844 | P59: 2632 | Q59: 3948 | R59: 6580 | S59: 1316 | T59: 2632 | U59: 10528 | V59: 2632 | W59: 5264 | X59: =SUM(L59:W59) -> 61852
A60: =+A59 -> 2018048 | K60: 健康保険 | L60: 13300 | M60: 13300 | N60: 13300 | O60: 13300 | P60: 13300 | Q60: 13300 | R60: 13300 | S60: 13300 | T60: 13300 | U60: 13300 | V60: 13300 | W60: 13300 | X60: =SUM(L60:W60) -> 159600
A61: =+A60 -> 2018048 | K61: 厚生年金 | L61: 25620 | M61: 25620 | N61: 25620 | O61: 25620 | P61: 25620 | Q61: 25620 | R61: 25620 | S61: 25620 | T61: 25620 | U61: 25620 | V61: 25620 | W61: 25620 | X61: =SUM(L61:W61) -> 307440
A62: =+A61 -> 2018048 | K62: 労災保険 | L62: 1408 | M62: 1333 | N62: 1446 | O62: 1567 | P62: 1316 | Q62: 1376 | R62: 1405 | S62: 1304 | T62: 1541 | U62: 1545 | V62: 1509 | W62: 1408 | X62: =SUM(L62:W62) -> 17158
A63: =+A62 -> 2018048 | K63: 雇用保険 | L63: 1549 | M63: 1466 | N63: 1591 | O63: 1723 | P63: 1448 | Q63: 1514 | R63: 1546 | S63: 1435 | T63: 1695 | U63: 1699 | V63: 1660 | W63: 1549 | X63: =SUM(L63:W63) -> 18875
A64: =+A63 -> 2018048 | K64: 粗利 | L64: =L53-L56 -> 55151 | M64: =M53-M56 -> 61794 | N64: =N53-N56 -> 75207 | O64: =O53-O56 -> 90208 | P64: =P53-P56 -> -6249 | Q64: =Q53-Q56 -> 82077 | R64: =R53-R56 -> 93474 | S64: =S53-S56 -> 64790 | ... X64: =X53-X56 -> 838649
A65: 2018034 | C65: =C53+1 -> 6 | D65: 派遣 | E65: 転出 | G65: ビジネス推進本部ビジネス企画推進部ビジネス企画推進二室 | I65: 営業事務 | J65: 社員 | K65: 総受注金額 | L65: =L66+L67 -> 398775 | M65: =M66+M67 -> 371800 | N65: =N66+N67 -> 387725 | O65: =O66+O67 -> 1125600 | P65: =P66+P67 -> 0 | Q65: =Q66+Q67 -> 0 | R65: =R66+R67 -> 0 | S65: =S66+S67 -> 0 | ... W65: =W66+W67 -> 0 | X65: =SUM(L65:W65) -> 2283900
A66: =+A65 -> 2018034 | K66: 派遣金額 | L66: 398775 | M66: 371800 | N66: 387725 | O66: 1125600 | X66: =SUM(L66:W66) -> 2283900
A67: =+A66 -> 2018034 | K67: 交通費 | X67: =SUM(L67:W67) -> 0
A68: =+A67 -> 2018034 | K68: 総経費 | L68: =SUM(L69:L75) -> 318334 | M68: =SUM(M69:M75) -> 300946 | N68: =SUM(N69:N75) -> 316214 | O68: =SUM(O69:O75) -> 0 | P68: =SUM(P69:P75) -> 0 | Q68: =SUM(Q69:Q75) -> 0 | R68: =SUM(R69:R75) -> 0 | S68: =SUM(S69:S75) -> 0 | ... W68: =SUM(W69:W75) -> 0 | X68: =SUM(L68:W68) -> 935494
A69: =+A68 -> 2018034 | K69: 賃金 | L69: 274662 | M69: 256535 | N69: 272574 | X69: =SUM(L69:W69) -> 803771
A70: =+A69 -> 2018034 | K70: 交通費その他 | X70: =SUM(L70:W70) -> 0
A71: =+A70 -> 2018034 | K71: 通勤定期代 | L71: 4600 | M71: 5520 | N71: 4590 | X71: =SUM(L71:W71) -> 14710
A72: =+A71 -> 2018034 | K72: 健康保険 | L72: 12350 | M72: 12350 | N72: 12350 | X72: =SUM(L72:W72) -> 37050
A73: =+A72 -> 2018034 | K73: 厚生年金 | L73: 23790 | M73: 23790 | N73: 23790 | X73: =SUM(L73:W73) -> 71370
A74: =+A73 -> 2018034 | K74: 労災保険 | L74: 1396 | M74: 1310 | N74: 1386 | X74: =SUM(L74:W74) -> 4092
A75: =+A74 -> 2018034 | K75: 雇用保険 | L75: 1536 | M75: 1441 | N75: 1524 | X75: =SUM(L75:W75) -> 4501
A76: =+A75 -> 2018034 | K76: 粗利 | L76: =L65-L68 -> 80441 | M76: =M65-M68 -> 70854 | N76: =N65-N68 -> 71511 | O76: =O65-O68 -> 1125600 | P76: =P65-P68 -> 0 | Q76: =Q65-Q68 -> 0 | R76: =R65-R68 -> 0 | S76: =S65-S68 -> 0 | ... X76: =X65-X68 -> 1348406
A77: 2018025 | C77: =C65+1 -> 7 | D77: 派遣 | G77: ビジネス推進本部ビジネス企画推進部ビジネス企画推進二室 | I77: 営業事務 | J77: 社員 | K77: 総受注金額 | L77: =L78+L79 -> 373905 | M77: =M78+M79 -> 394695 | N77: =N78+N79 -> 428085 | O77: =O78+O79 -> 447930 | P77: =P78+P79 -> 404145 | Q77: =Q78+Q79 -> 424620 | R77: =R78+R79 -> 466200 | S77: =S78+S79 -> 381150 | ... W77: =W78+W79 -> 0 | X77: =SUM(L77:W77) -> 4385430
A78: =+A77 -> 2018025 | K78: 派遣金額 | L78: 373905 | M78: 394695 | N78: 428085 | O78: 447930 | P78: 404145 | Q78: 424620 | R78: 466200 | S78: 381150 | T78: 448245 | U78: 403200 | V78: 213255 | X78: =SUM(L78:W78) -> 4385430
A79: =+A78 -> 2018025 | K79: 交通費 | X79: =SUM(L79:W79) -> 0
A80: =+A79 -> 2018025 | K80: 総経費 | L80: =SUM(L81:L87) -> 314622 | M80: =SUM(M81:M87) -> 299907 | N80: =SUM(N81:N87) -> 321388 | O80: =SUM(O81:O87) -> 338356 | P80: =SUM(P81:P87) -> 306561 | Q80: =SUM(Q81:Q87) -> 321237 | R80: =SUM(R81:R87) -> 355048 | S80: =SUM(S81:S87) -> 298929 | ... W80: =SUM(W81:W87) -> 314622 | X80: =SUM(L80:W80) -> 3827208
A81: =+A80 -> 2018025 | K81: 賃金 | L81: 273260 | M81: 259474 | N81: 281508 | O81: 295196 | P81: 264507 | Q81: 276279 | R81: 311291 | S81: 255755 | T81: 293291 | U81: 276082 | V81: 249859 | W81: 273260 | X81: =SUM(L81:W81) -> 3309762
A82: =+A81 -> 2018025 | K82: 交通費その他 | X82: =SUM(L82:W82) -> 0
A83: =+A82 -> 2018025 | K83: 通勤定期代 | L83: 2328 | M83: 1552 | N83: 776 | O83: 3880 | P83: 3104 | Q83: 3104 | R83: 1552 | S83: 1552 | T83: 3104 | U83: 2328 | V83: 6208 | W83: 2328 | X83: =SUM(L83:W83) -> 31816
A84: =+A83 -> 2018025 | K84: 健康保険 | L84: 12350 | M84: 12350 | N84: 12350 | O84: 12350 | P84: 12350 | Q84: 13300 | R84: 13300 | S84: 13300 | T84: 13300 | U84: 13300 | V84: 13300 | W84: 12350 | X84: =SUM(L84:W84) -> 153900
A85: =+A84 -> 2018025 | K85: 厚生年金 | L85: 23790 | M85: 23790 | N85: 23790 | O85: 23790 | P85: 23790 | Q85: 25620 | R85: 25620 | S85: 25620 | T85: 25620 | U85: 25620 | V85: 25620 | W85: 23790 | X85: =SUM(L85:W85) -> 296460
A86: =+A85 -> 2018025 | K86: 労災保険 | L86: 1378 | M86: 1305 | N86: 1411 | O86: 1495 | P86: 1338 | Q86: 1397 | R86: 1564 | S86: 1287 | T86: 1482 | U86: 1392 | V86: 1367 | W86: 1378 | X86: =SUM(L86:W86) -> 16794
A87: =+A86 -> 2018025 | K87: 雇用保険 | L87: 1516 | M87: 1436 | N87: 1553 | O87: 1645 | P87: 1472 | Q87: 1537 | R87: 1721 | S87: 1415 | T87: 1630 | U87: 1531 | V87: 1504 | W87: 1516 | X87: =SUM(L87:W87) -> 18476
A88: =+A87 -> 2018025 | K88: 粗利 | L88: =L77-L80 -> 59283 | M88: =M77-M80 -> 94788 | N88: =N77-N80 -> 106697 | O88: =O77-O80 -> 109574 | P88: =P77-P80 -> 97584 | Q88: =Q77-Q80 -> 103383 | R88: =R77-R80 -> 111152 | S88: =S77-S80 -> 82221 | ... X88: =X77-X80 -> 558222
A89: 2017006 | C89: =C77+1 -> 8 | D89: 派遣 | G89: ビジネス推進本部ビジネス企画推進部ビジネス企画推進二室 | I89: 営業事務 | J89: 社員 | K89: 総受注金額 | L89: =L90+L91 -> 372450 | M89: =M90+M91 -> 373750 | N89: =N90+N91 -> 376350 | O89: =O90+O91 -> 451100 | P89: =P90+P91 -> 388375 | Q89: =Q90+Q91 -> 409175 | R89: =R90+R91 -> 429975 | S89: =S90+S91 -> 329875 | ... W89: =W90+W91 -> 372450 | X89: =SUM(L89:W89) -> 4641000
A90: =+A89 -> 2017006 | K90: 派遣金額 | L90: 372450 | M90: 373750 | N90: 376350 | O90: 451100 | P90: 388375 | Q90: 409175 | R90: 429975 | S90: 329875 | T90: 398450 | U90: 364650 | V90: 374400 | W90: 372450 | X90: =SUM(L90:W90) -> 4641000
A91: =+A90 -> 2017006 | K91: 交通費 | X91: =SUM(L91:W91) -> 0
A92: =+A91 -> 2017006 | K92: 総経費 | L92: =SUM(L93:L99) -> 361077 | M92: =SUM(M93:M99) -> 339165 | N92: =SUM(N93:N99) -> 365539 | O92: =SUM(O93:O99) -> 384050 | P92: =SUM(P93:P99) -> 349396 | Q92: =SUM(Q93:Q99) -> 358895 | R92: =SUM(R93:R99) -> 384764 | S92: =SUM(S93:S99) -> 324958 | ... W92: =SUM(W93:W99) -> 361077 | X92: =SUM(L92:W92) -> 4267037
A93: =+A92 -> 2017006 | K93: 賃金 | L93: 306250 | M93: 286350 | N93: 312450 | O93: 327200 | P93: 296475 | Q93: 305875 | R93: 331475 | S93: 274075 | T93: 314875 | U93: 286550 | V93: 272500 | W93: 306250 | X93: =SUM(L93:W93) -> 3620325
A94: =+A93 -> 2017006 | K94: 交通費その他 | X94: =SUM(L94:W94) -> 0
A95: =+A94 -> 2017006 | K95: 通勤定期代 | L95: 7136 | M95: 5352 | N95: 5352 | O95: 8920 | P95: 5352 | Q95: 5352 | R95: 5352 | S95: 3568 | T95: 5352 | U95: 8920 | V95: 7136 | W95: 7136 | X95: =SUM(L95:W95) -> 74928
A96: =+A95 -> 2017006 | K96: 健康保険 | L96: 16950 | M96: 16950 | N96: 16950 | O96: 16950 | P96: 16950 | Q96: 16950 | R96: 16950 | S96: 16950 | T96: 16950 | U96: 16950 | V96: 16950 | W96: 16950 | X96: =SUM(L96:W96) -> 203400
A97: =+A96 -> 2017006 | K97: 厚生年金 | L97: 27450 | M97: 27450 | N97: 27450 | O97: 27450 | P97: 27450 | Q97: 27450 | R97: 27450 | S97: 27450 | T97: 27450 | U97: 27450 | V97: 27450 | W97: 27450 | X97: =SUM(L97:W97) -> 329400
A98: =+A97 -> 2017006 | K98: 労災保険 | L98: 1567 | M98: 1459 | N98: 1589 | O98: 1681 | P98: 1509 | Q98: 1556 | R98: 1684 | S98: 1388 | T98: 1601 | U98: 1477 | V98: 1485 | W98: 1567 | X98: =SUM(L98:W98) -> 18563
A99: =+A98 -> 2017006 | K99: 雇用保険 | L99: 1724 | M99: 1604 | N99: 1748 | O99: 1849 | P99: 1660 | Q99: 1712 | R99: 1853 | S99: 1527 | T99: 1761 | U99: 1625 | V99: 1634 | W99: 1724 | X99: =SUM(L99:W99) -> 20421
A100: =+A99 -> 2017006 | K100: 粗利 | L100: =L89-L92 -> 11373 | M100: =M89-M92 -> 34585 | N100: =N89-N92 -> 10811 | O100: =O89-O92 -> 67050 | P100: =P89-P92 -> 38979 | Q100: =Q89-Q92 -> 50280 | R100: =R89-R92 -> 45211 | S100: =S89-S92 -> 4917 | ... X100: =X89-X92 -> 373963
...

Sheet DXシステム本部
A1: 社員番号 | B1: 氏名 | C1: No | D1: 派遣/請負 | E1: 担当 | F1: 氏名 | G1: 派遣先部署 | H1: 作業名 | I1: 契約先 | J1: 外注会社 | K1: 売上単価 (支払単価） 【≒粗利】 | L1: 4月 | M1: 5月 | N1: 6月 | O1: 7月 | P1: 8月 | Q1: 9月 | R1: 10月 | S1: 11月 | T1: 12月 | U1: 1月 | V1: 2月 | W1: 3月 | X1: 合計
C2: DXシステム本部 | K2: 売上 | L2: =L89 -> 2493700 | M2: =M89 -> 2299200 | N2: =N89 -> 2549200 | O2: =O89 -> 2549200 | P2: =P89 -> 3285160 | Q2: =Q89 -> 3139830 | R2: =R89 -> 3299200 | S2: =S89 -> 3247650 | ... W2: =W89 -> 3899200 | X2: =SUM(L2:W2) -> 37150670
K3: 仕入 | L3: =L90 -> 1960995.5 | M3: =M90 -> 1946020 | N3: =N90 -> 1974776 | O3: =O90 -> 2013459 | P3: =P90 -> 2547631 | Q3: =Q90 -> 2550410 | R3: =R90 -> 2540711 | S3: =S90 -> 2539305 | ... W3: =W90 -> 3038749 | X3: =SUM(L3:W3) -> 29242126
K4: 粗利 | L4: =L2-L3 -> 532704.48 | M4: =M2-M3 -> 353180 | N4: =N2-N3 -> 574424 | O4: =O2-O3 -> 535741 | P4: =P2-P3 -> 737529 | Q4: =Q2-Q3 -> 589420 | R4: =R2-R3 -> 758489 | S4: =S2-S3 -> 708345 | ... W4: =W2-W3 -> 860451 | X4: =SUM(L4:W4) -> 7908544.5
A5: 2023003 | C5: 1 | D5: 派遣 | G5: DXシステム本部ＤＸ＆プロセス革新推進部システム運営室 | J5: 社員 | K5: 総受注金額 | L5: =L6+L7 -> 250000 | M5: =M6+M7 -> 400000 | N5: =N6+N7 -> 650000 | O5: =O6+O7 -> 650000 | P5: =P6+P7 -> 650000 | Q5: =Q6+Q7 -> 554590 | R5: =R6+R7 -> 650000 | S5: =S6+S7 -> 629700 | ... W5: =W6+W7 -> 650000 | X5: =SUM(L5:W5) -> 7013990
A6: =+A5 -> 2023003 | K6: 派遣金額 | L6: 250000 | M6: 400000 | N6: 650000 | O6: 650000 | P6: 650000 | Q6: 554590 | R6: 650000 | S6: 629700 | T6: 650000 | U6: 650000 | V6: 629700 | W6: 650000 | X6: =SUM(L6:W6) -> 7013990
A7: =+A6 -> 2023003 | K7: 交通費 | X7: 0
A8: =+A7 -> 2023003 | K8: 総経費 | L8: =SUM(L9:L15) -> 184641.52 | M8: =SUM(M9:M15) -> 473782 | N8: =SUM(N9:N15) -> 495215 | O8: =SUM(O9:O15) -> 494397 | P8: =SUM(P9:P15) -> 493588 | Q8: =SUM(Q9:Q15) -> 491971 | R8: =SUM(R9:R15) -> 494801 | S8: =SUM(S9:S15) -> 493184 | ... W8: =SUM(W9:W15) -> 498720 | X8: =SUM(L8:W8) -> 5591270.5
A9: =+A8 -> 2023003 | K9: 賃金 | L9: =402000/21*8 -> 153142.86 | M9: 407600 | N9: 427600 | O9: 428000 | P9: 427200 | Q9: 425600 | R9: 428400 | S9: 426800 | T9: 427200 | U9: 427200 | V9: 415045 | W9: 420000 | X9: =SUM(L9:W9) -> 4813787.9
A10: =+A9 -> 2023003 | K10: 交通費その他 | X10: =SUM(L10:W10) -> 0
A11: =+A10 -> 2023003 | K11: 通勤定期代 | L11: =17598/21*8 -> 6704 | M11: 1210 | N11: 2420 | O11: 1210 | P11: 1210 | Q11: 1210 | R11: 1210 | S11: 1210 | T11: 2420 | U11: 1164 | V11: 2328 | W11: 20000 | X11: =SUM(L11:W11) -> 42296
A12: =+A11 -> 2023003 | K12: 健康保険 | L12: =23165/21*8 -> 8824.7619 | M12: 23165 | N12: 23165 | O12: 23165 | P12: 23165 | Q12: 23165 | R12: 23165 | S12: 23165 | T12: 23165 | U12: 23165 | V12: 23165 | W12: 17425 | X12: =SUM(L12:W12) -> 257899.76
A13: =+A12 -> 2023003 | K13: 厚生年金 | L13: =37515/21*8 -> 14291.429 | M13: 37515 | N13: 37515 | O13: 37515 | P13: 37515 | Q13: 37515 | R13: 37515 | S13: 37515 | T13: 37515 | U13: 37515 | V13: 37515 | W13: 37515 | X13: =SUM(L13:W13) -> 426956.43
A14: =+A13 -> 2023003 | K14: 労災保険 | L14: =2098/21*8 -> 799.2381 | M14: 2044 | N14: 2150 | O14: 2146 | P14: 2142 | Q14: 2134 | R14: 2148 | S14: 2140 | T14: 2148 | U14: 2142 | V14: 2174 | W14: 1260 | X14: =SUM(L14:W14) -> 23427.238
A15: =+A14 -> 2023003 | K15: 雇用保険 | L15: =2308/21*8 -> 879.2381 | M15: 2248 | N15: 2365 | O15: 2361 | P15: 2356 | Q15: 2347 | R15: 2363 | S15: 2354 | T15: 2363 | U15: 2356 | V15: 2391 | W15: 2520 | X15: =SUM(L15:W15) -> 26903.238
A16: =+A15 -> 2023003 | K16: 粗利 | L16: =L5-L8 -> 65358.476 | M16: =M5-M8 -> -73782 | N16: =N5-N8 -> 154785 | O16: =O5-O8 -> 155603 | P16: =P5-P8 -> 156412 | Q16: =Q5-Q8 -> 62619 | R16: =R5-R8 -> 155199 | S16: =S5-S8 -> 136516 | ... X16: =X5-X8 -> 1422719.5
A17: 2023008 | C17: =C5+1 -> 2 | D17: 派遣 | E17: 転出 | G17: DXシステム本部ＤＸ＆プロセス革新推進部システム運営室 | J17: 社員 | K17: 総受注金額 | L17: =L18+L19 -> 344500 | M17: =M18+M19 -> 0 | N17: =N18+N19 -> 0 | O17: =O18+O19 -> 0 | P17: =P18+P19 -> 0 | Q17: =Q18+Q19 -> 0 | R17: =R18+R19 -> 0 | S17: =S18+S19 -> 0 | ... W17: =W18+W19 -> 0 | X17: =SUM(L17:W17) -> 344500
A18: =+A17 -> 2023008 | K18: 派遣金額 | L18: 344500 | X18: =SUM(L18:W18) -> 344500
A19: =+A18 -> 2023008 | K19: 交通費 | X19: 0
A20: =+A19 -> 2023008 | K20: 総経費 | L20: =SUM(L21:L27) -> 292066 | M20: =SUM(M21:M27) -> 0 | N20: =SUM(N21:N27) -> 0 | O20: =SUM(O21:O27) -> 0 | P20: =SUM(P21:P27) -> 0 | Q20: =SUM(Q21:Q27) -> 0 | R20: =SUM(R21:R27) -> 0 | S20: =SUM(S21:S27) -> 0 | ... W20: =SUM(W21:W27) -> 0 | X20: =SUM(L20:W20) -> 292066
A21: =+A20 -> 2023008 | K21: 賃金 | L21: 255600 | X21: =SUM(L21:W21) -> 255600
A22: =+A21 -> 2023008 | K22: 交通費その他 | X22: =SUM(L22:W22) -> 0
A23: =+A22 -> 2023008 | K23: 通勤定期代 | L23: 418 | X23: =SUM(L23:W23) -> 418
A24: =+A23 -> 2023008 | K24: 健康保険 | L24: 11400 | X24: =SUM(L24:W24) -> 11400
A25: =+A24 -> 2023008 | K25: 厚生年金 | L25: 21960 | X25: =SUM(L25:W25) -> 21960
A26: =+A25 -> 2023008 | K26: 労災保険 | L26: 1280 | X26: =SUM(L26:W26) -> 1280
A27: =+A26 -> 2023008 | K27: 雇用保険 | L27: 1408 | X27: =SUM(L27:W27) -> 1408
A28: =+A27 -> 2023008 | K28: 粗利 | L28: =L17-L20 -> 52434 | M28: =M17-M20 -> 0 | N28: =N17-N20 -> 0 | O28: =O17-O20 -> 0 | P28: =P17-P20 -> 0 | Q28: =Q17-Q20 -> 0 | R28: =R17-R20 -> 0 | S28: =S17-S20 -> 0 | ... X28: =X17-X20 -> 52434
A29: 2022012 | C29: =C17+1 -> 3 | D29: 派遣 | G29: DXシステム本部ＤＸ＆プロセス革新推進部システム運営室 | J29: 社員 | K29: 総受注金額 | L29: =L30+L31 -> 800000 | M29: =M30+M31 -> 800000 | N29: =N30+N31 -> 800000 | O29: =O30+O31 -> 800000 | P29: =P30+P31 -> 800000 | Q29: =Q30+Q31 -> 800000 | R29: =R30+R31 -> 800000 | S29: =S30+S31 -> 800000 | ... W29: =W30+W31 -> 800000 | X29: =SUM(L29:W29) -> 9600000
A30: =+A29 -> 2022012 | K30: 派遣金額 | L30: 800000 | M30: 800000 | N30: 800000 | O30: 800000 | P30: 800000 | Q30: 800000 | R30: 800000 | S30: 800000 | T30: 800000 | U30: 800000 | V30: 800000 | W30: 800000 | X30: =SUM(L30:W30) -> 9600000
A31: =+A30 -> 2022012 | K31: 交通費 | X31: =SUM(L31:W31) -> 0
A32: =+A31 -> 2022012 | K32: 総経費 | L32: =SUM(L33:L39) -> 617441 | M32: =SUM(M33:M39) -> 616632 | N32: =SUM(N33:N39) -> 618285 | O32: =SUM(O33:O39) -> 654182 | P32: =SUM(P33:P39) -> 616632 | Q32: =SUM(Q33:Q39) -> 616632 | R32: =SUM(R33:R39) -> 617845 | S32: =SUM(S33:S39) -> 615824 | ... W32: =SUM(W33:W39) -> 617441 | X32: =SUM(L32:W32) -> 7448476
A33: =+A32 -> 2022012 | K33: 賃金 | L33: 533400 | M33: 532600 | N33: 533000 | O33: 569759 | P33: 532600 | Q33: 532600 | R33: 533800 | S33: 531800 | T33: 540405 | U33: 532600 | V33: 532200 | W33: 533400 | X33: =SUM(L33:W33) -> 6438164
A34: =+A33 -> 2022012 | K34: 交通費その他 | X34: =SUM(L34:W34) -> 0
A35: =+A34 -> 2022012 | K35: 通勤定期代 | L35: 0 | M35: 0 | N35: 1236 | O35: 0 | P35: 0 | Q35: 0 | R35: 0 | S35: 0 | T35: 0 | U35: 0 | V35: 0 | W35: 0 | X35: =SUM(L35:W35) -> 1236
A36: =+A35 -> 2022012 | K36: 健康保険 | L36: 29945 | M36: 29945 | N36: 29945 | O36: 29945 | P36: 29945 | Q36: 29945 | R36: 29945 | S36: 29945 | T36: 29945 | U36: 29945 | V36: 29945 | W36: 29945 | X36: =SUM(L36:W36) -> 359340
A37: =+A36 -> 2022012 | K37: 厚生年金 | L37: 48495 | M37: 48495 | N37: 48495 | O37: 48495 | P37: 48495 | Q37: 48495 | R37: 48495 | S37: 48495 | T37: 48495 | U37: 48495 | V37: 48495 | W37: 48495 | X37: =SUM(L37:W37) -> 581940
A38: =+A37 -> 2022012 | K38: 労災保険 | L38: 2667 | M38: 2663 | N38: 2671 | O38: 2849 | P38: 2663 | Q38: 2663 | R38: 2669 | S38: 2659 | T38: 2702 | U38: 2663 | V38: 2748 | W38: 2667 | X38: =SUM(L38:W38) -> 32284
A39: =+A38 -> 2022012 | K39: 雇用保険 | L39: 2934 | M39: 2929 | N39: 2938 | O39: 3134 | P39: 2929 | Q39: 2929 | R39: 2936 | S39: 2925 | T39: 2972 | U39: 2929 | V39: 3023 | W39: 2934 | X39: =SUM(L39:W39) -> 35512
A40: =+A39 -> 2022012 | K40: 粗利 | L40: =L29-L32 -> 182559 | M40: =M29-M32 -> 183368 | N40: =N29-N32 -> 181715 | O40: =O29-O32 -> 145818 | P40: =P29-P32 -> 183368 | Q40: =Q29-Q32 -> 183368 | R40: =R29-R32 -> 182155 | S40: =S29-S32 -> 184176 | ... X40: =X29-X32 -> 2151524
A41: 2016005 | C41: =C29+1 -> 4 | D41: 派遣 | G41: DXシステム本部ＤＸ＆プロセス革新推進部システム運営室 | J41: 社員 | K41: 総受注金額 | L41: =L42+L43 -> 499200 | M41: =M42+M43 -> 499200 | N41: =N42+N43 -> 499200 | O41: =O42+O43 -> 499200 | P41: =P42+P43 -> 485160 | Q41: =Q42+Q43 -> 435240 | R41: =R42+R43 -> 499200 | S41: =S42+S43 -> 491400 | ... W41: =W42+W43 -> 499200 | X41: =SUM(L41:W41) -> 5839080
A42: =+A41 -> 2016005 | K42: 派遣金額 | L42: 499200 | M42: 499200 | N42: 499200 | O42: 499200 | P42: 485160 | Q42: 435240 | R42: 499200 | S42: 491400 | T42: 499200 | U42: 480480 | V42: 452400 | W42: 499200 | X42: =SUM(L42:W42) -> 5839080
A43: =+A42 -> 2016005 | K43: 交通費 | X43: 0
A44: =+A43 -> 2016005 | K44: 総経費 | L44: =SUM(L45:L51) -> 387444 | M44: =SUM(M45:M51) -> 386332 | N44: =SUM(N45:N51) -> 388138 | O44: =SUM(O45:O51) -> 387136 | P44: =SUM(P45:P51) -> 385923 | Q44: =SUM(Q45:Q51) -> 387895 | R44: =SUM(R45:R51) -> 389512 | S44: =SUM(S45:S51) -> 389407 | ... W44: =SUM(W45:W51) -> 387444 | X44: =SUM(L44:W44) -> 4655718
A45: =+A44 -> 2016005 | K45: 賃金 | L45: 337200 | M45: 337200 | N45: 336800 | O45: 338000 | P45: 336800 | Q45: 336000 | R45: 337600 | S45: 336400 | T45: 336400 | U45: 336400 | V45: 335600 | W45: 337200 | X45: =SUM(L45:W45) -> 4041600
A46: =+A45 -> 2016005 | K46: 交通費その他 | X46: =SUM(L46:W46) -> 0
A47: =+A46 -> 2016005 | K47: 通勤定期代 | L47: 2200 | M47: 1100 | N47: 3288 | O47: 1096 | P47: 1096 | Q47: 1096 | R47: 1096 | S47: 2192 | T47: 2192 | U47: 1096 | V47: 2192 | W47: 2200 | X47: =SUM(L47:W47) -> 20844
A48: =+A47 -> 2016005 | K48: 健康保険 | L48: 15200 | M48: 15200 | N48: 15200 | O48: 15200 | P48: 15200 | Q48: 16150 | R48: 16150 | S48: 16150 | T48: 16150 | U48: 16150 | V48: 16150 | W48: 15200 | X48: =SUM(L48:W48) -> 188100
A49: =+A48 -> 2016005 | K49: 厚生年金 | L49: 29280 | M49: 29280 | N49: 29280 | O49: 29280 | P49: 29280 | Q49: 31110 | R49: 31110 | S49: 31110 | T49: 31110 | U49: 31110 | V49: 31110 | W49: 29280 | X49: =SUM(L49:W49) -> 362340
A50: =+A49 -> 2016005 | K50: 労災保険 | L50: 1697 | M50: 1691 | N50: 1700 | O50: 1695 | P50: 1689 | Q50: 1685 | R50: 1693 | S50: 1693 | T50: 1693 | U50: 1687 | V50: 1776 | W50: 1697 | X50: =SUM(L50:W50) -> 20396
A51: =+A50 -> 2016005 | K51: 雇用保険 | L51: 1867 | M51: 1861 | N51: 1870 | O51: 1865 | P51: 1858 | Q51: 1854 | R51: 1863 | S51: 1862 | T51: 1862 | U51: 1856 | V51: 1953 | W51: 1867 | X51: =SUM(L51:W51) -> 22438
A52: =+A51 -> 2016005 | K52: 粗利 | L52: =L41-L44 -> 111756 | M52: =M41-M44 -> 112868 | N52: =N41-N44 -> 111062 | O52: =O41-O44 -> 112064 | P52: =P41-P44 -> 99237 | Q52: =Q41-Q44 -> 47345 | R52: =R41-R44 -> 109688 | S52: =S41-S44 -> 101993 | ... X52: =X41-X44 -> 1183362
A53: 2025012 | C53: =C41+1 -> 5 | D53: 派遣 | G53: DXシステム本部情報システム部システム基盤管理室 | J53: 社員 | K53: 総受注金額 | L53: =L54+L55 -> 0 | M53: =M54+M55 -> 0 | N53: =N54+N55 -> 0 | O53: =O54+O55 -> 0 | P53: =P54+P55 -> 750000 | Q53: =Q54+Q55 -> 750000 | R53: =R54+R55 -> 750000 | S53: =S54+S55 -> 726550 | ... W53: =W54+W55 -> 750000 | X53: =SUM(L53:W53) -> 5953100
A54: =+A53 -> 2025012 | K54: 派遣金額 | P54: 750000 | Q54: 750000 | R54: 750000 | S54: 726550 | T54: 750000 | U54: 750000 | V54: 726550 | W54: 750000 | X54: =SUM(L54:W54) -> 5953100
A55: =+A54 -> 2025012 | K55: 交通費 | X55: 0
A56: =+A55 -> 2025012 | K56: 総経費 | L56: =SUM(L57:L63) -> 0 | M56: =SUM(M57:M63) -> 0 | N56: =SUM(N57:N63) -> 0 | O56: =SUM(O57:O63) -> 0 | P56: =SUM(P57:P63) -> 583022 | Q56: =SUM(Q57:Q63) -> 585042 | R56: =SUM(R57:R63) -> 577363 | S56: =SUM(S57:S63) -> 577363 | ... W56: =SUM(W57:W63) -> 575962 | X56: =SUM(L56:W56) -> 4648792
A57: =+A56 -> 2025012 | K57: 賃金 | P57: 499200 | Q57: 499600 | R57: 492000 | S57: 492000 | T57: 500000 | U57: 499600 | V57: 499200 | W57: 492000 | X57: =SUM(L57:W57) -> 3973600
A58: =+A57 -> 2025012 | K58: 交通費その他 | X58: =SUM(L58:W58) -> 0
A59: =+A58 -> 2025012 | K59: 通勤定期代 | P59: 4860 | Q59: 1738 | R59: 1738 | S59: 1738 | T59: 0 | U59: 0 | V59: 0 | W59: 5000 | X59: =SUM(L59:W59) -> 15074
A60: =+A59 -> 2025012 | K60: 健康保険 | P60: 25175 | Q60: 29945 | R60: 29945 | S60: 29945 | T60: 29945 | U60: 29945 | V60: 29945 | W60: 25175 | X60: =SUM(L60:W60) -> 230020
A61: =+A60 -> 2025012 | K61: 厚生年金 | P61: 48495 | Q61: 48495 | R61: 48495 | S61: 48495 | T61: 48495 | U61: 48495 | V61: 48495 | W61: 48495 | X61: =SUM(L61:W61) -> 387960
A62: =+A61 -> 2025012 | K62: 労災保険 | P62: 2520 | Q62: 2507 | R62: 2469 | S62: 2469 | T62: 2500 | U62: 2498 | V62: 2583 | W62: 2520 | X62: =SUM(L62:W62) -> 20066
A63: =+A62 -> 2025012 | K63: 雇用保険 | P63: 2772 | Q63: 2757 | R63: 2716 | S63: 2716 | T63: 2750 | U63: 2748 | V63: 2841 | W63: 2772 | X63: =SUM(L63:W63) -> 22072
A64: =+A63 -> 2025012 | K64: 粗利 | L64: =L53-L56 -> 0 | M64: =M53-M56 -> 0 | N64: =N53-N56 -> 0 | O64: =O53-O56 -> 0 | P64: =P53-P56 -> 166978 | Q64: =Q53-Q56 -> 164958 | R64: =R53-R56 -> 172637 | S64: =S53-S56 -> 149187 | ... X64: =X53-X56 -> 1304308
A65: 2023022 | C65: =C53+1 -> 6 | D65: 委託 | G65: 情報システム部システム運営室 | J65: 社員 | K65: 総受注金額 | L65: =L66+L67 -> 600000 | M65: =M66+M67 -> 600000 | N65: =N66+N67 -> 600000 | O65: =O66+O67 -> 600000 | P65: =P66+P67 -> 600000 | Q65: =Q66+Q67 -> 600000 | R65: =R66+R67 -> 600000 | S65: =S66+S67 -> 600000 | ... W65: =W66+W67 -> 600000 | X65: =SUM(L65:W65) -> 7200000
A66: =+A65 -> 2023022 | K66: 派遣金額 | L66: 600000 | M66: 600000 | N66: 600000 | O66: 600000 | P66: 600000 | Q66: 600000 | R66: 600000 | S66: 600000 | T66: 600000 | U66: 600000 | V66: 600000 | W66: 600000 | X66: =SUM(L66:W66) -> 7200000
A67: =+A66 -> 2023022 | K67: 交通費 | X67: 0
A68: =+A67 -> 2023022 | K68: 総経費 | L68: =SUM(L69:L75) -> 479403 | M68: =SUM(M69:M75) -> 469274 | N68: =SUM(N69:N75) -> 473138 | O68: =SUM(O69:O75) -> 477744 | P68: =SUM(P69:P75) -> 468466 | Q68: =SUM(Q69:Q75) -> 468870 | R68: =SUM(R69:R75) -> 461190 | S68: =SUM(S69:S75) -> 463527 | ... W68: =SUM(W69:W75) -> 479403 | X68: =SUM(L68:W68) -> 5647403
A69: =+A68 -> 2023022 | K69: 賃金 | L69: 415712 | M69: 408000 | N69: 407200 | O69: 416382 | P69: 407200 | Q69: 407600 | R69: 400000 | S69: 400000 | T69: 408000 | U69: 407200 | V69: 407200 | W69: 415712 | X69: =SUM(L69:W69) -> 4900206
A70: =+A69 -> 2023022 | K70: 交通費その他 | X70: =SUM(L70:W70) -> 0
A71: =+A70 -> 2023022 | K71: 通勤定期代 | L71: 2312 | M71: 0 | N71: 4624 | O71: 0 | P71: 0 | Q71: 0 | R71: 0 | S71: 2312 | T71: 0 | U71: 0 | V71: 0 | W71: 2312 | X71: =SUM(L71:W71) -> 11560
A72: =+A71 -> 2023022 | K72: 健康保険 | L72: 19475 | M72: 19475 | N72: 19475 | O72: 19475 | P72: 19475 | Q72: 19475 | R72: 19475 | S72: 19475 | T72: 19475 | U72: 19475 | V72: 19475 | W72: 19475 | X72: =SUM(L72:W72) -> 233700
A73: =+A72 -> 2023022 | K73: 厚生年金 | L73: 37515 | M73: 37515 | N73: 37515 | O73: 37515 | P73: 37515 | Q73: 37515 | R73: 37515 | S73: 37515 | T73: 37515 | U73: 37515 | V73: 37515 | W73: 37515 | X73: =SUM(L73:W73) -> 450180
A74: =+A73 -> 2023022 | K74: 労災保険 | L74: 2090 | M74: 2040 | N74: 2059 | O74: 2082 | P74: 2036 | Q74: 2038 | R74: 2000 | S74: 2012 | T74: 2040 | U74: 2036 | V74: 2123 | W74: 2090 | X74: =SUM(L74:W74) -> 24646
A75: =+A74 -> 2023022 | K75: 雇用保険 | L75: 2299 | M75: 2244 | N75: 2265 | O75: 2290 | P75: 2240 | Q75: 2242 | R75: 2200 | S75: 2213 | T75: 2244 | U75: 2240 | V75: 2335 | W75: 2299 | X75: =SUM(L75:W75) -> 27111
A76: =+A75 -> 2023022 | K76: 粗利 | L76: =L65-L68 -> 120597 | M76: =M65-M68 -> 130726 | N76: =N65-N68 -> 126862 | O76: =O65-O68 -> 122256 | P76: =P65-P68 -> 131534 | Q76: =Q65-Q68 -> 131130 | R76: =R65-R68 -> 138810 | S76: =S65-S68 -> 136473 | ... X76: =X65-X68 -> 1552597
A77: 2025028 | C77: =C65+1 -> 7 | D77: 委託 | G77: 情報システム部システム運営室 | J77: 社員 | K77: 総受注金額 | L77: =L78+L79 -> 0 | M77: =M78+M79 -> 0 | N77: =N78+N79 -> 0 | O77: =O78+O79 -> 0 | P77: =P78+P79 -> 0 | Q77: =Q78+Q79 -> 0 | R77: =R78+R79 -> 0 | S77: =S78+S79 -> 0 | ... W77: =W78+W79 -> 600000 | X77: =SUM(L77:W77) -> 1200000
A78: =+A77 -> 2025028 | K78: 派遣金額 | V78: 600000 | W78: 600000 | X78: =SUM(L78:W78) -> 1200000
A79: =+A78 -> 2025028 | B79: =+B78 -> 0 | K79: 交通費 | X79: 0
A80: =+A79 -> 2025028 | B80: =+B79 -> 0 | K80: 総経費 | L80: =SUM(L81:L87) -> 0 | M80: =SUM(M81:M87) -> 0 | N80: =SUM(N81:N87) -> 0 | O80: =SUM(O81:O87) -> 0 | P80: =SUM(P81:P87) -> 0 | Q80: =SUM(Q81:Q87) -> 0 | R80: =SUM(R81:R87) -> 0 | S80: =SUM(S81:S87) -> 0 | ... W80: =SUM(W81:W87) -> 479779 | X80: =SUM(L80:W80) -> 958400
A81: =+A80 -> 2025028 | B81: =+B80 -> 0 | K81: 賃金 | V81: 415600 | W81: 410000 | X81: =SUM(L81:W81) -> 825600
A82: =+A81 -> 2025028 | B82: =+B81 -> 0 | K82: 交通費その他 | X82: =SUM(L82:W82) -> 0
A83: =+A82 -> 2025028 | B83: =+B82 -> 0 | K83: 通勤定期代 | V83: 1470 | W83: 8400 | X83: =SUM(L83:W83) -> 9870
A84: =+A83 -> 2025028 | B84: =+B83 -> 0 | K84: 健康保険 | V84: 19475 | W84: 19475 | X84: =SUM(L84:W84) -> 38950
A85: =+A84 -> 2025028 | B85: =+B84 -> 0 | K85: 厚生年金 | V85: 37515 | W85: 37515 | X85: =SUM(L85:W85) -> 75030
A86: =+A85 -> 2025028 | B86: =+B85 -> 0 | K86: 労災保険 | V86: 2172 | W86: 2090 | X86: =SUM(L86:W86) -> 4262
A87: =+A86 -> 2025028 | B87: =+B86 -> 0 | K87: 雇用保険 | V87: 2389 | W87: 2299 | X87: =SUM(L87:W87) -> 4688
A88: =+A87 -> 2025028 | B88: =+B87 -> 0 | K88: 粗利 | L88: =L77-L80 -> 0 | M88: =M77-M80 -> 0 | N88: =N77-N80 -> 0 | O88: =O77-O80 -> 0 | P88: =P77-P80 -> 0 | Q88: =Q77-Q80 -> 0 | R88: =R77-R80 -> 0 | S88: =S77-S80 -> 0 | ... X88: =X77-X80 -> 241600
C89: =C2 -> DXシステム本部 | K89: 売上 | L89: =L5+L17+L29+L41+L53+L65+L77 -> 2493700 | M89: =M5+M17+M29+M41+M53+M65+M77 -> 2299200 | N89: =N5+N17+N29+N41+N53+N65+N77 -> 2549200 | O89: =O5+O17+O29+O41+O53+O65+O77 -> 2549200 | P89: =P5+P17+P29+P41+P53+P65+P77 -> 3285160 | Q89: =Q5+Q17+Q29+Q41+Q53+Q65+Q77 -> 3139830 | R89: =R5+R17+R29+R41+R53+R65+R77 -> 3299200 | S89: =S5+S17+S29+S41+S53+S65+S77 -> 3247650 | ... W89: =W5+W17+W29+W41+W53+W65+W77 -> 3899200 | X89: =SUM(L89:W89) -> 37150670
K90: 仕入 | L90: =L8+L20+L32+L44+L56+L68+L80 -> 1960995.5 | M90: =M8+M20+M32+M44+M56+M68+M80 -> 1946020 | N90: =N8+N20+N32+N44+N56+N68+N80 -> 1974776 | O90: =O8+O20+O32+O44+O56+O68+O80 -> 2013459 | P90: =P8+P20+P32+P44+P56+P68+P80 -> 2547631 | Q90: =Q8+Q20+Q32+Q44+Q56+Q68+Q80 -> 2550410 | R90: =R8+R20+R32+R44+R56+R68+R80 -> 2540711 | S90: =S8+S20+S32+S44+S56+S68+S80 -> 2539305 | ... W90: =W8+W20+W32+W44+W56+W68+W80 -> 3038749 | X90: =SUM(L90:W90) -> 29242126
K91: 粗利 | L91: =L89-L90 -> 532704.48 | M91: =M89-M90 -> 353180 | N91: =N89-N90 -> 574424 | O91: =O89-O90 -> 535741 | P91: =P89-P90 -> 737529 | Q91: =Q89-Q90 -> 589420 | R91: =R89-R90 -> 758489 | S91: =S89-S90 -> 708345 | ... W91: =W89-W90 -> 860451 | X91: =SUM(L91:W91) -> 7908544.5
K92: Q売上 | L92: =SUM(L89:N89) -> 7342100 | O92: =SUM(O89:Q89) -> 8974190 | R92: =SUM(R89:T89) -> 9846050 | U92: =SUM(U89:W89) -> 10988330 | X92: =SUM(L92:W92) -> 37150670
K93: Q仕入 | L93: =SUM(L90:N90) -> 5881791.5 | O93: =SUM(O90:Q90) -> 7111500 | R93: =SUM(R90:T90) -> 7641717 | U93: =SUM(U90:W90) -> 8607117 | X93: =SUM(L93:W93) -> 29242126
K94: Q粗利 | L94: =SUM(L91:N91) -> 1460308.5 | O94: =SUM(O91:Q91) -> 1862690 | R94: =SUM(R91:T91) -> 2204333 | U94: =SUM(U91:W91) -> 2381213 | X94: =SUM(L94:W94) -> 7908544.5

Sheet マーケティングコミュニケーション本部
A1: 社員番号 | B1: 氏名 | C1: No | D1: 派遣/請負 | E1: 担当 | F1: 氏名 | G1: 派遣先部署 | H1: 作業名 | I1: 契約先 | J1: 外注会社 | K1: 売上単価 (支払単価） 【≒粗利】 | L1: 4月 | M1: 5月 | N1: 6月 | O1: 7月 | P1: 8月 | Q1: 9月 | R1: 10月 | S1: 11月 | T1: 12月 | U1: 1月 | V1: 2月 | W1: 3月 | X1: 合計
C2: マーケティングコミュニケーション本部 | K2: 売上 | L2: =L65 -> 1497500 | M2: =M65 -> 1692200 | N2: =N65 -> 1674800 | O2: =O65 -> 1923740 | P2: =P65 -> 1709080 | Q2: =Q65 -> 1741555 | R2: =R65 -> 1784720 | S2: =S65 -> 1738930 | ... W2: =W65 -> 2106500 | X2: =SUM(L2:W2) -> 21731455
K3: 仕入 | L3: =L66 -> 1238221.7 | M3: =M66 -> 1460165 | N3: =N66 -> 1671530 | O3: =O66 -> 1628669 | P3: =P66 -> 1428100 | Q3: =Q66 -> 1423623.3 | R3: =R66 -> 1318886 | S3: =S66 -> 1510767.9 | ... W3: =W66 -> 1621088 | X3: =SUM(L3:W3) -> 17586253
K4: 粗利 | L4: =L2-L3 -> 259278.33 | M4: =M2-M3 -> 232035 | N4: =N2-N3 -> 3270 | O4: =O2-O3 -> 295071 | P4: =P2-P3 -> 280980.03 | Q4: =Q2-Q3 -> 317931.66 | R4: =R2-R3 -> 465834.04 | S4: =S2-S3 -> 228162.09 | ... W4: =W2-W3 -> 485412 | X4: =SUM(L4:W4) -> 4145202.1
A5: 2024032 | C5: 1 | D5: 派遣 | G5: マーケティングコミュニケーション本部戦略企画推進部 | J5: 社員 | K5: 総受注金額 | L5: =L6+L7 -> 540000 | M5: =M6+M7 -> 502200 | N5: =N6+N7 -> 672300 | O5: =O6+O7 -> 658800 | P5: =P6+P7 -> 467100 | Q5: =Q6+Q7 -> 521100 | R5: =R6+R7 -> 450900 | S5: =S6+S7 -> 337500 | ... W5: =W6+W7 -> 540000 | X5: =SUM(L5:W5) -> 5591700
A6: =+A5 -> 2024032 | K6: 派遣金額 | L6: 540000 | M6: 502200 | N6: 672300 | O6: 658800 | P6: 467100 | Q6: 521100 | R6: 450900 | S6: 337500 | T6: 491400 | U6: 248400 | V6: 162000 | W6: 540000 | X6: =SUM(L6:W6) -> 5591700
A7: =+A6 -> 2024032 | K7: 交通費 | X7: =SUM(L7:W7) -> 0
A8: =+A7 -> 2024032 | K8: 総経費 | L8: =SUM(L9:L15) -> 402600 | M8: =SUM(M9:M15) -> 392535 | N8: =SUM(N9:N15) -> 603900 | O8: =SUM(O9:O15) -> 603900 | P8: =SUM(P9:P15) -> 387250.97 | Q8: =SUM(Q9:Q15) -> 400510.34 | R8: =SUM(R9:R15) -> 283721.96 | S8: =SUM(S9:S15) -> 394575.91 | ... W8: =SUM(W9:W15) -> 402600 | X8: =SUM(L8:W8) -> 4500303.3
A9: =+A8 -> 2024032 | K9: 賃金 | L9: =500000/21*14 -> 333333.33 | M9: =500000/20*13 -> 325000 | N9: 500000 | O9: 500000 | P9: =500000/164.46*105.46 -> 320625.08 | Q9: =500000/171.47*113.72 -> 331603.2 | R9: =606499/210.68*84.01 -> 241845.36 | S9: =500000/144.25*94.25 -> 326689.77 | T9: =500000/177.06*77.31 -> 218315.83 | U9: =500000/174.23*57.23 -> 164236.93 | V9: =518685/182.82*48.91 -> 138764.27 | W9: =500000/21*14 -> 333333.33 | X9: =SUM(L9:W9) -> 3733747.1
A10: =+A9 -> 2024032 | K10: 交通費その他 | X10: =SUM(L10:W10) -> 0
A11: =+A10 -> 2024032 | K11: 通勤定期代 | L11: 13333.333 | M11: =20000/20*13 -> 13000 | N11: 20000 | O11: 20000 | P11: =20000/164.46*105.46 -> 12825.003 | Q11: =20000/171.47*113.72 -> 13264.128 | R11: =20000/210.68*84.01 -> 7975.1282 | S11: =20000/144.25*94.25 -> 13067.591 | T11: =20000/177.06*77.31 -> 8732.633 | U11: =20000/174.23*57.23 -> 6569.4771 | V11: =20000/182.82*48.91 -> 5350.6181 | W11: 13333.333 | X11: =SUM(L11:W11) -> 147451.24
A12: =+A11 -> 2024032 | K12: 健康保険 | L12: 19963.333 | M12: =29945/20*13 -> 19464.25 | N12: 29945 | O12: 29945 | P12: =29945/164.46*105.46 -> 19202.236 | Q12: =29945/171.47*113.72 -> 19859.715 | R12: =29945/210.68*84.01 -> 11940.761 | S12: =29945/144.25*94.25 -> 19565.451 | T12: =29945/177.06*77.31 -> 13074.935 | U12: =29945/174.23*57.23 -> 9836.1496 | V12: =29945/182.82*48.91 -> 8011.2129 | W12: 19963.333 | X12: =SUM(L12:W12) -> 220771.38
A13: =+A12 -> 2024032 | K13: 厚生年金 | L13: 32330 | M13: =48495/20*13 -> 31521.75 | N13: 48495 | O13: 48495 | P13: =48495/164.46*105.46 -> 31097.426 | Q13: =48495/171.47*113.72 -> 32162.194 | R13: =48495/210.68*84.01 -> 19337.692 | S13: =48495/144.25*94.25 -> 31685.641 | T13: =48495/177.06*77.31 -> 21174.452 | U13: =48495/174.23*57.23 -> 15929.34 | V13: =48495/182.82*48.91 -> 12973.911 | W13: 32330 | X13: =SUM(L13:W13) -> 357532.41
A14: =+A13 -> 2024032 | K14: 労災保険 | L14: 1733.3333 | M14: =2600/20*13 -> 1690 | N14: 2600 | O14: 2600 | P14: =2600/164.46*105.46 -> 1667.2504 | Q14: =2600/171.47*113.72 -> 1724.3366 | R14: =3132/210.68*84.01 -> 1248.9051 | S14: =2600/144.25*94.25 -> 1698.7868 | T14: =2600/177.06*77.31 -> 1135.2423 | U14: =2600/174.23*57.23 -> 854.03203 | V14: =2780/182.82*48.91 -> 743.73592 | W14: 1733.3333 | X14: =SUM(L14:W14) -> 19428.956
A15: =+A14 -> 2024032 | K15: 雇用保険 | L15: 1906.6667 | M15: =2860/20*13 -> 1859 | N15: 2860 | O15: 2860 | P15: =2860/164.46*105.46 -> 1833.9754 | Q15: =2860/171.47*113.72 -> 1896.7703 | R15: =3446/210.68*84.01 -> 1374.1146 | S15: =2860/144.25*94.25 -> 1868.6655 | T15: =2860/177.06*77.31 -> 1248.7665 | U15: =2860/174.23*57.23 -> 939.43523 | V15: =3058/182.82*48.91 -> 818.10951 | W15: 1906.6667 | X15: =SUM(L15:W15) -> 21372.17
A16: =+A15 -> 2024032 | K16: 粗利 | L16: =L5-L8 -> 137400 | M16: =M5-M8 -> 109665 | N16: =N5-N8 -> 68400 | O16: =O5-O8 -> 54900 | P16: =P5-P8 -> 79849.033 | Q16: =Q5-Q8 -> 120589.66 | R16: =R5-R8 -> 167178.04 | S16: =S5-S8 -> -57075.91 | ... X16: =X5-X8 -> 1091396.7
A17: 2022003 | C17: =C5+1 -> 2 | D17: 派遣 | E17: 転出 | G17: マーケティングコミュニケーション本部戦略企画推進部 | J17: 社員 | K17: 総受注金額 | L17: =L18+L19 -> 157500 | M17: =M18+M19 -> 390000 | N17: =N18+N19 -> 202500 | O17: =O18+O19 -> 0 | P17: =P18+P19 -> 0 | Q17: =Q18+Q19 -> 0 | R17: =R18+R19 -> 0 | S17: =S18+S19 -> 0 | ... W17: =W18+W19 -> 0 | X17: =SUM(L17:W17) -> 750000
A18: =+A17 -> 2022003 | K18: 派遣金額 | L18: 157500 | M18: 390000 | N18: 202500 | X18: =SUM(L18:W18) -> 750000
A19: =+A18 -> 2022003 | K19: 交通費 | X19: =SUM(L19:W19) -> 0
A20: =+A19 -> 2022003 | K20: 総経費 | L20: =SUM(L21:L27) -> 115621.67 | M20: =SUM(M21:M27) -> 347630 | N20: =SUM(N21:N27) -> 347630 | O20: =SUM(O21:O27) -> 0 | P20: =SUM(P21:P27) -> 0 | Q20: =SUM(Q21:Q27) -> 0 | R20: =SUM(R21:R27) -> 0 | S20: =SUM(S21:S27) -> 0 | ... W20: =SUM(W21:W27) -> 0 | X20: =SUM(L20:W20) -> 810881.67
A21: =+A20 -> 2022003 | K21: 賃金 | L21: =279243/21*7 -> 93081 | M21: 280000 | N21: 280000 | X21: =SUM(L21:W21) -> 653081
A22: =+A21 -> 2022003 | K22: 交通費その他 | X22: =SUM(L22:W22) -> 0
A23: =+A22 -> 2022003 | K23: 通勤定期代 | L23: =20000/21*7 -> 6666.6667 | M23: 20000 | N23: 20000 | X23: =SUM(L23:W23) -> 46666.667
A24: =+A23 -> 2022003 | K24: 健康保険 | L24: =15200/21*7 -> 5066.6667 | M24: 15200 | N24: 15200 | X24: =SUM(L24:W24) -> 35466.667
A25: =+A24 -> 2022003 | K25: 厚生年金 | L25: =29280/21*7 -> 9760 | M25: 29280 | N25: 29280 | X25: =SUM(L25:W25) -> 68320
A26: =+A25 -> 2022003 | K26: 労災保険 | L26: =1496/21*7 -> 498.66667 | M26: 1500 | N26: 1500 | X26: =SUM(L26:W26) -> 3498.6667
A27: =+A26 -> 2022003 | K27: 雇用保険 | L27: =1646/21*7 -> 548.66667 | M27: 1650 | N27: 1650 | X27: =SUM(L27:W27) -> 3848.6667
A28: =+A27 -> 2022003 | K28: 粗利 | L28: =L17-L20 -> 41878.333 | M28: =M17-M20 -> 42370 | N28: =N17-N20 -> -145130 | O28: =O17-O20 -> 0 | P28: =P17-P20 -> 0 | Q28: =Q17-Q20 -> 0 | R28: =R17-R20 -> 0 | S28: =S17-S20 -> 0 | ... X28: =X17-X20 -> -60881.667
A29: － | C29: =C17+1 -> 3 | D29: 委託 | G29: マーケティングコミュニケーション本部戦略企画推進部 | J29: 業務委託 | K29: 総受注金額 | L29: =L30+L31 -> 800000 | M29: =M30+M31 -> 800000 | N29: =N30+N31 -> 800000 | O29: =O30+O31 -> 800000 | P29: =P30+P31 -> 800000 | Q29: =Q30+Q31 -> 800000 | R29: =R30+R31 -> 800000 | S29: =S30+S31 -> 800000 | ... W29: =W30+W31 -> 800000 | X29: =SUM(L29:W29) -> 9600000
A30: =+A29 -> － | K30: 派遣金額 | L30: 800000 | M30: 800000 | N30: 800000 | O30: 800000 | P30: 800000 | Q30: 800000 | R30: 800000 | S30: 800000 | T30: 800000 | U30: 800000 | V30: 800000 | W30: 800000 | X30: =SUM(L30:W30) -> 9600000
A31: =+A30 -> － | K31: 交通費 | X31: =SUM(L31:W31) -> 0
A32: =+A31 -> － | K32: 総経費 | L32: =SUM(L33:L39) -> 720000 | M32: =SUM(M33:M39) -> 720000 | N32: =SUM(N33:N39) -> 720000 | O32: =SUM(O33:O39) -> 720000 | P32: =SUM(P33:P39) -> 720000 | Q32: =SUM(Q33:Q39) -> 720000 | R32: =SUM(R33:R39) -> 720000 | S32: =SUM(S33:S39) -> 720000 | ... W32: =SUM(W33:W39) -> 720000 | X32: =SUM(L32:W32) -> 8640000
A33: =+A32 -> － | K33: 賃金 | L33: 720000 | M33: 720000 | N33: 720000 | O33: 720000 | P33: 720000 | Q33: 720000 | R33: 720000 | S33: 720000 | T33: 720000 | U33: 720000 | V33: 720000 | W33: 720000 | X33: =SUM(L33:W33) -> 8640000
A34: =+A33 -> － | K34: 交通費その他 | X34: =SUM(L34:W34) -> 0
A35: =+A34 -> － | K35: 通勤定期代 | X35: =SUM(L35:W35) -> 0
A36: =+A35 -> － | K36: 健康保険 | X36: =SUM(L36:W36) -> 0
A37: =+A36 -> － | K37: 厚生年金 | X37: =SUM(L37:W37) -> 0
A38: =+A37 -> － | K38: 労災保険 | X38: =SUM(L38:W38) -> 0
A39: =+A38 -> － | K39: 雇用保険 | X39: =SUM(L39:W39) -> 0
A40: =+A39 -> － | K40: 粗利 | L40: =L29-L32 -> 80000 | M40: =M29-M32 -> 80000 | N40: =N29-N32 -> 80000 | O40: =O29-O32 -> 80000 | P40: =P29-P32 -> 80000 | Q40: =Q29-Q32 -> 80000 | R40: =R29-R32 -> 80000 | S40: =S29-S32 -> 80000 | ... X40: =X29-X32 -> 960000
A41: 2024027 | C41: =C29+1 -> 4 | D41: 派遣 | G41: マーケティングコミュニケーション本部戦略企画推進部 | J41: 社員 | K41: 総受注金額 | L41: =L42+L43 -> 0 | M41: =M42+M43 -> 0 | N41: =N42+N43 -> 0 | O41: =O42+O43 -> 464940 | P41: =P42+P43 -> 441980 | Q41: =Q42+Q43 -> 420455 | R41: =R42+R43 -> 533820 | S41: =S42+S43 -> 398930 | ... W41: =W42+W43 -> 430500 | X41: =SUM(L41:W41) -> 3893155
A42: =+A41 -> 2024027 | K42: 派遣金額 | O42: 464940 | P42: 441980 | Q42: 420455 | R42: 533820 | S42: 398930 | T42: 439110 | U42: 340095 | V42: 423325 | W42: =2870*150 -> 430500 | X42: =SUM(L42:W42) -> 3893155
A43: =+A42 -> 2024027 | K43: 交通費 | X43: =SUM(L43:W43) -> 0
A44: =+A43 -> 2024027 | K44: 総経費 | L44: =SUM(L45:L51) -> 0 | M44: =SUM(M45:M51) -> 0 | N44: =SUM(N45:N51) -> 0 | O44: =SUM(O45:O51) -> 304769 | P44: =SUM(P45:P51) -> 320849 | Q44: =SUM(Q45:Q51) -> 303113 | R44: =SUM(R45:R51) -> 315164 | S44: =SUM(S45:S51) -> 307762 | ... W44: =SUM(W45:W51) -> 312744 | X44: =SUM(L44:W44) -> 2778572
A45: =+A44 -> 2024027 | K45: 賃金 | O45: 240000 | P45: 240000 | Q45: 240000 | R45: 251926 | S45: 240000 | T45: 240000 | U45: 240000 | V45: 240000 | W45: 248000 | X45: =SUM(L45:W45) -> 2179926
A46: =+A45 -> 2024027 | K46: 交通費その他 | X46: =SUM(L46:W46) -> 0
A47: =+A46 -> 2024027 | K47: 通勤定期代 | O47: 26000 | P47: 41750 | Q47: 26950 | R47: 26950 | S47: 31550 | T47: 31550 | U47: 26950 | V47: 26950 | W47: 26000 | X47: =SUM(L47:W47) -> 264650
A48: =+A47 -> 2024027 | K48: 健康保険 | O48: 12350 | P48: 12350 | Q48: 11400 | R48: 11400 | S48: 11400 | T48: 11400 | U48: 11400 | V48: 11400 | W48: 12350 | X48: =SUM(L48:W48) -> 105450
A49: =+A48 -> 2024027 | K49: 厚生年金 | O49: 23790 | P49: 23790 | Q49: 21960 | R49: 21960 | S49: 21960 | T49: 21960 | U49: 21960 | V49: 21960 | W49: 23790 | X49: =SUM(L49:W49) -> 203130
A50: =+A49 -> 2024027 | K50: 労災保険 | O50: 1252 | P50: 1409 | Q50: 1335 | R50: 1394 | S50: 1358 | T50: 1358 | U50: 1335 | V50: 1422 | W50: 1240 | X50: =SUM(L50:W50) -> 12103
A51: =+A50 -> 2024027 | K51: 雇用保険 | O51: 1377 | P51: 1550 | Q51: 1468 | R51: 1534 | S51: 1494 | T51: 1494 | U51: 1468 | V51: 1564 | W51: 1364 | X51: =SUM(L51:W51) -> 13313
A52: =+A51 -> 2024027 | K52: 粗利 | L52: =L41-L44 -> 0 | M52: =M41-M44 -> 0 | N52: =N41-N44 -> 0 | O52: =O41-O44 -> 160171 | P52: =P41-P44 -> 121131 | Q52: =Q41-Q44 -> 117342 | R52: =R41-R44 -> 218656 | S52: =S41-S44 -> 91168 | ... X52: =X41-X44 -> 1114583
A53: 2025018 | C53: =C41+1 -> 5 | D53: 派遣 | G53: マーケティングコミュニケーション本部戦略企画推進部 | J53: 社員 | K53: 総受注金額 | L53: =L54+L55 -> 0 | M53: =M54+M55 -> 0 | N53: =N54+N55 -> 0 | O53: =O54+O55 -> 0 | P53: =P54+P55 -> 0 | Q53: =Q54+Q55 -> 0 | R53: =R54+R55 -> 0 | S53: =S54+S55 -> 202500 | ... W53: =W54+W55 -> 336000 | X53: =SUM(L53:W53) -> 1896600
A54: =+A53 -> 2025018 | B54: =+B53 -> 0 | K54: 派遣金額 | S54: 202500 | T54: 407700 | U54: 521100 | V54: 429300 | W54: 336000 | X54: =SUM(L54:W54) -> 1896600
A55: =+A54 -> 2025018 | B55: =+B54 -> 0 | K55: 交通費 | X55: =SUM(L55:W55) -> 0
A56: =+A55 -> 2025018 | B56: =+B55 -> 0 | K56: 総経費 | L56: =SUM(L57:L63) -> 0 | M56: =SUM(M57:M63) -> 0 | N56: =SUM(N57:N63) -> 0 | O56: =SUM(O57:O63) -> 0 | P56: =SUM(P57:P63) -> 0 | Q56: =SUM(Q57:Q63) -> 0 | R56: =SUM(R57:R63) -> 0 | S56: =SUM(S57:S63) -> 88430 | ... W56: =SUM(W57:W63) -> 185744 | X56: =SUM(L56:W56) -> 856496
A57: =+A56 -> 2025018 | B57: =+B56 -> 0 | K57: 賃金 | S57: 85250 | T57: 168838 | U57: 165000 | V57: 223300 | W57: 176000 | X57: =SUM(L57:W57) -> 818388
A58: =+A57 -> 2025018 | B58: =+B57 -> 0 | K58: 交通費その他 | X58: =SUM(L58:W58) -> 0
A59: =+A58 -> 2025018 | B59: =+B58 -> 0 | K59: 通勤定期代 | S59: 3180 | T59: 6716 | U59: 5800 | V59: 6436 | W59: 8000 | X59: =SUM(L59:W59) -> 30132
A60: =+A59 -> 2025018 | B60: =+B59 -> 0 | K60: 健康保険 | S60: 0 | T60: 0 | U60: 0 | V60: 0 | W60: 0 | X60: =SUM(L60:W60) -> 0
A61: =+A60 -> 2025018 | B61: =+B60 -> 0 | K61: 厚生年金 | S61: 0 | T61: 0 | U61: 0 | V61: 0 | W61: 0 | X61: =SUM(L61:W61) -> 0
A62: =+A61 -> 2025018 | B62: =+B61 -> 0 | K62: 労災保険 | S62: 0 | T62: 878 | U62: 854 | V62: 1236 | W62: 552 | X62: =SUM(L62:W62) -> 3520
A63: =+A62 -> 2025018 | B63: =+B62 -> 0 | K63: 雇用保険 | S63: 0 | T63: 966 | U63: 939 | V63: 1359 | W63: 1192 | X63: =SUM(L63:W63) -> 4456
A64: =+A63 -> 2025018 | B64: =+B63 -> 0 | K64: 粗利 | L64: =L53-L56 -> 0 | M64: =M53-M56 -> 0 | N64: =N53-N56 -> 0 | O64: =O53-O56 -> 0 | P64: =P53-P56 -> 0 | Q64: =Q53-Q56 -> 0 | R64: =R53-R56 -> 0 | S64: =S53-S56 -> 114070 | ... X64: =X53-X56 -> 1040104
C65: =C2 -> マーケティングコミュニケーション本部 | K65: 売上 | L65: =L5+L17+L29+L41+L53 -> 1497500 | M65: =M5+M17+M29+M41+M53 -> 1692200 | N65: =N5+N17+N29+N41+N53 -> 1674800 | O65: =O5+O17+O29+O41+O53 -> 1923740 | P65: =P5+P17+P29+P41+P53 -> 1709080 | Q65: =Q5+Q17+Q29+Q41+Q53 -> 1741555 | R65: =R5+R17+R29+R41+R53 -> 1784720 | S65: =S5+S17+S29+S41+S53 -> 1738930 | ... W65: =W5+W17+W29+W41+W53 -> 2106500 | X65: =SUM(L65:W65) -> 21731455
K66: 仕入 | L66: =L8+L20+L32+L44+L56 -> 1238221.7 | M66: =M8+M20+M32+M44+M56 -> 1460165 | N66: =N8+N20+N32+N44+N56 -> 1671530 | O66: =O8+O20+O32+O44+O56 -> 1628669 | P66: =P8+P20+P32+P44+P56 -> 1428100 | Q66: =Q8+Q20+Q32+Q44+Q56 -> 1423623.3 | R66: =R8+R20+R32+R44+R56 -> 1318886 | S66: =S8+S20+S32+S44+S56 -> 1510767.9 | ... W66: =W8+W20+W32+W44+W56 -> 1621088 | X66: =SUM(L66:W66) -> 17586253
K67: 粗利 | L67: =L65-L66 -> 259278.33 | M67: =M65-M66 -> 232035 | N67: =N65-N66 -> 3270 | O67: =O65-O66 -> 295071 | P67: =P65-P66 -> 280980.03 | Q67: =Q65-Q66 -> 317931.66 | R67: =R65-R66 -> 465834.04 | S67: =S65-S66 -> 228162.09 | ... W67: =W65-W66 -> 485412 | X67: =SUM(L67:W67) -> 4145202.1
K68: Q売上 | L68: =SUM(L65:N65) -> 4864500 | O68: =SUM(O65:Q65) -> 5374375 | R68: =SUM(R65:T65) -> 5661860 | U68: =SUM(U65:W65) -> 5830720 | X68: =X65 -> 21731455
K69: Q仕入 | L69: =SUM(L66:N66) -> 4369916.7 | O69: =SUM(O66:Q66) -> 4480392.3 | R69: =SUM(R66:T66) -> 4298495.7 | U69: =SUM(U66:W66) -> 4437448.2 | X69: =X66 -> 17586253
K70: Q粗利 | L70: =SUM(L67:N67) -> 494583.33 | O70: =SUM(O67:Q67) -> 893982.69 | R70: =SUM(R67:T67) -> 1363364.3 | U70: =SUM(U67:W67) -> 1393271.8 | X70: =X67 -> 4145202.1

Sheet ネットワークサービス本部
A1: 社員番号 | B1: 氏名 | C1: No | D1: 派遣/請負 | E1: 担当 | F1: 氏名 | G1: 派遣先部署 | H1: 作業名 | I1: 契約先 | J1: 外注会社 | K1: 売上単価 (支払単価） 【≒粗利】 | L1: 4月 | M1: 5月 | N1: 6月 | O1: 7月 | P1: 8月 | Q1: 9月 | R1: 10月 | S1: 11月 | T1: 12月 | U1: 1月 | V1: 2月 | W1: 3月 | X1: 合計
C2: ネットワークサービス本部 | K2: 売上 | L2: =L29 -> 1150000 | M2: =M29 -> 1127150 | N2: =N29 -> 1150000 | O2: =O29 -> 1150000 | P2: =P29 -> 1150000 | Q2: =Q29 -> 1150000 | R2: =R29 -> 1150000 | S2: =S29 -> 1062805 | ... W2: =W29 -> 1150000 | X2: =SUM(L2:W2) -> 13482055
K3: 仕入 | L3: =L30 -> 866552 | M3: =M30 -> 863755 | N3: =N30 -> 869534 | O3: =O30 -> 867547 | P3: =P30 -> 862003 | Q3: =Q30 -> 864804 | R3: =R30 -> 866337 | S3: =S30 -> 852634 | ... W3: =W30 -> 866552 | X3: =SUM(L3:W3) -> 10360502
K4: 粗利 | L4: =L2-L3 -> 283448 | M4: =M2-M3 -> 263395 | N4: =N2-N3 -> 280466 | O4: =O2-O3 -> 282453 | P4: =P2-P3 -> 287997 | Q4: =Q2-Q3 -> 285196 | R4: =R2-R3 -> 283663 | S4: =S2-S3 -> 210171 | ... W4: =W2-W3 -> 283448 | X4: =SUM(L4:W4) -> 3121553
A5: 2019019 | C5: 1 | D5: 派遣 | G5: ネットワークサービス本部テクニカルサポート二部 | J5: 社員 | K5: 総受注金額 | L5: =L6+L7 -> 730000 | M5: =M6+M7 -> 707150 | N5: =N6+N7 -> 730000 | O5: =O6+O7 -> 730000 | P5: =P6+P7 -> 730000 | Q5: =Q6+Q7 -> 730000 | R5: =R6+R7 -> 730000 | S5: =S6+S7 -> 654595 | ... W5: =W6+W7 -> 730000 | X5: =SUM(L5:W5) -> 8542925
A6: =+A5 -> 2019019 | K6: 派遣金額 | L6: 730000 | M6: 707150 | N6: 730000 | O6: 730000 | P6: 730000 | Q6: 730000 | R6: 730000 | S6: 654595 | T6: 643170 | U6: 704865 | V6: 723145 | W6: 730000 | X6: =SUM(L6:W6) -> 8542925
A7: =+A6 -> 2019019 | K7: 交通費 | X7: 0
A8: =+A7 -> 2019019 | K8: 総経費 | L8: =SUM(L9:L15) -> 571714 | M8: =SUM(M9:M15) -> 568917 | N8: =SUM(N9:N15) -> 574696 | O8: =SUM(O9:O15) -> 572709 | P8: =SUM(P9:P15) -> 571714 | Q8: =SUM(Q9:Q15) -> 575346 | R8: =SUM(R9:R15) -> 576879 | S8: =SUM(S9:S15) -> 570914 | ... W8: =SUM(W9:W15) -> 571714 | X8: =SUM(L8:W8) -> 6870256
A9: =+A8 -> 2019019 | K9: 賃金 | L9: 491400 | M9: 491400 | N9: 490200 | O9: 492600 | P9: 491400 | Q9: 490600 | R9: 492600 | S9: 487178 | T9: 491400 | U9: 491400 | V9: 491000 | W9: 491400 | X9: =SUM(L9:W9) -> 5892578
A10: =+A9 -> 2019019 | K10: 交通費その他 | X10: =SUM(L10:W10) -> 0
A11: =+A10 -> 2019019 | K11: 通勤定期代 | L11: 5536 | M11: 2768 | N11: 9688 | O11: 5320 | P11: 5536 | Q11: 5536 | R11: 5054 | S11: 4572 | T11: 0 | U11: 1384 | V11: 2768 | W11: 5536 | X11: =SUM(L11:W11) -> 53698
A12: =+A11 -> 2019019 | K12: 健康保険 | L12: 26555 | M12: 26555 | N12: 26555 | O12: 26555 | P12: 26555 | Q12: 28250 | R12: 28250 | S12: 28250 | T12: 28250 | U12: 28250 | V12: 28250 | W12: 26555 | X12: =SUM(L12:W12) -> 328830
A13: =+A12 -> 2019019 | K13: 厚生年金 | L13: 43005 | M13: 43005 | N13: 43005 | O13: 43005 | P13: 43005 | Q13: 45750 | R13: 45750 | S13: 45750 | T13: 45750 | U13: 45750 | V13: 45750 | W13: 43005 | X13: =SUM(L13:W13) -> 532530
A14: =+A13 -> 2019019 | K14: 労災保険 | L14: 2485 | M14: 2471 | N14: 2499 | O14: 2490 | P14: 2485 | Q14: 2481 | R14: 2488 | S14: 2459 | T14: 2457 | U14: 2464 | V14: 2556 | W14: 2485 | X14: =SUM(L14:W14) -> 29820
A15: =+A14 -> 2019019 | K15: 雇用保険 | L15: 2733 | M15: 2718 | N15: 2749 | O15: 2739 | P15: 2733 | Q15: 2729 | R15: 2737 | S15: 2705 | T15: 2703 | U15: 2710 | V15: 2811 | W15: 2733 | X15: =SUM(L15:W15) -> 32800
A16: =+A15 -> 2019019 | K16: 粗利 | L16: =L5-L8 -> 158286 | M16: =M5-M8 -> 138233 | N16: =N5-N8 -> 155304 | O16: =O5-O8 -> 157291 | P16: =P5-P8 -> 158286 | Q16: =Q5-Q8 -> 154654 | R16: =R5-R8 -> 153121 | S16: =S5-S8 -> 83681 | ... X16: =X5-X8 -> 1672669
A17: 2024019 | C17: =C5+1 -> 2 | D17: 派遣 | G17: ネットワークサービス本部テクニカルサポート二部 | J17: 社員 | K17: 総受注金額 | L17: =L18+L19 -> 420000 | M17: =M18+M19 -> 420000 | N17: =N18+N19 -> 420000 | O17: =O18+O19 -> 420000 | P17: =P18+P19 -> 420000 | Q17: =Q18+Q19 -> 420000 | R17: =R18+R19 -> 420000 | S17: =S18+S19 -> 408210 | ... W17: =W18+W19 -> 420000 | X17: =SUM(L17:W17) -> 4939130
A18: =+A17 -> 2024019 | B18: =+B17 -> 0 | K18: 派遣金額 | L18: 420000 | M18: 420000 | N18: 420000 | O18: 420000 | P18: 420000 | Q18: 420000 | R18: 420000 | S18: 408210 | T18: 420000 | U18: 420000 | V18: 330920 | W18: 420000 | X18: =SUM(L18:W18) -> 4939130
A19: =+A18 -> 2024019 | B19: =+B18 -> 0 | K19: 交通費 | X19: 0
A20: =+A19 -> 2024019 | B20: =+B19 -> 0 | K20: 総経費 | L20: =SUM(L21:L27) -> 294838 | M20: =SUM(M21:M27) -> 294838 | N20: =SUM(N21:N27) -> 294838 | O20: =SUM(O21:O27) -> 294838 | P20: =SUM(P21:P27) -> 290289 | Q20: =SUM(Q21:Q27) -> 289458 | R20: =SUM(R21:R27) -> 289458 | S20: =SUM(S21:S27) -> 281720 | ... W20: =SUM(W21:W27) -> 294838 | X20: =SUM(L20:W20) -> 3490246
A21: =+A20 -> 2024019 | B21: =+B20 -> 0 | K21: 賃金 | L21: 240000 | M21: 240000 | N21: 240000 | O21: 240000 | P21: 240000 | Q21: 240000 | R21: 240000 | S21: 234808 | T21: 243200 | U21: 243600 | V21: 237208 | W21: 240000 | X21: =SUM(L21:W21) -> 2878816
A22: =+A21 -> 2024019 | B22: =+B21 -> 0 | K22: 交通費その他 | X22: =SUM(L22:W22) -> 0
A23: =+A22 -> 2024019 | B23: =+B22 -> 0 | K23: 通勤定期代 | L23: 16010 | M23: 16010 | N23: 16010 | O23: 16010 | P23: 11508 | Q23: 10686 | R23: 10686 | S23: 8220 | T23: 9864 | U23: 8220 | V23: 6576 | W23: 16010 | X23: =SUM(L23:W23) -> 145810
A24: =+A23 -> 2024019 | B24: =+B23 -> 0 | K24: 健康保険 | L24: 12350 | M24: 12350 | N24: 12350 | O24: 12350 | P24: 12350 | Q24: 12350 | R24: 12350 | S24: 12350 | T24: 12350 | U24: 12350 | V24: 12350 | W24: 12350 | X24: =SUM(L24:W24) -> 148200
A25: =+A24 -> 2024019 | B25: =+B24 -> 0 | K25: 厚生年金 | L25: 23790 | M25: 23790 | N25: 23790 | O25: 23790 | P25: 23790 | Q25: 23790 | R25: 23790 | S25: 23790 | T25: 23790 | U25: 23790 | V25: 23790 | W25: 23790 | X25: =SUM(L25:W25) -> 285480
A26: =+A25 -> 2024019 | B26: =+B25 -> 0 | K26: 労災保険 | L26: 1280 | M26: 1280 | N26: 1280 | O26: 1280 | P26: 1258 | Q26: 1253 | R26: 1253 | S26: 1215 | T26: 1265 | U26: 1259 | V26: 1306 | W26: 1280 | X26: =SUM(L26:W26) -> 15209
A27: =+A26 -> 2024019 | B27: =+B26 -> 0 | K27: 雇用保険 | L27: 1408 | M27: 1408 | N27: 1408 | O27: 1408 | P27: 1383 | Q27: 1379 | R27: 1379 | S27: 1337 | T27: 1392 | U27: 1385 | V27: 1436 | W27: 1408 | X27: =SUM(L27:W27) -> 16731
A28: =+A27 -> 2024019 | B28: =+B27 -> 0 | K28: 粗利 | L28: =L17-L20 -> 125162 | M28: =M17-M20 -> 125162 | N28: =N17-N20 -> 125162 | O28: =O17-O20 -> 125162 | P28: =P17-P20 -> 129711 | Q28: =Q17-Q20 -> 130542 | R28: =R17-R20 -> 130542 | S28: =S17-S20 -> 126490 | ... X28: =X17-X20 -> 1448884
C29: =C2 -> ネットワークサービス本部 | K29: 売上 | L29: =L5+L17 -> 1150000 | M29: =M5+M17 -> 1127150 | N29: =N5+N17 -> 1150000 | O29: =O5+O17 -> 1150000 | P29: =P5+P17 -> 1150000 | Q29: =Q5+Q17 -> 1150000 | R29: =R5+R17 -> 1150000 | S29: =S5+S17 -> 1062805 | ... W29: =W5+W17 -> 1150000 | X29: =SUM(L29:W29) -> 13482055
K30: 仕入 | L30: =L8+L20 -> 866552 | M30: =M8+M20 -> 863755 | N30: =N8+N20 -> 869534 | O30: =O8+O20 -> 867547 | P30: =P8+P20 -> 862003 | Q30: =Q8+Q20 -> 864804 | R30: =R8+R20 -> 866337 | S30: =S8+S20 -> 852634 | ... W30: =W8+W20 -> 866552 | X30: =SUM(L30:W30) -> 10360502
K31: 粗利 | L31: =L29-L30 -> 283448 | M31: =M29-M30 -> 263395 | N31: =N29-N30 -> 280466 | O31: =O29-O30 -> 282453 | P31: =P29-P30 -> 287997 | Q31: =Q29-Q30 -> 285196 | R31: =R29-R30 -> 283663 | S31: =S29-S30 -> 210171 | ... W31: =W29-W30 -> 283448 | X31: =SUM(L31:W31) -> 3121553
K32: Q売上 | L32: =SUM(L29:N29) -> 3427150 | O32: =SUM(O29:Q29) -> 3450000 | R32: =SUM(R29:T29) -> 3275975 | U32: =SUM(U29:W29) -> 3328930 | X32: =X29 -> 13482055
K33: Q仕入 | L33: =SUM(L30:N30) -> 2599841 | O33: =SUM(O30:Q30) -> 2594354 | R33: =SUM(R30:T30) -> 2581392 | U33: =SUM(U30:W30) -> 2584915 | X33: =X30 -> 10360502
K34: Q粗利 | L34: =SUM(L31:N31) -> 827309 | O34: =SUM(O31:Q31) -> 855646 | R34: =SUM(R31:T31) -> 694583 | U34: =SUM(U31:W31) -> 744015 | X34: =X31 -> 3121553

Sheet アカウントサービス第一本部
A1: 社員番号 | B1: 氏名 | C1: No | D1: 派遣/請負 | E1: 担当 | F1: 氏名 | G1: 派遣先部署 | H1: 作業名 | I1: 契約先 | J1: 外注会社 | K1: 売上単価 (支払単価） 【≒粗利】 | L1: 4月 | M1: 5月 | N1: 6月 | O1: 7月 | P1: 8月 | Q1: 9月 | R1: 10月 | S1: 11月 | T1: 12月 | U1: 1月 | V1: 2月 | W1: 3月 | X1: 合計
C2: アカウントサービス第一本部 | K2: 売上 | L2: =L125 -> 7233400 | M2: =M125 -> 7381230 | N2: =N125 -> 7754925 | O2: =O125 -> 7945385 | P2: =P125 -> 7255870 | Q2: =Q125 -> 7501850 | R2: =R125 -> 7944685 | S2: =S125 -> 7497605 | ... W2: =W125 -> 7247882.8 | X2: =SUM(L2:W2) -> 90010903
K3: 仕入 | L3: =L126 -> 5961660 | M3: =M126 -> 5817622 | N3: =N126 -> 6261808 | O3: =O126 -> 6454475 | P3: =P126 -> 5955003 | Q3: =Q126 -> 5994003 | R3: =R126 -> 6284881 | S3: =S126 -> 6005666 | ... W3: =W126 -> 5939386.1 | X3: =SUM(L3:W3) -> 72953630
K4: 粗利 | L4: =L2-L3 -> 1271740 | M4: =M2-M3 -> 1563608 | N4: =N2-N3 -> 1493117 | O4: =O2-O3 -> 1490910 | P4: =P2-P3 -> 1300867 | Q4: =Q2-Q3 -> 1507847 | R4: =R2-R3 -> 1659804 | S4: =S2-S3 -> 1491939 | ... W4: =W2-W3 -> 1308496.7 | X4: =SUM(L4:W4) -> 17057273
A5: 2017038 | C5: 1 | D5: 派遣 | G5: アカウントサービス第一本部システムサービス二部 | J5: 社員 | K5: 総受注金額 | L5: =L6+L7 -> 728500 | M5: =M6+M7 -> 700300 | N5: =N6+N7 -> 834250 | O5: =O6+O7 -> 749650 | P5: =P6+P7 -> 688550 | Q5: =Q6+Q7 -> 747300 | R5: =R6+R7 -> 801350 | S5: =S6+S7 -> 768450 | ... W5: =W6+W7 -> 717088.89 | X5: =SUM(L5:W5) -> 8631888.9
A6: =+A5 -> 2017038 | K6: 派遣金額 | L6: 728500 | M6: 700300 | N6: 834250 | O6: 749650 | P6: 688550 | Q6: 747300 | R6: 801350 | S6: 768450 | T6: 749650 | U6: 662700 | V6: 484100 | W6: 717088.89 | X6: =SUM(L6:W6) -> 8631888.9
A7: =+A6 -> 2017038 | K7: 交通費 | X7: =SUM(L7:W7) -> 0
A8: =+A7 -> 2017038 | K8: 総経費 | L8: =SUM(L9:L15) -> 601640 | M8: =SUM(M9:M15) -> 555940 | N8: =SUM(N9:N15) -> 692574 | O8: =SUM(O9:O15) -> 620335 | P8: =SUM(P9:P15) -> 638247 | Q8: =SUM(Q9:Q15) -> 591132 | R8: =SUM(R9:R15) -> 624847 | S8: =SUM(S9:S15) -> 621564 | ... W8: =SUM(W9:W15) -> 594380.89 | X8: =SUM(L8:W8) -> 7260707.9
A9: =+A8 -> 2017038 | K9: 賃金 | L9: 520669 | M9: 476932 | N9: 611154 | O9: 540658 | P9: 558384 | Q9: 510766 | R9: 543851 | S9: 541875 | T9: 556470 | U9: 478879 | V9: 446952 | W9: 513409.89 | X9: =SUM(L9:W9) -> 6299999.9
A10: =+A9 -> 2017038 | K10: 交通費その他 | X10: =SUM(L10:W10) -> 0
A11: =+A10 -> 2017038 | K11: 通勤定期代 | L11: 1488 | M11: 0 | N11: 992 | O11: 0 | P11: 0 | Q11: 992 | R11: 1272 | S11: 0 | T11: 0 | U11: 0 | V11: 0 | W11: 1488 | X11: =SUM(L11:W11) -> 6232
A12: =+A11 -> 2017038 | K12: 健康保険 | L12: 28250 | M12: 28250 | N12: 28250 | O12: 28250 | P12: 28250 | Q12: 28250 | R12: 28250 | S12: 28250 | T12: 28250 | U12: 28250 | V12: 28250 | W12: 28250 | X12: =SUM(L12:W12) -> 339000
A13: =+A12 -> 2017038 | K13: 厚生年金 | L13: 45750 | M13: 45750 | N13: 45750 | O13: 45750 | P13: 45750 | Q13: 45750 | R13: 45750 | S13: 45750 | T13: 45750 | U13: 45750 | V13: 45750 | W13: 45750 | X13: =SUM(L13:W13) -> 549000
A14: =+A13 -> 2017038 | K14: 労災保険 | L14: 2611 | M14: 2385 | N14: 3061 | O14: 2703 | P14: 2792 | Q14: 2559 | R14: 2726 | S14: 2709 | T14: 2782 | U14: 2394 | V14: 2322 | W14: 2611 | X14: =SUM(L14:W14) -> 31655
A15: =+A14 -> 2017038 | K15: 雇用保険 | L15: 2872 | M15: 2623 | N15: 3367 | O15: 2974 | P15: 3071 | Q15: 2815 | R15: 2998 | S15: 2980 | T15: 3061 | U15: 2634 | V15: 2554 | W15: 2872 | X15: =SUM(L15:W15) -> 34821
A16: =+A15 -> 2017038 | K16: 粗利 | L16: =L5-L8 -> 126860 | M16: =M5-M8 -> 144360 | N16: =N5-N8 -> 141676 | O16: =O5-O8 -> 129315 | P16: =P5-P8 -> 50303 | Q16: =Q5-Q8 -> 156168 | R16: =R5-R8 -> 176503 | S16: =S5-S8 -> 146886 | ... X16: =X5-X8 -> 1371181
A17: 2024041 | C17: =C5+1 -> 2 | D17: 派遣 | G17: アカウントサービス第一本部システムサービス三部 | J17: 社員 | K17: 総受注金額 | L17: =L18+L19 -> 801150 | M17: =M18+M19 -> 899250 | N17: =N18+N19 -> 926500 | O17: =O18+O19 -> 1046400 | P17: =P18+P19 -> 869275 | Q17: =Q18+Q19 -> 839300 | R17: =R18+R19 -> 1008250 | S17: =S18+S19 -> 923775 | ... W17: =W18+W19 -> 907425 | X17: =SUM(L17:W17) -> 10889100
A18: =+A17 -> 2024041 | K18: 派遣金額 | L18: 801150 | M18: 899250 | N18: 926500 | O18: 1046400 | P18: 869275 | Q18: 839300 | R18: 1008250 | S18: 923775 | T18: 967375 | U18: 880175 | V18: 820225 | W18: 907425 | X18: =SUM(L18:W18) -> 10889100
A19: =+A18 -> 2024041 | K19: 交通費 | X19: 0
A20: =+A19 -> 2024041 | K20: 総経費 | L20: =SUM(L21:L27) -> 644124 | M20: =SUM(M21:M27) -> 645337 | N20: =SUM(N21:N27) -> 654555 | O20: =SUM(O21:O27) -> 685607 | P20: =SUM(P21:P27) -> 672741 | Q20: =SUM(Q21:Q27) -> 641813 | R20: =SUM(R21:R27) -> 661970 | S20: =SUM(S21:S27) -> 639657 | ... W20: =SUM(W21:W27) -> 645124 | X20: =SUM(L20:W20) -> 7855951
A21: =+A20 -> 2024041 | K21: 賃金 | L21: 540400 | M21: 541600 | N21: 550722 | O21: 582972 | P21: 568931 | Q21: 541200 | R21: 570917 | S21: 545600 | T21: 589056 | U21: 546000 | V21: 545200 | W21: 541400 | X21: =SUM(L21:W21) -> 6663998
A22: =+A21 -> 2024041 | K22: 交通費その他 | X22: =SUM(L22:W22) -> 0
A23: =+A22 -> 2024041 | K23: 通勤定期代 | L23: 20000 | M23: 20000 | N23: 20000 | O23: 18480 | P23: 19788 | Q23: 16912 | R23: 7144 | S23: 5392 | T23: 5392 | U23: 5392 | V23: 7328 | W23: 20000 | X23: =SUM(L23:W23) -> 165828
A24: =+A23 -> 2024041 | K24: 健康保険 | L24: 26600 | M24: 26600 | N24: 26600 | O24: 26600 | P24: 26600 | Q24: 26600 | R24: 26600 | S24: 31640 | T24: 31640 | U24: 31640 | V24: 31640 | W24: 26600 | X24: =SUM(L24:W24) -> 339360
A25: =+A24 -> 2024041 | K25: 厚生年金 | L25: 51240 | M25: 51240 | N25: 51240 | O25: 51240 | P25: 51240 | Q25: 51240 | R25: 51240 | S25: 51240 | T25: 51240 | U25: 51240 | V25: 51240 | W25: 51240 | X25: =SUM(L25:W25) -> 614880
A26: =+A25 -> 2024041 | K26: 労災保険 | L26: 2802 | M26: 2808 | N26: 2854 | O26: 3007 | P26: 2944 | Q26: 2791 | R26: 2890 | S26: 2755 | T26: 2972 | U26: 2757 | V26: 2850 | W26: 2802 | X26: =SUM(L26:W26) -> 34232
A27: =+A26 -> 2024041 | K27: 雇用保険 | L27: 3082 | M27: 3089 | N27: 3139 | O27: 3308 | P27: 3238 | Q27: 3070 | R27: 3179 | S27: 3030 | T27: 3269 | U27: 3033 | V27: 3134 | W27: 3082 | X27: =SUM(L27:W27) -> 37653
A28: =+A27 -> 2024041 | K28: 粗利 | L28: =L17-L20 -> 157026 | M28: =M17-M20 -> 253913 | N28: =N17-N20 -> 271945 | O28: =O17-O20 -> 360793 | P28: =P17-P20 -> 196534 | Q28: =Q17-Q20 -> 197487 | R28: =R17-R20 -> 346280 | S28: =S17-S20 -> 284118 | ... X28: =X17-X20 -> 3033149
A29: 2019029 | C29: =C17+1 -> 3 | D29: 派遣 | G29: アカウントサービス第一本部システムサービス三部 | J29: 社員 | K29: 総受注金額 | L29: =L30+L31 -> 730000 | M29: =M30+M31 -> 730000 | N29: =N30+N31 -> 730000 | O29: =O30+O31 -> 730000 | P29: =P30+P31 -> 730000 | Q29: =Q30+Q31 -> 730000 | R29: =R30+R31 -> 730000 | S29: =S30+S31 -> 730000 | ... W29: =W30+W31 -> 700000 | X29: =SUM(L29:W29) -> 8730000
A30: =+A29 -> 2019029 | K30: 派遣金額 | L30: 730000 | M30: 730000 | N30: 730000 | O30: 730000 | P30: 730000 | Q30: 730000 | R30: 730000 | S30: 730000 | T30: 730000 | U30: 730000 | V30: 730000 | W30: 700000 | X30: =SUM(L30:W30) -> 8730000
A31: =+A30 -> 2019029 | K31: 交通費 | X31: 0
A32: =+A31 -> 2019029 | K32: 総経費 | L32: =SUM(L33:L39) -> 541348 | M32: =SUM(M33:M39) -> 546004 | N32: =SUM(N33:N39) -> 549885 | O32: =SUM(O33:O39) -> 546037 | P32: =SUM(P33:P39) -> 544825 | Q32: =SUM(Q33:Q39) -> 548333 | R32: =SUM(R33:R39) -> 548737 | S32: =SUM(S33:S39) -> 550136 | ... W32: =SUM(W33:W39) -> 529481.33 | X32: =SUM(L32:W32) -> 6559126.3
A33: =+A32 -> 2019029 | K33: 賃金 | L33: 466400 | M33: 464000 | N33: 462000 | O33: 465200 | P33: 464000 | Q33: 462800 | R33: 463200 | S33: 460800 | T33: 462800 | U33: 461200 | V33: 460400 | W33: 454533.33 | X33: =SUM(L33:W33) -> 5547333.3
A34: =+A33 -> 2019029 | K34: 交通費その他 | X34: =SUM(L34:W34) -> 0
A35: =+A34 -> 2019029 | K35: 通勤定期代 | L35: 4672 | M35: 11680 | N35: 17520 | O35: 10512 | P35: 10512 | Q35: 15184 | R35: 15184 | S35: 18968 | T35: 9766 | U35: 16862 | V35: 19430 | W35: 4672 | X35: =SUM(L35:W35) -> 154962
A36: =+A35 -> 2019029 | K36: 健康保険 | L36: 22325 | M36: 22325 | N36: 22325 | O36: 22325 | P36: 22325 | Q36: 22325 | R36: 22325 | S36: 22325 | T36: 26555 | U36: 26555 | V36: 26555 | W36: 22325 | X36: =SUM(L36:W36) -> 280590
A37: =+A36 -> 2019029 | K37: 厚生年金 | L37: 43005 | M37: 43005 | N37: 43005 | O37: 43005 | P37: 43005 | Q37: 43005 | R37: 43005 | S37: 43005 | T37: 43005 | U37: 43005 | V37: 43005 | W37: 43005 | X37: =SUM(L37:W37) -> 516060
A38: =+A37 -> 2019029 | K38: 労災保険 | L38: 2355 | M38: 2378 | N38: 2398 | O38: 2379 | P38: 2373 | Q38: 2390 | R38: 2392 | S38: 2399 | T38: 2363 | U38: 2390 | V38: 2486 | W38: 2355 | X38: =SUM(L38:W38) -> 28658
A39: =+A38 -> 2019029 | K39: 雇用保険 | L39: 2591 | M39: 2616 | N39: 2637 | O39: 2616 | P39: 2610 | Q39: 2629 | R39: 2631 | S39: 2639 | T39: 2599 | U39: 2629 | V39: 2735 | W39: 2591 | X39: =SUM(L39:W39) -> 31523
A40: =+A39 -> 2019029 | K40: 粗利 | L40: =L29-L32 -> 188652 | M40: =M29-M32 -> 183996 | N40: =N29-N32 -> 180115 | O40: =O29-O32 -> 183963 | P40: =P29-P32 -> 185175 | Q40: =Q29-Q32 -> 181667 | R40: =R29-R32 -> 181263 | S40: =S29-S32 -> 179864 | ... X40: =X29-X32 -> 2170873.7
A41: 2009009 | C41: =C29+1 -> 4 | D41: 派遣 | G41: アカウントサービス第一本部システムサービス三部 | J41: 社員 | K41: 総受注金額 | L41: =L42+L43 -> 520000 | M41: =M42+M43 -> 497250 | N41: =N42+N43 -> 497250 | O41: =O42+O43 -> 520000 | P41: =P42+P43 -> 497250 | Q41: =Q42+Q43 -> 497250 | R41: =R42+R43 -> 520000 | S41: =S42+S43 -> 455000 | ... W41: =W42+W43 -> 483013.33 | X41: =SUM(L41:W41) -> 5891013.3
A42: =+A41 -> 2009009 | K42: 派遣金額 | L42: 520000 | M42: 497250 | N42: 497250 | O42: 520000 | P42: 497250 | Q42: 497250 | R42: 520000 | S42: 455000 | T42: 474500 | U42: 474500 | V42: 455000 | W42: 483013.33 | X42: =SUM(L42:W42) -> 5891013.3
A43: =+A42 -> 2009009 | K43: 交通費 | X43: 0
A44: =+A43 -> 2009009 | K44: 総経費 | L44: =SUM(L45:L51) -> 417386 | M44: =SUM(M45:M51) -> 397648 | N44: =SUM(N45:N51) -> 418153 | O44: =SUM(O45:O51) -> 437890 | P44: =SUM(P45:P51) -> 400570 | Q44: =SUM(Q45:Q51) -> 391765 | R44: =SUM(R45:R51) -> 427146 | S44: =SUM(S45:S51) -> 363693 | ... W44: =SUM(W45:W51) -> 404152.11 | X44: =SUM(L44:W44) -> 4850530.1
A45: =+A44 -> 2009009 | K45: 賃金 | L45: 347400 | M45: 331560 | N45: 348160 | O45: 364000 | P45: 330760 | Q45: 332360 | R45: 363680 | S45: 299040 | T45: 345840 | U45: 331230 | V45: 312485 | W45: 334166.11 | X45: =SUM(L45:W45) -> 4040681.1
A46: =+A45 -> 2009009 | K46: 交通費その他 | X46: =SUM(L46:W46) -> 0
A47: =+A46 -> 2009009 | K47: 通勤定期代 | L47: 12922 | M47: 9230 | N47: 12922 | O47: 16614 | P47: 12922 | Q47: 5538 | R47: 9230 | S47: 11076 | T47: 11076 | U47: 12922 | V47: 16614 | W47: 12922 | X47: =SUM(L47:W47) -> 143988
A48: =+A47 -> 2009009 | K48: 健康保険 | L48: 20340 | M48: 20340 | N48: 20340 | O48: 20340 | P48: 20340 | Q48: 19210 | R48: 19210 | S48: 19210 | T48: 19210 | U48: 19210 | V48: 19210 | W48: 20340 | X48: =SUM(L48:W48) -> 237300
A49: =+A48 -> 2009009 | K49: 厚生年金 | L49: 32940 | M49: 32940 | N49: 32940 | O49: 32940 | P49: 32940 | Q49: 31110 | R49: 31110 | S49: 31110 | T49: 31110 | U49: 31110 | V49: 31110 | W49: 32940 | X49: =SUM(L49:W49) -> 384300
A50: =+A49 -> 2009009 | K50: 労災保険 | L50: 1802 | M50: 1704 | N50: 1805 | O50: 1903 | P50: 1718 | Q50: 1689 | R50: 1865 | S50: 1551 | T50: 1785 | U50: 1721 | V50: 1732 | W50: 1802 | X50: =SUM(L50:W50) -> 21077
A51: =+A50 -> 2009009 | K51: 雇用保険 | L51: 1982 | M51: 1874 | N51: 1986 | O51: 2093 | P51: 1890 | Q51: 1858 | R51: 2051 | S51: 1706 | T51: 1963 | U51: 1893 | V51: 1906 | W51: 1982 | X51: =SUM(L51:W51) -> 23184
A52: =+A51 -> 2009009 | K52: 粗利 | L52: =L41-L44 -> 102614 | M52: =M41-M44 -> 99602 | N52: =N41-N44 -> 79097 | O52: =O41-O44 -> 82110 | P52: =P41-P44 -> 96680 | Q52: =Q41-Q44 -> 105485 | R52: =R41-R44 -> 92854 | S52: =S41-S44 -> 91307 | ... X52: =X41-X44 -> 1040483.2
A53: 2017031 | C53: =C41+1 -> 5 | D53: 派遣 | G53: アカウントサービス第一本部システムサービス三部 | J53: 社員 | K53: 総受注金額 | L53: =L54+L55 -> 570000 | M53: =M54+M55 -> 570000 | N53: =N54+N55 -> 570000 | O53: =O54+O55 -> 673530 | P53: =P54+P55 -> 570000 | Q53: =Q54+Q55 -> 570000 | R53: =R54+R55 -> 669960 | S53: =S54+S55 -> 570000 | ... W53: =W54+W55 -> 530735.56 | X53: =SUM(L53:W53) -> 7345160.6
A54: =+A53 -> 2017031 | K54: 派遣金額 | L54: 570000 | M54: 570000 | N54: 570000 | O54: 673530 | P54: 570000 | Q54: 570000 | R54: 669960 | S54: 570000 | T54: 682455 | U54: 798480 | V54: 570000 | W54: 530735.56 | X54: =SUM(L54:W54) -> 7345160.6
A55: =+A54 -> 2017031 | K55: 交通費 | X55: 0
A56: =+A55 -> 2017031 | K56: 総経費 | L56: =SUM(L57:L63) -> 425176 | M56: =SUM(M57:M63) -> 425694 | N56: =SUM(N57:N63) -> 469730 | O56: =SUM(O57:O63) -> 490504 | P56: =SUM(P57:P63) -> 421410 | Q56: =SUM(Q57:Q63) -> 422381 | R56: =SUM(R57:R63) -> 489366 | S56: =SUM(S57:S63) -> 425647 | ... W56: =SUM(W57:W63) -> 413415.78 | X56: =SUM(L56:W56) -> 5551081.8
A57: =+A56 -> 2017031 | K57: 賃金 | L57: 360967 | M57: 358200 | N57: 398658 | O57: 419608 | P57: 361000 | Q57: 357800 | R57: 417129 | S57: 355000 | T57: 447754 | U57: 536234 | V57: 384866 | W57: 349206.78 | X57: =SUM(L57:W57) -> 4746422.8
A58: =+A57 -> 2017031 | K58: 交通費その他 | X58: =SUM(L58:W58) -> 0
A59: =+A58 -> 2017031 | K59: 通勤定期代 | L59: 7520 | M59: 10800 | N59: 13920 | O59: 13528 | P59: 3760 | Q59: 10672 | R59: 17632 | S59: 16704 | T59: 12992 | U59: 12992 | V59: 7888 | W59: 7520 | X59: =SUM(L59:W59) -> 135928
A60: =+A59 -> 2017031 | K60: 健康保険 | L60: 18050 | M60: 18050 | N60: 18050 | O60: 18050 | P60: 18050 | Q60: 17100 | R60: 17100 | S60: 17100 | T60: 17100 | U60: 17100 | V60: 17100 | W60: 18050 | X60: =SUM(L60:W60) -> 210900
A61: =+A60 -> 2017031 | K61: 厚生年金 | L61: 34770 | M61: 34770 | N61: 34770 | O61: 34770 | P61: 34770 | Q61: 32940 | R61: 32940 | S61: 32940 | T61: 32940 | U61: 32940 | V61: 32940 | W61: 34770 | X61: =SUM(L61:W61) -> 406260
A62: =+A61 -> 2017031 | K62: 労災保険 | L62: 1842 | M62: 1845 | N62: 2063 | O62: 2166 | P62: 1824 | Q62: 1842 | R62: 2174 | S62: 1859 | T62: 2304 | U62: 2746 | V62: 2051 | W62: 1842 | X62: =SUM(L62:W62) -> 24558
A63: =+A62 -> 2017031 | K63: 雇用保険 | L63: 2027 | M63: 2029 | N63: 2269 | O63: 2382 | P63: 2006 | Q63: 2027 | R63: 2391 | S63: 2044 | T63: 2534 | U63: 3021 | V63: 2256 | W63: 2027 | X63: =SUM(L63:W63) -> 27013
A64: =+A63 -> 2017031 | K64: 粗利 | L64: =L53-L56 -> 144824 | M64: =M53-M56 -> 144306 | N64: =N53-N56 -> 100270 | O64: =O53-O56 -> 183026 | P64: =P53-P56 -> 148590 | Q64: =Q53-Q56 -> 147619 | R64: =R53-R56 -> 180594 | S64: =S53-S56 -> 144353 | ... X64: =X53-X56 -> 1794078.8
A65: 2013024 | C65: =C53+1 -> 6 | D65: 派遣 | G65: アカウントサービス第一本部システムサービス三部 | H65: NM | J65: 社員 | K65: 総受注金額 | L65: =L66+L67 -> 770000 | M65: =M66+M67 -> 844555 | N65: =N66+N67 -> 854175 | O65: =O66+O67 -> 943160 | P65: =P66+P67 -> 770000 | Q65: =Q66+Q67 -> 770000 | R65: =R66+R67 -> 770000 | S65: =S66+S67 -> 770000 | ... W65: =W66+W67 -> 813022.78 | X65: =SUM(L65:W65) -> 9482637.8
A66: =+A65 -> 2013024 | K66: 派遣金額 | L66: 770000 | M66: 844555 | N66: 854175 | O66: 943160 | P66: 770000 | Q66: 770000 | R66: 770000 | S66: 770000 | T66: 770000 | U66: 770000 | V66: 637725 | W66: 813022.78 | X66: =SUM(L66:W66) -> 9482637.8
A67: =+A66 -> 2013024 | K67: 交通費 | X67: 0
A68: =+A67 -> 2013024 | K68: 総経費 | L68: =SUM(L69:L75) -> 644719 | M68: =SUM(M69:M75) -> 700748 | N68: =SUM(N69:N75) -> 711214 | O68: =SUM(O69:O75) -> 787144 | P68: =SUM(P69:P75) -> 638841 | Q68: =SUM(Q69:Q75) -> 630365 | R68: =SUM(R69:R75) -> 631161 | S68: =SUM(S69:S75) -> 630963 | ... W68: =SUM(W69:W75) -> 673672.33 | X68: =SUM(L68:W68) -> 7919985.3
A69: =+A68 -> 2013024 | K69: 賃金 | L69: 543033 | M69: 595120 | N69: 597313 | O69: 676524 | P69: 537200 | Q69: 537600 | R69: 539200 | S69: 536400 | T69: 536000 | U69: 537600 | V69: 522020 | W69: 571986.33 | X69: =SUM(L69:W69) -> 6729996.3
A70: =+A69 -> 2013024 | K70: 交通費その他 | X70: =SUM(L70:W70) -> 0
A71: =+A70 -> 2013024 | K71: 通勤定期代 | L71: 4180 | M71: 7540 | N71: 15704 | O71: 11634 | P71: 4196 | Q71: 4196 | R71: 3384 | S71: 5988 | T71: 5372 | U71: 2226 | V71: 2260 | W71: 4180 | X71: =SUM(L71:W71) -> 70860
A72: =+A71 -> 2013024 | K72: 健康保険 | L72: 35030 | M72: 35030 | N72: 35030 | O72: 35030 | P72: 35030 | Q72: 31640 | R72: 31640 | S72: 31640 | T72: 31640 | U72: 31640 | V72: 31640 | W72: 35030 | X72: =SUM(L72:W72) -> 400020
A73: =+A72 -> 2013024 | K73: 厚生年金 | L73: 56730 | M73: 56730 | N73: 56730 | O73: 56730 | P73: 56730 | Q73: 51240 | R73: 51240 | S73: 51240 | T73: 51240 | U73: 51240 | V73: 51240 | W73: 56730 | X73: =SUM(L73:W73) -> 647820
A74: =+A73 -> 2013024 | K74: 労災保険 | L74: 2736 | M74: 3013 | N74: 3065 | O74: 3441 | P74: 2707 | Q74: 2709 | R74: 2713 | S74: 2712 | T74: 2707 | U74: 2699 | V74: 2708 | W74: 2736 | X74: =SUM(L74:W74) -> 33946
A75: =+A74 -> 2013024 | K75: 雇用保険 | L75: 3010 | M75: 3315 | N75: 3372 | O75: 3785 | P75: 2978 | Q75: 2980 | R75: 2984 | S75: 2983 | T75: 2978 | U75: 2969 | V75: 2979 | W75: 3010 | X75: =SUM(L75:W75) -> 37343
A76: =+A75 -> 2013024 | K76: 粗利 | L76: =L65-L68 -> 125281 | M76: =M65-M68 -> 143807 | N76: =N65-N68 -> 142961 | O76: =O65-O68 -> 156016 | P76: =P65-P68 -> 131159 | Q76: =Q65-Q68 -> 139635 | R76: =R65-R68 -> 138839 | S76: =S65-S68 -> 139037 | ... X76: =X65-X68 -> 1562652.4
A77: 2014012 | C77: =C65+1 -> 7 | D77: 派遣 | G77: アカウントサービス第一本部システムサービス三部 | J77: 社員 | K77: 総受注金額 | L77: =L78+L79 -> 691375 | M77: =M78+M79 -> 693720 | N77: =N78+N79 -> 750000 | O77: =O78+O79 -> 750000 | P77: =P78+P79 -> 747655 | Q77: =Q78+Q79 -> 750000 | R77: =R78+R79 -> 750000 | S77: =S78+S79 -> 750000 | ... W77: =W78+W79 -> 701750 | X77: =SUM(L77:W77) -> 8724285
A78: =+A77 -> 2014012 | K78: 派遣金額 | L78: 691375 | M78: 693720 | N78: 750000 | O78: 750000 | P78: 747655 | Q78: 750000 | R78: 750000 | S78: 750000 | T78: 693720 | U78: 696065 | V78: 750000 | W78: 701750 | X78: =SUM(L78:W78) -> 8724285
A79: =+A78 -> 2014012 | K79: 交通費 | X79: 0
A80: =+A79 -> 2014012 | K80: 総経費 | L80: =SUM(L81:L87) -> 639267 | M80: =SUM(M81:M87) -> 633669 | N80: =SUM(N81:N87) -> 640076 | O80: =SUM(O81:O87) -> 637873 | P80: =SUM(P81:P87) -> 635932 | Q80: =SUM(Q81:Q87) -> 641192 | R80: =SUM(R81:R87) -> 639281 | S80: =SUM(S81:S87) -> 643344 | ... W80: =SUM(W81:W87) -> 632778.11 | X80: =SUM(L80:W80) -> 7659044.1
A81: =+A80 -> 2014012 | K81: 賃金 | L81: 535000 | M81: 535400 | N81: 535800 | O81: 537000 | P81: 537000 | Q81: 537800 | R81: 540200 | S81: 538200 | T81: 537800 | U81: 537800 | V81: 540200 | W81: 528511.11 | X81: =SUM(L81:W81) -> 6440711.1
A82: =+A81 -> 2014012 | K82: 交通費その他 | X82: =SUM(L82:W82) -> 0
A83: =+A82 -> 2014012 | K83: 通勤定期代 | L83: 20000 | M83: 14060 | N83: 20000 | O83: 16620 | P83: 14700 | Q83: 14710 | R83: 10420 | S83: 16440 | T83: 12320 | U83: 12250 | V83: 9120 | W83: 20000 | X83: =SUM(L83:W83) -> 180640
A84: =+A83 -> 2014012 | K84: 健康保険 | L84: 29945 | M84: 29945 | N84: 29945 | O84: 29945 | P84: 29945 | Q84: 31640 | R84: 31640 | S84: 31640 | T84: 31640 | U84: 31640 | V84: 31640 | W84: 29945 | X84: =SUM(L84:W84) -> 369510
A85: =+A84 -> 2014012 | K85: 厚生年金 | L85: 48495 | M85: 48495 | N85: 48495 | O85: 48495 | P85: 48495 | Q85: 51240 | R85: 51240 | S85: 51240 | T85: 51240 | U85: 51240 | V85: 51240 | W85: 48495 | X85: =SUM(L85:W85) -> 598410
A86: =+A85 -> 2014012 | K86: 労災保険 | L86: 2775 | M86: 2747 | N86: 2779 | O86: 2768 | P86: 2758 | Q86: 2763 | R86: 2753 | S86: 2773 | T86: 2751 | U86: 2750 | V86: 2833 | W86: 2775 | X86: =SUM(L86:W86) -> 33225
A87: =+A86 -> 2014012 | K87: 雇用保険 | L87: 3052 | M87: 3022 | N87: 3057 | O87: 3045 | P87: 3034 | Q87: 3039 | R87: 3028 | S87: 3051 | T87: 3026 | U87: 3025 | V87: 3117 | W87: 3052 | X87: =SUM(L87:W87) -> 36548
A88: =+A87 -> 2014012 | K88: 粗利 | L88: =L77-L80 -> 52108 | M88: =M77-M80 -> 60051 | N88: =N77-N80 -> 109924 | O88: =O77-O80 -> 112127 | P88: =P77-P80 -> 111723 | Q88: =Q77-Q80 -> 108808 | R88: =R77-R80 -> 110719 | S88: =S77-S80 -> 106656 | ... X88: =X77-X80 -> 1065240.9
A89: 2011001 | C89: =C77+1 -> 8 | D89: 派遣 | G89: アカウントサービス第一本部システムサービス三部 | H89: UCシステム設計、構築 | I89: 技術第一本部東日本技術統括部UCテクノロジー部 (五十嵐部長） | J89: 社員 | K89: 総受注金額 | L89: =L90+L91 -> 850000 | M89: =M90+M91 -> 836725 | N89: =N90+N91 -> 850000 | O89: =O90+O91 -> 873895 | P89: =P90+P91 -> 786280 | Q89: =Q90+Q91 -> 850000 | R89: =R90+R91 -> 850000 | S89: =S90+S91 -> 905755 | ... W89: =W90+W91 -> 803722.22 | X89: =SUM(L89:W89) -> 10137792
A90: =+A89 -> 2011001 | K90: 派遣金額 | L90: 850000 | M90: 836725 | N90: 850000 | O90: 873895 | P90: 786280 | Q90: 850000 | R90: 850000 | S90: 905755 | T90: 850000 | U90: 850000 | V90: 831415 | W90: 803722.22 | X90: =SUM(L90:W90) -> 10137792
A91: =+A90 -> 2011001 | K91: 交通費 | X91: =SUM(L91:W91) -> 0
A92: =+A91 -> 2011001 | K92: 総経費 | L92: =SUM(L93:L99) -> 654493 | M92: =SUM(M93:M99) -> 657504 | N92: =SUM(N93:N99) -> 721652 | O92: =SUM(O93:O99) -> 758150 | P92: =SUM(P93:P99) -> 649845 | Q92: =SUM(Q93:Q99) -> 720142 | R92: =SUM(R93:R99) -> 706136 | S92: =SUM(S93:S99) -> 791887 | ... W92: =SUM(W93:W99) -> 729905.89 | X92: =SUM(L92:W92) -> 8418604.9
A93: =+A92 -> 2011001 | K93: 賃金 | L93: 541280 | M93: 544260 | N93: 607740 | O93: 643860 | P93: 536680 | Q93: 610640 | R93: 596780 | S93: 681640 | T93: 661292 | U93: 542600 | V93: 497680 | W93: 616692.89 | X93: =SUM(L93:W93) -> 7081144.9
A94: =+A93 -> 2011001 | K94: 交通費その他 | X94: =SUM(L94:W94) -> 0
A95: =+A94 -> 2011001 | K95: 通勤定期代 | L95: 20000 | M95: 20000 | N95: 20000 | O95: 20000 | P95: 20000 | Q95: 20000 | R95: 20000 | S95: 20000 | T95: 20000 | U95: 20000 | V95: 20000 | W95: 20000 | X95: =SUM(L95:W95) -> 240000
A96: =+A95 -> 2011001 | K96: 健康保険 | L96: 33335 | M96: 33335 | N96: 33335 | O96: 33335 | P96: 33335 | Q96: 31640 | R96: 31640 | S96: 31640 | T96: 31640 | U96: 31640 | V96: 31640 | W96: 33335 | X96: =SUM(L96:W96) -> 389850
A97: =+A96 -> 2011001 | K97: 厚生年金 | L97: 53985 | M97: 53985 | N97: 53985 | O97: 53985 | P97: 53985 | Q97: 51240 | R97: 51240 | S97: 51240 | T97: 51240 | U97: 51240 | V97: 51240 | W97: 53985 | X97: =SUM(L97:W97) -> 631350
A98: =+A97 -> 2011001 | K98: 労災保険 | L98: 2806 | M98: 2821 | N98: 3139 | O98: 3319 | P98: 2783 | Q98: 3153 | R98: 3084 | S98: 3508 | T98: 3406 | U98: 2813 | V98: 2675 | W98: 2806 | X98: =SUM(L98:W98) -> 36313
A99: =+A98 -> 2011001 | K99: 雇用保険 | L99: 3087 | M99: 3103 | N99: 3453 | O99: 3651 | P99: 3062 | Q99: 3469 | R99: 3392 | S99: 3859 | T99: 3747 | U99: 3094 | V99: 2943 | W99: 3087 | X99: =SUM(L99:W99) -> 39947
A100: =+A99 -> 2011001 | K100: 粗利 | L100: =L89-L92 -> 195507 | M100: =M89-M92 -> 179221 | N100: =N89-N92 -> 128348 | O100: =O89-O92 -> 115745 | P100: =P89-P92 -> 136435 | Q100: =Q89-Q92 -> 129858 | R100: =R89-R92 -> 143864 | S100: =S89-S92 -> 113868 | ... X100: =X89-X92 -> 1719187.3
...

Sheet アカウントサービス第二本部
A1: 社員番号 | B1: 氏名 | C1: No | D1: 派遣/請負 | E1: 担当 | F1: 氏名 | G1: 派遣先部署 | H1: 作業名 | I1: 契約先 | J1: 外注会社 | K1: 売上単価 (支払単価） 【≒粗利】 | L1: 4月 | M1: 5月 | N1: 6月 | O1: 7月 | P1: 8月 | Q1: 9月 | R1: 10月 | S1: 11月 | T1: 12月 | U1: 1月 | V1: 2月 | W1: 3月 | X1: 合計
C2: アカウントサービス第二本部 | K2: 売上 | L2: =L41 -> 760000 | M2: =M41 -> 1051235 | N2: =N41 -> 1070905 | O2: =O41 -> 1450000 | P2: =P41 -> 1454060 | Q2: =Q41 -> 1450000 | R2: =R41 -> 1614020 | S2: =S41 -> 1450000 | ... W2: =W41 -> 1410000 | X2: =SUM(L2:W2) -> 15985220
K3: 仕入 | L3: =L42 -> 612134 | M3: =M42 -> 910091 | N3: =N42 -> 865244 | O3: =O42 -> 1017483 | P3: =P42 -> 1013218 | Q3: =Q42 -> 999652 | R3: =R42 -> 1142236 | S3: =S42 -> 1020062 | ... W3: =W42 -> 976783 | X3: =SUM(L3:W3) -> 11642566
K4: 粗利 | L4: =L2-L3 -> 147866 | M4: =M2-M3 -> 141144 | N4: =N2-N3 -> 205661 | O4: =O2-O3 -> 432517 | P4: =P2-P3 -> 440842 | Q4: =Q2-Q3 -> 450348 | R4: =R2-R3 -> 471784 | S4: =S2-S3 -> 429938 | ... W4: =W2-W3 -> 433217 | X4: =SUM(L4:W4) -> 4342654
A5: 2024011 | C5: 1 | D5: 派遣 | G5: アカウントサービス第二本部公共ＩＣＴエンジニアリング三部 | J5: 社員 | K5: 総受注金額 | L5: =L6+L7 -> 760000 | M5: =M6+M7 -> 760000 | N5: =N6+N7 -> 760000 | O5: =O6+O7 -> 800000 | P5: =P6+P7 -> 800000 | Q5: =Q6+Q7 -> 800000 | R5: =R6+R7 -> 895000 | S5: =S6+S7 -> 800000 | ... W5: =W6+W7 -> 760000 | X5: =SUM(L5:W5) -> 9460000
A6: =+A5 -> 2024011 | K6: 派遣金額 | L6: 760000 | M6: 760000 | N6: 760000 | O6: 800000 | P6: 800000 | Q6: 800000 | R6: 895000 | S6: 800000 | T6: 800000 | U6: 800000 | V6: 725000 | W6: 760000 | X6: =SUM(L6:W6) -> 9460000
A7: =+A6 -> 2024011 | K7: 交通費 | X7: 0
A8: =+A7 -> 2024011 | K8: 総経費 | L8: =SUM(L9:L15) -> 612134 | M8: =SUM(M9:M15) -> 610817 | N8: =SUM(N9:N15) -> 610817 | O8: =SUM(O9:O15) -> 652434 | P8: =SUM(P9:P15) -> 637891 | Q8: =SUM(Q9:Q15) -> 628639 | R8: =SUM(R9:R15) -> 726380 | S8: =SUM(S9:S15) -> 634700 | ... W8: =SUM(W9:W15) -> 612134 | X8: =SUM(L8:W8) -> 7653768
A9: =+A8 -> 2024011 | K9: 賃金 | L9: 519400 | M9: 519400 | N9: 519400 | O9: 558125 | P9: 548800 | Q9: 546800 | R9: 630723 | S9: 555200 | T9: 556400 | U9: 559600 | V9: 557200 | W9: 519400 | X9: =SUM(L9:W9) -> 6590448
A10: =+A9 -> 2024011 | K10: 交通費その他 | X10: =SUM(L10:W10) -> 0
A11: =+A10 -> 2024011 | K11: 通勤定期代 | L11: 5216 | M11: 3912 | N11: 3912 | O11: 6372 | P11: 1304 | Q11: 2402 | R11: 15204 | S11: 0 | T11: 2312 | U11: 1304 | V11: 3826 | W11: 5216 | X11: =SUM(L11:W11) -> 50980
A12: =+A11 -> 2024011 | K12: 健康保険 | L12: 28025 | M12: 28025 | N12: 28025 | O12: 28025 | P12: 28025 | Q12: 25175 | R12: 25175 | S12: 25175 | T12: 25175 | U12: 25175 | V12: 28025 | W12: 28025 | X12: =SUM(L12:W12) -> 322050
A13: =+A12 -> 2024011 | K13: 厚生年金 | L13: 53985 | M13: 53985 | N13: 53985 | O13: 53985 | P13: 53985 | Q13: 48495 | R13: 48495 | S13: 48495 | T13: 48495 | U13: 48495 | V13: 53985 | W13: 53985 | X13: =SUM(L13:W13) -> 620370
A14: =+A13 -> 2024011 | K14: 労災保険 | L14: 2623 | M14: 2617 | N14: 2617 | O14: 2822 | P14: 2751 | Q14: 2746 | R14: 3230 | S14: 2776 | T14: 2794 | U14: 2805 | V14: 2892 | W14: 2623 | X14: =SUM(L14:W14) -> 33296
A15: =+A14 -> 2024011 | K15: 雇用保険 | L15: 2885 | M15: 2878 | N15: 2878 | O15: 3105 | P15: 3026 | Q15: 3021 | R15: 3553 | S15: 3054 | T15: 3073 | U15: 3085 | V15: 3181 | W15: 2885 | X15: =SUM(L15:W15) -> 36624
A16: =+A15 -> 2024011 | K16: 粗利 | L16: =L5-L8 -> 147866 | M16: =M5-M8 -> 149183 | N16: =N5-N8 -> 149183 | O16: =O5-O8 -> 147566 | P16: =P5-P8 -> 162109 | Q16: =Q5-Q8 -> 171361 | R16: =R5-R8 -> 168620 | S16: =S5-S8 -> 165300 | ... X16: =X5-X8 -> 1806232
A17: 2024049 | C17: =C5+1 -> 2 | D17: 派遣 | E17: 転出 | G17: アカウントサービス第二本部。公共ＩＣＴエンジニアリング一部 | J17: 社員 | K17: 総受注金額 | L17: =L18+L19 -> 0 | M17: =M18+M19 -> 291235 | N17: =N18+N19 -> 310905 | O17: =O18+O19 -> 0 | P17: =P18+P19 -> 0 | Q17: =Q18+Q19 -> 0 | R17: =R18+R19 -> 0 | S17: =S18+S19 -> 0 | ... W17: =W18+W19 -> 0 | X17: =SUM(L17:W17) -> 602140
A18: =+A17 -> 2024049 | K18: 派遣金額 | M18: 291235 | N18: 310905 | X18: =SUM(L18:W18) -> 602140
A19: =+A18 -> 2024049 | K19: 交通費 | X19: 0
A20: =+A19 -> 2024049 | K20: 総経費 | L20: =SUM(L21:L27) -> 0 | M20: =SUM(M21:M27) -> 299274 | N20: =SUM(N21:N27) -> 254427 | O20: =SUM(O21:O27) -> 0 | P20: =SUM(P21:P27) -> 0 | Q20: =SUM(Q21:Q27) -> 0 | R20: =SUM(R21:R27) -> 0 | S20: =SUM(S21:S27) -> 0 | ... W20: =SUM(W21:W27) -> 0 | X20: =SUM(L20:W20) -> 553701
A21: =+A20 -> 2024049 | K21: 賃金 | M21: 240400 | N21: 196019 | X21: =SUM(L21:W21) -> 436419
A22: =+A21 -> 2024049 | K22: 交通費その他 | X22: =SUM(L22:W22) -> 0
A23: =+A22 -> 2024049 | K23: 通勤定期代 | M23: 20000 | N23: 20000 | X23: =SUM(L23:W23) -> 40000
A24: =+A23 -> 2024049 | K24: 健康保険 | M24: 12350 | N24: 12350 | X24: =SUM(L24:W24) -> 24700
A25: =+A24 -> 2024049 | K25: 厚生年金 | M25: 23790 | N25: 23790 | X25: =SUM(L25:W25) -> 47580
A26: =+A25 -> 2024049 | K26: 労災保険 | M26: 1302 | N26: 1080 | X26: =SUM(L26:W26) -> 2382
A27: =+A26 -> 2024049 | K27: 雇用保険 | M27: 1432 | N27: 1188 | X27: =SUM(L27:W27) -> 2620
A28: =+A27 -> 2024049 | K28: 粗利 | L28: =L17-L20 -> 0 | M28: =M17-M20 -> -8039 | N28: =N17-N20 -> 56478 | O28: =O17-O20 -> 0 | P28: =P17-P20 -> 0 | Q28: =Q17-Q20 -> 0 | R28: =R17-R20 -> 0 | S28: =S17-S20 -> 0 | ... X28: =X17-X20 -> 48439
A29: 2023013 | C29: =C17+1 -> 3 | D29: 派遣 | G29: アカウントサービス第二本部。公共ＩＣＴエンジニアリング一部 | J29: 社員 | K29: 総受注金額 | L29: =L30+L31 -> 0 | M29: =M30+M31 -> 0 | N29: =N30+N31 -> 0 | O29: =O30+O31 -> 650000 | P29: =P30+P31 -> 654060 | Q29: =Q30+Q31 -> 650000 | R29: =R30+R31 -> 719020 | S29: =S30+S31 -> 650000 | ... W29: =W30+W31 -> 650000 | X29: =SUM(L29:W29) -> 5923080
A30: =+A29 -> 2023013 | B30: =+B29 -> 0 | K30: 派遣金額 | O30: 650000 | P30: 654060 | Q30: 650000 | R30: 719020 | S30: 650000 | T30: 650000 | U30: 650000 | V30: 650000 | W30: 650000 | X30: =SUM(L30:W30) -> 5923080
A31: =+A30 -> 2023013 | B31: =+B30 -> 0 | K31: 交通費 | X31: 0
A32: =+A31 -> 2023013 | B32: =+B31 -> 0 | K32: 総経費 | L32: =SUM(L33:L39) -> 0 | M32: =SUM(M33:M39) -> 0 | N32: =SUM(N33:N39) -> 0 | O32: =SUM(O33:O39) -> 365049 | P32: =SUM(P33:P39) -> 375327 | Q32: =SUM(Q33:Q39) -> 371013 | R32: =SUM(R33:R39) -> 415856 | S32: =SUM(S33:S39) -> 385362 | ... W32: =SUM(W33:W39) -> 364649 | X32: =SUM(L32:W32) -> 3435097
A33: =+A32 -> 2023013 | B33: =+B32 -> 0 | K33: 賃金 | O33: 300400 | P33: 305069 | Q33: 300800 | R33: 345177 | S33: 315000 | T33: 315800 | U33: 315000 | V33: 315400 | W33: 300000 | X33: =SUM(L33:W33) -> 2812646
A34: =+A33 -> 2023013 | B34: =+B33 -> 0 | K34: 交通費その他 | X34: =SUM(L34:W34) -> 0
A35: =+A34 -> 2023013 | B35: =+B34 -> 0 | K35: 通勤定期代 | O35: 22340 | P35: 22340 | Q35: 22340 | R35: 22340 | S35: 22340 | T35: 22340 | U35: 22340 | V35: 22696 | W35: 22340 | X35: =SUM(L35:W35) -> 201416
A36: =+A35 -> 2023013 | B36: =+B35 -> 0 | K36: 健康保険 | O36: 13300 | P36: 15200 | Q36: 15200 | R36: 15200 | S36: 15200 | T36: 15200 | U36: 15200 | V36: 15200 | W36: 13300 | X36: =SUM(L36:W36) -> 133000
A37: =+A36 -> 2023013 | B37: =+B36 -> 0 | K37: 厚生年金 | O37: 25620 | P37: 29280 | Q37: 29280 | R37: 29280 | S37: 29280 | T37: 29280 | U37: 29280 | V37: 29280 | W37: 25620 | X37: =SUM(L37:W37) -> 256200
A38: =+A37 -> 2023013 | B38: =+B37 -> 0 | K38: 労災保険 | O38: 1614 | P38: 1637 | Q38: 1616 | R38: 1838 | S38: 1687 | T38: 1691 | U38: 1687 | V38: 1777 | W38: 1614 | X38: =SUM(L38:W38) -> 15161
A39: =+A38 -> 2023013 | B39: =+B38 -> 0 | K39: 雇用保険 | O39: 1775 | P39: 1801 | Q39: 1777 | R39: 2021 | S39: 1855 | T39: 1860 | U39: 1855 | V39: 1955 | W39: 1775 | X39: =SUM(L39:W39) -> 16674
A40: =+A39 -> 2023013 | B40: =+B39 -> 0 | K40: 粗利 | L40: =L29-L32 -> 0 | M40: =M29-M32 -> 0 | N40: =N29-N32 -> 0 | O40: =O29-O32 -> 284951 | P40: =P29-P32 -> 278733 | Q40: =Q29-Q32 -> 278987 | R40: =R29-R32 -> 303164 | S40: =S29-S32 -> 264638 | ... X40: =X29-X32 -> 2487983
C41: =C2 -> アカウントサービス第二本部 | K41: 売上 | L41: =L5+L17+L29 -> 760000 | M41: =M5+M17+M29 -> 1051235 | N41: =N5+N17+N29 -> 1070905 | O41: =O5+O17+O29 -> 1450000 | P41: =P5+P17+P29 -> 1454060 | Q41: =Q5+Q17+Q29 -> 1450000 | R41: =R5+R17+R29 -> 1614020 | S41: =S5+S17+S29 -> 1450000 | ... W41: =W5+W17+W29 -> 1410000 | X41: =SUM(L41:W41) -> 15985220
K42: 仕入 | L42: =L8+L20+L32 -> 612134 | M42: =M8+M20+M32 -> 910091 | N42: =N8+N20+N32 -> 865244 | O42: =O8+O20+O32 -> 1017483 | P42: =P8+P20+P32 -> 1013218 | Q42: =Q8+Q20+Q32 -> 999652 | R42: =R8+R20+R32 -> 1142236 | S42: =S8+S20+S32 -> 1020062 | ... W42: =W8+W20+W32 -> 976783 | X42: =SUM(L42:W42) -> 11642566
K43: 粗利 | L43: =L41-L42 -> 147866 | M43: =M41-M42 -> 141144 | N43: =N41-N42 -> 205661 | O43: =O41-O42 -> 432517 | P43: =P41-P42 -> 440842 | Q43: =Q41-Q42 -> 450348 | R43: =R41-R42 -> 471784 | S43: =S41-S42 -> 429938 | ... W43: =W41-W42 -> 433217 | X43: =SUM(L43:W43) -> 4342654
K44: Q売上 | L44: =SUM(L41:N41) -> 2882140 | O44: =SUM(O41:Q41) -> 4354060 | R44: =SUM(R41:T41) -> 4514020 | U44: =SUM(U41:W41) -> 4235000 | X44: =X41 -> 15985220
K45: Q仕入 | L45: =SUM(L42:N42) -> 2387469 | O45: =SUM(O42:Q42) -> 3030353 | R45: =SUM(R42:T42) -> 3186718 | U45: =SUM(U42:W42) -> 3038026 | X45: =X42 -> 11642566
K46: Q粗利 | L46: =SUM(L43:N43) -> 494671 | O46: =SUM(O43:Q43) -> 1323707 | R46: =SUM(R43:T43) -> 1327302 | U46: =SUM(U43:W43) -> 1196974 | X46: =X43 -> 4342654

Sheet アカウントサービス第五本部
A1: 社員番号 | B1: 氏名 | C1: No | D1: 派遣/請負 | E1: 担当 | F1: 氏名 | G1: 派遣先部署 | H1: 作業名 | I1: 契約先 | J1: 外注会社 | K1: 売上単価 (支払単価） 【≒粗利】 | L1: 4月 | M1: 5月 | N1: 6月 | O1: 7月 | P1: 8月 | Q1: 9月 | R1: 10月 | S1: 11月 | T1: 12月 | U1: 1月 | V1: 2月 | W1: 3月 | X1: 合計
C2: アカウントサービス第五本部 | K2: 売上 | L2: =L137 -> 5097600 | M2: =M137 -> 4924750 | N2: =N137 -> 4957050 | O2: =O137 -> 5049400 | P2: =P137 -> 4693700 | Q2: =Q137 -> 4794295 | R2: =R137 -> 4373550 | S2: =S137 -> 4130180 | ... W2: =W137 -> 6412600 | X2: =SUM(L2:W2) -> 61402520
K3: 仕入 | L3: =L138 -> 3846091 | M3: =M138 -> 3740385 | N3: =N138 -> 3815448 | O3: =O138 -> 3977832 | P3: =P138 -> 3788701 | Q3: =Q138 -> 3631814 | R3: =R138 -> 3207288 | S3: =S138 -> 3338455 | ... W3: =W138 -> 4605472 | X3: =SUM(L3:W3) -> 46730823
K4: 粗利 | L4: =L2-L3 -> 1251509 | M4: =M2-M3 -> 1184365 | N4: =N2-N3 -> 1141602 | O4: =O2-O3 -> 1071568 | P4: =P2-P3 -> 904999 | Q4: =Q2-Q3 -> 1162481 | R4: =R2-R3 -> 1166262 | S4: =S2-S3 -> 791725 | ... W4: =W2-W3 -> 1807128 | X4: =SUM(L4:W4) -> 14671697
A5: 2012006 | C5: 1 | D5: 派遣 | G5: アカウントサービス第五本部サービス三部 | H5: 情報処理システム設計 | I5: 技術第一本部東日本技術統括部 ソフトバンクプロジェクト | J5: 社員 | K5: 総受注金額 | L5: =L6+L7 -> 769000 | M5: =M6+M7 -> 769000 | N5: =N6+N7 -> 769000 | O5: =O6+O7 -> 805075 | P5: =P6+P7 -> 769000 | Q5: =Q6+Q7 -> 769000 | R5: =R6+R7 -> 769000 | S5: =S6+S7 -> 769000 | ... W5: =W6+W7 -> 769000 | X5: =SUM(L5:W5) -> 9264075
A6: =+A5 -> 2012006 | K6: 派遣金額 | L6: 769000 | M6: 769000 | N6: 769000 | O6: 805075 | P6: 769000 | Q6: 769000 | R6: 769000 | S6: 769000 | T6: 769000 | U6: 769000 | V6: 769000 | W6: 769000 | X6: =SUM(L6:W6) -> 9264075
A7: =+A6 -> 2012006 | K7: 交通費 | X7: =SUM(L7:W7) -> 0
A8: =+A7 -> 2012006 | K8: 総経費 | L8: =SUM(L9:L15) -> 596376 | M8: =SUM(M9:M15) -> 595972 | N8: =SUM(N9:N15) -> 594945 | O8: =SUM(O9:O15) -> 613409 | P8: =SUM(P9:P15) -> 593329 | Q8: =SUM(Q9:Q15) -> 595618 | R8: =SUM(R9:R15) -> 584302 | S8: =SUM(S9:S15) -> 596560 | ... W8: =SUM(W9:W15) -> 596376 | X8: =SUM(L8:W8) -> 7152307
A9: =+A8 -> 2012006 | K9: 賃金 | L9: 511800 | M9: 511400 | N9: 512600 | O9: 526474 | P9: 511000 | Q9: 511800 | R9: 505000 | S9: 509800 | T9: 511400 | U9: 511000 | V9: 511400 | W9: 511800 | X9: =SUM(L9:W9) -> 6145474
A10: =+A9 -> 2012006 | K10: 交通費その他 | X10: =SUM(L10:W10) -> 0
A11: =+A10 -> 2012006 | K11: 通勤定期代 | L11: 5148 | M11: 5148 | N11: 2932 | O11: 7330 | P11: 2932 | Q11: 4398 | R11: 0 | S11: 7330 | T11: 5864 | U11: 4398 | V11: 2932 | W11: 5148 | X11: =SUM(L11:W11) -> 53560
A12: =+A11 -> 2012006 | K12: 健康保険 | L12: 28250 | M12: 28250 | N12: 28250 | O12: 28250 | P12: 28250 | Q12: 28250 | R12: 28250 | S12: 28250 | T12: 28250 | U12: 28250 | V12: 28250 | W12: 28250 | X12: =SUM(L12:W12) -> 339000
A13: =+A12 -> 2012006 | K13: 厚生年金 | L13: 45750 | M13: 45750 | N13: 45750 | O13: 45750 | P13: 45750 | Q13: 45750 | R13: 45750 | S13: 45750 | T13: 45750 | U13: 45750 | V13: 45750 | W13: 45750 | X13: =SUM(L13:W13) -> 549000
A14: =+A13 -> 2012006 | K14: 労災保険 | L14: 2585 | M14: 2583 | N14: 2578 | O14: 2669 | P14: 2570 | Q14: 2581 | R14: 2525 | S14: 2586 | T14: 2586 | U14: 2577 | V14: 2659 | W14: 2585 | X14: =SUM(L14:W14) -> 31084
A15: =+A14 -> 2012006 | K15: 雇用保険 | L15: 2843 | M15: 2841 | N15: 2835 | O15: 2936 | P15: 2827 | Q15: 2839 | R15: 2777 | S15: 2844 | T15: 2845 | U15: 2835 | V15: 2924 | W15: 2843 | X15: =SUM(L15:W15) -> 34189
A16: =+A15 -> 2012006 | K16: 粗利 | L16: =L5-L8 -> 172624 | M16: =M5-M8 -> 173028 | N16: =N5-N8 -> 174055 | O16: =O5-O8 -> 191666 | P16: =P5-P8 -> 175671 | Q16: =Q5-Q8 -> 173382 | R16: =R5-R8 -> 184698 | S16: =S5-S8 -> 172440 | ... X16: =X5-X8 -> 2111768
A17: 2023017 | C17: =C5+1 -> 2 | D17: 派遣 | G17: アカウントサービス第五本部サービス五部 | J17: 社員 | K17: 総受注金額 | L17: =L18+L19 -> 430000 | M17: =M18+M19 -> 430000 | N17: =N18+N19 -> 430000 | O17: =O18+O19 -> 430000 | P17: =P18+P19 -> 425965 | Q17: =Q18+Q19 -> 430000 | R17: =R18+R19 -> 430000 | S17: =S18+S19 -> 384270 | ... W17: =W18+W19 -> 430000 | X17: =SUM(L17:W17) -> 5038950
A18: =+A17 -> 2023017 | K18: 派遣金額 | L18: 430000 | M18: 430000 | N18: 430000 | O18: 430000 | P18: 425965 | Q18: 430000 | R18: 430000 | S18: 384270 | T18: 430000 | U18: 405790 | V18: 382925 | W18: 430000 | X18: =SUM(L18:W18) -> 5038950
A19: =+A18 -> 2023017 | K19: 交通費 | X19: =SUM(L19:W19) -> 0
A20: =+A19 -> 2023017 | K20: 総経費 | L20: =SUM(L21:L27) -> 302376 | M20: =SUM(M21:M27) -> 302376 | N20: =SUM(N21:N27) -> 302376 | O20: =SUM(O21:O27) -> 302376 | P20: =SUM(P21:P27) -> 331252 | Q20: =SUM(Q21:Q27) -> 302376 | R20: =SUM(R21:R27) -> 301942 | S20: =SUM(S21:S27) -> 301942 | ... W20: =SUM(W21:W27) -> 302376 | X20: =SUM(L20:W20) -> 3666426
A21: =+A20 -> 2023017 | K21: 賃金 | L21: 250000 | M21: 250000 | N21: 250000 | O21: 250000 | P21: 280000 | Q21: 250000 | R21: 250000 | S21: 250000 | T21: 250000 | U21: 255000 | V21: 255000 | W21: 250000 | X21: =SUM(L21:W21) -> 3040000
A22: =+A21 -> 2023017 | K22: 交通費その他 | X22: =SUM(L22:W22) -> 0
A23: =+A22 -> 2023017 | K23: 通勤定期代 | L23: 13470 | M23: 13470 | N23: 13470 | O23: 13470 | P23: 12046 | Q23: 13470 | R23: 13040 | S23: 13040 | T23: 13040 | U23: 13470 | V23: 13470 | W23: 13470 | X23: =SUM(L23:W23) -> 158926
A24: =+A23 -> 2023017 | K24: 健康保険 | L24: 12350 | M24: 12350 | N24: 12350 | O24: 12350 | P24: 12350 | Q24: 12350 | R24: 12350 | S24: 12350 | T24: 12350 | U24: 12350 | V24: 12350 | W24: 12350 | X24: =SUM(L24:W24) -> 148200
A25: =+A24 -> 2023017 | K25: 厚生年金 | L25: 23790 | M25: 23790 | N25: 23790 | O25: 23790 | P25: 23790 | Q25: 23790 | R25: 23790 | S25: 23790 | T25: 23790 | U25: 23790 | V25: 23790 | W25: 23790 | X25: =SUM(L25:W25) -> 285480
A26: =+A25 -> 2023017 | K26: 労災保険 | L26: 1317 | M26: 1317 | N26: 1317 | O26: 1317 | P26: 1460 | Q26: 1317 | R26: 1315 | S26: 1315 | T26: 1340 | U26: 1342 | V26: 1429 | W26: 1317 | X26: =SUM(L26:W26) -> 16103
A27: =+A26 -> 2023017 | K27: 雇用保険 | L27: 1449 | M27: 1449 | N27: 1449 | O27: 1449 | P27: 1606 | Q27: 1449 | R27: 1447 | S27: 1447 | T27: 1474 | U27: 1477 | V27: 1572 | W27: 1449 | X27: =SUM(L27:W27) -> 17717
A28: =+A27 -> 2023017 | K28: 粗利 | L28: =L17-L20 -> 127624 | M28: =M17-M20 -> 127624 | N28: =N17-N20 -> 127624 | O28: =O17-O20 -> 127624 | P28: =P17-P20 -> 94713 | Q28: =Q17-Q20 -> 127624 | R28: =R17-R20 -> 128058 | S28: =S17-S20 -> 82328 | ... X28: =X17-X20 -> 1372524
A29: 2020011 | C29: =C17+1 -> 3 | D29: 派遣 | G29: アカウントサービス第五本部サービス五部 | J29: 社員 | K29: 総受注金額 | L29: =L30+L31 -> 643125 | M29: =M30+M31 -> 586875 | N29: =N30+N31 -> 600000 | O29: =O30+O31 -> 600000 | P29: =P30+P31 -> 600000 | Q29: =Q30+Q31 -> 590625 | R29: =R30+R31 -> 600000 | S29: =S30+S31 -> 553125 | ... W29: =W30+W31 -> 643125 | X29: =SUM(L29:W29) -> 7136250
A30: =+A29 -> 2020011 | K30: 派遣金額 | L30: 643125 | M30: 586875 | N30: 600000 | O30: 600000 | P30: 600000 | Q30: 590625 | R30: 600000 | S30: 553125 | T30: 600000 | U30: 538125 | V30: 581250 | W30: 643125 | X30: =SUM(L30:W30) -> 7136250
A31: =+A30 -> 2020011 | K31: 交通費 | X31: =SUM(L31:W31) -> 0
A32: =+A31 -> 2020011 | K32: 総経費 | L32: =SUM(L33:L39) -> 420856 | M32: =SUM(M33:M39) -> 394548 | N32: =SUM(N33:N39) -> 394548 | O32: =SUM(O33:O39) -> 394548 | P32: =SUM(P33:P39) -> 394548 | Q32: =SUM(Q33:Q39) -> 394548 | R32: =SUM(R33:R39) -> 394548 | S32: =SUM(S33:S39) -> 385398 | ... W32: =SUM(W33:W39) -> 420856 | X32: =SUM(L32:W32) -> 4775480
A33: =+A32 -> 2020011 | K33: 賃金 | L33: 361034 | M33: 335000 | N33: 335000 | O33: 335000 | P33: 335000 | Q33: 335000 | R33: 335000 | S33: 325945 | T33: 335000 | U33: 332283 | V33: 335000 | W33: 361034 | X33: =SUM(L33:W33) -> 4060296
A34: =+A33 -> 2020011 | K34: 交通費その他 | X34: =SUM(L34:W34) -> 0
A35: =+A34 -> 2020011 | K35: 通勤定期代 | L35: 8680 | M35: 8680 | N35: 8680 | O35: 8680 | P35: 8680 | Q35: 8680 | R35: 8680 | S35: 8680 | T35: 8680 | U35: 8680 | V35: 8680 | W35: 8680 | X35: =SUM(L35:W35) -> 104160
A36: =+A35 -> 2020011 | K36: 健康保険 | L36: 16150 | M36: 16150 | N36: 16150 | O36: 16150 | P36: 16150 | Q36: 16150 | R36: 16150 | S36: 16150 | T36: 16150 | U36: 16150 | V36: 16150 | W36: 16150 | X36: =SUM(L36:W36) -> 193800
A37: =+A36 -> 2020011 | K37: 厚生年金 | L37: 31110 | M37: 31110 | N37: 31110 | O37: 31110 | P37: 31110 | Q37: 31110 | R37: 31110 | S37: 31110 | T37: 31110 | U37: 31110 | V37: 31110 | W37: 31110 | X37: =SUM(L37:W37) -> 373320
A38: =+A37 -> 2020011 | K38: 労災保険 | L38: 1849 | M38: 1718 | N38: 1718 | O38: 1718 | P38: 1718 | Q38: 1718 | R38: 1718 | S38: 1673 | T38: 1718 | U38: 1705 | V38: 1805 | W38: 1849 | X38: =SUM(L38:W38) -> 20907
A39: =+A38 -> 2020011 | K39: 雇用保険 | L39: 2033 | M39: 1890 | N39: 1890 | O39: 1890 | P39: 1890 | Q39: 1890 | R39: 1890 | S39: 1840 | T39: 1890 | U39: 1875 | V39: 1986 | W39: 2033 | X39: =SUM(L39:W39) -> 22997
A40: =+A39 -> 2020011 | K40: 粗利 | L40: =L29-L32 -> 222269 | M40: =M29-M32 -> 192327 | N40: =N29-N32 -> 205452 | O40: =O29-O32 -> 205452 | P40: =P29-P32 -> 205452 | Q40: =Q29-Q32 -> 196077 | R40: =R29-R32 -> 205452 | S40: =S29-S32 -> 167727 | ... X40: =X29-X32 -> 2360770
A41: 2022018 | C41: =C29+1 -> 4 | D41: 派遣 | E41: 転出 | G41: アカウントサービス第五本部サービス五部 | J41: 社員 | K41: 総受注金額 | L41: =L42+L43 -> 735000 | M41: =M42+M43 -> 735000 | N41: =N42+N43 -> 735000 | O41: =O42+O43 -> 735000 | P41: =P42+P43 -> 735000 | Q41: =Q42+Q43 -> 622545 | R41: =R42+R43 -> 0 | S41: =S42+S43 -> 0 | ... W41: =W42+W43 -> 0 | X41: =SUM(L41:W41) -> 4297545
A42: =+A41 -> 2022018 | K42: 派遣金額 | L42: 735000 | M42: 735000 | N42: 735000 | O42: 735000 | P42: 735000 | Q42: 622545 | X42: =SUM(L42:W42) -> 4297545
A43: =+A42 -> 2022018 | K43: 交通費 | X43: =SUM(L43:W43) -> 0
A44: =+A43 -> 2022018 | K44: 総経費 | L44: =SUM(L45:L51) -> 621281 | M44: =SUM(M45:M51) -> 603031 | N44: =SUM(N45:N51) -> 622978 | O44: =SUM(O45:O51) -> 726409 | P44: =SUM(P45:P51) -> 635201 | Q44: =SUM(Q45:Q51) -> 530634 | R44: =SUM(R45:R51) -> 0 | S44: =SUM(S45:S51) -> 0 | ... W44: =SUM(W45:W51) -> 0 | X44: =SUM(L44:W44) -> 3739534
A45: =+A44 -> 2022018 | K45: 賃金 | L45: 537200 | M45: 519140 | N45: 538880 | O45: 641236 | P45: 550976 | Q45: 525120 | X45: =SUM(L45:W45) -> 3312552
A46: =+A45 -> 2022018 | K46: 交通費その他 | X46: =SUM(L46:W46) -> 0
A47: =+A46 -> 2022018 | K47: 通勤定期代 | L47: 0 | M47: 0 | N47: 0 | O47: 0 | P47: 0 | Q47: 0 | X47: =SUM(L47:W47) -> 0
A48: =+A47 -> 2022018 | K48: 健康保険 | L48: 29945 | M48: 29945 | N48: 29945 | O48: 29945 | P48: 29945 | Q48: 0 | X48: =SUM(L48:W48) -> 149725
A49: =+A48 -> 2022018 | K49: 厚生年金 | L49: 48495 | M49: 48495 | N49: 48495 | O49: 48495 | P49: 48495 | Q49: 0 | X49: =SUM(L49:W49) -> 242475
A50: =+A49 -> 2022018 | K50: 労災保険 | L50: 2686 | M50: 2596 | N50: 2694 | O50: 3206 | P50: 2755 | Q50: 2626 | X50: =SUM(L50:W50) -> 16563
A51: =+A50 -> 2022018 | K51: 雇用保険 | L51: 2955 | M51: 2855 | N51: 2964 | O51: 3527 | P51: 3030 | Q51: 2888 | X51: =SUM(L51:W51) -> 18219
A52: =+A51 -> 2022018 | K52: 粗利 | L52: =L41-L44 -> 113719 | M52: =M41-M44 -> 131969 | N52: =N41-N44 -> 112022 | O52: =O41-O44 -> 8591 | P52: =P41-P44 -> 99799 | Q52: =Q41-Q44 -> 91911 | R52: =R41-R44 -> 0 | S52: =S41-S44 -> 0 | ... X52: =X41-X44 -> 558011
A53: 2018016 | C53: =C41+1 -> 5 | D53: 派遣 | G53: アカウントサービス第五本部サービス五部 | J53: 社員 | K53: 総受注金額 | L53: =L54+L55 -> 680000 | M53: =M54+M55 -> 680000 | N53: =N54+N55 -> 680000 | O53: =O54+O55 -> 680000 | P53: =P54+P55 -> 637500 | Q53: =Q54+Q55 -> 667250 | R53: =R54+R55 -> 680000 | S53: =S54+S55 -> 531250 | ... W53: =W54+W55 -> 680000 | X53: =SUM(L53:W53) -> 7888000
A54: =+A53 -> 2018016 | K54: 派遣金額 | L54: 680000 | M54: 680000 | N54: 680000 | O54: 680000 | P54: 637500 | Q54: 667250 | R54: 680000 | S54: 531250 | T54: 680000 | U54: 626875 | V54: 665125 | W54: 680000 | X54: =SUM(L54:W54) -> 7888000
A55: =+A54 -> 2018016 | K55: 交通費 | X55: =SUM(L55:W55) -> 0
A56: =+A55 -> 2018016 | K56: 総経費 | L56: =SUM(L57:L63) -> 497129 | M56: =SUM(M57:M63) -> 495553 | N56: =SUM(N57:N63) -> 494643 | O56: =SUM(O57:O63) -> 493148 | P56: =SUM(P57:P63) -> 490035 | Q56: =SUM(Q57:Q63) -> 484504 | R56: =SUM(R57:R63) -> 490607 | S56: =SUM(S57:S63) -> 482887 | ... W56: =SUM(W57:W63) -> 497129 | X56: =SUM(L56:W56) -> 5875777
A57: =+A56 -> 2018016 | K57: 賃金 | L57: 413600 | M57: 413200 | N57: 414800 | O57: 415600 | P57: 414800 | Q57: 416000 | R57: 415200 | S57: 414400 | T57: 416800 | U57: 416000 | V57: 416245 | W57: 413600 | X57: =SUM(L57:W57) -> 4980245
A58: =+A57 -> 2018016 | K58: 交通費その他 | X58: =SUM(L58:W58) -> 0
A59: =+A58 -> 2018016 | K59: 通勤定期代 | L59: 13920 | M59: 12760 | N59: 10260 | O59: 7980 | P59: 5700 | Q59: 3420 | R59: 10260 | S59: 3420 | T59: 2280 | U59: 2280 | V59: 1140 | W59: 13920 | X59: =SUM(L59:W59) -> 87340
A60: =+A59 -> 2018016 | K60: 健康保険 | L60: 24860 | M60: 24860 | N60: 24860 | O60: 24860 | P60: 24860 | Q60: 23165 | R60: 23165 | S60: 23165 | T60: 23165 | U60: 23165 | V60: 23165 | W60: 24860 | X60: =SUM(L60:W60) -> 288150
A61: =+A60 -> 2018016 | K61: 厚生年金 | L61: 40260 | M61: 40260 | N61: 40260 | O61: 40260 | P61: 40260 | Q61: 37515 | R61: 37515 | S61: 37515 | T61: 37515 | U61: 37515 | V61: 37515 | W61: 40260 | X61: =SUM(L61:W61) -> 466650
A62: =+A61 -> 2018016 | K62: 労災保険 | L62: 2138 | M62: 2130 | N62: 2125 | O62: 2118 | P62: 2102 | Q62: 2097 | R62: 2127 | S62: 2089 | T62: 2095 | U62: 2091 | V62: 2174 | W62: 2138 | X62: =SUM(L62:W62) -> 25424
A63: =+A62 -> 2018016 | K63: 雇用保険 | L63: 2351 | M63: 2343 | N63: 2338 | O63: 2330 | P63: 2313 | Q63: 2307 | R63: 2340 | S63: 2298 | T63: 2305 | U63: 2301 | V63: 2391 | W63: 2351 | X63: =SUM(L63:W63) -> 27968
A64: =+A63 -> 2018016 | K64: 粗利 | L64: =L53-L56 -> 182871 | M64: =M53-M56 -> 184447 | N64: =N53-N56 -> 185357 | O64: =O53-O56 -> 186852 | P64: =P53-P56 -> 147465 | Q64: =Q53-Q56 -> 182746 | R64: =R53-R56 -> 189393 | S64: =S53-S56 -> 48363 | ... X64: =X53-X56 -> 2012223
A65: 2014005 | C65: =C53+1 -> 6 | D65: 派遣 | G65: アカウントサービス第五本部サービス五部 | J65: 社員 | K65: 総受注金額 | L65: =L66+L67 -> 692300 | M65: =M66+M67 -> 619200 | N65: =N66+N67 -> 653600 | O65: =O66+O67 -> 677250 | P65: =P66+P67 -> 563300 | Q65: =Q66+Q67 -> 645000 | R65: =R66+R67 -> 718100 | S65: =S66+S67 -> 554700 | ... W65: =W66+W67 -> 692300 | X65: =SUM(L65:W65) -> 7447600
A66: =+A65 -> 2014005 | K66: 派遣金額 | L66: 692300 | M66: 619200 | N66: 653600 | O66: 677250 | P66: 563300 | Q66: 645000 | R66: 718100 | S66: 554700 | T66: 548250 | U66: 567600 | V66: 516000 | W66: 692300 | X66: =SUM(L66:W66) -> 7447600
A67: =+A66 -> 2014005 | K67: 交通費 | X67: 0
A68: =+A67 -> 2014005 | K68: 総経費 | L68: =SUM(L69:L75) -> 562093 | M68: =SUM(M69:M75) -> 532935 | N68: =SUM(N69:N75) -> 554530 | O68: =SUM(O69:O75) -> 569563 | P68: =SUM(P69:P75) -> 533938 | Q68: =SUM(Q69:Q75) -> 523347 | R68: =SUM(R69:R75) -> 577421 | S68: =SUM(S69:S75) -> 483369 | ... W68: =SUM(W69:W75) -> 562093 | X68: =SUM(L68:W68) -> 6457495
A69: =+A68 -> 2014005 | K69: 賃金 | L69: 475615 | M69: 445580 | N69: 471670 | O69: 487800 | P69: 454880 | Q69: 444400 | R69: 493240 | S69: 406005 | T69: 465900 | U69: 439255 | V69: 423160 | W69: 475615 | X69: =SUM(L69:W69) -> 5483120
A70: =+A69 -> 2014005 | K70: 交通費その他 | X70: =SUM(L70:W70) -> 0
A71: =+A70 -> 2014005 | K71: 通勤定期代 | L71: 11800 | M71: 12980 | N71: 8260 | O71: 7008 | P71: 4672 | Q71: 4672 | R71: 9344 | S71: 3504 | T71: 2336 | U71: 2336 | V71: 2336 | W71: 11800 | X71: =SUM(L71:W71) -> 81048
A72: =+A71 -> 2014005 | K72: 健康保険 | L72: 26555 | M72: 26555 | N72: 26555 | O72: 26555 | P72: 26555 | Q72: 26555 | R72: 26555 | S72: 26555 | T72: 26555 | U72: 26555 | V72: 26555 | W72: 26555 | X72: =SUM(L72:W72) -> 318660
A73: =+A72 -> 2014005 | K73: 厚生年金 | L73: 43005 | M73: 43005 | N73: 43005 | O73: 43005 | P73: 43005 | Q73: 43005 | R73: 43005 | S73: 43005 | T73: 43005 | U73: 43005 | V73: 43005 | W73: 43005 | X73: =SUM(L73:W73) -> 516060
A74: =+A73 -> 2014005 | K74: 労災保険 | L74: 2437 | M74: 2293 | N74: 2400 | O74: 2474 | P74: 2298 | Q74: 2245 | R74: 2513 | S74: 2048 | T74: 2341 | U74: 2208 | V74: 2214 | W74: 2437 | X74: =SUM(L74:W74) -> 27908
A75: =+A74 -> 2014005 | K75: 雇用保険 | L75: 2681 | M75: 2522 | N75: 2640 | O75: 2721 | P75: 2528 | Q75: 2470 | R75: 2764 | S75: 2252 | T75: 2575 | U75: 2429 | V75: 2436 | W75: 2681 | X75: =SUM(L75:W75) -> 30699
A76: =+A75 -> 2014005 | K76: 粗利 | L76: =L65-L68 -> 130207 | M76: =M65-M68 -> 86265 | N76: =N65-N68 -> 99070 | O76: =O65-O68 -> 107687 | P76: =P65-P68 -> 29362 | Q76: =Q65-Q68 -> 121653 | R76: =R65-R68 -> 140679 | S76: =S65-S68 -> 71331 | ... X76: =X65-X68 -> 990105
A77: 2010006 | C77: =C65+1 -> 7 | D77: 派遣 | G77: アカウントサービス第五本部サービス五部 | H77: IP電話システムの運用業務全般、及び運用設計 | I77: 技術第三本部フィールドインテグレーションセンター サイトサービスセンター（於保部長/齋藤正英グループMgr） | J77: 社員 | K77: 総受注金額 | L77: =L78+L79 -> 698175 | M77: =M78+M79 -> 654675 | N77: =N78+N79 -> 639450 | O77: =O78+O79 -> 672075 | P77: =P78+P79 -> 524175 | Q77: =Q78+Q79 -> 619875 | R77: =R78+R79 -> 726450 | S77: =S78+S79 -> 558975 | ... W77: =W78+W79 -> 698175 | X77: =SUM(L77:W77) -> 7586400
A78: =+A77 -> 2010006 | K78: 派遣金額 | L78: 698175 | M78: 654675 | N78: 639450 | O78: 672075 | P78: 524175 | Q78: 619875 | R78: 726450 | S78: 558975 | T78: 678600 | U78: 561150 | V78: 554625 | W78: 698175 | X78: =SUM(L78:W78) -> 7586400
A79: =+A78 -> 2010006 | K79: 交通費 | X79: =SUM(L79:W79) -> 0
A80: =+A79 -> 2010006 | K80: 総経費 | L80: =SUM(L81:L87) -> 548689 | M80: =SUM(M81:M87) -> 517828 | N80: =SUM(N81:N87) -> 553286 | O80: =SUM(O81:O87) -> 579509 | P80: =SUM(P81:P87) -> 514620 | Q80: =SUM(Q81:Q87) -> 505009 | R80: =SUM(R81:R87) -> 562690 | S80: =SUM(S81:S87) -> 464589 | ... W80: =SUM(W81:W87) -> 548689 | X80: =SUM(L80:W80) -> 6319693
A81: =+A80 -> 2010006 | K81: 賃金 | L81: 454150 | M81: 426600 | N81: 458700 | O81: 484650 | P81: 425400 | Q81: 427800 | R81: 472400 | S81: 387800 | T81: 465000 | U81: 411700 | V81: 426200 | W81: 454150 | X81: =SUM(L81:W81) -> 5294550
A82: =+A81 -> 2010006 | K82: 交通費その他 | X82: =SUM(L82:W82) -> 0
A83: =+A82 -> 2010006 | K83: 通勤定期代 | L83: 20000 | M83: 17010 | N83: 20000 | O83: 20000 | P83: 15036 | Q83: 7518 | R83: 20000 | S83: 7518 | T83: 7518 | U83: 2506 | V83: 2506 | W83: 20000 | X83: =SUM(L83:W83) -> 159612
A84: =+A83 -> 2010006 | K84: 健康保険 | L84: 26555 | M84: 26555 | N84: 26555 | O84: 26555 | P84: 26555 | Q84: 24860 | R84: 24860 | S84: 24860 | T84: 24860 | U84: 24860 | V84: 24860 | W84: 26555 | X84: =SUM(L84:W84) -> 308490
A85: =+A84 -> 2010006 | K85: 厚生年金 | L85: 43005 | M85: 43005 | N85: 43005 | O85: 43005 | P85: 43005 | Q85: 40260 | R85: 40260 | S85: 40260 | T85: 40260 | U85: 40260 | V85: 40260 | W85: 43005 | X85: =SUM(L85:W85) -> 499590
A86: =+A85 -> 2010006 | K86: 労災保険 | L86: 2371 | M86: 2218 | N86: 2393 | O86: 2523 | P86: 2202 | Q86: 2177 | R86: 2462 | S86: 1977 | T86: 2363 | U86: 2071 | V86: 2230 | W86: 2371 | X86: =SUM(L86:W86) -> 27358
A87: =+A86 -> 2010006 | K87: 雇用保険 | L87: 2608 | M87: 2440 | N87: 2633 | O87: 2776 | P87: 2422 | Q87: 2394 | R87: 2708 | S87: 2174 | T87: 2599 | U87: 2278 | V87: 2453 | W87: 2608 | X87: =SUM(L87:W87) -> 30093
A88: =+A87 -> 2010006 | K88: 粗利 | L88: =L77-L80 -> 149486 | M88: =M77-M80 -> 136847 | N88: =N77-N80 -> 86164 | O88: =O77-O80 -> 92566 | P88: =P77-P80 -> 9555 | Q88: =Q77-Q80 -> 114866 | R88: =R77-R80 -> 163760 | S88: =S77-S80 -> 94386 | ... X88: =X77-X80 -> 1266707
A89: 2024047 | C89: =C77+1 -> 8 | D89: 派遣 | G89: アカウントサービス第五本部ネットワーク＆デザイン部 | J89: 社員 | K89: 総受注金額 | L89: =L90+L91 -> 450000 | M89: =M90+M91 -> 450000 | N89: =N90+N91 -> 450000 | O89: =O90+O91 -> 450000 | P89: =P90+P91 -> 438760 | Q89: =Q90+Q91 -> 450000 | R89: =R90+R91 -> 450000 | S89: =S90+S91 -> 450000 | ... W89: =W90+W91 -> 450000 | X89: =SUM(L89:W89) -> 5388760
A90: =+A89 -> 2024047 | K90: 派遣金額 | L90: 450000 | M90: 450000 | N90: 450000 | O90: 450000 | P90: 438760 | Q90: 450000 | R90: 450000 | S90: 450000 | T90: 450000 | U90: 450000 | V90: 450000 | W90: 450000 | X90: =SUM(L90:W90) -> 5388760
A91: =+A90 -> 2024047 | K91: 交通費 | X91: =SUM(L91:W91) -> 0
A92: =+A91 -> 2024047 | K92: 総経費 | L92: =SUM(L93:L99) -> 297291 | M92: =SUM(M93:M99) -> 298142 | N92: =SUM(N93:N99) -> 298142 | O92: =SUM(O93:O99) -> 298870 | P92: =SUM(P93:P99) -> 295778 | Q92: =SUM(Q93:Q99) -> 295778 | R92: =SUM(R93:R99) -> 295778 | S92: =SUM(S93:S99) -> 295778 | ... W92: =SUM(W93:W99) -> 297291 | X92: =SUM(L92:W92) -> 3560823
A93: =+A92 -> 2024047 | K93: 賃金 | L93: 240000 | M93: 240000 | N93: 240000 | O93: 240000 | P93: 240000 | Q93: 240000 | R93: 240000 | S93: 240000 | T93: 240000 | U93: 240000 | V93: 240000 | W93: 240000 | X93: =SUM(L93:W93) -> 2880000
A94: =+A93 -> 2024047 | K94: 交通費その他 | X94: =SUM(L94:W94) -> 0
A95: =+A94 -> 2024047 | K95: 通勤定期代 | L95: 18438 | M95: 19280 | N95: 19280 | O95: 20000 | P95: 16940 | Q95: 16940 | R95: 16940 | S95: 16940 | T95: 16940 | U95: 17393 | V95: 16940 | W95: 18438 | X95: =SUM(L95:W95) -> 214469
A96: =+A95 -> 2024047 | K96: 健康保険 | L96: 12350 | M96: 12350 | N96: 12350 | O96: 12350 | P96: 12350 | Q96: 12350 | R96: 12350 | S96: 12350 | T96: 12350 | U96: 12350 | V96: 12350 | W96: 12350 | X96: =SUM(L96:W96) -> 148200
A97: =+A96 -> 2024047 | K97: 厚生年金 | L97: 23790 | M97: 23790 | N97: 23790 | O97: 23790 | P97: 23790 | Q97: 23790 | R97: 23790 | S97: 23790 | T97: 23790 | U97: 23790 | V97: 23790 | W97: 23790 | X97: =SUM(L97:W97) -> 285480
A98: =+A97 -> 2024047 | K98: 労災保険 | L98: 1292 | M98: 1296 | N98: 1296 | O98: 1300 | P98: 1285 | Q98: 1285 | R98: 1285 | S98: 1285 | T98: 1285 | U98: 1287 | V98: 1372 | W98: 1292 | X98: =SUM(L98:W98) -> 15560
A99: =+A98 -> 2024047 | K99: 雇用保険 | L99: 1421 | M99: 1426 | N99: 1426 | O99: 1430 | P99: 1413 | Q99: 1413 | R99: 1413 | S99: 1413 | T99: 1413 | U99: 1416 | V99: 1509 | W99: 1421 | X99: =SUM(L99:W99) -> 17114
A100: =+A99 -> 2024047 | K100: 粗利 | L100: =L89-L92 -> 152709 | M100: =M89-M92 -> 151858 | N100: =N89-N92 -> 151858 | O100: =O89-O92 -> 151130 | P100: =P89-P92 -> 142982 | Q100: =Q89-Q92 -> 154222 | R100: =R89-R92 -> 154222 | S100: =S89-S92 -> 154222 | ... X100: =X89-X92 -> 1827937
...

Sheet マネージドサービス第一本部
A1: 社員番号 | B1: 氏名 | C1: No | D1: 派遣/請負 | E1: 担当 | F1: 氏名 | G1: 派遣先部署 | H1: 作業名 | I1: 契約先 | J1: 外注会社 | K1: 売上単価 (支払単価） 【≒粗利】 | L1: 4月 | M1: 5月 | N1: 6月 | O1: 7月 | P1: 8月 | Q1: 9月 | R1: 10月 | S1: 11月 | T1: 12月 | U1: 1月 | V1: 2月 | W1: 3月 | X1: 合計
C2: マネージドサービス第一本部 | K2: 売上 | L2: =L209 -> 9019005 | M2: =M209 -> 8517400 | N2: =N209 -> 8553300 | O2: =O209 -> 8728550 | P2: =P209 -> 8362195 | Q2: =Q209 -> 8137740 | R2: =R209 -> 9029510 | S2: =S209 -> 8574705 | ... W2: =W209 -> 8615508.3 | X2: =SUM(L2:W2) -> 1.0363969e+08
K3: 仕入 | L3: =L210 -> 7421278 | M3: =M210 -> 7091978 | N3: =N210 -> 7112189 | O3: =O210 -> 7197283 | P3: =P210 -> 7091566 | Q3: =Q210 -> 7109635 | R3: =R210 -> 7364005.5 | S3: =S210 -> 7404708 | ... W3: =W210 -> 7251849.2 | X3: =SUM(L3:W3) -> 87186306
K4: 粗利 | L4: =L2-L3 -> 1597727 | M4: =M2-M3 -> 1425422 | N4: =N2-N3 -> 1441111 | O4: =O2-O3 -> 1531267 | P4: =P2-P3 -> 1270629 | Q4: =Q2-Q3 -> 1028105 | R4: =R2-R3 -> 1665504.5 | S4: =S2-S3 -> 1169997 | ... W4: =W2-W3 -> 1363659.1 | X4: =SUM(L4:W4) -> 16453383
A5: 2024003 | C5: 1 | D5: 派遣 | G5: マネージドサービス第一本部クラウドマネージドサービス一部 | J5: 社員 | K5: 総受注金額 | L5: =L6+L7 -> 442500 | M5: =M6+M7 -> 480000 | N5: =N6+N7 -> 480000 | O5: =O6+O7 -> 480000 | P5: =P6+P7 -> 480000 | Q5: =Q6+Q7 -> 465000 | R5: =R6+R7 -> 480000 | S5: =S6+S7 -> 456000 | ... W5: =W6+W7 -> 475833.33 | X5: =SUM(L5:W5) -> 5650833.3
A6: =+A5 -> 2024003 | K6: 派遣金額 | L6: 442500 | M6: 480000 | N6: 480000 | O6: 480000 | P6: 480000 | Q6: 465000 | R6: 480000 | S6: 456000 | T6: 480000 | U6: 480000 | V6: 451500 | W6: 475833.33 | X6: =SUM(L6:W6) -> 5650833.3
A7: =+A6 -> 2024003 | K7: 顧客対応当番 | X7: =SUM(L7:W7) -> 0
A8: =+A7 -> 2024003 | K8: 総経費 | L8: =SUM(L9:L15) -> 351721 | M8: =SUM(M9:M15) -> 352530 | N8: =SUM(N9:N15) -> 353338 | O8: =SUM(O9:O15) -> 353338 | P8: =SUM(P9:P15) -> 352530 | Q8: =SUM(Q9:Q15) -> 352126 | R8: =SUM(R9:R15) -> 353742 | S8: =SUM(S9:S15) -> 352126 | ... W8: =SUM(W9:W15) -> 352302.11 | X8: =SUM(L8:W8) -> 4227843.1
A9: =+A8 -> 2024003 | K9: 賃金 | L9: 306800 | M9: 307600 | N9: 308400 | O9: 308400 | P9: 307600 | Q9: 307200 | R9: 308800 | S9: 307200 | T9: 308000 | U9: 307600 | V9: 303556 | W9: 307381.11 | X9: =SUM(L9:W9) -> 3688537.1
A10: =+A9 -> 2024003 | K10: 交通費その他 | X10: =SUM(L10:W10) -> 0
A11: =+A10 -> 2024003 | K11: 通勤定期代 | L11: 0 | M11: 0 | N11: 0 | O11: 0 | P11: 0 | Q11: 0 | R11: 0 | S11: 0 | T11: 0 | U11: 0 | V11: 0 | W11: 0 | X11: =SUM(L11:W11) -> 0
A12: =+A11 -> 2024003 | K12: 健康保険 | L12: 14250 | M12: 14250 | N12: 14250 | O12: 14250 | P12: 14250 | Q12: 14250 | R12: 14250 | S12: 14250 | T12: 14250 | U12: 14250 | V12: 14250 | W12: 14250 | X12: =SUM(L12:W12) -> 171000
A13: =+A12 -> 2024003 | K13: 厚生年金 | L13: 27450 | M13: 27450 | N13: 27450 | O13: 27450 | P13: 27450 | Q13: 27450 | R13: 27450 | S13: 27450 | T13: 27450 | U13: 27450 | V13: 27450 | W13: 27450 | X13: =SUM(L13:W13) -> 329400
A14: =+A13 -> 2024003 | K14: 労災保険 | L14: 1534 | M14: 1538 | N14: 1542 | O14: 1542 | P14: 1538 | Q14: 1536 | R14: 1544 | S14: 1536 | T14: 1540 | U14: 1538 | V14: 1605 | W14: 1534 | X14: =SUM(L14:W14) -> 18527
A15: =+A14 -> 2024003 | K15: 雇用保険 | L15: 1687 | M15: 1692 | N15: 1696 | O15: 1696 | P15: 1692 | Q15: 1690 | R15: 1698 | S15: 1690 | T15: 1694 | U15: 1692 | V15: 1765 | W15: 1687 | X15: =SUM(L15:W15) -> 20379
A16: =+A15 -> 2024003 | K16: 粗利 | L16: =L5-L8 -> 90779 | M16: =M5-M8 -> 127470 | N16: =N5-N8 -> 126662 | O16: =O5-O8 -> 126662 | P16: =P5-P8 -> 127470 | Q16: =Q5-Q8 -> 112874 | R16: =R5-R8 -> 126258 | S16: =S5-S8 -> 103874 | ... X16: =X5-X8 -> 1422990.2
A17: 2024031 | C17: =C5+1 -> 2 | D17: 派遣 | E17: 転出 | G17: マネージドサービス第一本部モニタリング＆マネジメント部 | H17: 運用チームオペレータ | J17: 社員 | K17: 総受注金額 | L17: =L19+L18 -> 450000 | M17: =M18+M19 -> 0 | N17: =N18+N19 -> 0 | O17: =O18+O19 -> 0 | P17: =P18+P19 -> 0 | Q17: =Q18+Q19 -> 0 | R17: =R18+R19 -> 0 | S17: =S18+S19 -> 0 | T17: =T18+T19 -> 0 | ... W17: =W18+W19 -> 0 | X17: =SUM(L17:W17) -> 450000
A18: =+A17 -> 2024031 | K18: 派遣金額 | L18: 450000 | X18: =SUM(L18:W18) -> 450000
A19: =+A18 -> 2024031 | K19: 顧客対応当番 | X19: =SUM(L19:W19) -> 0
A20: =+A19 -> 2024031 | K20: 総経費 | L20: =SUM(L21:L27) -> 296309 | M20: =SUM(M21:M27) -> 0 | N20: =SUM(N21:N27) -> 0 | O20: =SUM(O21:O27) -> 0 | P20: =SUM(P21:P27) -> 0 | Q20: =SUM(Q21:Q27) -> 0 | R20: =SUM(R21:R27) -> 0 | S20: =SUM(S21:S27) -> 0 | ... W20: =SUM(W21:W27) -> 0 | X20: =SUM(L20:W20) -> 296309
A21: =+A20 -> 2024031 | K21: 賃金 | L21: 240834 | X21: =SUM(L21:W21) -> 240834
A22: =+A21 -> 2024031 | K22: 交通費その他 | X22: =SUM(L22:W22) -> 0
A23: =+A22 -> 2024031 | K23: 通勤定期代 | L23: 16632 | X23: =SUM(L23:W23) -> 16632
A24: =+A23 -> 2024031 | K24: 健康保険 | L24: 12350 | X24: =SUM(L24:W24) -> 12350
A25: =+A24 -> 2024031 | K25: 厚生年金 | L25: 23790 | X25: =SUM(L25:W25) -> 23790
A26: =+A25 -> 2024031 | K26: 労災保険 | L26: 1287 | X26: =SUM(L26:W26) -> 1287
A27: =+A26 -> 2024031 | K27: 雇用保険 | L27: 1416 | X27: =SUM(L27:W27) -> 1416
A28: =+A27 -> 2024031 | K28: 粗利 | L28: =L17-L20 -> 153691 | M28: =M17-M20 -> 0 | N28: =N17-N20 -> 0 | O28: =O17-O20 -> 0 | P28: =P17-P20 -> 0 | Q28: =Q17-Q20 -> 0 | R28: =R17-R20 -> 0 | S28: =S17-S20 -> 0 | ... X28: =X17-X20 -> 153691
A29: 2024026 | C29: =C17+1 -> 3 | D29: 派遣 | G29: マネージドサービス第一本部モニタリング＆マネジメント部 | H29: 運用チームオペレータ | J29: 社員 | K29: 総受注金額 | L29: =L30+L31 -> 450000 | M29: =M30+M31 -> 450000 | N29: =N30+N31 -> 450000 | O29: =O30+O31 -> 450000 | P29: =P30+P31 -> 450000 | Q29: =Q30+Q31 -> 371320 | R29: =R30+R31 -> 450000 | S29: =S30+S31 -> 414875 | ... W29: =W30+W31 -> 438291.67 | X29: =SUM(L29:W29) -> 5239361.7
A30: =+A29 -> 2024026 | K30: 派遣金額 | L30: 450000 | M30: 450000 | N30: 450000 | O30: 450000 | P30: 450000 | Q30: 371320 | R30: 450000 | S30: 414875 | T30: 450000 | U30: 450000 | V30: 414875 | W30: 438291.67 | X30: =SUM(L30:W30) -> 5239361.7
A31: =+A30 -> 2024026 | K31: 顧客対応当番 | X31: =SUM(L31:W31) -> 0
A32: =+A31 -> 2024026 | K32: 総経費 | L32: =SUM(L33:L39) -> 303922 | M32: =SUM(M33:M39) -> 303922 | N32: =SUM(N33:N39) -> 303922 | O32: =SUM(O33:O39) -> 303922 | P32: =SUM(P33:P39) -> 303922 | Q32: =SUM(Q33:Q39) -> 303922 | R32: =SUM(R33:R39) -> 303922 | S32: =SUM(S33:S39) -> 303922 | ... W32: =SUM(W33:W39) -> 293922 | X32: =SUM(L32:W32) -> 3620510
A33: =+A32 -> 2024026 | K33: 賃金 | L33: 245000 | M33: 245000 | N33: 245000 | O33: 245000 | P33: 245000 | Q33: 245000 | R33: 245000 | S33: 245000 | T33: 245000 | U33: 245000 | V33: 228437 | W33: 235000 | X33: =SUM(L33:W33) -> 2913437
A34: =+A33 -> 2024026 | K34: 交通費その他 | X34: =SUM(L34:W34) -> 0
A35: =+A34 -> 2024026 | K35: 通勤定期代 | L35: 20000 | M35: 20000 | N35: 20000 | O35: 20000 | P35: 20000 | Q35: 20000 | R35: 20000 | S35: 20000 | T35: 20000 | U35: 20000 | V35: 20000 | W35: 20000 | X35: =SUM(L35:W35) -> 240000
A36: =+A35 -> 2024026 | K36: 健康保険 | L36: 12350 | M36: 12350 | N36: 12350 | O36: 12350 | P36: 12350 | Q36: 12350 | R36: 12350 | S36: 12350 | T36: 12350 | U36: 12350 | V36: 12350 | W36: 12350 | X36: =SUM(L36:W36) -> 148200
A37: =+A36 -> 2024026 | K37: 厚生年金 | L37: 23790 | M37: 23790 | N37: 23790 | O37: 23790 | P37: 23790 | Q37: 23790 | R37: 23790 | S37: 23790 | T37: 23790 | U37: 23790 | V37: 23790 | W37: 23790 | X37: =SUM(L37:W37) -> 285480
A38: =+A37 -> 2024026 | K38: 労災保険 | L38: 1325 | M38: 1325 | N38: 1325 | O38: 1325 | P38: 1325 | Q38: 1325 | R38: 1325 | S38: 1325 | T38: 1325 | U38: 1325 | V38: 1329 | W38: 1325 | X38: =SUM(L38:W38) -> 15904
A39: =+A38 -> 2024026 | K39: 雇用保険 | L39: 1457 | M39: 1457 | N39: 1457 | O39: 1457 | P39: 1457 | Q39: 1457 | R39: 1457 | S39: 1457 | T39: 1457 | U39: 1457 | V39: 1462 | W39: 1457 | X39: =SUM(L39:W39) -> 17489
A40: =+A39 -> 2024026 | K40: 粗利 | L40: =L29-L32 -> 146078 | M40: =M29-M32 -> 146078 | N40: =N29-N32 -> 146078 | O40: =O29-O32 -> 146078 | P40: =P29-P32 -> 146078 | Q40: =Q29-Q32 -> 67398 | R40: =R29-R32 -> 146078 | S40: =S29-S32 -> 110953 | ... X40: =X29-X32 -> 1618851.7
A41: 2023030 | C41: =C29+1 -> 4 | D41: 派遣 | G41: マネージドサービス第一本部モニタリング＆マネジメント部 | J41: 社員 | K41: 総受注金額 | L41: =L42+L43 -> 450000 | M41: =M42+M43 -> 450000 | N41: =N42+N43 -> 450000 | O41: =O42+O43 -> 450000 | P41: =P42+P43 -> 407850 | Q41: =Q42+Q43 -> 450000 | R41: =R42+R43 -> 450000 | S41: =S42+S43 -> 450000 | ... W41: =W42+W43 -> 435013.33 | X41: =SUM(L41:W41) -> 5274018.3
A42: =+A41 -> 2023030 | K42: 派遣金額 | L42: 450000 | M42: 450000 | N42: 450000 | O42: 450000 | P42: 407850 | Q42: 450000 | R42: 450000 | S42: 450000 | T42: 450000 | U42: 405040 | V42: 426115 | W42: 435013.33 | X42: =SUM(L42:W42) -> 5274018.3
A43: =+A42 -> 2023030 | K43: 顧客対応当番 | X43: =SUM(L43:W43) -> 0
A44: =+A43 -> 2023030 | K44: 総経費 | L44: =SUM(L45:L51) -> 306034 | M44: =SUM(M45:M51) -> 306640 | N44: =SUM(N45:N51) -> 306640 | O44: =SUM(O45:O51) -> 306640 | P44: =SUM(P45:P51) -> 306640 | Q44: =SUM(Q45:Q51) -> 306640 | R44: =SUM(R45:R51) -> 306640 | S44: =SUM(S45:S51) -> 321798 | ... W44: =SUM(W45:W51) -> 291034 | X44: =SUM(L44:W44) -> 3710143
A45: =+A44 -> 2023030 | K45: 賃金 | L45: 250000 | M45: 250000 | N45: 250000 | O45: 250000 | P45: 250000 | Q45: 250000 | R45: 250000 | S45: 265000 | T45: 265000 | U45: 263527 | V45: 252479 | W45: 235000 | X45: =SUM(L45:W45) -> 3031006
A46: =+A45 -> 2023030 | K46: 交通費その他 | X46: =SUM(L46:W46) -> 0
A47: =+A46 -> 2023030 | K47: 通勤定期代 | L47: 17090 | M47: 17690 | N47: 17690 | O47: 17690 | P47: 17690 | Q47: 17690 | R47: 17690 | S47: 17690 | T47: 17690 | U47: 17690 | V47: 17690 | W47: 17090 | X47: =SUM(L47:W47) -> 211080
A48: =+A47 -> 2023030 | K48: 健康保険 | L48: 12350 | M48: 12350 | N48: 12350 | O48: 12350 | P48: 12350 | Q48: 12350 | R48: 12350 | S48: 12350 | T48: 12350 | U48: 12350 | V48: 12350 | W48: 12350 | X48: =SUM(L48:W48) -> 148200
A49: =+A48 -> 2023030 | K49: 厚生年金 | L49: 23790 | M49: 23790 | N49: 23790 | O49: 23790 | P49: 23790 | Q49: 23790 | R49: 23790 | S49: 23790 | T49: 23790 | U49: 23790 | V49: 23790 | W49: 23790 | X49: =SUM(L49:W49) -> 285480
A50: =+A49 -> 2023030 | K50: 労災保険 | L50: 1335 | M50: 1338 | N50: 1338 | O50: 1338 | P50: 1338 | Q50: 1338 | R50: 1338 | S50: 1413 | T50: 1413 | U50: 1406 | V50: 1438 | W50: 1335 | X50: =SUM(L50:W50) -> 16368
A51: =+A50 -> 2023030 | K51: 雇用保険 | L51: 1469 | M51: 1472 | N51: 1472 | O51: 1472 | P51: 1472 | Q51: 1472 | R51: 1472 | S51: 1555 | T51: 1555 | U51: 1547 | V51: 1582 | W51: 1469 | X51: =SUM(L51:W51) -> 18009
A52: =+A51 -> 2023030 | K52: 粗利 | L52: =L41-L44 -> 143966 | M52: =M41-M44 -> 143360 | N52: =N41-N44 -> 143360 | O52: =O41-O44 -> 143360 | P52: =P41-P44 -> 101210 | Q52: =Q41-Q44 -> 143360 | R52: =R41-R44 -> 143360 | S52: =S41-S44 -> 128202 | ... X52: =X41-X44 -> 1563875.3
A53: 2016021 | C53: =C41+1 -> 5 | D53: 派遣 | G53: マネージドサービス第一本部モニタリング＆マネジメント部 | J53: 社員 | K53: 総受注金額 | L53: =L54+L55 -> 710000 | M53: =M54+M55 -> 710000 | N53: =N54+N55 -> 710000 | O53: =O54+O55 -> 710000 | P53: =P54+P55 -> 710000 | Q53: =Q54+Q55 -> 698900 | R53: =R54+R55 -> 710000 | S53: =S54+S55 -> 638960 | ... W53: =W54+W55 -> 664180.56 | X53: =SUM(L53:W53) -> 8318780.6
A54: =+A53 -> 2016021 | K54: 派遣金額 | L54: 710000 | M54: 710000 | N54: 710000 | O54: 710000 | P54: 710000 | Q54: 698900 | R54: 710000 | S54: 638960 | T54: 696680 | U54: 687800 | V54: 672260 | W54: 664180.56 | X54: =SUM(L54:W54) -> 8318780.6
A55: =+A54 -> 2016021 | K55: 交通費 | X55: =SUM(L55:W55) -> 0
A56: =+A55 -> 2016021 | K56: 総経費 | L56: =SUM(L57:L63) -> 569757 | M56: =SUM(M57:M63) -> 571977 | N56: =SUM(N57:N63) -> 572381 | O56: =SUM(O57:O63) -> 571271 | P56: =SUM(P57:P63) -> 569706 | Q56: =SUM(Q57:Q63) -> 574498 | R56: =SUM(R57:R63) -> 573793 | S56: =SUM(S57:S63) -> 572985 | ... W56: =SUM(W57:W63) -> 558423.67 | X56: =SUM(L56:W56) -> 6844094.7
A57: =+A56 -> 2016021 | K57: 賃金 | L57: 495000 | M57: 494200 | N57: 494600 | O57: 495000 | P57: 494200 | Q57: 493800 | R57: 494600 | S57: 493800 | T57: 494200 | U57: 493800 | V57: 483668 | W57: 483666.67 | X57: =SUM(L57:W57) -> 5910534.7
A58: =+A57 -> 2016021 | K58: 交通費その他 | X58: =SUM(L58:W58) -> 0
A59: =+A58 -> 2016021 | K59: 通勤定期代 | L59: 0 | M59: 2996 | N59: 2996 | O59: 1498 | P59: 749 | Q59: 1498 | R59: 0 | S59: 0 | T59: 0 | U59: 0 | V59: 0 | W59: 0 | X59: =SUM(L59:W59) -> 9737
A60: =+A59 -> 2016021 | K60: 健康保険 | L60: 26555 | M60: 26555 | N60: 26555 | O60: 26555 | P60: 26555 | Q60: 28250 | R60: 28250 | S60: 28250 | T60: 28250 | U60: 28250 | V60: 28250 | W60: 26555 | X60: =SUM(L60:W60) -> 328830
A61: =+A60 -> 2016021 | K61: 厚生年金 | L61: 43005 | M61: 43005 | N61: 43005 | O61: 43005 | P61: 43005 | Q61: 45750 | R61: 45750 | S61: 45750 | T61: 45750 | U61: 45750 | V61: 45750 | W61: 43005 | X61: =SUM(L61:W61) -> 532530
A62: =+A61 -> 2016021 | K62: 労災保険 | L62: 2475 | M62: 2486 | N62: 2488 | O62: 2482 | P62: 2475 | Q62: 2476 | R62: 2473 | S62: 2469 | T62: 2471 | U62: 2469 | V62: 2505 | W62: 2475 | X62: =SUM(L62:W62) -> 29744
A63: =+A62 -> 2016021 | K63: 雇用保険 | L63: 2722 | M63: 2735 | N63: 2737 | O63: 2731 | P63: 2722 | Q63: 2724 | R63: 2720 | S63: 2716 | T63: 2718 | U63: 2716 | V63: 2756 | W63: 2722 | X63: =SUM(L63:W63) -> 32719
A64: =+A63 -> 2016021 | K64: 粗利 | L64: =L53-L56 -> 140243 | M64: =M53-M56 -> 138023 | N64: =N53-N56 -> 137619 | O64: =O53-O56 -> 138729 | P64: =P53-P56 -> 140294 | Q64: =Q53-Q56 -> 124402 | R64: =R53-R56 -> 136207 | S64: =S53-S56 -> 65975 | ... X64: =X53-X56 -> 1474685.9
A65: 2010005 | C65: =C53+1 -> 6 | D65: 派遣 | G65: マネージドサービス第一本部モニタリング＆マネジメント部 | H65: 運用チームオペレータ | I65: Uniadex 技術第三本部フィールドインテグレーションセンター マネージメントサービスセンター（春山グループMgr） | J65: 社員 | K65: 総受注金額 | L65: =L66+L67 -> 569705 | M65: =M66+M67 -> 590000 | N65: =N66+N67 -> 590000 | O65: =O66+O67 -> 590000 | P65: =P66+P67 -> 547565 | Q65: =Q66+Q67 -> 590000 | R65: =R66+R67 -> 590000 | S65: =S66+S67 -> 571550 | ... W65: =W66+W67 -> 558250 | X65: =SUM(L65:W65) -> 6948620
A66: =+A65 -> 2010005 | K66: 派遣金額 | L66: 569705 | M66: 590000 | N66: 590000 | O66: 590000 | P66: 547565 | Q66: 590000 | R66: 590000 | S66: 571550 | T66: 590000 | U66: 590000 | V66: 571550 | W66: 558250 | X66: =SUM(L66:W66) -> 6948620
A67: =+A66 -> 2010005 | K67: 交通費 | X67: 0
A68: =+A67 -> 2010005 | K68: 総経費 | L68: =SUM(L69:L75) -> 531971 | M68: =SUM(M69:M75) -> 531971 | N68: =SUM(N69:N75) -> 531971 | O68: =SUM(O69:O75) -> 531971 | P68: =SUM(P69:P75) -> 531971 | Q68: =SUM(Q69:Q75) -> 536411 | R68: =SUM(R69:R75) -> 536411 | S68: =SUM(S69:S75) -> 536411 | ... W68: =SUM(W69:W75) -> 522971 | X68: =SUM(L68:W68) -> 6398153
A69: =+A68 -> 2010005 | K69: 賃金 | L69: 442000 | M69: 442000 | N69: 442000 | O69: 442000 | P69: 442000 | Q69: 442000 | R69: 442000 | S69: 442000 | T69: 442000 | U69: 442000 | V69: 438713 | W69: 433000 | X69: =SUM(L69:W69) -> 5291713
A70: =+A69 -> 2010005 | K70: 交通費その他 | X70: =SUM(L70:W70) -> 0
A71: =+A70 -> 2010005 | K71: 通勤定期代 | L71: 20000 | M71: 20000 | N71: 20000 | O71: 20000 | P71: 20000 | Q71: 20000 | R71: 20000 | S71: 20000 | T71: 20000 | U71: 20000 | V71: 20000 | W71: 20000 | X71: =SUM(L71:W71) -> 240000
A72: =+A71 -> 2010005 | K72: 健康保険 | L72: 24860 | M72: 24860 | N72: 24860 | O72: 24860 | P72: 24860 | Q72: 26555 | R72: 26555 | S72: 26555 | T72: 26555 | U72: 26555 | V72: 26555 | W72: 24860 | X72: =SUM(L72:W72) -> 308490
A73: =+A72 -> 2010005 | K73: 厚生年金 | L73: 40260 | M73: 40260 | N73: 40260 | O73: 40260 | P73: 40260 | Q73: 43005 | R73: 43005 | S73: 43005 | T73: 43005 | U73: 43005 | V73: 43005 | W73: 40260 | X73: =SUM(L73:W73) -> 499590
A74: =+A73 -> 2010005 | K74: 労災保険 | L74: 2310 | M74: 2310 | N74: 2310 | O74: 2310 | P74: 2310 | Q74: 2310 | R74: 2310 | S74: 2310 | T74: 2310 | U74: 2310 | V74: 2380 | W74: 2310 | X74: =SUM(L74:W74) -> 27790
A75: =+A74 -> 2010005 | K75: 雇用保険 | L75: 2541 | M75: 2541 | N75: 2541 | O75: 2541 | P75: 2541 | Q75: 2541 | R75: 2541 | S75: 2541 | T75: 2541 | U75: 2541 | V75: 2619 | W75: 2541 | X75: =SUM(L75:W75) -> 30570
A76: =+A75 -> 2010005 | K76: 粗利 | L76: =L65-L68 -> 37734 | M76: =M65-M68 -> 58029 | N76: =N65-N68 -> 58029 | O76: =O65-O68 -> 58029 | P76: =P65-P68 -> 15594 | Q76: =Q65-Q68 -> 53589 | R76: =R65-R68 -> 53589 | S76: =S65-S68 -> 35139 | ... X76: =X65-X68 -> 550467
A77: 2010001 | C77: =C65+1 -> 7 | D77: 派遣 | G77: マネージドサービス第一本部モニタリング＆マネジメント部 | H77: 運用チームオペレータ | I77: Uniadex 技術第三本部フィールドインテグレーションセンター マネージメントサービスセンター（春山グループMgr） | J77: 社員 | K77: 総受注金額 | L77: =L78+L79 -> 540000 | M77: =M78+M79 -> 540000 | N77: =N78+N79 -> 540000 | O77: =O78+O79 -> 540000 | P77: =P78+P79 -> 514650 | Q77: =Q78+Q79 -> 533240 | R77: =R78+R79 -> 540000 | S77: =S78+S79 -> 540000 | ... W77: =W78+W79 -> 536807.78 | X77: =SUM(L77:W77) -> 6397377.8
A78: =+A77 -> 2010001 | K78: 派遣金額 | L78: 540000 | M78: 540000 | N78: 540000 | O78: 540000 | P78: 514650 | Q78: 533240 | R78: 540000 | S78: 540000 | T78: 518030 | U78: 540000 | V78: 514650 | W78: 536807.78 | X78: =SUM(L78:W78) -> 6397377.8
A79: =+A78 -> 2010001 | K79: 交通費 | X79: =SUM(L79:W79) -> 0
A80: =+A79 -> 2010001 | K80: 総経費 | L80: =SUM(L81:L87) -> 478744 | M80: =SUM(M81:M87) -> 478744 | N80: =SUM(N81:N87) -> 478744 | O80: =SUM(O81:O87) -> 488546 | P80: =SUM(P81:P87) -> 478744 | Q80: =SUM(Q81:Q87) -> 478744 | R80: =SUM(R81:R87) -> 478744 | S80: =SUM(S81:S87) -> 478744 | ... W80: =SUM(W81:W87) -> 473094.22 | X80: =SUM(L80:W80) -> 5749262.2
A81: =+A80 -> 2010001 | K81: 賃金 | L81: 399000 | M81: 399000 | N81: 399000 | O81: 408700 | P81: 399000 | Q81: 399000 | R81: 399000 | S81: 399000 | T81: 399000 | U81: 399000 | V81: 399000 | W81: 393350.22 | X81: =SUM(L81:W81) -> 4792050.2
A82: =+A81 -> 2010001 | K82: 交通費その他 | X82: =SUM(L82:W82) -> 0
A83: =+A82 -> 2010001 | K83: 通勤定期代 | L83: 14720 | M83: 14720 | N83: 14720 | O83: 14720 | P83: 14720 | Q83: 14720 | R83: 14720 | S83: 14720 | T83: 14720 | U83: 14720 | V83: 14720 | W83: 14720 | X83: =SUM(L83:W83) -> 176640
A84: =+A83 -> 2010001 | K84: 健康保険 | L84: 23165 | M84: 23165 | N84: 23165 | O84: 23165 | P84: 23165 | Q84: 23165 | R84: 23165 | S84: 23165 | T84: 23165 | U84: 23165 | V84: 23165 | W84: 23165 | X84: =SUM(L84:W84) -> 277980
A85: =+A84 -> 2010001 | K85: 厚生年金 | L85: 37515 | M85: 37515 | N85: 37515 | O85: 37515 | P85: 37515 | Q85: 37515 | R85: 37515 | S85: 37515 | T85: 37515 | U85: 37515 | V85: 37515 | W85: 37515 | X85: =SUM(L85:W85) -> 450180
A86: =+A85 -> 2010001 | K86: 労災保険 | L86: 2069 | M86: 2069 | N86: 2069 | O86: 2117 | P86: 2069 | Q86: 2069 | R86: 2069 | S86: 2069 | T86: 2069 | U86: 2069 | V86: 2155 | W86: 2069 | X86: =SUM(L86:W86) -> 24962
A87: =+A86 -> 2010001 | K87: 雇用保険 | L87: 2275 | M87: 2275 | N87: 2275 | O87: 2329 | P87: 2275 | Q87: 2275 | R87: 2275 | S87: 2275 | T87: 2275 | U87: 2275 | V87: 2371 | W87: 2275 | X87: =SUM(L87:W87) -> 27450
A88: =+A87 -> 2010001 | K88: 粗利 | L88: =L77-L80 -> 61256 | M88: =M77-M80 -> 61256 | N88: =N77-N80 -> 61256 | O88: =O77-O80 -> 51454 | P88: =P77-P80 -> 35906 | Q88: =Q77-Q80 -> 54496 | R88: =R77-R80 -> 61256 | S88: =S77-S80 -> 61256 | ... X88: =X77-X80 -> 648115.56
A89: 2013026 | C89: =C77+1 -> 8 | D89: 派遣 | G89: マネージドサービス第一本部モニタリング＆マネジメント部 | H89: 運用チームオペレータ | I89: Uniadeｘ 技術第三本部フィールドインテグレーションセンター マネージメントサービスセンター（春山グループMgr） | J89: 社員 | K89: 総受注金額 | L89: =L90+L91 -> 550000 | M89: =M90+M91 -> 550000 | N89: =N90+N91 -> 550000 | O89: =O90+O91 -> 550000 | P89: =P90+P91 -> 550000 | Q89: =Q90+Q91 -> 548280 | R89: =R90+R91 -> 550000 | S89: =S90+S91 -> 550000 | ... W89: =W90+W91 -> 549808.89 | X89: =SUM(L89:W89) -> 6556808.9
A90: =+A89 -> 2013026 | K90: 派遣金額 | L90: 550000 | M90: 550000 | N90: 550000 | O90: 550000 | P90: 550000 | Q90: 548280 | R90: 550000 | S90: 550000 | T90: 550000 | U90: 550000 | V90: 508720 | W90: 549808.89 | X90: =SUM(L90:W90) -> 6556808.9
A91: =+A90 -> 2013026 | K91: 交通費 | X91: =SUM(L91:W91) -> 0
A92: =+A91 -> 2013026 | K92: 総経費 | L92: =SUM(L93:L99) -> 472569 | M92: =SUM(M93:M99) -> 471221 | N92: =SUM(N93:N99) -> 464482 | O92: =SUM(O93:O99) -> 464482 | P92: =SUM(P93:P99) -> 472569 | Q92: =SUM(Q93:Q99) -> 468922 | R92: =SUM(R93:R99) -> 478357 | S92: =SUM(S93:S99) -> 468922 | ... W92: =SUM(W93:W99) -> 456324.11 | X92: =SUM(L92:W92) -> 5624797.1
A93: =+A92 -> 2013026 | K93: 賃金 | L93: 392003 | M93: 390669 | N93: 384000 | O93: 384000 | P93: 392003 | Q93: 384000 | R93: 393337 | S93: 384000 | T93: 384000 | U93: 384000 | V93: 384000 | W93: 375758.11 | X93: =SUM(L93:W93) -> 4631770.1
A94: =+A93 -> 2013026 | K94: 交通費その他 | X94: =SUM(L94:W94) -> 0
A95: =+A94 -> 2013026 | K95: 通勤定期代 | L95: 20000 | M95: 20000 | N95: 20000 | O95: 20000 | P95: 20000 | Q95: 20000 | R95: 20000 | S95: 20000 | T95: 20000 | U95: 20000 | V95: 20000 | W95: 20000 | X95: =SUM(L95:W95) -> 240000
A96: =+A95 -> 2013026 | K96: 健康保険 | L96: 21470 | M96: 21470 | N96: 21470 | O96: 21470 | P96: 21470 | Q96: 23165 | R96: 23165 | S96: 23165 | T96: 23165 | U96: 23165 | V96: 23165 | W96: 21470 | X96: =SUM(L96:W96) -> 267810
A97: =+A96 -> 2013026 | K97: 厚生年金 | L97: 34770 | M97: 34770 | N97: 34770 | O97: 34770 | P97: 34770 | Q97: 37515 | R97: 37515 | S97: 37515 | T97: 37515 | U97: 37515 | V97: 37515 | W97: 34770 | X97: =SUM(L97:W97) -> 433710
A98: =+A97 -> 2013026 | K98: 労災保険 | L98: 2060 | M98: 2053 | N98: 2020 | O98: 2020 | P98: 2060 | Q98: 2020 | R98: 2067 | S98: 2020 | T98: 2020 | U98: 2020 | V98: 2107 | W98: 2060 | X98: =SUM(L98:W98) -> 24527
A99: =+A98 -> 2013026 | K99: 雇用保険 | L99: 2266 | M99: 2259 | N99: 2222 | O99: 2222 | P99: 2266 | Q99: 2222 | R99: 2273 | S99: 2222 | T99: 2222 | U99: 2222 | V99: 2318 | W99: 2266 | X99: =SUM(L99:W99) -> 26980
A100: =+A99 -> 2013026 | K100: 粗利 | L100: =L89-L92 -> 77431 | M100: =M89-M92 -> 78779 | N100: =N89-N92 -> 85518 | O100: =O89-O92 -> 85518 | P100: =P89-P92 -> 77431 | Q100: =Q89-Q92 -> 79358 | R100: =R89-R92 -> 71643 | S100: =S89-S92 -> 81078 | ... X100: =X89-X92 -> 932011.78
...

Sheet マネージドサービス第二本部
A1: 社員番号 | B1: 氏名 | C1: No | D1: 派遣/請負 | E1: 担当 | F1: 氏名 | G1: 作業名 | H1: 契約先 | I1: 外注会社 | J1: 売上単価 (支払単価） 【≒粗利】 | K1: 4月 | L1: 5月 | M1: 6月 | N1: 7月 | O1: 8月 | P1: 9月 | Q1: 10月 | R1: 11月 | S1: 12月 | T1: 1月 | U1: 2月 | V1: 3月 | W1: 合計
C2: マネージドサービス第二本部 | J2: 売上 | K2: =K125 -> 4758625 | L2: =L125 -> 4539760 | M2: =M125 -> 4685890 | N2: =N125 -> 4235550 | O2: =O125 -> 4232000 | P2: =P125 -> 4305625 | Q2: =Q125 -> 4286630 | R2: =R125 -> 4035400 | ... V2: =V125 -> 3789575 | W2: =SUM(K2:V2) -> 50536465
J3: 仕入 | K3: =K126 -> 3409115 | L3: =L126 -> 3360925 | M3: =M126 -> 3405027 | N3: =N126 -> 2977481 | O3: =O126 -> 2953730 | P3: =P126 -> 2930924 | Q3: =Q126 -> 3114891 | R3: =R126 -> 2919826 | ... V3: =V126 -> 2676301 | W3: =SUM(K3:V3) -> 36038836
J4: 粗利 | K4: =K2-K3 -> 1349510 | L4: =L2-L3 -> 1178835 | M4: =M2-M3 -> 1280863 | N4: =N2-N3 -> 1258069 | O4: =O2-O3 -> 1278270 | P4: =P2-P3 -> 1374701 | Q4: =Q2-Q3 -> 1171739 | R4: =R2-R3 -> 1115574 | ... V4: =V2-V3 -> 1113274 | W4: =SUM(K4:V4) -> 14497629
A5: 2020028 | C5: 1 | D5: 派遣 | G5: マネージドサービス第二本部サービスマネジメント部 | I5: 社員 | J5: 総受注金額 | K5: =K6+K7 -> 570000 | L5: =L6+L7 -> 570000 | M5: =M6+M7 -> 570000 | N5: =N6+N7 -> 570000 | O5: =O6+O7 -> 570000 | P5: =P6+P7 -> 600000 | Q5: =Q6+Q7 -> 600000 | R5: =R6+R7 -> 541875 | ... V5: =V6+V7 -> 570000 | W5: =SUM(K5:V5) -> 6815625
A6: =+A5 -> 2020028 | J6: 派遣金額 | K6: 570000 | L6: 570000 | M6: 570000 | N6: 570000 | O6: 570000 | P6: 600000 | Q6: 600000 | R6: 541875 | S6: 581250 | T6: 575625 | U6: 496875 | V6: 570000 | W6: =SUM(K6:V6) -> 6815625
A7: =+A6 -> 2020028 | J7: 交通費 | W7: =SUM(K7:V7) -> 0
A8: =+A7 -> 2020028 | J8: 総経費 | K8: =SUM(K9:K15) -> 414440 | L8: =SUM(L9:L15) -> 411675 | M8: =SUM(M9:M15) -> 412079 | N8: =SUM(N9:N15) -> 414440 | O8: =SUM(O9:O15) -> 411675 | P8: =SUM(P9:P15) -> 415039 | Q8: =SUM(Q9:Q15) -> 431005 | R8: =SUM(R9:R15) -> 420971 | ... V8: =SUM(V9:V15) -> 414440 | W8: =SUM(K8:V8) -> 5032494
A9: =+A8 -> 2020028 | J9: 賃金 | K9: 358000 | L9: 357600 | M9: 358000 | N9: 358000 | O9: 357600 | P9: 358000 | Q9: 373800 | R9: 361535 | S9: 372200 | T9: 371800 | U9: 371000 | V9: 358000 | W9: =SUM(K9:V9) -> 4355535
A10: =+A9 -> 2020028 | J10: 交通費その他 | W10: =SUM(K10:V10) -> 0
A11: =+A10 -> 2020028 | J11: 通勤定期代 | K11: 2336 | L11: 0 | M11: 0 | N11: 2336 | O11: 0 | P11: 0 | Q11: 0 | R11: 2336 | S11: 0 | T11: 0 | U11: 0 | V11: 2336 | W11: =SUM(K11:V11) -> 9344
A12: =+A11 -> 2020028 | J12: 健康保険 | K12: 19210 | L12: 19210 | M12: 19210 | N12: 19210 | O12: 19210 | P12: 20340 | Q12: 20340 | R12: 20340 | S12: 20340 | T12: 20340 | U12: 20340 | V12: 19210 | W12: =SUM(K12:V12) -> 237300
