Workbook

Sheet まとめ
D1: 売上単価 (支払単価） 【≒粗利】 | E1: 4月 | F1: 5月 | G1: 6月 | H1: 7月 | I1: 8月 | J1: 9月 | K1: 10月 | L1: 11月 | M1: 12月 | N1: 1月 | O1: 2月 | P1: 3月 | Q1: 合計
A2: その他 総計 | D2: 売上 | E2: =E5+E8+E11+E14+E17+E20+E23 -> 24106655 | F2: =F5+F8+F11+F14+F17+F20+F23 -> 23112898 | G2: =G5+G8+G11+G14+G17+G20+G23 -> 23401232 | H2: =H5+H8+H11+H14+H17+H20+H23 -> 23014084 | I2: =I5+I8+I11+I14+I17+I20+I23 -> 22947961 | J2: =J5+J8+J11+J14+J17+J20+J23 -> 23155345 | K2: =K5+K8+K11+K14+K17+K20+K23 -> 25958629 | L2: =L5+L8+L11+L14+L17+L20+L23 -> 24902172 | ... P2: =P5+P8+P11+P14+P17+P20+P23 -> 26244946 | Q2: =SUM(E2:P2) -> 2.9209205e+08
D3: 仕入 | E3: =E6+E9+E12+E15+E18+E21+E24 -> 18425351 | F3: =F6+F9+F12+F15+F18+F21+F24 -> 17622177 | G3: =G6+G9+G12+G15+G18+G21+G24 -> 17764506 | H3: =H6+H9+H12+H15+H18+H21+H24 -> 17979492 | I3: =I6+I9+I12+I15+I18+I21+I24 -> 17777157 | J3: =J6+J9+J12+J15+J18+J21+J24 -> 17800129 | K3: =K6+K9+K12+K15+K18+K21+K24 -> 20061535 | L3: =L6+L9+L12+L15+L18+L21+L24 -> 19629756 | ... P3: =P6+P9+P12+P15+P18+P21+P24 -> 20655609 | Q3: =SUM(E3:P3) -> 2.2765335e+08
D4: 粗利 | E4: =E2-E3 -> 5681304 | F4: =F2-F3 -> 5490721 | G4: =G2-G3 -> 5636726 | H4: =H2-H3 -> 5034592 | I4: =I2-I3 -> 5170804 | J4: =J2-J3 -> 5355216.3 | K4: =K2-K3 -> 5897094.3 | L4: =L2-L3 -> 5272415.9 | ... P4: =P2-P3 -> 5589336.1 | Q4: =SUM(E4:P4) -> 64438702
A5: =EXA!C2 -> EXA | D5: 売上 | E5: =EXA!L2 -> 1185250 | F5: =EXA!M2 -> 576000 | G5: =EXA!N2 -> 686000 | H5: =EXA!O2 -> 742000 | I5: =EXA!P2 -> 528000 | J5: =EXA!Q2 -> 644000 | K5: =EXA!R2 -> 776000 | L5: =EXA!S2 -> 686000 | ... P5: =EXA!W2 -> 670000 | Q5: =SUM(E5:P5) -> 8437250
D6: 仕入 | E6: =EXA!L3 -> 970141 | F6: =EXA!M3 -> 481881 | G6: =EXA!N3 -> 496562 | H6: =EXA!O3 -> 534047 | I6: =EXA!P3 -> 469872 | J6: =EXA!Q3 -> 494050 | K6: =EXA!R3 -> 578839 | L6: =EXA!S3 -> 517198 | ... P6: =EXA!W3 -> 503926 | Q6: =SUM(E6:P6) -> 6596112
D7: 粗利 | E7: =E5-E6 -> 215109 | F7: =F5-F6 -> 94119 | G7: =G5-G6 -> 189438 | H7: =H5-H6 -> 207953 | I7: =I5-I6 -> 58128 | J7: =J5-J6 -> 149950 | K7: =K5-K6 -> 197161 | L7: =L5-L6 -> 168802 | ... P7: =P5-P6 -> 166074 | Q7: =SUM(E7:P7) -> 1841138
A8: =Ericson!C2 -> Ericson | D8: 売上 | E8: =Ericson!L2 -> 1605750 | F8: =Ericson!M2 -> 1637900 | G8: =Ericson!N2 -> 1673300 | H8: =Ericson!O2 -> 1733525 | I8: =Ericson!P2 -> 1499800 | J8: =Ericson!Q2 -> 1641800 | K8: =Ericson!R2 -> 1747800 | L8: =Ericson!S2 -> 1475950 | ... P8: =Ericson!W2 -> 1955666.7 | Q8: =SUM(E8:P8) -> 18979842
D9: 仕入 | E9: =Ericson!L3 -> 1251775 | F9: =Ericson!M3 -> 1269463 | G9: =Ericson!N3 -> 1273715 | H9: =Ericson!O3 -> 1313839 | I9: =Ericson!P3 -> 1209884 | J9: =Ericson!Q3 -> 1248621 | K9: =Ericson!R3 -> 1335136 | L9: =Ericson!S3 -> 1174705 | ... P9: =Ericson!W3 -> 1470620.7 | Q9: =SUM(E9:P9) -> 15051679
D10: 粗利 | E10: =E8-E9 -> 353975 | F10: =F8-F9 -> 368437 | G10: =G8-G9 -> 399585 | H10: =H8-H9 -> 419686 | I10: =I8-I9 -> 289916 | J10: =J8-J9 -> 393179 | K10: =K8-K9 -> 412664 | L10: =L8-L9 -> 301245 | ... P10: =P8-P9 -> 485046 | Q10: =SUM(E10:P10) -> 3928163
A11: ='NI+C'!C2 -> NI+C | D11: 売上 | E11: ='NI+C'!L2 -> 1947060 | F11: ='NI+C'!M2 -> 1957920 | G11: ='NI+C'!N2 -> 2004980 | H11: ='NI+C'!O2 -> 2023080 | I11: ='NI+C'!P2 -> 1972400 | J11: ='NI+C'!Q2 -> 1932580 | K11: ='NI+C'!R2 -> 1983260 | L11: ='NI+C'!S2 -> 1915100 | ... P11: ='NI+C'!W2 -> 2711278.9 | Q11: =SUM(E11:P11) -> 25935719
D12: 仕入 | E12: ='NI+C'!L3 -> 1430802 | F12: ='NI+C'!M3 -> 1407510 | G12: ='NI+C'!N3 -> 1416521 | H12: ='NI+C'!O3 -> 1438714 | I12: ='NI+C'!P3 -> 1391316 | J12: ='NI+C'!Q3 -> 1389741 | K12: ='NI+C'!R3 -> 1447684 | L12: ='NI+C'!S3 -> 1361290 | ... P12: ='NI+C'!W3 -> 1859789.1 | Q12: =SUM(E12:P12) -> 18424933
D13: 粗利 | E13: =E11-E12 -> 516258 | F13: =F11-F12 -> 550410 | G13: =G11-G12 -> 588459 | H13: =H11-H12 -> 584366 | I13: =I11-I12 -> 581084 | J13: =J11-J12 -> 542839 | K13: =K11-K12 -> 535576 | L13: =L11-L12 -> 553810 | ... P13: =P11-P12 -> 851489.78 | Q13: =SUM(E13:P13) -> 7510785.8
A14: ='S&I'!C2 -> S&I | D14: 売上 | E14: ='S&I'!L2 -> 1416960 | F14: ='S&I'!M2 -> 1221510 | G14: ='S&I'!N2 -> 1450000 | H14: ='S&I'!O2 -> 1483040 | I14: ='S&I'!P2 -> 1361690 | J14: ='S&I'!Q2 -> 1394730 | K14: ='S&I'!R2 -> 1450000 | L14: ='S&I'!S2 -> 1350880 | ... P14: ='S&I'!W2 -> 1450000 | Q14: =SUM(E14:P14) -> 16927560
D15: 仕入 | E15: ='S&I'!L3 -> 1165794 | F15: ='S&I'!M3 -> 1135784 | G15: ='S&I'!N3 -> 1165868 | H15: ='S&I'!O3 -> 1219723 | I15: ='S&I'!P3 -> 1140263 | J15: ='S&I'!Q3 -> 1142102 | K15: ='S&I'!R3 -> 1192865 | L15: ='S&I'!S3 -> 1095377 | ... P15: ='S&I'!W3 -> 1162521.6 | Q15: =SUM(E15:P15) -> 13925478
D16: 粗利 | E16: =E14-E15 -> 251166 | F16: =F14-F15 -> 85726 | G16: =G14-G15 -> 284132 | H16: =H14-H15 -> 263317 | I16: =I14-I15 -> 221427 | J16: =J14-J15 -> 252628 | K16: =K14-K15 -> 257135 | L16: =L14-L15 -> 255503 | ... P16: =P14-P15 -> 287478.44 | Q16: =SUM(E16:P16) -> 3002082.4
A17: =ジャステック!C2 -> ジャステック | D17: 売上 | E17: =ジャステック!L2 -> 1240000 | F17: =ジャステック!M2 -> 1240000 | G17: =ジャステック!N2 -> 1240000 | H17: =ジャステック!O2 -> 1228165 | I17: =ジャステック!P2 -> 1240000 | J17: =ジャステック!Q2 -> 1240000 | K17: =ジャステック!R2 -> 1207125 | L17: =ジャステック!S2 -> 1142950 | ... P17: =ジャステック!W2 -> 1240000 | Q17: =SUM(E17:P17) -> 14713840
D18: 仕入 | E18: =ジャステック!L3 -> 972240 | F18: =ジャステック!M3 -> 971308 | G18: =ジャステック!N3 -> 971076 | H18: =ジャステック!O3 -> 1267611 | I18: =ジャステック!P3 -> 963651 | J18: =ジャステック!Q3 -> 962709 | K18: =ジャステック!R3 -> 964571 | L18: =ジャステック!S3 -> 955830 | ... P18: =ジャステック!W3 -> 958547 | Q18: =SUM(E18:P18) -> 11900035
D19: 粗利 | E19: =E17-E18 -> 267760 | F19: =F17-F18 -> 268692 | G19: =G17-G18 -> 268924 | H19: =H17-H18 -> -39446 | I19: =I17-I18 -> 276349 | J19: =J17-J18 -> 277291 | K19: =K17-K18 -> 242554 | L19: =L17-L18 -> 187120 | ... P19: =P17-P18 -> 281453 | Q19: =SUM(E19:P19) -> 2813805
A20: =NDICS!C2 -> 日本ディクス | D20: 売上 | E20: =NDICS!L2 -> 1415000 | F20: =NDICS!M2 -> 1310000 | G20: =NDICS!N2 -> 1310000 | H20: =NDICS!O2 -> 1310000 | I20: =NDICS!P2 -> 1310000 | J20: =NDICS!Q2 -> 1310000 | K20: =NDICS!R2 -> 1860000 | L20: =NDICS!S2 -> 1848240 | ... P20: =NDICS!W2 -> 1160000 | Q20: =SUM(E20:P20) -> 16936800
D21: 仕入 | E21: =NDICS!L3 -> 1100902 | F21: =NDICS!M3 -> 940274 | G21: =NDICS!N3 -> 956967 | H21: =NDICS!O3 -> 994665 | I21: =NDICS!P3 -> 951096 | J21: =NDICS!Q3 -> 987153 | K21: =NDICS!R3 -> 1364855 | L21: =NDICS!S3 -> 1339644 | ... P21: =NDICS!W3 -> 807304 | Q21: =SUM(E21:P21) -> 12705542
D22: 粗利 | E22: =E20-E21 -> 314098 | F22: =F20-F21 -> 369726 | G22: =G20-G21 -> 353033 | H22: =H20-H21 -> 315335 | I22: =I20-I21 -> 358904 | J22: =J20-J21 -> 322847 | K22: =K20-K21 -> 495145 | L22: =L20-L21 -> 508596 | ... P22: =P20-P21 -> 352696 | Q22: =SUM(E22:P22) -> 4231258
A23: =Other!C2 -> Other | D23: 売上 | E23: =Other!L2 -> 15296635 | F23: =Other!M2 -> 15169568 | G23: =Other!N2 -> 15036952 | H23: =Other!O2 -> 14494274 | I23: =Other!P2 -> 15036071 | J23: =Other!Q2 -> 14992235 | K23: =Other!R2 -> 16934444 | L23: =Other!S2 -> 16483052 | ... P23: =Other!W2 -> 17058000 | Q23: =SUM(E23:P23) -> 190161042
D24: 仕入 | E24: =Other!L3 -> 11533697 | F24: =Other!M3 -> 11415957 | G24: =Other!N3 -> 11483797 | H24: =Other!O3 -> 11210893 | I24: =Other!P3 -> 11651075 | J24: =Other!Q3 -> 11575753 | K24: =Other!R3 -> 13177585 | L24: =Other!S3 -> 13185712 | ... P24: =Other!W3 -> 13892901 | Q24: =SUM(E24:P24) -> 1.4904957e+08
D25: 粗利 | E25: =E23-E24 -> 3762938 | F25: =F23-F24 -> 3753611 | G25: =G23-G24 -> 3553155 | H25: =H23-H24 -> 3283381 | I25: =I23-I24 -> 3384996 | J25: =J23-J24 -> 3416482.3 | K25: =K23-K24 -> 3756859.3 | L25: =L23-L24 -> 3297339.9 | ... P25: =P23-P24 -> 3165098.9 | Q25: =SUM(E25:P25) -> 41111470

Sheet まとめ (2)
D1: 売上単価 (支払単価） 【≒粗利】 | E1: 4月 | F1: 5月 | G1: 6月 | H1: 7月 | I1: 8月 | J1: 9月 | K1: 10月 | L1: 11月 | M1: 12月 | N1: 1月 | O1: 2月 | P1: 3月 | Q1: 合計
A2: その他 総計 | D2: 売上 | E2: =(E5+E8+E11+E14+E17+E20+E23) -> 24106655 | F2: =(F5+F8+F11+F14+F17+F20+F23)*F28 -> 23112898 | G2: =(G5+G8+G11+G14+G17+G20+G23)*G28 -> 23401232 | H2: =(H5+H8+H11+H14+H17+H20+H23)*H28 -> 23014084 | I2: =(I5+I8+I11+I14+I17+I20+I23)*I28 -> 22947961 | J2: =(J5+J8+J11+J14+J17+J20+J23)*J28 -> 23155345 | K2: =(K5+K8+K11+K14+K17+K20+K23)*K28 -> 25958629 | L2: =(L5+L8+L11+L14+L17+L20+L23)*L28 -> 24902172 | M2: =(M5+M8+M11+M14+M17+M20+M23)*M28 -> 25337300 | ... P2: =(P5+P8+P11+P14+P17+P20+P23)*P28 -> 26244946 | Q2: =SUM(E2:P2) -> 2.9209205e+08
D3: 仕入 | E3: =(E6+E9+E12+E15+E18+E21+E24) -> 18425351 | F3: =(F6+F9+F12+F15+F18+F21+F24)*F29 -> 17622177 | G3: =(G6+G9+G12+G15+G18+G21+G24)*G29 -> 17764506 | H3: =(H6+H9+H12+H15+H18+H21+H24)*H29 -> 17979492 | I3: =(I6+I9+I12+I15+I18+I21+I24)*I29 -> 17777157 | J3: =(J6+J9+J12+J15+J18+J21+J24)*J29 -> 17800129 | K3: =(K6+K9+K12+K15+K18+K21+K24)*K29 -> 20061535 | L3: =(L6+L9+L12+L15+L18+L21+L24)*L29 -> 19629756 | M3: =(M6+M9+M12+M15+M18+M21+M24)*M29 -> 20398597 | ... P3: =(P6+P9+P12+P15+P18+P21+P24)*P29 -> 20655609 | Q3: =SUM(E3:P3) -> 2.2765335e+08
D4: 粗利 | E4: =E2-E3 -> 5681304 | F4: =F2-F3 -> 5490721 | G4: =G2-G3 -> 5636726 | H4: =H2-H3 -> 5034592 | I4: =I2-I3 -> 5170804 | J4: =J2-J3 -> 5355216.3 | K4: =K2-K3 -> 5897094.3 | L4: =L2-L3 -> 5272415.9 | ... P4: =P2-P3 -> 5589336.1 | Q4: =SUM(E4:P4) -> 64438702
A5: =EXA!C2 -> EXA | D5: 売上 | E5: =EXA!L2 -> 1185250 | F5: =EXA!M2 -> 576000 | G5: =EXA!N2 -> 686000 | H5: =EXA!O2 -> 742000 | I5: =EXA!P2 -> 528000 | J5: =EXA!Q2 -> 644000 | K5: =EXA!R2 -> 776000 | L5: =EXA!S2 -> 686000 | ... P5: =EXA!W2 -> 670000 | Q5: =SUM(E5:P5) -> 8437250
D6: 仕入 | E6: =EXA!L3 -> 970141 | F6: =EXA!M3 -> 481881 | G6: =EXA!N3 -> 496562 | H6: =EXA!O3 -> 534047 | I6: =EXA!P3 -> 469872 | J6: =EXA!Q3 -> 494050 | K6: =EXA!R3 -> 578839 | L6: =EXA!S3 -> 517198 | ... P6: =EXA!W3 -> 503926 | Q6: =SUM(E6:P6) -> 6596112
D7: 粗利 | E7: =E5-E6 -> 215109 | F7: =F5-F6 -> 94119 | G7: =G5-G6 -> 189438 | H7: =H5-H6 -> 207953 | I7: =I5-I6 -> 58128 | J7: =J5-J6 -> 149950 | K7: =K5-K6 -> 197161 | L7: =L5-L6 -> 168802 | ... P7: =P5-P6 -> 166074 | Q7: =SUM(E7:P7) -> 1841138
A8: =Ericson!C2 -> Ericson | D8: 売上 | E8: =Ericson!L2 -> 1605750 | F8: =Ericson!M2 -> 1637900 | G8: =Ericson!N2 -> 1673300 | H8: =Ericson!O2 -> 1733525 | I8: =Ericson!P2 -> 1499800 | J8: =Ericson!Q2 -> 1641800 | K8: =Ericson!R2 -> 1747800 | L8: =Ericson!S2 -> 1475950 | ... P8: =Ericson!W2 -> 1955666.7 | Q8: =SUM(E8:P8) -> 18979842
D9: 仕入 | E9: =Ericson!L3 -> 1251775 | F9: =Ericson!M3 -> 1269463 | G9: =Ericson!N3 -> 1273715 | H9: =Ericson!O3 -> 1313839 | I9: =Ericson!P3 -> 1209884 | J9: =Ericson!Q3 -> 1248621 | K9: =Ericson!R3 -> 1335136 | L9: =Ericson!S3 -> 1174705 | ... P9: =Ericson!W3 -> 1470620.7 | Q9: =SUM(E9:P9) -> 15051679
D10: 粗利 | E10: =E8-E9 -> 353975 | F10: =F8-F9 -> 368437 | G10: =G8-G9 -> 399585 | H10: =H8-H9 -> 419686 | I10: =I8-I9 -> 289916 | J10: =J8-J9 -> 393179 | K10: =K8-K9 -> 412664 | L10: =L8-L9 -> 301245 | ... P10: =P8-P9 -> 485046 | Q10: =SUM(E10:P10) -> 3928163
A11: ='NI+C'!C2 -> NI+C | D11: 売上 | E11: ='NI+C'!L2 -> 1947060 | F11: ='NI+C'!M2 -> 1957920 | G11: ='NI+C'!N2 -> 2004980 | H11: ='NI+C'!O2 -> 2023080 | I11: ='NI+C'!P2 -> 1972400 | J11: ='NI+C'!Q2 -> 1932580 | K11: ='NI+C'!R2 -> 1983260 | L11: ='NI+C'!S2 -> 1915100 | ... P11: ='NI+C'!W2 -> 2711278.9 | Q11: =SUM(E11:P11) -> 25935719
D12: 仕入 | E12: ='NI+C'!L3 -> 1430802 | F12: ='NI+C'!M3 -> 1407510 | G12: ='NI+C'!N3 -> 1416521 | H12: ='NI+C'!O3 -> 1438714 | I12: ='NI+C'!P3 -> 1391316 | J12: ='NI+C'!Q3 -> 1389741 | K12: ='NI+C'!R3 -> 1447684 | L12: ='NI+C'!S3 -> 1361290 | ... P12: ='NI+C'!W3 -> 1859789.1 | Q12: =SUM(E12:P12) -> 18424933
D13: 粗利 | E13: =E11-E12 -> 516258 | F13: =F11-F12 -> 550410 | G13: =G11-G12 -> 588459 | H13: =H11-H12 -> 584366 | I13: =I11-I12 -> 581084 | J13: =J11-J12 -> 542839 | K13: =K11-K12 -> 535576 | L13: =L11-L12 -> 553810 | ... P13: =P11-P12 -> 851489.78 | Q13: =SUM(E13:P13) -> 7510785.8
A14: ='S&I'!C2 -> S&I | D14: 売上 | E14: ='S&I'!L2 -> 1416960 | F14: ='S&I'!M2 -> 1221510 | G14: ='S&I'!N2 -> 1450000 | H14: ='S&I'!O2 -> 1483040 | I14: ='S&I'!P2 -> 1361690 | J14: ='S&I'!Q2 -> 1394730 | K14: ='S&I'!R2 -> 1450000 | L14: ='S&I'!S2 -> 1350880 | ... P14: ='S&I'!W2 -> 1450000 | Q14: =SUM(E14:P14) -> 16927560
D15: 仕入 | E15: ='S&I'!L3 -> 1165794 | F15: ='S&I'!M3 -> 1135784 | G15: ='S&I'!N3 -> 1165868 | H15: ='S&I'!O3 -> 1219723 | I15: ='S&I'!P3 -> 1140263 | J15: ='S&I'!Q3 -> 1142102 | K15: ='S&I'!R3 -> 1192865 | L15: ='S&I'!S3 -> 1095377 | ... P15: ='S&I'!W3 -> 1162521.6 | Q15: =SUM(E15:P15) -> 13925478
D16: 粗利 | E16: =E14-E15 -> 251166 | F16: =F14-F15 -> 85726 | G16: =G14-G15 -> 284132 | H16: =H14-H15 -> 263317 | I16: =I14-I15 -> 221427 | J16: =J14-J15 -> 252628 | K16: =K14-K15 -> 257135 | L16: =L14-L15 -> 255503 | ... P16: =P14-P15 -> 287478.44 | Q16: =SUM(E16:P16) -> 3002082.4
A17: =ジャステック!C2 -> ジャステック | D17: 売上 | E17: =ジャステック!L2 -> 1240000 | F17: =ジャステック!M2 -> 1240000 | G17: =ジャステック!N2 -> 1240000 | H17: =ジャステック!O2 -> 1228165 | I17: =ジャステック!P2 -> 1240000 | J17: =ジャステック!Q2 -> 1240000 | K17: =ジャステック!R2 -> 1207125 | L17: =ジャステック!S2 -> 1142950 | ... P17: =ジャステック!W2 -> 1240000 | Q17: =SUM(E17:P17) -> 14713840
D18: 仕入 | E18: =ジャステック!L3 -> 972240 | F18: =ジャステック!M3 -> 971308 | G18: =ジャステック!N3 -> 971076 | H18: =ジャステック!O3 -> 1267611 | I18: =ジャステック!P3 -> 963651 | J18: =ジャステック!Q3 -> 962709 | K18: =ジャステック!R3 -> 964571 | L18: =ジャステック!S3 -> 955830 | ... P18: =ジャステック!W3 -> 958547 | Q18: =SUM(E18:P18) -> 11900035
D19: 粗利 | E19: =E17-E18 -> 267760 | F19: =F17-F18 -> 268692 | G19: =G17-G18 -> 268924 | H19: =H17-H18 -> -39446 | I19: =I17-I18 -> 276349 | J19: =J17-J18 -> 277291 | K19: =K17-K18 -> 242554 | L19: =L17-L18 -> 187120 | ... P19: =P17-P18 -> 281453 | Q19: =SUM(E19:P19) -> 2813805
A20: =NDICS!C2 -> 日本ディクス | D20: 売上 | E20: =NDICS!L2 -> 1415000 | F20: =NDICS!M2 -> 1310000 | G20: =NDICS!N2 -> 1310000 | H20: =NDICS!O2 -> 1310000 | I20: =NDICS!P2 -> 1310000 | J20: =NDICS!Q2 -> 1310000 | K20: =NDICS!R2 -> 1860000 | L20: =NDICS!S2 -> 1848240 | ... P20: =NDICS!W2 -> 1160000 | Q20: =SUM(E20:P20) -> 16936800
D21: 仕入 | E21: =NDICS!L3 -> 1100902 | F21: =NDICS!M3 -> 940274 | G21: =NDICS!N3 -> 956967 | H21: =NDICS!O3 -> 994665 | I21: =NDICS!P3 -> 951096 | J21: =NDICS!Q3 -> 987153 | K21: =NDICS!R3 -> 1364855 | L21: =NDICS!S3 -> 1339644 | ... P21: =NDICS!W3 -> 807304 | Q21: =SUM(E21:P21) -> 12705542
D22: 粗利 | E22: =E20-E21 -> 314098 | F22: =F20-F21 -> 369726 | G22: =G20-G21 -> 353033 | H22: =H20-H21 -> 315335 | I22: =I20-I21 -> 358904 | J22: =J20-J21 -> 322847 | K22: =K20-K21 -> 495145 | L22: =L20-L21 -> 508596 | ... P22: =P20-P21 -> 352696 | Q22: =SUM(E22:P22) -> 4231258
A23: =Other!C2 -> Other | D23: 売上 | E23: =Other!L2 -> 15296635 | F23: =Other!M2 -> 15169568 | G23: =Other!N2 -> 15036952 | H23: =Other!O2 -> 14494274 | I23: =Other!P2 -> 15036071 | J23: =Other!Q2 -> 14992235 | K23: =Other!R2 -> 16934444 | L23: =Other!S2 -> 16483052 | ... P23: =Other!W2 -> 17058000 | Q23: =SUM(E23:P23) -> 190161042
D24: 仕入 | E24: =Other!L3 -> 11533697 | F24: =Other!M3 -> 11415957 | G24: =Other!N3 -> 11483797 | H24: =Other!O3 -> 11210893 | I24: =Other!P3 -> 11651075 | J24: =Other!Q3 -> 11575753 | K24: =Other!R3 -> 13177585 | L24: =Other!S3 -> 13185712 | ... P24: =Other!W3 -> 13892901 | Q24: =SUM(E24:P24) -> 1.4904957e+08
D25: 粗利 | E25: =E23-E24 -> 3762938 | F25: =F23-F24 -> 3753611 | G25: =G23-G24 -> 3553155 | H25: =H23-H24 -> 3283381 | I25: =I23-I24 -> 3384996 | J25: =J23-J24 -> 3416482.3 | K25: =K23-K24 -> 3756859.3 | L25: =L23-L24 -> 3297339.9 | ... P25: =P23-P24 -> 3165098.9 | Q25: =SUM(E25:P25) -> 41111470
C28: 契約単価上昇係数 | E28: 1 | F28: 1 | G28: 1 | H28: 1 | I28: 1 | J28: 1 | K28: 1 | L28: 1 | M28: 1 | N28: 1 | O28: 1 | P28: 1
C29: 賃上げ上昇係数 | E29: 1 | F29: 1 | G29: 1 | H29: 1 | I29: 1 | J29: 1 | K29: 1 | L29: 1 | M29: 1 | N29: 1 | O29: 1 | P29: 1

Sheet グラフ

Sheet EXA
A1: 社員番号 | B1: 氏名 | C1: No | D1: 派遣/委任 | E1: 担当 | F1: 氏名 | G1: 派遣先部署 | H1: 作業名 | I1: 契約先 | J1: 外注会社 | K1: 売上単価 (支払単価） 【≒粗利】 | L1: 4月 | M1: 5月 | N1: 6月 | O1: 7月 | P1: 8月 | Q1: 9月 | R1: 10月 | S1: 11月 | T1: 12月 | U1: 1月 | V1: 2月 | W1: 3月 | X1: 合計
C2: EXA | K2: 売上 | L2: =L29 -> 1185250 | M2: =M29 -> 576000 | N2: =N29 -> 686000 | O2: =O29 -> 742000 | P2: =P29 -> 528000 | Q2: =Q29 -> 644000 | R2: =R29 -> 776000 | S2: =S29 -> 686000 | ... W2: =W29 -> 670000 | X2: =SUM(L2:W2) -> 8437250
K3: 仕入 | L3: =L30 -> 970141 | M3: =M30 -> 481881 | N3: =N30 -> 496562 | O3: =O30 -> 534047 | P3: =P30 -> 469872 | Q3: =Q30 -> 494050 | R3: =R30 -> 578839 | S3: =S30 -> 517198 | ... W3: =W30 -> 503926 | X3: =SUM(L3:W3) -> 6596112
K4: 粗利 | L4: =L2-L3 -> 215109 | M4: =M2-M3 -> 94119 | N4: =N2-N3 -> 189438 | O4: =O2-O3 -> 207953 | P4: =P2-P3 -> 58128 | Q4: =Q2-Q3 -> 149950 | R4: =R2-R3 -> 197161 | S4: =S2-S3 -> 168802 | ... W4: =W2-W3 -> 166074 | X4: =SUM(L4:W4) -> 1841138
A5: 2018001 | C5: 1 | D5: 委任 | H5: 鶴見 | I5: EXA | J5: 社員 | K5: 総受注金額 | L5: =L6+L7 -> 670000 | M5: =M6+M7 -> 576000 | N5: =N6+N7 -> 686000 | O5: =O6+O7 -> 742000 | P5: =P6+P7 -> 528000 | Q5: =Q6+Q7 -> 644000 | R5: =R6+R7 -> 776000 | S5: =S6+S7 -> 686000 | ... W5: =W6+W7 -> 670000 | X5: =SUM(L5:W5) -> 7922000
A6: =+A5 -> 2018001 | K6: 派遣金額 | L6: 670000 | M6: 576000 | N6: 686000 | O6: 742000 | P6: 528000 | Q6: 644000 | R6: 776000 | S6: 686000 | T6: 716000 | U6: 642000 | V6: 586000 | W6: 670000 | X6: =SUM(L6:W6) -> 7922000
A7: =+A6 -> 2018001 | K7: 交通費 | X7: 0
A8: =+A7 -> 2018001 | K8: 総経費 | L8: =SUM(L9:L15) -> 503926 | M8: =SUM(M9:M15) -> 481881 | N8: =SUM(N9:N15) -> 496562 | O8: =SUM(O9:O15) -> 534047 | P8: =SUM(P9:P15) -> 469872 | Q8: =SUM(Q9:Q15) -> 494050 | R8: =SUM(R9:R15) -> 578839 | S8: =SUM(S9:S15) -> 517198 | ... W8: =SUM(W9:W15) -> 503926 | X8: =SUM(L8:W8) -> 6129897
A9: =+A8 -> 2018001 | K9: 賃金 | L9: 426500 | M9: 406000 | N9: 416580 | O9: 452100 | P9: 392800 | Q9: 412600 | R9: 492300 | S9: 431300 | T9: 485320 | U9: 416220 | V9: 390200 | W9: 426500 | X9: =SUM(L9:W9) -> 5148420
A10: =+A9 -> 2018001 | K10: 交通費その他 | X10: =SUM(L10:W10) -> 0
A11: =+A10 -> 2018001 | K11: 通勤定期代 | L11: 15792 | M11: 14476 | N11: 18424 | O11: 20000 | P11: 15792 | Q11: 15792 | R11: 20000 | S11: 20000 | T11: 20000 | U11: 20000 | V11: 20000 | W11: 15792 | X11: =SUM(L11:W11) -> 216068
A12: =+A11 -> 2018001 | K12: 健康保険 | L12: 19475 | M12: 19475 | N12: 19475 | O12: 19475 | P12: 19475 | Q12: 20900 | R12: 20900 | S12: 20900 | T12: 20900 | U12: 20900 | V12: 20900 | W12: 19475 | X12: =SUM(L12:W12) -> 242250
A13: =+A12 -> 2018001 | K13: 厚生年金 | L13: 37515 | M13: 37515 | N13: 37515 | O13: 37515 | P13: 37515 | Q13: 40260 | R13: 40260 | S13: 40260 | T13: 40260 | U13: 40260 | V13: 40260 | W13: 37515 | X13: =SUM(L13:W13) -> 466650
A14: =+A13 -> 2018001 | K14: 労災保険 | L14: 2211 | M14: 2102 | N14: 2175 | O14: 2360 | P14: 2043 | Q14: 2142 | R14: 2561 | S14: 2256 | T14: 2527 | U14: 2181 | V14: 2138 | W14: 2211 | X14: =SUM(L14:W14) -> 26907
A15: =+A14 -> 2018001 | K15: 雇用保険 | L15: 2433 | M15: 2313 | N15: 2393 | O15: 2597 | P15: 2247 | Q15: 2356 | R15: 2818 | S15: 2482 | T15: 2779 | U15: 2399 | V15: 2352 | W15: 2433 | X15: =SUM(L15:W15) -> 29602
A16: =+A15 -> 2018001 | K16: 粗利 | L16: =L5-L8 -> 166074 | M16: =M5-M8 -> 94119 | N16: =N5-N8 -> 189438 | O16: =O5-O8 -> 207953 | P16: =P5-P8 -> 58128 | Q16: =Q5-Q8 -> 149950 | R16: =R5-R8 -> 197161 | S16: =S5-S8 -> 168802 | ... X16: =X5-X8 -> 1792103
A17: 5000016 | C17: =C5+1 -> 2 | D17: 業務委託 | E17: 転出 | H17: 鶴見 | I17: EXA | J17: ベータ システム | K17: 総受注金額 | L17: =L18+L19 -> 515250 | M17: =M18+M19 -> 0 | N17: =N18+N19 -> 0 | O17: =O18+O19 -> 0 | P17: =P18+P19 -> 0 | Q17: =Q18+Q19 -> 0 | R17: =R18+R19 -> 0 | S17: =S18+S19 -> 0 | ... W17: =W18+W19 -> 0 | X17: =SUM(L17:W17) -> 515250
A18: =+A17 -> 5000016 | B18: =+B17 -> 0 | K18: 受注 | L18: 515250 | X18: =SUM(L18:W18) -> 515250
A19: =+A18 -> 5000016 | B19: =+B18 -> 0 | X19: 0
A20: =+A19 -> 5000016 | B20: =+B19 -> 0 | K20: 総経費 | L20: =SUM(L21:L27) -> 466215 | M20: =SUM(M21:M27) -> 0 | N20: =SUM(N21:N27) -> 0 | O20: =SUM(O21:O27) -> 0 | P20: =SUM(P21:P27) -> 0 | Q20: =SUM(Q21:Q27) -> 0 | R20: =SUM(R21:R27) -> 0 | S20: =SUM(S21:S27) -> 0 | ... W20: =SUM(W21:W27) -> 0 | X20: =SUM(L20:W20) -> 466215
A21: =+A20 -> 5000016 | B21: =+B20 -> 0 | K21: 仕入 | L21: 466215 | X21: =SUM(L21:W21) -> 466215
A22: =+A21 -> 5000016 | B22: =+B21 -> 0 | X22: =SUM(L22:W22) -> 0
A23: =+A22 -> 5000016 | B23: =+B22 -> 0 | X23: =SUM(L23:W23) -> 0
A24: =+A23 -> 5000016 | B24: =+B23 -> 0 | X24: =SUM(L24:W24) -> 0
A25: =+A24 -> 5000016 | B25: =+B24 -> 0 | X25: =SUM(L25:W25) -> 0
A26: =+A25 -> 5000016 | B26: =+B25 -> 0 | X26: =SUM(L26:W26) -> 0
A27: =+A26 -> 5000016 | B27: =+B26 -> 0 | X27: =SUM(L27:W27) -> 0
A28: =+A27 -> 5000016 | B28: =+B27 -> 0 | K28: 粗利 | L28: =L17-L20 -> 49035 | M28: =M17-M20 -> 0 | N28: =N17-N20 -> 0 | O28: =O17-O20 -> 0 | P28: =P17-P20 -> 0 | Q28: =Q17-Q20 -> 0 | R28: =R17-R20 -> 0 | S28: =S17-S20 -> 0 | ... X28: =X17-X20 -> 49035
C29: =C2 -> EXA | K29: 売上 | L29: =L5+L17 -> 1185250 | M29: =M5+M17 -> 576000 | N29: =N5+N17 -> 686000 | O29: =O5+O17 -> 742000 | P29: =P5+P17 -> 528000 | Q29: =Q5+Q17 -> 644000 | R29: =R5+R17 -> 776000 | S29: =S5+S17 -> 686000 | ... W29: =W5+W17 -> 670000 | X29: =SUM(L29:W29) -> 8437250
K30: 仕入 | L30: =L8+L20 -> 970141 | M30: =M8+M20 -> 481881 | N30: =N8+N20 -> 496562 | O30: =O8+O20 -> 534047 | P30: =P8+P20 -> 469872 | Q30: =Q8+Q20 -> 494050 | R30: =R8+R20 -> 578839 | S30: =S8+S20 -> 517198 | ... W30: =W8+W20 -> 503926 | X30: =SUM(L30:W30) -> 6596112
K31: 粗利 | L31: =L29-L30 -> 215109 | M31: =M29-M30 -> 94119 | N31: =N29-N30 -> 189438 | O31: =O29-O30 -> 207953 | P31: =P29-P30 -> 58128 | Q31: =Q29-Q30 -> 149950 | R31: =R29-R30 -> 197161 | S31: =S29-S30 -> 168802 | ... W31: =W29-W30 -> 166074 | X31: =SUM(L31:W31) -> 1841138
K32: Q売上 | L32: =SUM(L29:N29) -> 2447250 | O32: =SUM(O29:Q29) -> 1914000 | R32: =SUM(R29:T29) -> 2178000 | U32: =SUM(U29:W29) -> 1898000 | X32: =SUM(L32:W32) -> 8437250
K33: Q粗利 | L33: =SUM(L31:N31) -> 498666 | O33: =SUM(O31:Q31) -> 416031 | R33: =SUM(R31:T31) -> 510177 | U33: =SUM(U31:W31) -> 416264 | X33: =SUM(L33:W33) -> 1841138

Sheet Ericson
A1: 社員番号 | B1: 氏名 | C1: No | D1: 派遣/委任 | E1: 担当 | F1: 氏名 | G1: 派遣先部署 | H1: 作業名 | I1: 契約先 | J1: 外注会社 | K1: 売上単価 (支払単価） 【≒粗利】 | L1: 4月 | M1: 5月 | N1: 6月 | O1: 7月 | P1: 8月 | Q1: 9月 | R1: 10月 | S1: 11月 | T1: 12月 | U1: 1月 | V1: 2月 | W1: 3月 | X1: 合計
C2: Ericson | K2: 売上 | L2: =L41 -> 1605750 | M2: =M41 -> 1637900 | N2: =N41 -> 1673300 | O2: =O41 -> 1733525 | P2: =P41 -> 1499800 | Q2: =Q41 -> 1641800 | R2: =R41 -> 1747800 | S2: =S41 -> 1475950 | ... W2: =W41 -> 1955666.7 | X2: =SUM(L2:W2) -> 18979842
K3: 仕入 | L3: =L42 -> 1251775 | M3: =M42 -> 1269463 | N3: =N42 -> 1273715 | O3: =O42 -> 1313839 | P3: =P42 -> 1209884 | Q3: =Q42 -> 1248621 | R3: =R42 -> 1335136 | S3: =S42 -> 1174705 | ... W3: =W42 -> 1470620.7 | X3: =SUM(L3:W3) -> 15051679
K4: 粗利 | L4: =L43 -> 353975 | M4: =M43 -> 368437 | N4: =N43 -> 399585 | O4: =O43 -> 419686 | P4: =P43 -> 289916 | Q4: =Q43 -> 393179 | R4: =R43 -> 412664 | S4: =S43 -> 301245 | ... W4: =W43 -> 485046 | X4: =SUM(L4:W4) -> 3928163
A5: 2022013 | C5: 1 | D5: 派遣 | I5: エリクソン ・ジャパン | J5: 社員 | K5: 総受注金額 | L5: =L6+L7 -> 928600 | M5: =M6+M7 -> 935400 | N5: =N6+N7 -> 945650 | O5: =O6+O7 -> 1030850 | P5: =P6+P7 -> 857250 | Q5: =Q6+Q7 -> 943000 | R5: =R6+R7 -> 982950 | S5: =S6+S7 -> 869850 | ... W5: =W6+W7 -> 890666.67 | X5: =SUM(L5:W5) -> 10933867
A6: =+A5 -> 2022013 | K6: 派遣金額 | L6: 883600 | M6: 855400 | N6: 890650 | O6: 965850 | P6: 787250 | Q6: 893000 | R6: 932950 | S6: 824850 | T6: 824850 | U6: 787250 | V6: 782550 | W6: 829000 | X6: =SUM(L6:W6) -> 10257200
A7: =+A6 -> 2022013 | K7: On-call | L7: 45000 | M7: 80000 | N7: 55000 | O7: 65000 | P7: 70000 | Q7: 50000 | R7: 50000 | S7: 45000 | T7: 55000 | U7: 55000 | V7: 45000 | W7: 61666.667 | X7: =SUM(L7:W7) -> 676666.67
A8: =+A7 -> 2022013 | K8: 総経費 | L8: =SUM(L9:L15) -> 791787 | M8: =SUM(M9:M15) -> 799372 | N8: =SUM(N9:N15) -> 797319 | O8: =SUM(O9:O15) -> 836874 | P8: =SUM(P9:P15) -> 776109 | Q8: =SUM(Q9:Q15) -> 774262 | R8: =SUM(R9:R15) -> 823755 | S8: =SUM(S9:S15) -> 747117 | ... W8: =SUM(W9:W15) -> 778902.78 | X8: =SUM(L8:W8) -> 9326550.8
A9: =+A8 -> 2022013 | K9: 賃金 | L9: 686003 | M9: 687620 | N9: 685588 | O9: 721198 | P9: 664598 | Q9: 659915 | R9: 708893 | S9: 635408 | T9: 677938 | U9: 613678 | V9: 576903 | W9: 665397.22 | X9: =SUM(L9:W9) -> 7983139.2
A10: =+A9 -> 2022013 | K10: 交通費その他 | X10: =SUM(L10:W10) -> 0
A11: =+A10 -> 2022013 | K11: 通勤定期代 | L11: 2356 | M11: 8246 | N11: 8246 | O11: 11780 | P11: 8246 | Q11: 9424 | R11: 9424 | S11: 7068 | T11: 7068 | U11: 5890 | V11: 5890 | W11: 10077.556 | X11: =SUM(L11:W11) -> 93715.556
A12: =+A11 -> 2022013 | K12: 健康保険 | L12: 36725 | M12: 36725 | N12: 36725 | O12: 36725 | P12: 36725 | Q12: 38420 | R12: 38420 | S12: 38420 | T12: 38420 | U12: 38420 | V12: 38420 | W12: 36725 | X12: =SUM(L12:W12) -> 450870
A13: =+A12 -> 2022013 | K13: 厚生年金 | L13: 59475 | M13: 59475 | N13: 59475 | O13: 59475 | P13: 59475 | Q13: 59475 | R13: 59475 | S13: 59475 | T13: 59475 | U13: 59475 | V13: 59475 | W13: 59475 | X13: =SUM(L13:W13) -> 713700
A14: =+A13 -> 2022013 | K14: 労災保険 | L14: 3442 | M14: 3479 | N14: 3469 | O14: 3665 | P14: 3364 | Q14: 3347 | R14: 3592 | S14: 3212 | T14: 3425 | U14: 3098 | V14: 3001 | W14: 3442 | X14: =SUM(L14:W14) -> 40536
A15: =+A14 -> 2022013 | K15: 雇用保険 | L15: 3786 | M15: 3827 | N15: 3816 | O15: 4031 | P15: 3701 | Q15: 3681 | R15: 3951 | S15: 3534 | T15: 3768 | U15: 3408 | V15: 3301 | W15: 3786 | X15: =SUM(L15:W15) -> 44590
A16: =+A15 -> 2022013 | K16: 粗利 | L16: =L5-L8 -> 136813 | M16: =M5-M8 -> 136028 | N16: =N5-N8 -> 148331 | O16: =O5-O8 -> 193976 | P16: =P5-P8 -> 81141 | Q16: =Q5-Q8 -> 168738 | R16: =R5-R8 -> 159195 | S16: =S5-S8 -> 122733 | ... X16: =X5-X8 -> 1607315.9
A17: 2022002 | C17: =C5+1 -> 2 | D17: 派遣 | I17: エリクソン ・ジャパン | J17: 社員 | K17: 総受注金額 | L17: =L18+L19 -> 677150 | M17: =M18+M19 -> 702500 | N17: =N18+N19 -> 727650 | O17: =O18+O19 -> 702675 | P17: =P18+P19 -> 642550 | Q17: =Q18+Q19 -> 698800 | R17: =R18+R19 -> 764850 | S17: =S18+S19 -> 606100 | ... W17: =W18+W19 -> 612000 | X17: =SUM(L17:W17) -> 7592975
A18: =+A17 -> 2022002 | K18: 派遣金額 | L18: 627150 | M18: 647500 | N18: 682650 | O18: 657675 | P18: 597550 | Q18: 643800 | R18: 704850 | S18: 566100 | T18: 608650 | U18: 508750 | V18: 181300 | W18: 592000 | X18: =SUM(L18:W18) -> 7017975
A19: =+A18 -> 2022002 | K19: On-call | L19: 50000 | M19: 55000 | N19: 45000 | O19: 45000 | P19: 45000 | Q19: 55000 | R19: 60000 | S19: 40000 | T19: 60000 | U19: 60000 | V19: 40000 | W19: 20000 | X19: =SUM(L19:W19) -> 575000
A20: =+A19 -> 2022002 | K20: 総経費 | L20: =SUM(L21:L27) -> 459988 | M20: =SUM(M21:M27) -> 470091 | N20: =SUM(N21:N27) -> 476396 | O20: =SUM(O21:O27) -> 476965 | P20: =SUM(P21:P27) -> 433775 | Q20: =SUM(Q21:Q27) -> 474359 | R20: =SUM(R21:R27) -> 511381 | S20: =SUM(S21:S27) -> 427588 | ... W20: =SUM(W21:W27) -> 373791.89 | X20: =SUM(L20:W20) -> 5407201.9
A21: =+A20 -> 2022002 | K21: 賃金 | L21: 403799 | M21: 406237 | N21: 416255 | O21: 413039 | P21: 363420 | Q21: 403582 | R21: 442110 | S21: 361077 | T21: 418873 | U21: 378989 | V21: 310753 | W21: 308800 | X21: =SUM(L21:W21) -> 4626934
A22: =+A21 -> 2022002 | K22: 交通費その他 | X22: =SUM(L22:W22) -> 0
A23: =+A22 -> 2022002 | K23: 通勤定期代 | L23: 1890 | M23: 9450 | N23: 5670 | O23: 9450 | P23: 9450 | Q23: 9450 | R23: 7560 | S23: 5670 | T23: 5670 | U23: 3780 | V23: 1890 | W23: 10692.889 | X23: =SUM(L23:W23) -> 80622.889
A24: =+A23 -> 2022002 | K24: 健康保険 | L24: 17100 | M24: 17100 | N24: 17100 | O24: 17100 | P24: 19475 | Q24: 19475 | R24: 19475 | S24: 19475 | T24: 19475 | U24: 19475 | V24: 19475 | W24: 17100 | X24: =SUM(L24:W24) -> 221825
A25: =+A24 -> 2022002 | K25: 厚生年金 | L25: 32940 | M25: 32940 | N25: 32940 | O25: 32940 | P25: 37515 | Q25: 37515 | R25: 37515 | S25: 37515 | T25: 37515 | U25: 37515 | V25: 37515 | W25: 32940 | X25: =SUM(L25:W25) -> 427305
A26: =+A25 -> 2022002 | K26: 労災保険 | L26: 2028 | M26: 2078 | N26: 2110 | O26: 2112 | P26: 1864 | Q26: 2065 | R26: 2248 | S26: 1834 | T26: 2123 | U26: 1914 | V26: 1650 | W26: 2028 | X26: =SUM(L26:W26) -> 24054
A27: =+A26 -> 2022002 | K27: 雇用保険 | L27: 2231 | M27: 2286 | N27: 2321 | O27: 2324 | P27: 2051 | Q27: 2272 | R27: 2473 | S27: 2017 | T27: 2335 | U27: 2105 | V27: 1815 | W27: 2231 | X27: =SUM(L27:W27) -> 26461
A28: =+A27 -> 2022002 | K28: 粗利 | L28: =L17-L20 -> 217162 | M28: =M17-M20 -> 232409 | N28: =N17-N20 -> 251254 | O28: =O17-O20 -> 225710 | P28: =P17-P20 -> 208775 | Q28: =Q17-Q20 -> 224441 | R28: =R17-R20 -> 253469 | S28: =S17-S20 -> 178512 | ... X28: =X17-X20 -> 2185773.1
A29: 2025030 | C29: =C17+1 -> 3 | D29: 派遣 | I29: エリクソン ・ジャパン | J29: 社員 | K29: 総受注金額 | L29: =L30+L31 -> 0 | M29: =M30+M31 -> 0 | N29: =N30+N31 -> 0 | O29: =O30+O31 -> 0 | P29: =P30+P31 -> 0 | Q29: =Q30+Q31 -> 0 | R29: =R30+R31 -> 0 | S29: =S30+S31 -> 0 | ... W29: =W30+W31 -> 453000 | X29: =SUM(L29:W29) -> 453000
A30: =+A29 -> 2025030 | B30: =+B29 -> 0 | K30: 派遣金額 | W30: 453000 | X30: =SUM(L30:W30) -> 453000
A31: =+A30 -> 2025030 | B31: =+B30 -> 0 | K31: On-call | X31: =SUM(L31:W31) -> 0
A32: =+A31 -> 2025030 | B32: =+B31 -> 0 | K32: 総経費 | L32: =SUM(L33:L39) -> 0 | M32: =SUM(M33:M39) -> 0 | N32: =SUM(N33:N39) -> 0 | O32: =SUM(O33:O39) -> 0 | P32: =SUM(P33:P39) -> 0 | Q32: =SUM(Q33:Q39) -> 0 | R32: =SUM(R33:R39) -> 0 | S32: =SUM(S33:S39) -> 0 | ... W32: =SUM(W33:W39) -> 317926 | X32: =SUM(L32:W32) -> 317926
A33: =+A32 -> 2025030 | B33: =+B32 -> 0 | K33: 賃金 | W33: 260000 | X33: =SUM(L33:W33) -> 260000
A34: =+A33 -> 2025030 | B34: =+B33 -> 0 | K34: 交通費その他 | X34: =SUM(L34:W34) -> 0
A35: =+A34 -> 2025030 | B35: =+B34 -> 0 | K35: 通勤定期代 | W35: 18844 | X35: =SUM(L35:W35) -> 18844
A36: =+A35 -> 2025030 | B36: =+B35 -> 0 | K36: 健康保険 | W36: 12350 | X36: =SUM(L36:W36) -> 12350
A37: =+A36 -> 2025030 | B37: =+B36 -> 0 | K37: 厚生年金 | W37: 23790 | X37: =SUM(L37:W37) -> 23790
A38: =+A37 -> 2025030 | B38: =+B37 -> 0 | K38: 労災保険 | W38: 1401 | X38: =SUM(L38:W38) -> 1401
A39: =+A38 -> 2025030 | B39: =+B38 -> 0 | K39: 雇用保険 | W39: 1541 | X39: =SUM(L39:W39) -> 1541
A40: =+A39 -> 2025030 | B40: =+B39 -> 0 | K40: 粗利 | L40: =L29-L32 -> 0 | M40: =M29-M32 -> 0 | N40: =N29-N32 -> 0 | O40: =O29-O32 -> 0 | P40: =P29-P32 -> 0 | Q40: =Q29-Q32 -> 0 | R40: =R29-R32 -> 0 | S40: =S29-S32 -> 0 | ... X40: =X29-X32 -> 135074
C41: =C2 -> Ericson | K41: 売上 | L41: =L5+L17+L29 -> 1605750 | M41: =M5+M17+M29 -> 1637900 | N41: =N5+N17+N29 -> 1673300 | O41: =O5+O17+O29 -> 1733525 | P41: =P5+P17+P29 -> 1499800 | Q41: =Q5+Q17+Q29 -> 1641800 | R41: =R5+R17+R29 -> 1747800 | S41: =S5+S17+S29 -> 1475950 | ... W41: =W5+W17+W29 -> 1955666.7 | X41: =SUM(L41:W41) -> 18979842
K42: 仕入 | L42: =L8+L20+L32 -> 1251775 | M42: =M8+M20+M32 -> 1269463 | N42: =N8+N20+N32 -> 1273715 | O42: =O8+O20+O32 -> 1313839 | P42: =P8+P20+P32 -> 1209884 | Q42: =Q8+Q20+Q32 -> 1248621 | R42: =R8+R20+R32 -> 1335136 | S42: =S8+S20+S32 -> 1174705 | ... W42: =W8+W20+W32 -> 1470620.7 | X42: =SUM(L42:W42) -> 15051679
K43: 粗利 | L43: =L41-L42 -> 353975 | M43: =M41-M42 -> 368437 | N43: =N41-N42 -> 399585 | O43: =O41-O42 -> 419686 | P43: =P41-P42 -> 289916 | Q43: =Q41-Q42 -> 393179 | R43: =R41-R42 -> 412664 | S43: =S41-S42 -> 301245 | ... W43: =W41-W42 -> 485046 | X43: =SUM(L43:W43) -> 3928163
K44: Q売上 | L44: =SUM(L41:N41) -> 4916950 | O44: =SUM(O41:Q41) -> 4875125 | R44: =SUM(R41:T41) -> 4772250 | U44: =SUM(U41:W41) -> 4415516.7 | X44: =SUM(X41) -> 18979842
K45: Q粗利 | L45: =SUM(L43:N43) -> 1121997 | O45: =SUM(O43:Q43) -> 1102781 | R45: =SUM(R43:T43) -> 986324 | U45: =SUM(U43:W43) -> 717061 | X45: =SUM(X43) -> 3928163

Sheet NI+C
A1: 社員番号 | B1: 氏名 | C1: No | D1: 派遣/委任 | E1: 担当 | F1: 氏名 | G1: 派遣先部署 | H1: 作業名 | I1: 契約先 | J1: 外注会社 | K1: 売上単価 (支払単価） 【≒粗利】 | L1: 4月 | M1: 5月 | N1: 6月 | O1: 7月 | P1: 8月 | Q1: 9月 | R1: 10月 | S1: 11月 | T1: 12月 | U1: 1月 | V1: 2月 | W1: 3月 | X1: 合計
C2: NI+C | K2: 売上 | L2: =L53 -> 1947060 | M2: =M53 -> 1957920 | N2: =N53 -> 2004980 | O2: =O53 -> 2023080 | P2: =P53 -> 1972400 | Q2: =Q53 -> 1932580 | R2: =R53 -> 1983260 | S2: =S53 -> 1915100 | ... W2: =W53 -> 2711278.9 | X2: =SUM(L2:W2) -> 25935719
K3: 仕入 | L3: =L54 -> 1430802 | M3: =M54 -> 1407510 | N3: =N54 -> 1416521 | O3: =O54 -> 1438714 | P3: =P54 -> 1391316 | Q3: =Q54 -> 1389741 | R3: =R54 -> 1447684 | S3: =S54 -> 1361290 | ... W3: =W54 -> 1859789.1 | X3: =SUM(L3:W3) -> 18424933
K4: 粗利 | L4: =L2-L3 -> 516258 | M4: =M2-M3 -> 550410 | N4: =N2-N3 -> 588459 | O4: =O2-O3 -> 584366 | P4: =P2-P3 -> 581084 | Q4: =Q2-Q3 -> 542839 | R4: =R2-R3 -> 535576 | S4: =S2-S3 -> 553810 | ... W4: =W2-W3 -> 851489.78 | X4: =SUM(L4:W4) -> 7510785.8
A5: 2016014 | C5: 1 | D5: 派遣 | I5: エヌアイシー・パートナーズ | J5: 社員 | K5: 総受注金額 | L5: =L6+L7 -> 627060 | M5: =M6+M7 -> 637920 | N5: =N6+N7 -> 684980 | O5: =O6+O7 -> 703080 | P5: =P6+P7 -> 652400 | Q5: =Q6+Q7 -> 612580 | R5: =R6+R7 -> 663260 | S5: =S6+S7 -> 601720 | ... W5: =W6+W7 -> 611278.89 | X5: =SUM(L5:W5) -> 7762338.9
A6: =+A5 -> 2016014 | K6: 派遣金額 | L6: 627060 | M6: 637920 | N6: 684980 | O6: 703080 | P6: 652400 | Q6: 612580 | R6: 663260 | S6: 601720 | T6: 659640 | U6: 666880 | V6: 641540 | W6: 611278.89 | X6: =SUM(L6:W6) -> 7762338.9
A7: =+A6 -> 2016014 | K7: 交通費 | X7: 0
A8: =+A7 -> 2016014 | K8: 総経費 | L8: =SUM(L9:L15) -> 497001 | M8: =SUM(M9:M15) -> 489665 | N8: =SUM(N9:N15) -> 499155 | O8: =SUM(O9:O15) -> 507873 | P8: =SUM(P9:P15) -> 479431 | Q8: =SUM(Q9:Q15) -> 471935 | R8: =SUM(R9:R15) -> 517947 | S8: =SUM(S9:S15) -> 452823 | ... W8: =SUM(W9:W15) -> 479402.11 | X8: =SUM(L8:W8) -> 5866243.1
A9: =+A8 -> 2016014 | K9: 賃金 | L9: 431787 | M9: 424527 | N9: 433918 | O9: 442546 | P9: 414400 | Q9: 406982 | R9: 452515 | S9: 388069 | T9: 433760 | U9: 427552 | V9: 414084 | W9: 406469.89 | X9: =SUM(L9:W9) -> 5076609.9
A10: =+A9 -> 2016014 | K10: 交通費その他 | X10: =SUM(L10:W10) -> 0
A11: =+A10 -> 2016014 | K11: 通勤定期代 | L11: 0 | M11: 0 | N11: 0 | O11: 0 | P11: 0 | Q11: 0 | R11: 0 | S11: 0 | T11: 0 | U11: 0 | V11: 0 | W11: 7718.2222 | X11: =SUM(L11:W11) -> 7718.2222
A12: =+A11 -> 2016014 | K12: 健康保険 | L12: 23165 | M12: 23165 | N12: 23165 | O12: 23165 | P12: 23165 | Q12: 23165 | R12: 23165 | S12: 23165 | T12: 23165 | U12: 23165 | V12: 23165 | W12: 23165 | X12: =SUM(L12:W12) -> 277980
A13: =+A12 -> 2016014 | K13: 厚生年金 | L13: 37515 | M13: 37515 | N13: 37515 | O13: 37515 | P13: 37515 | Q13: 37515 | R13: 37515 | S13: 37515 | T13: 37515 | U13: 37515 | V13: 37515 | W13: 37515 | X13: =SUM(L13:W13) -> 450180
A14: =+A13 -> 2016014 | K14: 労災保険 | L14: 2159 | M14: 2123 | N14: 2170 | O14: 2213 | P14: 2072 | Q14: 2035 | R14: 2263 | S14: 1940 | T14: 2169 | U14: 2138 | V14: 2157 | W14: 2159 | X14: =SUM(L14:W14) -> 25598
A15: =+A14 -> 2016014 | K15: 雇用保険 | L15: 2375 | M15: 2335 | N15: 2387 | O15: 2434 | P15: 2279 | Q15: 2238 | R15: 2489 | S15: 2134 | T15: 2386 | U15: 2352 | V15: 2373 | W15: 2375 | X15: =SUM(L15:W15) -> 28157
A16: =+A15 -> 2016014 | K16: 粗利 | L16: =L5-L8 -> 130059 | M16: =M5-M8 -> 148255 | N16: =N5-N8 -> 185825 | O16: =O5-O8 -> 195207 | P16: =P5-P8 -> 172969 | Q16: =Q5-Q8 -> 140645 | R16: =R5-R8 -> 145313 | S16: =S5-S8 -> 148897 | ... X16: =X5-X8 -> 1896095.8
A17: 2020018 | C17: =C5+1 -> 2 | D17: 派遣 | I17: エヌアイシー・パートナーズ | J17: 社員 | K17: 総受注金額 | L17: =L18+L19 -> 530000 | M17: =M18+M19 -> 530000 | N17: =N18+N19 -> 530000 | O17: =O18+O19 -> 530000 | P17: =P18+P19 -> 530000 | Q17: =Q18+Q19 -> 530000 | R17: =R18+R19 -> 530000 | S17: =S18+S19 -> 523380 | ... W17: =W18+W19 -> 530000 | X17: =SUM(L17:W17) -> 6353380
A18: =+A17 -> 2020018 | K18: 派遣金額 | L18: 530000 | M18: 530000 | N18: 530000 | O18: 530000 | P18: 530000 | Q18: 530000 | R18: 530000 | S18: 523380 | T18: 530000 | U18: 530000 | V18: 530000 | W18: 530000 | X18: =SUM(L18:W18) -> 6353380
A19: =+A18 -> 2020018 | K19: 交通費 | X19: 0
A20: =+A19 -> 2020018 | K20: 総経費 | L20: =SUM(L21:L27) -> 417588 | M20: =SUM(M21:M27) -> 413758 | N20: =SUM(N21:N27) -> 413602 | O20: =SUM(O21:O27) -> 415871 | P20: =SUM(P21:P27) -> 413602 | Q20: =SUM(Q21:Q27) -> 412949 | R20: =SUM(R21:R27) -> 406886 | S20: =SUM(S21:S27) -> 407943 | ... W20: =SUM(W21:W27) -> 388388 | X20: =SUM(L20:W20) -> 4929866
A21: =+A20 -> 2020018 | K21: 賃金 | L21: 355200 | M21: 356800 | N21: 355600 | O21: 356800 | P21: 355600 | Q21: 356000 | R21: 350000 | S21: 350000 | T21: 356400 | U21: 355200 | V21: 355600 | W21: 326000 | X21: =SUM(L21:W21) -> 4229200
A22: =+A21 -> 2020018 | K22: 交通費その他 | X22: =SUM(L22:W22) -> 0
A23: =+A22 -> 2020018 | K23: 通勤定期代 | L23: 8528 | M23: 3138 | N23: 4184 | O23: 5230 | P23: 4184 | Q23: 3138 | R23: 3138 | S23: 4184 | T23: 3138 | U23: 4184 | V23: 3138 | W23: 8528 | X23: =SUM(L23:W23) -> 54712
A24: =+A23 -> 2020018 | K24: 健康保険 | L24: 17100 | M24: 17100 | N24: 17100 | O24: 17100 | P24: 17100 | Q24: 17100 | R24: 17100 | S24: 17100 | T24: 17100 | U24: 17100 | V24: 17100 | W24: 17100 | X24: =SUM(L24:W24) -> 205200
A25: =+A24 -> 2020018 | K25: 厚生年金 | L25: 32940 | M25: 32940 | N25: 32940 | O25: 32940 | P25: 32940 | Q25: 32940 | R25: 32940 | S25: 32940 | T25: 32940 | U25: 32940 | V25: 32940 | W25: 32940 | X25: =SUM(L25:W25) -> 395280
A26: =+A25 -> 2020018 | K26: 労災保険 | L26: 1819 | M26: 1800 | N26: 1799 | O26: 1810 | P26: 1799 | Q26: 1796 | R26: 1766 | S26: 1771 | T26: 1798 | U26: 1797 | V26: 1881 | W26: 1819 | X26: =SUM(L26:W26) -> 21655
A27: =+A26 -> 2020018 | K27: 雇用保険 | L27: 2001 | M27: 1980 | N27: 1979 | O27: 1991 | P27: 1979 | Q27: 1975 | R27: 1942 | S27: 1948 | T27: 1977 | U27: 1977 | V27: 2069 | W27: 2001 | X27: =SUM(L27:W27) -> 23819
A28: =+A27 -> 2020018 | K28: 粗利 | L28: =L17-L20 -> 112412 | M28: =M17-M20 -> 116242 | N28: =N17-N20 -> 116398 | O28: =O17-O20 -> 114129 | P28: =P17-P20 -> 116398 | Q28: =Q17-Q20 -> 117051 | R28: =R17-R20 -> 123114 | S28: =S17-S20 -> 115437 | ... X28: =X17-X20 -> 1423514
A29: 2013008 | C29: =C17+1 -> 3 | D29: 派遣 | I29: エヌアイシー・ソフト | J29: 社員 | K29: 総受注金額 | L29: =L30+L31 -> 790000 | M29: =M30+M31 -> 790000 | N29: =N30+N31 -> 790000 | O29: =O30+O31 -> 790000 | P29: =P30+P31 -> 790000 | Q29: =Q30+Q31 -> 790000 | R29: =R30+R31 -> 790000 | S29: =S30+S31 -> 790000 | ... W29: =W30+W31 -> 790000 | X29: =SUM(L29:W29) -> 9480000
A30: =+A29 -> 2013008 | K30: 派遣金額 | L30: 790000 | M30: 790000 | N30: 790000 | O30: 790000 | P30: 790000 | Q30: 790000 | R30: 790000 | S30: 790000 | T30: 790000 | U30: 790000 | V30: 790000 | W30: 790000 | X30: =SUM(L30:W30) -> 9480000
A31: =+A30 -> 2013008 | K31: 交通費 | X31: 0
A32: =+A31 -> 2013008 | K32: 総経費 | L32: =SUM(L33:L39) -> 516213 | M32: =SUM(M33:M39) -> 504087 | N32: =SUM(N33:N39) -> 503764 | O32: =SUM(O33:O39) -> 514970 | P32: =SUM(P33:P39) -> 498283 | Q32: =SUM(Q33:Q39) -> 504857 | R32: =SUM(R33:R39) -> 522851 | S32: =SUM(S33:S39) -> 500524 | ... W32: =SUM(W33:W39) -> 483746 | X32: =SUM(L32:W32) -> 6102923
A33: =+A32 -> 2013008 | K33: 賃金 | L33: 433200 | M33: 421200 | N33: 424336 | O33: 437601 | P33: 420000 | Q33: 423200 | R33: 441007 | S33: 420000 | T33: 461524 | U33: 423200 | V33: 423200 | W33: 400733 | X33: =SUM(L33:W33) -> 5129201
A34: =+A33 -> 2013008 | K34: 交通費その他 | X34: =SUM(L34:W34) -> 0
A35: =+A34 -> 2013008 | K35: 通勤定期代 | L35: 17600 | M35: 17600 | N35: 14144 | O35: 11968 | P35: 13056 | Q35: 11968 | R35: 11968 | S35: 10880 | T35: 13056 | U35: 12114 | V35: 10880 | W35: 17600 | X35: =SUM(L35:W35) -> 162834
A36: =+A35 -> 2013008 | K36: 健康保険 | L36: 23165 | M36: 23165 | N36: 23165 | O36: 23165 | P36: 23165 | Q36: 24860 | R36: 24860 | S36: 24860 | T36: 24860 | U36: 24860 | V36: 24860 | W36: 23165 | X36: =SUM(L36:W36) -> 288150
A37: =+A36 -> 2013008 | K37: 厚生年金 | L37: 37515 | M37: 37515 | N37: 37515 | O37: 37515 | P37: 37515 | Q37: 40260 | R37: 40260 | S37: 40260 | T37: 40260 | U37: 40260 | V37: 40260 | W37: 37515 | X37: =SUM(L37:W37) -> 466650
A38: =+A37 -> 2013008 | K38: 労災保険 | L38: 2254 | M38: 2194 | N38: 2192 | O38: 2248 | P38: 2165 | Q38: 2176 | R38: 2265 | S38: 2154 | T38: 2373 | U38: 2177 | V38: 2257 | W38: 2254 | X38: =SUM(L38:W38) -> 26709
A39: =+A38 -> 2013008 | K39: 雇用保険 | L39: 2479 | M39: 2413 | N39: 2412 | O39: 2473 | P39: 2382 | Q39: 2393 | R39: 2491 | S39: 2370 | T39: 2610 | U39: 2394 | V39: 2483 | W39: 2479 | X39: =SUM(L39:W39) -> 29379
A40: =+A39 -> 2013008 | K40: 粗利 | L40: =L29-L32 -> 273787 | M40: =M29-M32 -> 285913 | N40: =N29-N32 -> 286236 | O40: =O29-O32 -> 275030 | P40: =P29-P32 -> 291717 | Q40: =Q29-Q32 -> 285143 | R40: =R29-R32 -> 267149 | S40: =S29-S32 -> 289476 | ... X40: =X29-X32 -> 3377077
A41: 2025023 | C41: =C29+1 -> 4 | D41: 派遣 | I41: エヌアイシー・ソフト | J41: 社員 | K41: 総受注金額 | L41: =L42+L43 -> 0 | M41: =M42+M43 -> 0 | N41: =N42+N43 -> 0 | O41: =O42+O43 -> 0 | P41: =P42+P43 -> 0 | Q41: =Q42+Q43 -> 0 | R41: =R42+R43 -> 0 | S41: =S42+S43 -> 0 | ... W41: =W42+W43 -> 780000 | X41: =SUM(L41:W41) -> 2340000
A42: =+A41 -> 2025023 | B42: =+B41 -> 0 | K42: 派遣金額 | U42: 780000 | V42: 780000 | W42: 780000 | X42: =SUM(L42:W42) -> 2340000
A43: =+A42 -> 2025023 | B43: =+B42 -> 0 | K43: 交通費 | X43: 0
A44: =+A43 -> 2025023 | B44: =+B43 -> 0 | K44: 総経費 | L44: =SUM(L45:L51) -> 0 | M44: =SUM(M45:M51) -> 0 | N44: =SUM(N45:N51) -> 0 | O44: =SUM(O45:O51) -> 0 | P44: =SUM(P45:P51) -> 0 | Q44: =SUM(Q45:Q51) -> 0 | R44: =SUM(R45:R51) -> 0 | S44: =SUM(S45:S51) -> 0 | ... W44: =SUM(W45:W51) -> 508253 | X44: =SUM(L44:W44) -> 1525901
A45: =+A44 -> 2025023 | B45: =+B44 -> 0 | K45: 賃金 | U45: 437200 | V45: 435600 | W45: 430000 | X45: =SUM(L45:W45) -> 1302800
A46: =+A45 -> 2025023 | B46: =+B45 -> 0 | K46: 交通費その他 | X46: =SUM(L46:W46) -> 0
A47: =+A46 -> 2025023 | B47: =+B46 -> 0 | K47: 通勤定期代 | U47: 1278 | V47: 3928 | W47: 8400 | X47: =SUM(L47:W47) -> 13606
A48: =+A47 -> 2025023 | B48: =+B47 -> 0 | K48: 健康保険 | U48: 24860 | V48: 24860 | W48: 24860 | X48: =SUM(L48:W48) -> 74580
A49: =+A48 -> 2025023 | B49: =+B48 -> 0 | K49: 厚生年金 | U49: 40260 | V49: 40260 | W49: 40260 | X49: =SUM(L49:W49) -> 120780
A50: =+A49 -> 2025023 | B50: =+B49 -> 0 | K50: 労災保険 | U50: 2192 | V50: 2285 | W50: 2254 | X50: =SUM(L50:W50) -> 6731
A51: =+A50 -> 2025023 | B51: =+B50 -> 0 | K51: 雇用保険 | U51: 2412 | V51: 2513 | W51: 2479 | X51: =SUM(L51:W51) -> 7404
A52: =+A51 -> 2025023 | B52: =+B51 -> 0 | K52: 粗利 | L52: =L41-L44 -> 0 | M52: =M41-M44 -> 0 | N52: =N41-N44 -> 0 | O52: =O41-O44 -> 0 | P52: =P41-P44 -> 0 | Q52: =Q41-Q44 -> 0 | R52: =R41-R44 -> 0 | S52: =S41-S44 -> 0 | ... X52: =X41-X44 -> 814099
C53: =C2 -> NI+C | K53: 売上 | L53: =L5+L17+L29+L41 -> 1947060 | M53: =M5+M17+M29+M41 -> 1957920 | N53: =N5+N17+N29+N41 -> 2004980 | O53: =O5+O17+O29+O41 -> 2023080 | P53: =P5+P17+P29+P41 -> 1972400 | Q53: =Q5+Q17+Q29+Q41 -> 1932580 | R53: =R5+R17+R29+R41 -> 1983260 | S53: =S5+S17+S29+S41 -> 1915100 | ... W53: =W5+W17+W29+W41 -> 2711278.9 | X53: =SUM(L53:W53) -> 25935719
K54: 仕入 | L54: =L8+L20+L32+L44 -> 1430802 | M54: =M8+M20+M32+M44 -> 1407510 | N54: =N8+N20+N32+N44 -> 1416521 | O54: =O8+O20+O32+O44 -> 1438714 | P54: =P8+P20+P32+P44 -> 1391316 | Q54: =Q8+Q20+Q32+Q44 -> 1389741 | R54: =R8+R20+R32+R44 -> 1447684 | S54: =S8+S20+S32+S44 -> 1361290 | ... W54: =W8+W20+W32+W44 -> 1859789.1 | X54: =SUM(L54:W54) -> 18424933
K55: 粗利 | L55: =L53-L54 -> 516258 | M55: =M53-M54 -> 550410 | N55: =N53-N54 -> 588459 | O55: =O53-O54 -> 584366 | P55: =P53-P54 -> 581084 | Q55: =Q53-Q54 -> 542839 | R55: =R53-R54 -> 535576 | S55: =S53-S54 -> 553810 | ... W55: =W53-W54 -> 851489.78 | X55: =SUM(L55:W55) -> 7510785.8
K56: Q売上 | L56: =SUM(L53:N53) -> 5909960 | O56: =SUM(O53:Q53) -> 5928060 | R56: =SUM(R53:T53) -> 5878000 | U56: =SUM(U53:W53) -> 8219698.9 | X56: =SUM(L56:W56) -> 25935719
K57: Q粗利 | L57: =SUM(L55:N55) -> 1655127 | O57: =SUM(O55:Q55) -> 1708289 | R57: =SUM(R55:T55) -> 1611995 | U57: =SUM(U55:W55) -> 2535374.8 | X57: =SUM(L57:W57) -> 7510785.8

Sheet S&I
A1: 社員番号 | B1: 氏名 | C1: No | D1: 派遣/委任 | E1: 担当 | F1: 氏名 | G1: 派遣先部署 | H1: 作業名 | I1: 契約先 | J1: 外注会社 | K1: 売上単価 (支払単価） 【≒粗利】 | L1: 4月 | M1: 5月 | N1: 6月 | O1: 7月 | P1: 8月 | Q1: 9月 | R1: 10月 | S1: 11月 | T1: 12月 | U1: 1月 | V1: 2月 | W1: 3月 | X1: 合計
C2: S&I | K2: 売上 | L2: =L29 -> 1416960 | M2: =M29 -> 1221510 | N2: =N29 -> 1450000 | O2: =O29 -> 1483040 | P2: =P29 -> 1361690 | Q2: =Q29 -> 1394730 | R2: =R29 -> 1450000 | S2: =S29 -> 1350880 | ... W2: =W29 -> 1450000 | X2: =SUM(L2:W2) -> 16927560
K3: 仕入 | L3: =L30 -> 1165794 | M3: =M30 -> 1135784 | N3: =N30 -> 1165868 | O3: =O30 -> 1219723 | P3: =P30 -> 1140263 | Q3: =Q30 -> 1142102 | R3: =R30 -> 1192865 | S3: =S30 -> 1095377 | ... W3: =W30 -> 1162521.6 | X3: =SUM(L3:W3) -> 13925478
K4: 粗利 | L4: =L31 -> 251166 | M4: =M31 -> 85726 | N4: =N31 -> 284132 | O4: =O31 -> 263317 | P4: =P31 -> 221427 | Q4: =Q31 -> 252628 | R4: =R31 -> 257135 | S4: =S31 -> 255503 | ... W4: =W31 -> 287478.44 | X4: =SUM(L4:W4) -> 3002082.4
A5: 2015021 | C5: 1 | D5: 派遣 | H5: 情報処理 システム開発 | I5: S＆I | J5: 社員 | K5: 総受注金額 | L5: =L6+L7 -> 626960 | M5: =M6+M7 -> 527840 | N5: =N6+N7 -> 660000 | O5: =O6+O7 -> 693040 | P5: =P6+P7 -> 593920 | Q5: =Q6+Q7 -> 626960 | R5: =R6+R7 -> 660000 | S5: =S6+S7 -> 560880 | ... W5: =W6+W7 -> 660000 | X5: =SUM(L5:W5) -> 7457440
A6: =+A5 -> 2015021 | K6: 派遣金額 | L6: 626960 | M6: 527840 | N6: 660000 | O6: 693040 | P6: 593920 | Q6: 626960 | R6: 660000 | S6: 560880 | T6: 626960 | U6: 626960 | V6: 593920 | W6: 660000 | X6: =SUM(L6:W6) -> 7457440
A7: =+A6 -> 2015021 | K7: 交通費 | X7: =SUM(L7:W7) -> 0
A8: =+A7 -> 2015021 | K8: 総経費 | L8: =SUM(L9:L15) -> 562696 | M8: =SUM(M9:M15) -> 533899 | N8: =SUM(N9:N15) -> 562374 | O8: =SUM(O9:O15) -> 616827 | P8: =SUM(P9:P15) -> 537577 | Q8: =SUM(Q9:Q15) -> 534976 | R8: =SUM(R9:R15) -> 582732 | S8: =SUM(S9:S15) -> 488251 | ... W8: =SUM(W9:W15) -> 574290.22 | X8: =SUM(L8:W8) -> 6553441.2
A9: =+A8 -> 2015021 | K9: 賃金 | L9: 481880 | M9: 455120 | N9: 483300 | O9: 535209 | P9: 458760 | Q9: 460580 | R9: 507840 | S9: 414340 | T9: 481480 | U9: 439280 | V9: 416160 | W9: 493474.22 | X9: =SUM(L9:W9) -> 5627423.2
A10: =+A9 -> 2015021 | K10: 交通費その他 | X10: =SUM(L10:W10) -> 0
A11: =+A10 -> 2015021 | K11: 通勤定期代 | L11: 1738 | M11: 0 | N11: 0 | O11: 1977 | P11: 0 | Q11: 0 | R11: 0 | S11: 0 | T11: 0 | U11: 0 | V11: 0 | W11: 1738 | X11: =SUM(L11:W11) -> 5453
A12: =+A11 -> 2015021 | K12: 健康保険 | L12: 28250 | M12: 28250 | N12: 28250 | O12: 28250 | P12: 28250 | Q12: 26555 | R12: 26555 | S12: 26555 | T12: 26555 | U12: 26555 | V12: 26555 | W12: 28250 | X12: =SUM(L12:W12) -> 328830
A13: =+A12 -> 2015021 | K13: 厚生年金 | L13: 45750 | M13: 45750 | N13: 45750 | O13: 45750 | P13: 45750 | Q13: 43005 | R13: 43005 | S13: 43005 | T13: 43005 | U13: 43005 | V13: 43005 | W13: 45750 | X13: =SUM(L13:W13) -> 532530
A14: =+A13 -> 2015021 | K14: 労災保険 | L14: 2418 | M14: 2276 | N14: 2416 | O14: 2686 | P14: 2294 | Q14: 2303 | R14: 2539 | S14: 2072 | T14: 2407 | U14: 2196 | V14: 2168 | W14: 2418 | X14: =SUM(L14:W14) -> 28193
A15: =+A14 -> 2015021 | K15: 雇用保険 | L15: 2660 | M15: 2503 | N15: 2658 | O15: 2955 | P15: 2523 | Q15: 2533 | R15: 2793 | S15: 2279 | T15: 2648 | U15: 2416 | V15: 2384 | W15: 2660 | X15: =SUM(L15:W15) -> 31012
A16: =+A15 -> 2015021 | K16: 粗利 | L16: =L5-L8 -> 64264 | M16: =M5-M8 -> -6059 | N16: =N5-N8 -> 97626 | O16: =O5-O8 -> 76213 | P16: =P5-P8 -> 56343 | Q16: =Q5-Q8 -> 91984 | R16: =R5-R8 -> 77268 | S16: =S5-S8 -> 72629 | ... X16: =X5-X8 -> 903998.78
A17: 2017012 | C17: =C5+1 -> 2 | D17: 派遣 | H17: NW構築、 移行、運用保守支援業務 | I17: S＆I | J17: 社員 | K17: 総受注金額 | L17: =L18+L19 -> 790000 | M17: =M18+M19 -> 693670 | N17: =N18+N19 -> 790000 | O17: =O18+O19 -> 790000 | P17: =P18+P19 -> 767770 | Q17: =Q18+Q19 -> 767770 | R17: =R18+R19 -> 790000 | S17: =S18+S19 -> 790000 | ... W17: =W18+W19 -> 790000 | X17: =SUM(L17:W17) -> 9470120
A18: =+A17 -> 2017012 | B18: =+B17 -> 0 | K18: 派遣金額 | L18: 790000 | M18: 693670 | N18: 790000 | O18: 790000 | P18: 767770 | Q18: 767770 | R18: 790000 | S18: 790000 | T18: 790000 | U18: 920910 | V18: 790000 | W18: 790000 | X18: =SUM(L18:W18) -> 9470120
A19: =+A18 -> 2017012 | B19: =+B18 -> 0 | K19: 交通費 | X19: =SUM(L19:W19) -> 0
A20: =+A19 -> 2017012 | B20: =+B19 -> 0 | K20: 総経費 | L20: =SUM(L21:L27) -> 603098 | M20: =SUM(M21:M27) -> 601885 | N20: =SUM(N21:N27) -> 603494 | O20: =SUM(O21:O27) -> 602896 | P20: =SUM(P21:P27) -> 602686 | Q20: =SUM(Q21:Q27) -> 607126 | R20: =SUM(R21:R27) -> 610133 | S20: =SUM(S21:S27) -> 607126 | ... W20: =SUM(W21:W27) -> 588231.33 | X20: =SUM(L20:W20) -> 7372036.3
A21: =+A20 -> 2017012 | B21: =+B20 -> 0 | K21: 賃金 | L21: 522600 | M21: 521400 | N21: 523000 | O21: 523400 | P21: 522200 | Q21: 522200 | R21: 522200 | S21: 522200 | T21: 545116 | U21: 626583 | V21: 519400 | W21: 507733.33 | X21: =SUM(L21:W21) -> 6378032.3
A22: =+A21 -> 2017012 | B22: =+B21 -> 0 | K22: 交通費その他 | X22: =SUM(L22:W22) -> 0
A23: =+A22 -> 2017012 | B23: =+B22 -> 0 | K23: 通勤定期代 | L23: 1000 | M23: 1000 | N23: 992 | O23: 0 | P23: 992 | Q23: 992 | R23: 3968 | S23: 992 | T23: 992 | U23: 0 | V23: 0 | W23: 1000 | X23: =SUM(L23:W23) -> 11928
A24: =+A23 -> 2017012 | B24: =+B23 -> 0 | K24: 健康保険 | L24: 28250 | M24: 28250 | N24: 28250 | O24: 28250 | P24: 28250 | Q24: 29945 | R24: 29945 | S24: 29945 | T24: 29945 | U24: 29945 | V24: 29945 | W24: 28250 | X24: =SUM(L24:W24) -> 349170
A25: =+A24 -> 2017012 | B25: =+B24 -> 0 | K25: 厚生年金 | L25: 45750 | M25: 45750 | N25: 45750 | O25: 45750 | P25: 45750 | Q25: 48495 | R25: 48495 | S25: 48495 | T25: 48495 | U25: 48495 | V25: 48495 | W25: 45750 | X25: =SUM(L25:W25) -> 565470
A26: =+A25 -> 2017012 | B26: =+B25 -> 0 | K26: 労災保険 | L26: 2618 | M26: 2612 | N26: 2620 | O26: 2617 | P26: 2616 | Q26: 2616 | R26: 2631 | S26: 2616 | T26: 2731 | U26: 3133 | V26: 2684 | W26: 2618 | X26: =SUM(L26:W26) -> 32112
A27: =+A26 -> 2017012 | B27: =+B26 -> 0 | K27: 雇用保険 | L27: 2880 | M27: 2873 | N27: 2882 | O27: 2879 | P27: 2878 | Q27: 2878 | R27: 2894 | S27: 2878 | T27: 3004 | U27: 3446 | V27: 2952 | W27: 2880 | X27: =SUM(L27:W27) -> 35324
A28: =+A27 -> 2017012 | B28: =+B27 -> 0 | K28: 粗利 | L28: =L17-L20 -> 186902 | M28: =M17-M20 -> 91785 | N28: =N17-N20 -> 186506 | O28: =O17-O20 -> 187104 | P28: =P17-P20 -> 165084 | Q28: =Q17-Q20 -> 160644 | R28: =R17-R20 -> 179867 | S28: =S17-S20 -> 182874 | ... X28: =X17-X20 -> 2098083.7
C29: =C2 -> S&I | K29: 売上 | L29: =L5+L17 -> 1416960 | M29: =M5+M17 -> 1221510 | N29: =N5+N17 -> 1450000 | O29: =O5+O17 -> 1483040 | P29: =P5+P17 -> 1361690 | Q29: =Q5+Q17 -> 1394730 | R29: =R5+R17 -> 1450000 | S29: =S5+S17 -> 1350880 | ... W29: =W5+W17 -> 1450000 | X29: =SUM(L29:W29) -> 16927560
K30: 仕入 | L30: =L8+L20 -> 1165794 | M30: =M8+M20 -> 1135784 | N30: =N8+N20 -> 1165868 | O30: =O8+O20 -> 1219723 | P30: =P8+P20 -> 1140263 | Q30: =Q8+Q20 -> 1142102 | R30: =R8+R20 -> 1192865 | S30: =S8+S20 -> 1095377 | ... W30: =W8+W20 -> 1162521.6 | X30: =SUM(L30:W30) -> 13925478
K31: 粗利 | L31: =L29-L30 -> 251166 | M31: =M29-M30 -> 85726 | N31: =N29-N30 -> 284132 | O31: =O29-O30 -> 263317 | P31: =P29-P30 -> 221427 | Q31: =Q29-Q30 -> 252628 | R31: =R29-R30 -> 257135 | S31: =S29-S30 -> 255503 | ... W31: =W29-W30 -> 287478.44 | X31: =SUM(L31:W31) -> 3002082.4
K32: Q売上 | L32: =SUM(L29:N29) -> 4088470 | O32: =SUM(O29:Q29) -> 4239460 | R32: =SUM(R29:T29) -> 4217840 | U32: =SUM(U29:W29) -> 4381790 | X32: =SUM(L32:W32) -> 16927560
K33: Q粗利 | L33: =SUM(L31:N31) -> 621024 | O33: =SUM(O31:Q31) -> 737372 | R33: =SUM(R31:T31) -> 743220 | U33: =SUM(U31:W31) -> 900466.44 | X33: =SUM(L33:W33) -> 3002082.4

Sheet ジャステック
A1: 社員番号 | B1: 氏名 | C1: No | D1: 派遣/委任 | E1: 担当 | F1: 氏名 | G1: 派遣先部署 | H1: 作業名 | I1: 契約先 | J1: 外注会社 | K1: 売上単価 (支払単価） 【≒粗利】 | L1: 4月 | M1: 5月 | N1: 6月 | O1: 7月 | P1: 8月 | Q1: 9月 | R1: 10月 | S1: 11月 | T1: 12月 | U1: 1月 | V1: 2月 | W1: 3月 | X1: 合計
C2: ジャステック | K2: 売上 | L2: =L53 -> 1240000 | M2: =M53 -> 1240000 | N2: =N53 -> 1240000 | O2: =O53 -> 1228165 | P2: =P53 -> 1240000 | Q2: =Q53 -> 1240000 | R2: =R53 -> 1207125 | S2: =S53 -> 1142950 | ... W2: =W53 -> 1240000 | X2: =SUM(L2:W2) -> 14713840
K3: 仕入 | L3: =L54 -> 972240 | M3: =M54 -> 971308 | N3: =N54 -> 971076 | O3: =O54 -> 1267611 | P3: =P54 -> 963651 | Q3: =Q54 -> 962709 | R3: =R54 -> 964571 | S3: =S54 -> 955830 | ... W3: =W54 -> 958547 | X3: =SUM(L3:W3) -> 11900035
K4: 粗利 | L4: =L2-L3 -> 267760 | M4: =M2-M3 -> 268692 | N4: =N2-N3 -> 268924 | O4: =O2-O3 -> -39446 | P4: =P2-P3 -> 276349 | Q4: =Q2-Q3 -> 277291 | R4: =R2-R3 -> 242554 | S4: =S2-S3 -> 187120 | ... W4: =W2-W3 -> 281453 | X4: =SUM(L4:W4) -> 2813805
A5: 2019048 | B5: 阿部涼平 | C5: =1 -> 1 | D5: 派遣 | I5: ジャステック | J5: 社員 | K5: 総受注金額 | L5: =L6+L7 -> 420000 | M5: =M6+M7 -> 420000 | N5: =N6+N7 -> 420000 | O5: =O6+O7 -> 420000 | P5: =P6+P7 -> 420000 | Q5: =Q6+Q7 -> 420000 | R5: =R6+R7 -> 387125 | S5: =S6+S7 -> 327950 | ... W5: =W6+W7 -> 420000 | X5: =SUM(L5:W5) -> 4901925
A6: =+A5 -> 2019048 | K6: 派遣金額 | L6: 420000 | M6: 420000 | N6: 420000 | O6: 420000 | P6: 420000 | Q6: 420000 | R6: 387125 | S6: 327950 | T6: 420000 | U6: 420000 | V6: 406850 | W6: 420000 | X6: =SUM(L6:W6) -> 4901925
A7: =+A6 -> 2019048 | K7: 交通費 | X7: 0
A8: =+A7 -> 2019048 | K8: 総経費 | L8: =SUM(L9:L15) -> 336482 | M8: =SUM(M9:M15) -> 336482 | N8: =SUM(N9:N15) -> 336482 | O8: =SUM(O9:O15) -> 336482 | P8: =SUM(P9:P15) -> 336482 | Q8: =SUM(Q9:Q15) -> 339262 | R8: =SUM(R9:R15) -> 339262 | S8: =SUM(S9:S15) -> 332383 | ... W8: =SUM(W9:W15) -> 336482 | X8: =SUM(L8:W8) -> 4047767
A9: =+A8 -> 2019048 | K9: 賃金 | L9: 265000 | M9: 265000 | N9: 265000 | O9: 265000 | P9: 265000 | Q9: 265000 | R9: 265000 | S9: 258193 | T9: 265000 | U9: 265000 | V9: 265000 | W9: 265000 | X9: =SUM(L9:W9) -> 3173193
A10: =+A9 -> 2019048 | K10: 交通費その他 | X10: =SUM(L10:W10) -> 0
A11: =+A10 -> 2019048 | K11: 通勤定期代 | L11: 29470 | M11: 29470 | N11: 29470 | O11: 29470 | P11: 29470 | Q11: 29470 | R11: 29470 | S11: 29470 | T11: 29470 | U11: 29470 | V11: 29470 | W11: 29470 | X11: =SUM(L11:W11) -> 353640
A12: =+A11 -> 2019048 | K12: 健康保険 | L12: 13300 | M12: 13300 | N12: 13300 | O12: 13300 | P12: 13300 | Q12: 14250 | R12: 14250 | S12: 14250 | T12: 14250 | U12: 14250 | V12: 14250 | W12: 13300 | X12: =SUM(L12:W12) -> 165300
A13: =+A12 -> 2019048 | K13: 厚生年金 | L13: 25620 | M13: 25620 | N13: 25620 | O13: 25620 | P13: 25620 | Q13: 27450 | R13: 27450 | S13: 27450 | T13: 27450 | U13: 27450 | V13: 27450 | W13: 25620 | X13: =SUM(L13:W13) -> 318420
A14: =+A13 -> 2019048 | K14: 労災保険 | L14: 1472 | M14: 1472 | N14: 1472 | O14: 1472 | P14: 1472 | Q14: 1472 | R14: 1472 | S14: 1438 | T14: 1472 | U14: 1472 | V14: 1559 | W14: 1472 | X14: =SUM(L14:W14) -> 17717
A15: =+A14 -> 2019048 | K15: 雇用保険 | L15: 1620 | M15: 1620 | N15: 1620 | O15: 1620 | P15: 1620 | Q15: 1620 | R15: 1620 | S15: 1582 | T15: 1620 | U15: 1620 | V15: 1715 | W15: 1620 | X15: =SUM(L15:W15) -> 19497
A16: =+A15 -> 2019048 | K16: 粗利 | L16: =L5-L8 -> 83518 | M16: =M5-M8 -> 83518 | N16: =N5-N8 -> 83518 | O16: =O5-O8 -> 83518 | P16: =P5-P8 -> 83518 | Q16: =Q5-Q8 -> 80738 | R16: =R5-R8 -> 47863 | S16: =S5-S8 -> -4433 | ... X16: =X5-X8 -> 854158
A17: 2020010 | C17: =C5+1 -> 2 | D17: 派遣 | I17: ジャステック | J17: 社員 | K17: 総受注金額 | L17: =L18+L19 -> 420000 | M17: =M18+M19 -> 420000 | N17: =N18+N19 -> 420000 | O17: =O18+O19 -> 408165 | P17: =P18+P19 -> 420000 | Q17: =Q18+Q19 -> 420000 | R17: =R18+R19 -> 420000 | S17: =S18+S19 -> 420000 | ... W17: =W18+W19 -> 420000 | X17: =SUM(L17:W17) -> 5028165
A18: =+A17 -> 2020010 | K18: 派遣金額 | L18: 420000 | M18: 420000 | N18: 420000 | O18: 408165 | P18: 420000 | Q18: 420000 | R18: 420000 | S18: 420000 | T18: 420000 | U18: 420000 | V18: 420000 | W18: 420000 | X18: =SUM(L18:W18) -> 5028165
A19: =+A18 -> 2020010 | K19: 交通費 | X19: 0
A20: =+A19 -> 2020010 | K20: 総経費 | L20: =SUM(L21:L27) -> 327844 | M20: =SUM(M21:M27) -> 326912 | N20: =SUM(N21:N27) -> 326912 | O20: =SUM(O21:O27) -> 326912 | P20: =SUM(P21:P27) -> 330634 | Q20: =SUM(Q21:Q27) -> 326912 | R20: =SUM(R21:R27) -> 328774 | S20: =SUM(S21:S27) -> 326912 | ... W20: =SUM(W21:W27) -> 326923 | X20: =SUM(L20:W20) -> 3953471
A21: =+A20 -> 2020010 | K21: 賃金 | L21: 265921 | M21: 265000 | N21: 265000 | O21: 265000 | P21: 268683 | Q21: 265000 | R21: 266842 | S21: 265000 | T21: 301825 | U21: 251743 | V21: 265000 | W21: 265000 | X21: =SUM(L21:W21) -> 3210014
A22: =+A21 -> 2020010 | K22: 交通費その他 | X22: =SUM(L22:W22) -> 0
A23: =+A22 -> 2020010 | K23: 通勤定期代 | L23: 20000 | M23: 20000 | N23: 20000 | O23: 20000 | P23: 20000 | Q23: 20000 | R23: 20000 | S23: 20000 | T23: 20000 | U23: 20000 | V23: 20000 | W23: 20000 | X23: =SUM(L23:W23) -> 240000
A24: =+A23 -> 2020010 | K24: 健康保険 | L24: 13300 | M24: 13300 | N24: 13300 | O24: 13300 | P24: 13300 | Q24: 13300 | R24: 13300 | S24: 13300 | T24: 13300 | U24: 13300 | V24: 13300 | W24: 13300 | X24: =SUM(L24:W24) -> 159600
A25: =+A24 -> 2020010 | K25: 厚生年金 | L25: 25620 | M25: 25620 | N25: 25620 | O25: 25620 | P25: 25620 | Q25: 25620 | R25: 25620 | S25: 25620 | T25: 25620 | U25: 25620 | V25: 25620 | W25: 25620 | X25: =SUM(L25:W25) -> 307440
A26: =+A25 -> 2020010 | K26: 労災保険 | L26: 1430 | M26: 1425 | N26: 1425 | O26: 1425 | P26: 1443 | Q26: 1425 | R26: 1434 | S26: 1425 | T26: 1609 | U26: 1359 | V26: 1512 | W26: 1430 | X26: =SUM(L26:W26) -> 17342
A27: =+A26 -> 2020010 | K27: 雇用保険 | L27: 1573 | M27: 1567 | N27: 1567 | O27: 1567 | P27: 1588 | Q27: 1567 | R27: 1578 | S27: 1567 | T27: 1770 | U27: 1495 | V27: 1663 | W27: 1573 | X27: =SUM(L27:W27) -> 19075
A28: =+A27 -> 2020010 | K28: 粗利 | L28: =L17-L20 -> 92156 | M28: =M17-M20 -> 93088 | N28: =N17-N20 -> 93088 | O28: =O17-O20 -> 81253 | P28: =P17-P20 -> 89366 | Q28: =Q17-Q20 -> 93088 | R28: =R17-R20 -> 91226 | S28: =S17-S20 -> 93088 | ... X28: =X17-X20 -> 1074694
A29: 2024018 | C29: =C17+1 -> 3 | D29: 派遣 | E29: 転出 | I29: ジャステック | J29: 社員 | K29: 総受注金額 | L29: =L30+L31 -> 400000 | M29: =M30+M31 -> 400000 | N29: =N30+N31 -> 400000 | O29: =O30+O31 -> 400000 | P29: =P30+P31 -> 0 | Q29: =Q30+Q31 -> 0 | R29: =R30+R31 -> 0 | S29: =S30+S31 -> 0 | ... W29: =W30+W31 -> 0 | X29: =SUM(L29:W29) -> 1600000
A30: =+A29 -> 2024018 | K30: 派遣金額 | L30: 400000 | M30: 400000 | N30: 400000 | O30: 400000 | X30: =SUM(L30:W30) -> 1600000
A31: =+A30 -> 2024018 | K31: 交通費 | X31: 0
A32: =+A31 -> 2024018 | K32: 総経費 | L32: =SUM(L33:L39) -> 307914 | M32: =SUM(M33:M39) -> 307914 | N32: =SUM(N33:N39) -> 307682 | O32: =SUM(O33:O39) -> 307682 | P32: =SUM(P33:P39) -> 0 | Q32: =SUM(Q33:Q39) -> 0 | R32: =SUM(R33:R39) -> 0 | S32: =SUM(S33:S39) -> 0 | ... W32: =SUM(W33:W39) -> 0 | X32: =SUM(L32:W32) -> 1231192
A33: =+A32 -> 2024018 | K33: 賃金 | L33: 250000 | M33: 250000 | N33: 250000 | O33: 250000 | X33: =SUM(L33:W33) -> 1000000
A34: =+A33 -> 2024018 | K34: 交通費その他 | X34: =SUM(L34:W34) -> 0
A35: =+A34 -> 2024018 | K35: 通勤定期代 | L35: 18950 | M35: 18950 | N35: 18720 | O35: 18720 | X35: =SUM(L35:W35) -> 75340
A36: =+A35 -> 2024018 | K36: 健康保険 | L36: 12350 | M36: 12350 | N36: 12350 | O36: 12350 | X36: =SUM(L36:W36) -> 49400
A37: =+A36 -> 2024018 | K37: 厚生年金 | L37: 23790 | M37: 23790 | N37: 23790 | O37: 23790 | X37: =SUM(L37:W37) -> 95160
A38: =+A37 -> 2024018 | K38: 労災保険 | L38: 1345 | M38: 1345 | N38: 1344 | O38: 1344 | X38: =SUM(L38:W38) -> 5378
A39: =+A38 -> 2024018 | K39: 雇用保険 | L39: 1479 | M39: 1479 | N39: 1478 | O39: 1478 | X39: =SUM(L39:W39) -> 5914
A40: =+A39 -> 2024018 | K40: 粗利 | L40: =L29-L32 -> 92086 | M40: =M29-M32 -> 92086 | N40: =N29-N32 -> 92318 | O40: =O29-O32 -> 92318 | P40: =P29-P32 -> 0 | Q40: =Q29-Q32 -> 0 | R40: =R29-R32 -> 0 | S40: =S29-S32 -> 0 | ... X40: =X29-X32 -> 368808
A41: 2025004 | C41: =C29+1 -> 4 | D41: 派遣 | I41: ジャステック | J41: 社員 | K41: 総受注金額 | L41: =L42+L43 -> 0 | M41: =M42+M43 -> 0 | N41: =N42+N43 -> 0 | O41: =O42+O43 -> 0 | P41: =P42+P43 -> 400000 | Q41: =Q42+Q43 -> 400000 | R41: =R42+R43 -> 400000 | S41: =S42+S43 -> 395000 | ... W41: =W42+W43 -> 400000 | X41: =SUM(L41:W41) -> 3183750
A42: =+A41 -> 2025004 | B42: =+B41 -> 0 | K42: 派遣金額 | O42: 0 | P42: 400000 | Q42: 400000 | R42: 400000 | S42: 395000 | T42: 400000 | U42: 400000 | V42: 388750 | W42: 400000 | X42: =SUM(L42:W42) -> 3183750
A43: =+A42 -> 2025004 | B43: =+B42 -> 0 | K43: 交通費 | X43: 0
A44: =+A43 -> 2025004 | B44: =+B43 -> 0 | K44: 総経費 | L44: =SUM(L45:L51) -> 0 | M44: =SUM(M45:M51) -> 0 | N44: =SUM(N45:N51) -> 0 | O44: =SUM(O45:O51) -> 296535 | P44: =SUM(P45:P51) -> 296535 | Q44: =SUM(Q45:Q51) -> 296535 | R44: =SUM(R45:R51) -> 296535 | S44: =SUM(S45:S51) -> 296535 | ... W44: =SUM(W45:W51) -> 295142 | X44: =SUM(L44:W44) -> 2667605
A45: =+A44 -> 2025004 | B45: =+B44 -> 0 | K45: 賃金 | O45: 240000 | P45: 240000 | Q45: 240000 | R45: 240000 | S45: 240000 | T45: 240000 | U45: 240000 | V45: 240000 | W45: 240000 | X45: =SUM(L45:W45) -> 2160000
A46: =+A45 -> 2025004 | B46: =+B45 -> 0 | K46: 交通費その他 | X46: =SUM(L46:W46) -> 0
A47: =+A46 -> 2025004 | B47: =+B46 -> 0 | K47: 通勤定期代 | O47: 17690 | P47: 17690 | Q47: 17690 | R47: 17690 | S47: 17690 | T47: 17690 | U47: 17690 | V47: 17690 | W47: 16310 | X47: =SUM(L47:W47) -> 157830
A48: =+A47 -> 2025004 | B48: =+B47 -> 0 | K48: 健康保険 | O48: 12350 | P48: 12350 | Q48: 12350 | R48: 12350 | S48: 12350 | T48: 12350 | U48: 12350 | V48: 12350 | W48: 12350 | X48: =SUM(L48:W48) -> 111150
A49: =+A48 -> 2025004 | B49: =+B48 -> 0 | K49: 厚生年金 | O49: 23790 | P49: 23790 | Q49: 23790 | R49: 23790 | S49: 23790 | T49: 23790 | U49: 23790 | V49: 23790 | W49: 23790 | X49: =SUM(L49:W49) -> 214110
A50: =+A49 -> 2025004 | B50: =+B49 -> 0 | K50: 労災保険 | O50: 1288 | P50: 1288 | Q50: 1288 | R50: 1288 | S50: 1288 | T50: 1288 | U50: 1288 | V50: 1375 | W50: 1282 | X50: =SUM(L50:W50) -> 11673
A51: =+A50 -> 2025004 | B51: =+B50 -> 0 | K51: 雇用保険 | O51: 1417 | P51: 1417 | Q51: 1417 | R51: 1417 | S51: 1417 | T51: 1417 | U51: 1417 | V51: 1513 | W51: 1410 | X51: =SUM(L51:W51) -> 12842
A52: =+A51 -> 2025004 | B52: =+B51 -> 0 | K52: 粗利 | L52: =L41-L44 -> 0 | M52: =M41-M44 -> 0 | N52: =N41-N44 -> 0 | O52: =O41-O44 -> -296535 | P52: =P41-P44 -> 103465 | Q52: =Q41-Q44 -> 103465 | R52: =R41-R44 -> 103465 | S52: =S41-S44 -> 98465 | ... X52: =X41-X44 -> 516145
C53: =C2 -> ジャステック | K53: 売上 | L53: =L5+L17+L29+L41 -> 1240000 | M53: =M5+M17+M29+M41 -> 1240000 | N53: =N5+N17+N29+N41 -> 1240000 | O53: =O5+O17+O29+O41 -> 1228165 | P53: =P5+P17+P29+P41 -> 1240000 | Q53: =Q5+Q17+Q29+Q41 -> 1240000 | R53: =R5+R17+R29+R41 -> 1207125 | S53: =S5+S17+S29+S41 -> 1142950 | ... W53: =W5+W17+W29+W41 -> 1240000 | X53: =SUM(L53:W53) -> 14713840
K54: 仕入 | L54: =L8+L20+L32+L44 -> 972240 | M54: =M8+M20+M32+M44 -> 971308 | N54: =N8+N20+N32+N44 -> 971076 | O54: =O8+O20+O32+O44 -> 1267611 | P54: =P8+P20+P32+P44 -> 963651 | Q54: =Q8+Q20+Q32+Q44 -> 962709 | R54: =R8+R20+R32+R44 -> 964571 | S54: =S8+S20+S32+S44 -> 955830 | ... W54: =W8+W20+W32+W44 -> 958547 | X54: =SUM(L54:W54) -> 11900035
K55: 粗利 | L55: =L53-L54 -> 267760 | M55: =M53-M54 -> 268692 | N55: =N53-N54 -> 268924 | O55: =O53-O54 -> -39446 | P55: =P53-P54 -> 276349 | Q55: =Q53-Q54 -> 277291 | R55: =R53-R54 -> 242554 | S55: =S53-S54 -> 187120 | ... W55: =W53-W54 -> 281453 | X55: =SUM(L55:W55) -> 2813805
K56: Q売上 | L56: =SUM(L53:N53) -> 3720000 | O56: =SUM(O53:Q53) -> 3708165 | R56: =SUM(R53:T53) -> 3590075 | U56: =SUM(U53:W53) -> 3695600 | X56: =SUM(L56:W56) -> 14713840
K57: Q粗利 | L57: =SUM(L55:N55) -> 805376 | O57: =SUM(O55:Q55) -> 514194 | R57: =SUM(R55:T55) -> 669753 | U57: =SUM(U55:W55) -> 824482 | X57: =SUM(L57:W57) -> 2813805

Sheet NDICS
A1: 社員番号 | B1: 氏名 | C1: No | D1: 派遣/委任 | E1: 担当 | F1: 氏名 | G1: 派遣先部署 | H1: 作業名 | I1: 契約先 | J1: 外注会社 | K1: 売上単価 (支払単価） 【≒粗利】 | L1: 4月 | M1: 5月 | N1: 6月 | O1: 7月 | P1: 8月 | Q1: 9月 | R1: 10月 | S1: 11月 | T1: 12月 | U1: 1月 | V1: 2月 | W1: 3月 | X1: 合計
C2: 日本ディクス | K2: 売上 | L2: =L77 -> 1415000 | M2: =M77 -> 1310000 | N2: =N77 -> 1310000 | O2: =O77 -> 1310000 | P2: =P77 -> 1310000 | Q2: =Q77 -> 1310000 | R2: =R77 -> 1860000 | S2: =S77 -> 1848240 | ... W2: =W77 -> 1160000 | X2: =SUM(L2:W2) -> 16936800
K3: 仕入 | L3: =L78 -> 1100902 | M3: =M78 -> 940274 | N3: =N78 -> 956967 | O3: =O78 -> 994665 | P3: =P78 -> 951096 | Q3: =Q78 -> 987153 | R3: =R78 -> 1364855 | S3: =S78 -> 1339644 | ... W3: =W78 -> 807304 | X3: =SUM(L3:W3) -> 12705542
K4: 粗利 | L4: =L2-L3 -> 314098 | M4: =M2-M3 -> 369726 | N4: =N2-N3 -> 353033 | O4: =O2-O3 -> 315335 | P4: =P2-P3 -> 358904 | Q4: =Q2-Q3 -> 322847 | R4: =R2-R3 -> 495145 | S4: =S2-S3 -> 508596 | ... W4: =W2-W3 -> 352696 | X4: =SUM(L4:W4) -> 4231258
A5: 2018030 | C5: =1 -> 1 | D5: 派遣 | E5: 転出 | J5: 社員 | K5: 総受注金額 | L5: =L6+L7 -> 780000 | M5: =M6+M7 -> 780000 | N5: =N6+N7 -> 780000 | O5: =O6+O7 -> 780000 | P5: =P6+P7 -> 780000 | Q5: =Q6+Q7 -> 780000 | R5: =R6+R7 -> 780000 | S5: =S6+S7 -> 780000 | ... W5: =W6+W7 -> 0 | X5: =SUM(L5:W5) -> 7020000
A6: =+A5 -> 2018030 | K6: 派遣金額 | L6: 780000 | M6: 780000 | N6: 780000 | O6: 780000 | P6: 780000 | Q6: 780000 | R6: 780000 | S6: 780000 | T6: 780000 | X6: =SUM(L6:W6) -> 7020000
A7: =+A6 -> 2018030 | K7: 交通費 | X7: 0
A8: =+A7 -> 2018030 | K8: 総経費 | L8: =SUM(L9:L15) -> 550446 | M8: =SUM(M9:M15) -> 549638 | N8: =SUM(N9:N15) -> 554296 | O8: =SUM(O9:O15) -> 591994 | P8: =SUM(P9:P15) -> 548425 | Q8: =SUM(Q9:Q15) -> 584482 | R8: =SUM(R9:R15) -> 564063 | S8: =SUM(S9:S15) -> 547213 | ... W8: =SUM(W9:W15) -> 0 | X8: =SUM(L8:W8) -> 5070755
A9: =+A8 -> 2018030 | K9: 賃金 | L9: 463600 | M9: 462800 | N9: 467410 | O9: 504715 | P9: 461600 | Q9: 497281 | R9: 477074 | S9: 460400 | T9: 493042 | X9: =SUM(L9:W9) -> 4287922
A10: =+A9 -> 2018030 | K10: 交通費その他 | X10: =SUM(L10:W10) -> 0
A11: =+A10 -> 2018030 | K11: 通勤定期代 | L11: 12290 | M11: 12290 | N11: 12290 | O11: 12290 | P11: 12290 | Q11: 12290 | R11: 12290 | S11: 12290 | T11: 12290 | X11: =SUM(L11:W11) -> 110610
A12: =+A11 -> 2018030 | K12: 健康保険 | L12: 26555 | M12: 26555 | N12: 26555 | O12: 26555 | P12: 26555 | Q12: 26555 | R12: 26555 | S12: 26555 | T12: 26555 | X12: =SUM(L12:W12) -> 238995
A13: =+A12 -> 2018030 | K13: 厚生年金 | L13: 43005 | M13: 43005 | N13: 43005 | O13: 43005 | P13: 43005 | Q13: 43005 | R13: 43005 | S13: 43005 | T13: 43005 | X13: =SUM(L13:W13) -> 387045
A14: =+A13 -> 2018030 | K14: 労災保険 | L14: 2379 | M14: 2375 | N14: 2398 | O14: 2585 | P14: 2369 | Q14: 2548 | R14: 2447 | S14: 2363 | T14: 2527 | X14: =SUM(L14:W14) -> 21991
A15: =+A14 -> 2018030 | K15: 雇用保険 | L15: 2617 | M15: 2613 | N15: 2638 | O15: 2844 | P15: 2606 | Q15: 2803 | R15: 2692 | S15: 2600 | T15: 2779 | X15: =SUM(L15:W15) -> 24192
A16: =+A15 -> 2018030 | K16: 粗利 | L16: =L5-L8 -> 229554 | M16: =M5-M8 -> 230362 | N16: =N5-N8 -> 225704 | O16: =O5-O8 -> 188006 | P16: =P5-P8 -> 231575 | Q16: =Q5-Q8 -> 195518 | R16: =R5-R8 -> 215937 | S16: =S5-S8 -> 232787 | ... X16: =X5-X8 -> 1949245
A17: 2021004 | C17: =C5+1 -> 2 | D17: 派遣 | E17: 転出 | J17: 社員 | K17: 総受注金額 | L17: =L18+L19 -> 635000 | M17: =M18+M19 -> 0 | N17: =N18+N19 -> 0 | O17: =O18+O19 -> 0 | P17: =P18+P19 -> 0 | Q17: =Q18+Q19 -> 0 | R17: =R18+R19 -> 0 | S17: =S18+S19 -> 0 | ... W17: =W18+W19 -> 0 | X17: =SUM(L17:W17) -> 635000
A18: =+A17 -> 2021004 | K18: 派遣金額 | L18: 635000 | X18: =SUM(L18:W18) -> 635000
A19: =+A18 -> 2021004 | K19: 交通費 | X19: 0
A20: =+A19 -> 2021004 | K20: 総経費 | L20: =SUM(L21:L27) -> 550456 | M20: =SUM(M21:M27) -> 0 | N20: =SUM(N21:N27) -> 0 | O20: =SUM(O21:O27) -> 0 | P20: =SUM(P21:P27) -> 0 | Q20: =SUM(Q21:Q27) -> 0 | R20: =SUM(R21:R27) -> 0 | S20: =SUM(S21:S27) -> 0 | ... W20: =SUM(W21:W27) -> 0 | X20: =SUM(L20:W20) -> 550456
A21: =+A20 -> 2021004 | K21: 賃金 | L21: 450000 | X21: =SUM(L21:W21) -> 450000
A22: =+A21 -> 2021004 | K22: 交通費その他 | X22: =SUM(L22:W22) -> 0
A23: =+A22 -> 2021004 | K23: 通勤定期代 | L23: 25900 | X23: =SUM(L23:W23) -> 25900
A24: =+A23 -> 2021004 | K24: 健康保険 | L24: 26555 | X24: =SUM(L24:W24) -> 26555
A25: =+A24 -> 2021004 | K25: 厚生年金 | L25: 43005 | X25: =SUM(L25:W25) -> 43005
A26: =+A25 -> 2021004 | K26: 労災保険 | L26: 2379 | X26: =SUM(L26:W26) -> 2379
A27: =+A26 -> 2021004 | K27: 雇用保険 | L27: 2617 | X27: =SUM(L27:W27) -> 2617
A28: =+A27 -> 2021004 | K28: 粗利 | L28: =L17-L20 -> 84544 | M28: =M17-M20 -> 0 | N28: =N17-N20 -> 0 | O28: =O17-O20 -> 0 | P28: =P17-P20 -> 0 | Q28: =Q17-Q20 -> 0 | R28: =R17-R20 -> 0 | S28: =S17-S20 -> 0 | ... X28: =X17-X20 -> 84544
A29: 2020005 | C29: =C17+1 -> 3 | D29: 派遣 | J29: 社員 | K29: 総受注金額 | L29: =L30+L31 -> 0 | M29: =M30+M31 -> 530000 | N29: =N30+N31 -> 530000 | O29: =O30+O31 -> 530000 | P29: =P30+P31 -> 530000 | Q29: =Q30+Q31 -> 530000 | R29: =R30+R31 -> 530000 | S29: =S30+S31 -> 530000 | ... W29: =W30+W31 -> 530000 | X29: =SUM(L29:W29) -> 5830000
A30: =+A29 -> 2020005 | K30: 派遣金額 | M30: 530000 | N30: 530000 | O30: 530000 | P30: 530000 | Q30: 530000 | R30: 530000 | S30: 530000 | T30: 530000 | U30: 530000 | V30: 530000 | W30: 530000 | X30: =SUM(L30:W30) -> 5830000
A31: =+A30 -> 2020005 | K31: 交通費 | X31: 0
A32: =+A31 -> 2020005 | K32: 総経費 | L32: =SUM(L33:L39) -> 0 | M32: =SUM(M33:M39) -> 390636 | N32: =SUM(N33:N39) -> 402671 | O32: =SUM(O33:O39) -> 402671 | P32: =SUM(P33:P39) -> 402671 | Q32: =SUM(Q33:Q39) -> 402671 | R32: =SUM(R33:R39) -> 402671 | S32: =SUM(S33:S39) -> 403187 | ... W32: =SUM(W33:W39) -> 388200 | X32: =SUM(L32:W32) -> 4404246
A33: =+A32 -> 2020005 | K33: 賃金 | M33: 311350 | N33: 320000 | O33: 320000 | P33: 320000 | Q33: 320000 | R33: 320000 | S33: 320000 | T33: 320000 | U33: 320000 | V33: 319135 | W33: 320000 | X33: =SUM(L33:W33) -> 3510485
A34: =+A33 -> 2020005 | K34: 交通費その他 | X34: =SUM(L34:W34) -> 0
A35: =+A34 -> 2020005 | K35: 通勤定期代 | M35: 25430 | N35: 28690 | O35: 28690 | P35: 28690 | Q35: 28690 | R35: 28690 | S35: 29200 | T35: 28690 | U35: 29710 | V35: 29200 | W35: 19580 | X35: =SUM(L35:W35) -> 305260
A36: =+A35 -> 2020005 | K36: 健康保険 | M36: 19210 | N36: 19210 | O36: 19210 | P36: 19210 | Q36: 19210 | R36: 19210 | S36: 19210 | T36: 19210 | U36: 19210 | V36: 19210 | W36: 14450 | X36: =SUM(L36:W36) -> 206550
A37: =+A36 -> 2020005 | K37: 厚生年金 | M37: 31110 | N37: 31110 | O37: 31110 | P37: 31110 | Q37: 31110 | R37: 31110 | S37: 31110 | T37: 31110 | U37: 31110 | V37: 31110 | W37: 31110 | X37: =SUM(L37:W37) -> 342210
A38: =+A37 -> 2020005 | K38: 労災保険 | M38: 1684 | N38: 1743 | O38: 1743 | P38: 1743 | Q38: 1743 | R38: 1743 | S38: 1746 | T38: 1743 | U38: 1749 | V38: 1829 | W38: 1020 | X38: =SUM(L38:W38) -> 18486
A39: =+A38 -> 2020005 | K39: 雇用保険 | M39: 1852 | N39: 1918 | O39: 1918 | P39: 1918 | Q39: 1918 | R39: 1918 | S39: 1921 | T39: 1918 | U39: 1923 | V39: 2011 | W39: 2040 | X39: =SUM(L39:W39) -> 21255
A40: =+A39 -> 2020005 | K40: 粗利 | L40: =L29-L32 -> 0 | M40: =M29-M32 -> 139364 | N40: =N29-N32 -> 127329 | O40: =O29-O32 -> 127329 | P40: =P29-P32 -> 127329 | Q40: =Q29-Q32 -> 127329 | R40: =R29-R32 -> 127329 | S40: =S29-S32 -> 126813 | ... X40: =X29-X32 -> 1425754
A41: 2022025 | C41: 4 | D41: 派遣 | J41: 社員 | K41: 総受注金額 | L41: =L42+L43 -> 0 | M41: =M42+M43 -> 0 | N41: =N42+N43 -> 0 | O41: =O42+O43 -> 0 | P41: =P42+P43 -> 0 | Q41: =Q42+Q43 -> 0 | R41: =R42+R43 -> 550000 | S41: =S42+S43 -> 538240 | ... W41: =W42+W43 -> 550000 | X41: =SUM(L41:W41) -> 3211800
A42: =+A41 -> 2022025 | K42: 派遣金額 | R42: 550000 | S42: 538240 | T42: 550000 | U42: 504920 | V42: 518640 | W42: 550000 | X42: =SUM(L42:W42) -> 3211800
A43: =+A42 -> 2022025 | K43: 交通費 | X43: 0
A44: =+A43 -> 2022025 | K44: 総経費 | L44: =SUM(L45:L51) -> 0 | M44: =SUM(M45:M51) -> 0 | N44: =SUM(N45:N51) -> 0 | O44: =SUM(O45:O51) -> 0 | P44: =SUM(P45:P51) -> 0 | Q44: =SUM(Q45:Q51) -> 0 | R44: =SUM(R45:R51) -> 398121 | S44: =SUM(S45:S51) -> 389244 | ... W44: =SUM(W45:W51) -> 419104 | X44: =SUM(L44:W44) -> 2383330
A45: =+A44 -> 2022025 | K45: 賃金 | R45: 337784 | S45: 330400 | T45: 330000 | U45: 335000 | V45: 335000 | W45: 360000 | X45: =SUM(L45:W45) -> 2028184
A46: =+A45 -> 2022025 | K46: 交通費その他 | X46: =SUM(L46:W46) -> 0
A47: =+A46 -> 2022025 | K47: 通勤定期代 | R47: 6680 | S47: 5280 | T47: 5280 | U47: 5280 | V47: 5280 | W47: 5280 | X47: =SUM(L47:W47) -> 33080
A48: =+A47 -> 2022025 | K48: 健康保険 | R48: 17100 | S48: 17100 | T48: 17100 | U48: 17100 | V48: 17100 | W48: 17100 | X48: =SUM(L48:W48) -> 102600
A49: =+A48 -> 2022025 | K49: 厚生年金 | R49: 32940 | S49: 32940 | T49: 32940 | U49: 32940 | V49: 32940 | W49: 32940 | X49: =SUM(L49:W49) -> 197640
A50: =+A49 -> 2022025 | K50: 労災保険 | R50: 1722 | S50: 1678 | T50: 1701 | U50: 1701 | V50: 1788 | W50: 1802 | X50: =SUM(L50:W50) -> 10392
A51: =+A50 -> 2022025 | K51: 雇用保険 | R51: 1895 | S51: 1846 | T51: 1872 | U51: 1872 | V51: 1967 | W51: 1982 | X51: =SUM(L51:W51) -> 11434
A52: =+A51 -> 2022025 | K52: 粗利 | L52: =L41-L44 -> 0 | M52: =M41-M44 -> 0 | N52: =N41-N44 -> 0 | O52: =O41-O44 -> 0 | P52: =P41-P44 -> 0 | Q52: =Q41-Q44 -> 0 | R52: =R41-R44 -> 151879 | S52: =S41-S44 -> 148996 | ... X52: =X41-X44 -> 828470
A53: ー | C53: 5 | D53: 業務委託 | J53: プロトシステム | K53: 総受注金額 | L53: =L54+L55 -> 0 | M53: =M54+M55 -> 0 | N53: =N54+N55 -> 0 | O53: =O54+O55 -> 0 | P53: =P54+P55 -> 0 | Q53: =Q54+Q55 -> 0 | R53: =R54+R55 -> 0 | S53: =S54+S55 -> 0 | ... W53: =W54+W55 -> 80000 | X53: =SUM(L53:W53) -> 240000
A54: =+A53 -> ー | K54: 派遣金額 | U54: 80000 | V54: 80000 | W54: 80000 | X54: =SUM(L54:W54) -> 240000
A55: =+A54 -> ー | K55: 交通費 | X55: 0
A56: =+A55 -> ー | K56: 総経費 | L56: =SUM(L57:L63) -> 0 | M56: =SUM(M57:M63) -> 0 | N56: =SUM(N57:N63) -> 0 | O56: =SUM(O57:O63) -> 0 | P56: =SUM(P57:P63) -> 0 | Q56: =SUM(Q57:Q63) -> 0 | R56: =SUM(R57:R63) -> 0 | S56: =SUM(S57:S63) -> 0 | ... W56: =SUM(W57:W63) -> 0 | X56: =SUM(L56:W56) -> 296755
A57: =+A56 -> ー | K57: 賃金 | T57: 296755 | U57: 0 | V57: 0 | W57: 0 | X57: =SUM(L57:W57) -> 296755
A58: =+A57 -> ー | K58: 交通費その他 | X58: =SUM(L58:W58) -> 0
A59: =+A58 -> ー | K59: 通勤定期代 | X59: =SUM(L59:W59) -> 0
A60: =+A59 -> ー | K60: 健康保険 | X60: =SUM(L60:W60) -> 0
A61: =+A60 -> ー | K61: 厚生年金 | X61: =SUM(L61:W61) -> 0
A62: =+A61 -> ー | K62: 労災保険 | X62: =SUM(L62:W62) -> 0
A63: =+A62 -> ー | K63: 雇用保険 | X63: =SUM(L63:W63) -> 0
A64: =+A63 -> ー | K64: 粗利 | L64: =L53-L56 -> 0 | M64: =M53-M56 -> 0 | N64: =N53-N56 -> 0 | O64: =O53-O56 -> 0 | P64: =P53-P56 -> 0 | Q64: =Q53-Q56 -> 0 | R64: =R53-R56 -> 0 | S64: =S53-S56 -> 0 | ... X64: =X53-X56 -> -56755
C65: 6 | K65: 総受注金額 | L65: =L66+L67 -> 0 | M65: =M66+M67 -> 0 | N65: =N66+N67 -> 0 | O65: =O66+O67 -> 0 | P65: =P66+P67 -> 0 | Q65: =Q66+Q67 -> 0 | R65: =R66+R67 -> 0 | S65: =S66+S67 -> 0 | ... W65: =W66+W67 -> 0 | X65: =SUM(L65:W65) -> 0
K66: 派遣金額 | X66: =SUM(L66:W66) -> 0
A67: =+A66 -> 0 | B67: =+B66 -> 0 | K67: 交通費 | X67: 0
A68: =+A67 -> 0 | B68: =+B67 -> 0 | K68: 総経費 | L68: =SUM(L69:L75) -> 0 | M68: =SUM(M69:M75) -> 0 | N68: =SUM(N69:N75) -> 0 | O68: =SUM(O69:O75) -> 0 | P68: =SUM(P69:P75) -> 0 | Q68: =SUM(Q69:Q75) -> 0 | R68: =SUM(R69:R75) -> 0 | S68: =SUM(S69:S75) -> 0 | ... W68: =SUM(W69:W75) -> 0 | X68: =SUM(L68:W68) -> 0
A69: =+A68 -> 0 | B69: =+B68 -> 0 | K69: 賃金 | X69: =SUM(L69:W69) -> 0
A70: =+A69 -> 0 | B70: =+B69 -> 0 | K70: 交通費その他 | X70: =SUM(L70:W70) -> 0
A71: =+A70 -> 0 | B71: =+B70 -> 0 | K71: 通勤定期代 | X71: =SUM(L71:W71) -> 0
A72: =+A71 -> 0 | B72: =+B71 -> 0 | K72: 健康保険 | X72: =SUM(L72:W72) -> 0
A73: =+A72 -> 0 | B73: =+B72 -> 0 | K73: 厚生年金 | X73: =SUM(L73:W73) -> 0
A74: =+A73 -> 0 | B74: =+B73 -> 0 | K74: 労災保険 | X74: =SUM(L74:W74) -> 0
A75: =+A74 -> 0 | B75: =+B74 -> 0 | K75: 雇用保険 | X75: =SUM(L75:W75) -> 0
A76: =+A75 -> 0 | B76: =+B75 -> 0 | K76: 粗利 | L76: =L65-L68 -> 0 | M76: =M65-M68 -> 0 | N76: =N65-N68 -> 0 | O76: =O65-O68 -> 0 | P76: =P65-P68 -> 0 | Q76: =Q65-Q68 -> 0 | R76: =R65-R68 -> 0 | S76: =S65-S68 -> 0 | ... X76: =X65-X68 -> 0
K77: 売上 | L77: =L5+L17+L29+L41+L53+L65 -> 1415000 | M77: =M5+M17+M29+M41+M53+M65 -> 1310000 | N77: =N5+N17+N29+N41+N53+N65 -> 1310000 | O77: =O5+O17+O29+O41+O53+O65 -> 1310000 | P77: =P5+P17+P29+P41+P53+P65 -> 1310000 | Q77: =Q5+Q17+Q29+Q41+Q53+Q65 -> 1310000 | R77: =R5+R17+R29+R41+R53+R65 -> 1860000 | S77: =S5+S17+S29+S41+S53+S65 -> 1848240 | ... W77: =W5+W17+W29+W41+W53+W65 -> 1160000 | X77: =SUM(L77:W77) -> 16936800
K78: 仕入 | L78: =L8+L20+L32+L44+L56+L68 -> 1100902 | M78: =M8+M20+M32+M44+M56+M68 -> 940274 | N78: =N8+N20+N32+N44+N56+N68 -> 956967 | O78: =O8+O20+O32+O44+O56+O68 -> 994665 | P78: =P8+P20+P32+P44+P56+P68 -> 951096 | Q78: =Q8+Q20+Q32+Q44+Q56+Q68 -> 987153 | R78: =R8+R20+R32+R44+R56+R68 -> 1364855 | S78: =S8+S20+S32+S44+S56+S68 -> 1339644 | ... W78: =W8+W20+W32+W44+W56+W68 -> 807304 | X78: =SUM(L78:W78) -> 12705542
K79: 粗利 | L79: =L77-L78 -> 314098 | M79: =M77-M78 -> 369726 | N79: =N77-N78 -> 353033 | O79: =O77-O78 -> 315335 | P79: =P77-P78 -> 358904 | Q79: =Q77-Q78 -> 322847 | R79: =R77-R78 -> 495145 | S79: =S77-S78 -> 508596 | ... W79: =W77-W78 -> 352696 | X79: =SUM(L79:W79) -> 4231258
K80: Q売上 | L80: =SUM(L77:N77) -> 4035000 | O80: =SUM(O77:Q77) -> 3930000 | R80: =SUM(R77:T77) -> 5568240 | U80: =SUM(U77:W77) -> 3403560 | X80: =SUM(L80:W80) -> 16936800
K81: Q粗利 | L81: =SUM(L79:N79) -> 1036857 | O81: =SUM(O79:Q79) -> 997086 | R81: =SUM(R79:T79) -> 1195224 | U81: =SUM(U79:W79) -> 1002091 | X81: =SUM(L81:W81) -> 4231258

Sheet Other
A1: 社員番号 | B1: 氏名 | C1: No | D1: 派遣/委任 | E1: 担当 | F1: 氏名 | G1: 派遣先部署 | H1: 作業名 | I1: 契約先 | J1: 外注会社 | K1: 売上単価 (支払単価） 【≒粗利】 | L1: 4月 | M1: 5月 | N1: 6月 | O1: 7月 | P1: 8月 | Q1: 9月 | R1: 10月 | S1: 11月 | T1: 12月 | U1: 1月 | V1: 2月 | W1: 3月 | X1: 合計
C2: Other | K2: 売上 | L2: =L437 -> 15296635 | M2: =M437 -> 15169568 | N2: =N437 -> 15036952 | O2: =O437 -> 14494274 | P2: =P437 -> 15036071 | Q2: =Q437 -> 14992235 | R2: =R437 -> 16934444 | S2: =S437 -> 16483052 | ... W2: =W437 -> 17058000 | X2: =SUM(L2:W2) -> 190161042
K3: 仕入 | L3: =L438 -> 11533697 | M3: =M438 -> 11415957 | N3: =N438 -> 11483797 | O3: =O438 -> 11210893 | P3: =P438 -> 11651075 | Q3: =Q438 -> 11575753 | R3: =R438 -> 13177585 | S3: =S438 -> 13185712 | ... W3: =W438 -> 13892901 | X3: =SUM(L3:W3) -> 1.4904957e+08
K4: 粗利 | L4: =L2-L3 -> 3762938 | M4: =M2-M3 -> 3753611 | N4: =N2-N3 -> 3553155 | O4: =O2-O3 -> 3283381 | P4: =P2-P3 -> 3384996 | Q4: =Q2-Q3 -> 3416482.3 | R4: =R2-R3 -> 3756859.3 | S4: =S2-S3 -> 3297339.9 | ... W4: =W2-W3 -> 3165098.9 | X4: =SUM(L4:W4) -> 41111470
A5: 2019035 | C5: =1 -> 1 | D5: 委任 | I5: 永和情報 システム | J5: 社員 | K5: 総受注金額 | L5: =L6+L7 -> 820000 | M5: =M6+M7 -> 820000 | N5: =N6+N7 -> 820000 | O5: =O6+O7 -> 820000 | P5: =P6+P7 -> 820000 | Q5: =Q6+Q7 -> 820000 | R5: =R6+R7 -> 820000 | S5: =S6+S7 -> 820000 | ... W5: =W6+W7 -> 820000 | X5: =SUM(L5:W5) -> 9840000
A6: =+A5 -> 2019035 | K6: 派遣金額 | L6: 820000 | M6: 820000 | N6: 820000 | O6: 820000 | P6: 820000 | Q6: 820000 | R6: 820000 | S6: 820000 | T6: 820000 | U6: 820000 | V6: 820000 | W6: 820000 | X6: =SUM(L6:W6) -> 9840000
A7: =+A6 -> 2019035 | K7: 交通費 | X7: 0
A8: =+A7 -> 2019035 | K8: 総経費 | L8: =SUM(L9:L15) -> 700693 | M8: =SUM(M9:M15) -> 700693 | N8: =SUM(N9:N15) -> 701098 | O8: =SUM(O9:O15) -> 702152 | P8: =SUM(P9:P15) -> 699481 | Q8: =SUM(Q9:Q15) -> 705133 | R8: =SUM(R9:R15) -> 705133 | S8: =SUM(S9:S15) -> 704325 | ... W8: =SUM(W9:W15) -> 699475.22 | X8: =SUM(L8:W8) -> 8431744.2
A9: =+A8 -> 2019035 | K9: 賃金 | L9: 607000 | M9: 607000 | N9: 607400 | O9: 607400 | P9: 605800 | Q9: 607000 | R9: 607000 | S9: 606200 | T9: 607000 | U9: 606200 | V9: 605800 | W9: 604911.11 | X9: =SUM(L9:W9) -> 7278711.1
A10: =+A9 -> 2019035 | K10: 交通費その他 | X10: =SUM(L10:W10) -> 0
A11: =+A10 -> 2019035 | K11: 通勤定期代 | L11: 0 | M11: 0 | N11: 0 | O11: 1044 | P11: 0 | Q11: 0 | R11: 0 | S11: 0 | T11: 0 | U11: 0 | V11: 0 | W11: 0 | X11: =SUM(L11:W11) -> 1044
A12: =+A11 -> 2019035 | K12: 健康保険 | L12: 33335 | M12: 33335 | N12: 33335 | O12: 33335 | P12: 33335 | Q12: 35030 | R12: 35030 | S12: 35030 | T12: 35030 | U12: 35030 | V12: 35030 | W12: 33925 | X12: =SUM(L12:W12) -> 410780
A13: =+A12 -> 2019035 | K13: 厚生年金 | L13: 53985 | M13: 53985 | N13: 53985 | O13: 53985 | P13: 53985 | Q13: 56730 | R13: 56730 | S13: 56730 | T13: 56730 | U13: 56730 | V13: 56730 | W13: 53985 | X13: =SUM(L13:W13) -> 664290
A14: =+A13 -> 2019035 | K14: 労災保険 | L14: 3035 | M14: 3035 | N14: 3037 | O14: 3042 | P14: 3029 | Q14: 3035 | R14: 3035 | S14: 3031 | T14: 3035 | U14: 3031 | V14: 3116 | W14: 3024.5556 | X14: =SUM(L14:W14) -> 36485.556
A15: =+A14 -> 2019035 | K15: 雇用保険 | L15: 3338 | M15: 3338 | N15: 3341 | O15: 3346 | P15: 3332 | Q15: 3338 | R15: 3338 | S15: 3334 | T15: 3338 | U15: 3334 | V15: 3427 | W15: 3629.5556 | X15: =SUM(L15:W15) -> 40433.556
A16: =+A15 -> 2019035 | K16: 粗利 | L16: =L5-L8 -> 119307 | M16: =M5-M8 -> 119307 | N16: =N5-N8 -> 118902 | O16: =O5-O8 -> 117848 | P16: =P5-P8 -> 120519 | Q16: =Q5-Q8 -> 114867 | R16: =R5-R8 -> 114867 | S16: =S5-S8 -> 115675 | ... X16: =X5-X8 -> 1408255.8
A17: 2015013 | C17: =C5+1 -> 2 | D17: 委任 | I17: アクシス | J17: 社員 | K17: 総受注金額 | L17: =L18+L19 -> 800000 | M17: =M18+M19 -> 800000 | N17: =N18+N19 -> 800000 | O17: =O18+O19 -> 800000 | P17: =P18+P19 -> 800000 | Q17: =Q18+Q19 -> 800000 | R17: =R18+R19 -> 800000 | S17: =S18+S19 -> 800000 | ... W17: =W18+W19 -> 800000 | X17: =SUM(L17:W17) -> 9600000
A18: =+A17 -> 2015013 | K18: 派遣金額 | L18: 800000 | M18: 800000 | N18: 800000 | O18: 800000 | P18: 800000 | Q18: 800000 | R18: 800000 | S18: 800000 | T18: 800000 | U18: 800000 | V18: 800000 | W18: 800000 | X18: =SUM(L18:W18) -> 9600000
A19: =+A18 -> 2015013 | K19: 交通費 | X19: 0
A20: =+A19 -> 2015013 | K20: 総経費 | L20: =SUM(L21:L27) -> 648886 | M20: =SUM(M21:M27) -> 648886 | N20: =SUM(N21:N27) -> 645931 | O20: =SUM(O21:O27) -> 653986 | P20: =SUM(P21:P27) -> 645122 | Q20: =SUM(Q21:Q27) -> 660078 | R20: =SUM(R21:R27) -> 660482 | S20: =SUM(S21:S27) -> 660482 | ... W20: =SUM(W21:W27) -> 648130.44 | X20: =SUM(L20:W20) -> 7857652.4
A21: =+A20 -> 2015013 | K21: 賃金 | L21: 557600 | M21: 557600 | N21: 557200 | O21: 557600 | P21: 556400 | Q21: 551200 | R21: 551600 | S21: 551600 | T21: 552800 | U21: 552400 | V21: 553600 | W21: 556844.44 | X21: =SUM(L21:W21) -> 6656444.4
A22: =+A21 -> 2015013 | K22: 交通費その他 | X22: =SUM(L22:W22) -> 0
A23: =+A22 -> 2015013 | K23: 通勤定期代 | L23: 2524 | M23: 2524 | N23: 0 | O23: 7572 | P23: 0 | Q23: 20000 | R23: 20000 | S23: 20000 | T23: 20000 | U23: 20000 | V23: 20000 | W23: 2524 | X23: =SUM(L23:W23) -> 135144
A24: =+A23 -> 2015013 | K24: 健康保険 | L24: 31640 | M24: 31640 | N24: 31640 | O24: 31640 | P24: 31640 | Q24: 31640 | R24: 31640 | S24: 31640 | T24: 31640 | U24: 31640 | V24: 31640 | W24: 31640 | X24: =SUM(L24:W24) -> 379680
A25: =+A24 -> 2015013 | K25: 厚生年金 | L25: 51240 | M25: 51240 | N25: 51240 | O25: 51240 | P25: 51240 | Q25: 51240 | R25: 51240 | S25: 51240 | T25: 51240 | U25: 51240 | V25: 51240 | W25: 51240 | X25: =SUM(L25:W25) -> 614880
A26: =+A25 -> 2015013 | K26: 労災保険 | L26: 2801 | M26: 2801 | N26: 2786 | O26: 2826 | P26: 2782 | Q26: 2856 | R26: 2858 | S26: 2858 | T26: 2864 | U26: 2862 | V26: 2955 | W26: 2801 | X26: =SUM(L26:W26) -> 34050
A27: =+A26 -> 2015013 | K27: 雇用保険 | L27: 3081 | M27: 3081 | N27: 3065 | O27: 3108 | P27: 3060 | Q27: 3142 | R27: 3144 | S27: 3144 | T27: 3150 | U27: 3148 | V27: 3250 | W27: 3081 | X27: =SUM(L27:W27) -> 37454
A28: =+A27 -> 2015013 | K28: 粗利 | L28: =L17-L20 -> 151114 | M28: =M17-M20 -> 151114 | N28: =N17-N20 -> 154069 | O28: =O17-O20 -> 146014 | P28: =P17-P20 -> 154878 | Q28: =Q17-Q20 -> 139922 | R28: =R17-R20 -> 139518 | S28: =S17-S20 -> 139518 | ... X28: =X17-X20 -> 1742347.6
A29: 2015005 | C29: =C17+1 -> 3 | D29: 委任 | I29: フォーカス システムズ | J29: 社員 | K29: 総受注金額 | L29: =L30+L31 -> 730000 | M29: =M30+M31 -> 730000 | N29: =N30+N31 -> 730000 | O29: =O30+O31 -> 730000 | P29: =P30+P31 -> 730000 | Q29: =Q30+Q31 -> 730000 | R29: =R30+R31 -> 730000 | S29: =S30+S31 -> 730000 | ... W29: =W30+W31 -> 730000 | X29: =SUM(L29:W29) -> 8651865
A30: =+A29 -> 2015005 | K30: 派遣金額 | L30: 730000 | M30: 730000 | N30: 730000 | O30: 730000 | P30: 730000 | Q30: 730000 | R30: 730000 | S30: 730000 | T30: 730000 | U30: 621865 | V30: 730000 | W30: 730000 | X30: =SUM(L30:W30) -> 8651865
A31: =+A30 -> 2015005 | K31: 交通費 | X31: 0
A32: =+A31 -> 2015005 | K32: 総経費 | L32: =SUM(L33:L39) -> 508109 | M32: =SUM(M33:M39) -> 497696 | N32: =SUM(N33:N39) -> 516326 | O32: =SUM(O33:O39) -> 534439 | P32: =SUM(P33:P39) -> 519673 | Q32: =SUM(Q33:Q39) -> 507704 | R32: =SUM(R33:R39) -> 508840 | S32: =SUM(S33:S39) -> 500554 | ... W32: =SUM(W33:W39) -> 504125.44 | X32: =SUM(L32:W32) -> 6123892.4
A33: =+A32 -> 2015005 | K33: 賃金 | L33: 433200 | M33: 432000 | N33: 441333 | O33: 458688 | P33: 444983 | Q33: 432800 | R33: 433924 | S33: 428000 | T33: 440176 | U33: 431600 | V33: 432000 | W33: 429216.44 | X33: =SUM(L33:W33) -> 5237920.4
A34: =+A33 -> 2015005 | K34: 交通費その他 | X34: =SUM(L34:W34) -> 0
A35: =+A34 -> 2015005 | K35: 通勤定期代 | L35: 9104 | M35: 0 | N35: 9104 | O35: 9673 | P35: 8765 | Q35: 9104 | R35: 9104 | S35: 6828 | T35: 10242 | U35: 6828 | V35: 7966 | W35: 9104 | X35: =SUM(L35:W35) -> 95822
A36: =+A35 -> 2015005 | K36: 健康保険 | L36: 20900 | M36: 20900 | N36: 20900 | O36: 20900 | P36: 20900 | Q36: 20900 | R36: 20900 | S36: 20900 | T36: 20900 | U36: 20900 | V36: 20900 | W36: 20900 | X36: =SUM(L36:W36) -> 250800
A37: =+A36 -> 2015005 | K37: 厚生年金 | L37: 40260 | M37: 40260 | N37: 40260 | O37: 40260 | P37: 40260 | Q37: 40260 | R37: 40260 | S37: 40260 | T37: 40260 | U37: 40260 | V37: 40260 | W37: 40260 | X37: =SUM(L37:W37) -> 483120
A38: =+A37 -> 2015005 | K38: 労災保険 | L38: 2212 | M38: 2160 | N38: 2252 | O38: 2342 | P38: 2269 | Q38: 2210 | R38: 2215 | S38: 2174 | T38: 2252 | U38: 2192 | V38: 2287 | W38: 2212 | X38: =SUM(L38:W38) -> 26777
A39: =+A38 -> 2015005 | K39: 雇用保険 | L39: 2433 | M39: 2376 | N39: 2477 | O39: 2576 | P39: 2496 | Q39: 2430 | R39: 2437 | S39: 2392 | T39: 2477 | U39: 2411 | V39: 2515 | W39: 2433 | X39: =SUM(L39:W39) -> 29453
A40: =+A39 -> 2015005 | K40: 粗利 | L40: =L29-L32 -> 221891 | M40: =M29-M32 -> 232304 | N40: =N29-N32 -> 213674 | O40: =O29-O32 -> 195561 | P40: =P29-P32 -> 210327 | Q40: =Q29-Q32 -> 222296 | R40: =R29-R32 -> 221160 | S40: =S29-S32 -> 229446 | ... X40: =X29-X32 -> 2527972.6
A41: 2022016 | C41: =C29+1 -> 4 | D41: 委任 | I41: アプリケーションアシスト | J41: 社員 | K41: 総受注金額 | L41: =L42+L43 -> 650000 | M41: =M42+M43 -> 650000 | N41: =N42+N43 -> 650000 | O41: =O42+O43 -> 650000 | P41: =P42+P43 -> 650000 | Q41: =Q42+Q43 -> 650000 | R41: =R42+R43 -> 650000 | S41: =S42+S43 -> 650000 | ... W41: =W42+W43 -> 650000 | X41: =SUM(L41:W41) -> 7768535
A42: =+A41 -> 2022016 | K42: 派遣金額 | L42: 650000 | M42: 650000 | N42: 650000 | O42: 650000 | P42: 650000 | Q42: 650000 | R42: 650000 | S42: 650000 | T42: 650000 | U42: 618535 | V42: 650000 | W42: 650000 | X42: =SUM(L42:W42) -> 7768535
A43: =+A42 -> 2022016 | K43: 交通費 | X43: 0
A44: =+A43 -> 2022016 | K44: 総経費 | L44: =SUM(L45:L51) -> 414484 | M44: =SUM(M45:M51) -> 418435 | N44: =SUM(N45:N51) -> 418435 | O44: =SUM(O45:O51) -> 418435 | P44: =SUM(P45:P51) -> 431980 | Q44: =SUM(Q45:Q51) -> 430363 | R44: =SUM(R45:R51) -> 429555 | S44: =SUM(S45:S51) -> 429555 | ... W44: =SUM(W45:W51) -> 414084 | X44: =SUM(L44:W44) -> 5107914
A45: =+A44 -> 2022016 | K45: 賃金 | L45: 360400 | M45: 360000 | N45: 360000 | O45: 360000 | P45: 362400 | Q45: 360800 | R45: 360000 | S45: 360000 | T45: 365600 | U45: 363200 | V45: 364800 | W45: 360000 | X45: =SUM(L45:W45) -> 4337200
A46: =+A45 -> 2022016 | K46: 交通費その他 | X46: =SUM(L46:W46) -> 0
A47: =+A46 -> 2022016 | K47: 通勤定期代 | L47: 8510 | M47: 12820 | N47: 12820 | O47: 12820 | P47: 12820 | Q47: 12820 | R47: 12820 | S47: 12820 | T47: 12820 | U47: 12820 | V47: 12820 | W47: 8510 | X47: =SUM(L47:W47) -> 145220
A48: =+A47 -> 2022016 | K48: 健康保険 | L48: 14250 | M48: 14250 | N48: 14250 | O48: 14250 | P48: 18050 | Q48: 18050 | R48: 18050 | S48: 18050 | T48: 18050 | U48: 18050 | V48: 18050 | W48: 14250 | X48: =SUM(L48:W48) -> 197600
A49: =+A48 -> 2022016 | K49: 厚生年金 | L49: 27450 | M49: 27450 | N49: 27450 | O49: 27450 | P49: 34770 | Q49: 34770 | R49: 34770 | S49: 34770 | T49: 34770 | U49: 34770 | V49: 34770 | W49: 27450 | X49: =SUM(L49:W49) -> 380640
A50: =+A49 -> 2022016 | K50: 労災保険 | L50: 1845 | M50: 1864 | N50: 1864 | O50: 1864 | P50: 1876 | Q50: 1868 | R50: 1864 | S50: 1864 | T50: 1892 | U50: 1880 | V50: 1975 | W50: 1845 | X50: =SUM(L50:W50) -> 22501
A51: =+A50 -> 2022016 | K51: 雇用保険 | L51: 2029 | M51: 2051 | N51: 2051 | O51: 2051 | P51: 2064 | Q51: 2055 | R51: 2051 | S51: 2051 | T51: 2081 | U51: 2068 | V51: 2172 | W51: 2029 | X51: =SUM(L51:W51) -> 24753
A52: =+A51 -> 2022016 | K52: 粗利 | L52: =L41-L44 -> 235516 | M52: =M41-M44 -> 231565 | N52: =N41-N44 -> 231565 | O52: =O41-O44 -> 231565 | P52: =P41-P44 -> 218020 | Q52: =Q41-Q44 -> 219637 | R52: =R41-R44 -> 220445 | S52: =S41-S44 -> 220445 | ... X52: =X41-X44 -> 2660621
A53: 2014009 | C53: =C41+1 -> 5 | D53: 派遣 | I53: ルミナス・ビー・ ジャパン | J53: 社員 | K53: 総受注金額 | L53: =L54+L55 -> 940000 | M53: =M54+M55 -> 940000 | N53: =N54+N55 -> 940000 | O53: =O54+O55 -> 963500 | P53: =P54+P55 -> 940000 | Q53: =Q54+Q55 -> 940000 | R53: =R54+R55 -> 940000 | S53: =S54+S55 -> 916500 | ... W53: =W54+W55 -> 940000 | X53: =SUM(L53:W53) -> 11118437
A54: =+A53 -> 2014009 | K54: 派遣金額 | L54: 940000 | M54: 940000 | N54: 940000 | O54: 963500 | P54: 940000 | Q54: 940000 | R54: 940000 | S54: 916500 | T54: 940000 | U54: 940000 | V54: 778437 | W54: 940000 | X54: =SUM(L54:W54) -> 11118437
A55: =+A54 -> 2014009 | X55: =SUM(L55:W55) -> 0
A56: =+A55 -> 2014009 | K56: 総経費 | L56: =SUM(L57:L63) -> 758186 | M56: =SUM(M57:M63) -> 758186 | N56: =SUM(N57:N63) -> 758186 | O56: =SUM(O57:O63) -> 758186 | P56: =SUM(P57:P63) -> 758186 | Q56: =SUM(Q57:Q63) -> 756491 | R56: =SUM(R57:R63) -> 756491 | S56: =SUM(S57:S63) -> 757226 | ... W56: =SUM(W57:W63) -> 758186 | X56: =SUM(L56:W56) -> 9122023
A57: =+A56 -> 2014009 | K57: 賃金 | L57: 640000 | M57: 640000 | N57: 640000 | O57: 640000 | P57: 640000 | Q57: 640000 | R57: 640000 | S57: 640000 | T57: 640000 | U57: 690000 | V57: 622700 | W57: 640000 | X57: =SUM(L57:W57) -> 7712700
A58: =+A57 -> 2014009 | K58: 交通費その他 | X58: =SUM(L58:W58) -> 0
A59: =+A58 -> 2014009 | K59: 通勤定期代 | L59: 13430 | M59: 13430 | N59: 13430 | O59: 13430 | P59: 13430 | Q59: 13430 | R59: 13430 | S59: 13430 | T59: 13430 | U59: 13430 | V59: 13430 | W59: 13430 | X59: =SUM(L59:W59) -> 161160
A60: =+A59 -> 2014009 | K60: 健康保険 | L60: 38420 | M60: 38420 | N60: 38420 | O60: 38420 | P60: 38420 | Q60: 36725 | R60: 36725 | S60: 36725 | T60: 36725 | U60: 36725 | V60: 36725 | W60: 38420 | X60: =SUM(L60:W60) -> 450870
A61: =+A60 -> 2014009 | K61: 厚生年金 | L61: 59475 | M61: 59475 | N61: 59475 | O61: 59475 | P61: 59475 | Q61: 59475 | R61: 59475 | S61: 59475 | T61: 59475 | U61: 59475 | V61: 59475 | W61: 59475 | X61: =SUM(L61:W61) -> 713700
A62: =+A61 -> 2014009 | K62: 労災保険 | L62: 3267 | M62: 3267 | N62: 3267 | O62: 3267 | P62: 3267 | Q62: 3267 | R62: 3267 | S62: 3617 | T62: 3267 | U62: 3517 | V62: 3268 | W62: 3267 | X62: =SUM(L62:W62) -> 39805
A63: =+A62 -> 2014009 | K63: 雇用保険 | L63: 3594 | M63: 3594 | N63: 3594 | O63: 3594 | P63: 3594 | Q63: 3594 | R63: 3594 | S63: 3979 | T63: 3594 | U63: 3869 | V63: 3594 | W63: 3594 | X63: =SUM(L63:W63) -> 43788
A64: =+A63 -> 2014009 | K64: 粗利 | L64: =L53-L56 -> 181814 | M64: =M53-M56 -> 181814 | N64: =N53-N56 -> 181814 | O64: =O53-O56 -> 205314 | P64: =P53-P56 -> 181814 | Q64: =Q53-Q56 -> 183509 | R64: =R53-R56 -> 183509 | S64: =S53-S56 -> 159274 | ... X64: =X53-X56 -> 1996414
A65: 2011007 | C65: =C53+1 -> 6 | D65: 派遣 | I65: マンパワーグループ | J65: 社員 | K65: 総受注金額 | L65: =L66+L67 -> 850000 | M65: =M66+M67 -> 850000 | N65: =N66+N67 -> 850000 | O65: =O66+O67 -> 850000 | P65: =P66+P67 -> 850000 | Q65: =Q66+Q67 -> 850000 | R65: =R66+R67 -> 850000 | S65: =S66+S67 -> 850000 | ... W65: =W66+W67 -> 850000 | X65: =SUM(L65:W65) -> 10200000
A66: =+A65 -> 2011007 | K66: 派遣金額 | L66: 850000 | M66: 850000 | N66: 850000 | O66: 850000 | P66: 850000 | Q66: 850000 | R66: 850000 | S66: 850000 | T66: 850000 | U66: 850000 | V66: 850000 | W66: 850000 | X66: =SUM(L66:W66) -> 10200000
A67: =+A66 -> 2011007 | K67: 交通費 | X67: 0
A68: =+A67 -> 2011007 | K68: 総経費 | L68: =SUM(L69:L75) -> 630577 | M68: =SUM(M69:M75) -> 630173 | N68: =SUM(N69:N75) -> 630577 | O68: =SUM(O69:O75) -> 630577 | P68: =SUM(P69:P75) -> 629769 | Q68: =SUM(Q69:Q75) -> 629769 | R68: =SUM(R69:R75) -> 630981 | S68: =SUM(S69:S75) -> 629365 | ... W68: =SUM(W69:W75) -> 630577 | X68: =SUM(L68:W68) -> 7561449
A69: =+A68 -> 2011007 | K69: 賃金 | L69: 546400 | M69: 546000 | N69: 546400 | O69: 546400 | P69: 545600 | Q69: 545600 | R69: 546800 | S69: 545200 | T69: 546000 | U69: 544800 | V69: 545600 | W69: 546400 | X69: =SUM(L69:W69) -> 6551200
A70: =+A69 -> 2011007 | K70: 交通費その他 | X70: =SUM(L70:W70) -> 0
A71: =+A70 -> 2011007 | K71: 通勤定期代 | L71: 0 | M71: 0 | N71: 0 | O71: 0 | P71: 0 | Q71: 0 | R71: 0 | S71: 0 | T71: 0 | U71: 0 | V71: 0 | W71: 0 | X71: =SUM(L71:W71) -> 0
A72: =+A71 -> 2011007 | K72: 健康保険 | L72: 29945 | M72: 29945 | N72: 29945 | O72: 29945 | P72: 29945 | Q72: 29945 | R72: 29945 | S72: 29945 | T72: 29945 | U72: 29945 | V72: 29945 | W72: 29945 | X72: =SUM(L72:W72) -> 359340
A73: =+A72 -> 2011007 | K73: 厚生年金 | L73: 48495 | M73: 48495 | N73: 48495 | O73: 48495 | P73: 48495 | Q73: 48495 | R73: 48495 | S73: 48495 | T73: 48495 | U73: 48495 | V73: 48495 | W73: 48495 | X73: =SUM(L73:W73) -> 581940
A74: =+A73 -> 2011007 | K74: 労災保険 | L74: 2732 | M74: 2730 | N74: 2732 | O74: 2732 | P74: 2728 | Q74: 2728 | R74: 2734 | S74: 2726 | T74: 2730 | U74: 2724 | V74: 2815 | W74: 2732 | X74: =SUM(L74:W74) -> 32843
A75: =+A74 -> 2011007 | K75: 雇用保険 | L75: 3005 | M75: 3003 | N75: 3005 | O75: 3005 | P75: 3001 | Q75: 3001 | R75: 3007 | S75: 2999 | T75: 3003 | U75: 2996 | V75: 3096 | W75: 3005 | X75: =SUM(L75:W75) -> 36126
A76: =+A75 -> 2011007 | K76: 粗利 | L76: =L65-L68 -> 219423 | M76: =M65-M68 -> 219827 | N76: =N65-N68 -> 219423 | O76: =O65-O68 -> 219423 | P76: =P65-P68 -> 220231 | Q76: =Q65-Q68 -> 220231 | R76: =R65-R68 -> 219019 | S76: =S65-S68 -> 220635 | ... X76: =X65-X68 -> 2638551
A77: 2017023 | C77: =C65+1 -> 7 | D77: 派遣 | I77: ペンギンソリューションズ | J77: 社員 | K77: 総受注金額 | L77: =L78+L79 -> 791415 | M77: =M78+M79 -> 784608 | N77: =N78+N79 -> 767103 | O77: =O78+O79 -> 726258 | P77: =P78+P79 -> 806976 | Q77: =Q78+Q79 -> 737928 | R77: =R78+R79 -> 762240 | S77: =S78+S79 -> 770020 | ... W77: =W78+W79 -> 700000 | X77: =SUM(L77:W77) -> 9046716
A78: =+A77 -> 2017023 | K78: 派遣金額 | L78: 791415 | M78: 784608 | N78: 767103 | O78: 726258 | P78: 806976 | Q78: 737928 | R78: 762240 | S78: 770020 | T78: 700000 | U78: 737928 | V78: 762240 | W78: 700000 | X78: =SUM(L78:W78) -> 9046716
A79: =+A78 -> 2017023 | K79: 交通費 | X79: 0
A80: =+A79 -> 2017023 | K80: 総経費 | L80: =SUM(L81:L87) -> 699604 | M80: =SUM(M81:M87) -> 655389 | N80: =SUM(N81:N87) -> 639306 | O80: =SUM(O81:O87) -> 694774 | P80: =SUM(P81:P87) -> 636457 | Q80: =SUM(Q81:Q87) -> 648817 | R80: =SUM(R81:R87) -> 670618 | S80: =SUM(S81:S87) -> 600231 | ... W80: =SUM(W81:W87) -> 599461 | X80: =SUM(L80:W80) -> 7769553
A81: =+A80 -> 2017023 | K81: 賃金 | L81: 610143 | M81: 568628 | N81: 551272 | O81: 606707 | P81: 550085 | Q81: 550223 | R81: 569621 | S81: 502141 | T81: 551382 | U81: 551906 | V81: 523692 | W81: 510000 | X81: =SUM(L81:W81) -> 6645800
A82: =+A81 -> 2017023 | K82: 交通費その他 | X82: =SUM(L82:W82) -> 0
A83: =+A82 -> 2017023 | K83: 通勤定期代 | L83: 8960 | M83: 6720 | N83: 8160 | O83: 7616 | P83: 6528 | Q83: 5440 | R83: 7616 | S83: 5440 | T83: 5440 | U83: 6528 | V83: 6528 | W83: 8960 | X83: =SUM(L83:W83) -> 83936
A84: =+A83 -> 2017023 | K84: 健康保険 | L84: 28250 | M84: 28250 | N84: 28250 | O84: 28250 | P84: 28250 | Q84: 33335 | R84: 33335 | S84: 33335 | T84: 33335 | U84: 33335 | V84: 33335 | W84: 28250 | X84: =SUM(L84:W84) -> 369510
A85: =+A84 -> 2017023 | K85: 厚生年金 | L85: 45750 | M85: 45750 | N85: 45750 | O85: 45750 | P85: 45750 | Q85: 53985 | R85: 53985 | S85: 53985 | T85: 53985 | U85: 53985 | V85: 53985 | W85: 45750 | X85: =SUM(L85:W85) -> 598410
A86: =+A85 -> 2017023 | K86: 労災保険 | L86: 3096 | M86: 2877 | N86: 2797 | O86: 3072 | P86: 2783 | Q86: 2778 | R86: 2886 | S86: 2538 | T86: 2784 | U86: 2792 | V86: 2738 | W86: 3096 | X86: =SUM(L86:W86) -> 34237
A87: =+A86 -> 2017023 | K87: 雇用保険 | L87: 3405 | M87: 3164 | N87: 3077 | O87: 3379 | P87: 3061 | Q87: 3056 | R87: 3175 | S87: 2792 | T87: 3063 | U87: 3071 | V87: 3012 | W87: 3405 | X87: =SUM(L87:W87) -> 37660
A88: =+A87 -> 2017023 | K88: 粗利 | L88: =L77-L80 -> 91811 | M88: =M77-M80 -> 129219 | N88: =N77-N80 -> 127797 | O88: =O77-O80 -> 31484 | P88: =P77-P80 -> 170519 | Q88: =Q77-Q80 -> 89111 | R88: =R77-R80 -> 91622 | S88: =S77-S80 -> 169789 | ... X88: =X77-X80 -> 1277163
A89: 2009008 | C89: =C77+1 -> 8 | D89: 派遣 | I89: IT-ONE | J89: 社員 | K89: 総受注金額 | L89: =L90+L91 -> 800000 | M89: =M90+M91 -> 800000 | N89: =N90+N91 -> 800000 | O89: =O90+O91 -> 800000 | P89: =P90+P91 -> 800000 | Q89: =Q90+Q91 -> 800000 | R89: =R90+R91 -> 800000 | S89: =S90+S91 -> 800000 | ... W89: =W90+W91 -> 800000 | X89: =SUM(L89:W89) -> 9600000
A90: =+A89 -> 2009008 | K90: 派遣金額 | L90: 800000 | M90: 800000 | N90: 800000 | O90: 800000 | P90: 800000 | Q90: 800000 | R90: 800000 | S90: 800000 | T90: 800000 | U90: 800000 | V90: 800000 | W90: 800000 | X90: =SUM(L90:W90) -> 9600000
A91: =+A90 -> 2009008 | K91: 交通費 | X91: 0
A92: =+A91 -> 2009008 | K92: 総経費 | L92: =SUM(L93:L99) -> 532369 | M92: =SUM(M93:M99) -> 531965 | N92: =SUM(N93:N99) -> 533278 | O92: =SUM(O93:O99) -> 533682 | P92: =SUM(P93:P99) -> 532470 | Q92: =SUM(Q93:Q99) -> 532369 | R92: =SUM(R93:R99) -> 555669 | S92: =SUM(S93:S99) -> 531561 | ... W92: =SUM(W93:W99) -> 532369 | X92: =SUM(L92:W92) -> 6412415
A93: =+A92 -> 2009008 | K93: 賃金 | L93: 458000 | M93: 457600 | N93: 458000 | O93: 458400 | P93: 457200 | Q93: 458000 | R93: 481058 | S93: 457200 | T93: 457600 | U93: 457200 | V93: 456800 | W93: 458000 | X93: =SUM(L93:W93) -> 5515058
A94: =+A93 -> 2009008 | K94: 交通費その他 | X94: =SUM(L94:W94) -> 0
A95: =+A94 -> 2009008 | K95: 通勤定期代 | L95: 0 | M95: 0 | N95: 900 | O95: 900 | P95: 900 | Q95: 0 | R95: 0 | S95: 0 | T95: 0 | U95: 900 | V95: 900 | W95: 0 | X95: =SUM(L95:W95) -> 4500
A96: =+A95 -> 2009008 | K96: 健康保険 | L96: 26555 | M96: 26555 | N96: 26555 | O96: 26555 | P96: 26555 | Q96: 26555 | R96: 26555 | S96: 26555 | T96: 26555 | U96: 26555 | V96: 26555 | W96: 26555 | X96: =SUM(L96:W96) -> 318660
A97: =+A96 -> 2009008 | K97: 厚生年金 | L97: 43005 | M97: 43005 | N97: 43005 | O97: 43005 | P97: 43005 | Q97: 43005 | R97: 43005 | S97: 43005 | T97: 43005 | U97: 43005 | V97: 43005 | W97: 43005 | X97: =SUM(L97:W97) -> 516060
A98: =+A97 -> 2009008 | K98: 労災保険 | L98: 2290 | M98: 2288 | N98: 2294 | O98: 2296 | P98: 2290 | Q98: 2290 | R98: 2405 | S98: 2286 | T98: 2288 | U98: 2290 | V98: 2375 | W98: 2290 | X98: =SUM(L98:W98) -> 27682
A99: =+A98 -> 2009008 | K99: 雇用保険 | L99: 2519 | M99: 2517 | N99: 2524 | O99: 2526 | P99: 2520 | Q99: 2519 | R99: 2646 | S99: 2515 | T99: 2517 | U99: 2520 | V99: 2613 | W99: 2519 | X99: =SUM(L99:W99) -> 30455
A100: =+A99 -> 2009008 | K100: 粗利 | L100: =L89-L92 -> 267631 | M100: =M89-M92 -> 268035 | N100: =N89-N92 -> 266722 | O100: =O89-O92 -> 266318 | P100: =P89-P92 -> 267530 | Q100: =Q89-Q92 -> 267631 | R100: =R89-R92 -> 244331 | S100: =S89-S92 -> 268439 | ... X100: =X89-X92 -> 3187585
...
