Workbook

Sheet まとめ
B1: SI合計 | D1: 4月 | F1: 5月 | H1: 6月 | J1: 7月 | L1: 8月 | N1: 9月 | P1: 10月 | R1: 11月 | T1: 12月 | V1: 1月 | X1: 2月 | Z1: 3月 | AB1: 通期合計
B2: 売上合計 | E2: =E8+E20 -> 10973295 | G2: =G8+G20 -> 9119640 | I2: =I8+I20 -> 11622975 | K2: =K8+K20 -> 7466430 | M2: =M8+M20 -> 16917130 | O2: =O8+O20 -> 10738835 | Q2: =Q8+Q20 -> 7142475 | S2: =S8+S20 -> 5387205 | U2: =U8+U20 -> 13927540 | W2: =W8+W20 -> 33544559 | Y2: =Y8+Y20 -> 8506185 | AA2: =AA8+AA20 -> 21956000 | AC2: =SUM(E2:AA2) -> 157302269
B3: 原価 | E3: =E9+E21 -> 9525494 | G3: =G9+G21 -> 7393220 | I3: =I9+I21 -> 9652770 | K3: =K9+K21 -> 5820529 | M3: =M9+M21 -> 14576520 | O3: =O9+O21 -> 8814514 | Q3: =Q9+Q21 -> 5196086 | S3: =S9+S21 -> 4008642 | U3: =U9+U21 -> 11911923 | W3: =W9+W21 -> 30491125 | Y3: =Y9+Y21 -> 6749650 | AA3: =AA9+AA21 -> 19289137 | AC3: =SUM(E3:AA3) -> 133429610
B4: 粗利 | E4: =E2-E3 -> 1447801 | G4: =G2-G3 -> 1726420 | I4: =I2-I3 -> 1970205 | K4: =K2-K3 -> 1645901 | M4: =M2-M3 -> 2340610 | O4: =O2-O3 -> 1924321 | Q4: =Q2-Q3 -> 1946389 | S4: =S2-S3 -> 1378563 | U4: =U2-U3 -> 2015617 | W4: =W2-W3 -> 3053434 | Y4: =Y2-Y3 -> 1756535 | AA4: =AA2-AA3 -> 2666863 | AC4: =SUM(E4:AA4) -> 23872659
B7: UAL
B8: 売上合計 | E8: =E11+E14 -> 6629295 | G8: =G11+G14 -> 7361140 | I8: =I11+I14 -> 7632975 | K8: =K11+K14 -> 7466430 | M8: =M11+M14 -> 7304380 | O8: =O11+O14 -> 7065585 | Q8: =Q11+Q14 -> 6276225 | S8: =S11+S14 -> 5387205 | U8: =U11+U14 -> 5674540 | W8: =W11+W14 -> 6119195 | Y8: =Y11+Y14 -> 5902185 | AA8: =AA11+AA14 -> 6198000 | AC8: =SUM(E8:AA8) -> 79017155
B9: 原価 | E9: =E12+E15 -> 5525494 | G9: =G12+G15 -> 5743220 | I9: =I12+I15 -> 5852770 | K9: =K12+K15 -> 5820529 | M9: =M12+M15 -> 5421520 | O9: =O12+O15 -> 5369514 | Q9: =Q12+Q15 -> 4371086 | S9: =S12+S15 -> 4008642 | U9: =U12+U15 -> 4051923 | W9: =W12+W15 -> 4511464 | Y9: =Y12+Y15 -> 4499650 | AA9: =AA12+AA15 -> 4389137 | AC9: =SUM(E9:AA9) -> 59564949
B10: 粗利 | E10: =E8-E9 -> 1103801 | G10: =G8-G9 -> 1617920 | I10: =I8-I9 -> 1780205 | K10: =K8-K9 -> 1645901 | M10: =M8-M9 -> 1882860 | O10: =O8-O9 -> 1696071 | Q10: =Q8-Q9 -> 1905139 | S10: =S8-S9 -> 1378563 | U10: =U8-U9 -> 1622617 | W10: =W8-W9 -> 1607731 | Y10: =Y8-Y9 -> 1402535 | AA10: =AA8-AA9 -> 1808863 | AC10: =SUM(E10:AA10) -> 19452206
B11: 受託 | E11: =UAL常駐!L241 -> 0 | G11: =UAL常駐!M241 -> 0 | I11: =UAL常駐!N241 -> 0 | K11: =UAL常駐!O241 -> 0 | M11: =UAL常駐!P241 -> 0 | O11: =UAL常駐!Q241 -> 0 | Q11: =UAL常駐!R241 -> 0 | S11: =UAL常駐!S241 -> 0 | U11: =UAL常駐!T241 -> 0 | W11: =UAL常駐!U241 -> 0 | Y11: =UAL常駐!V241 -> 0 | AA11: =UAL常駐!W241 -> 0 | AC11: =SUM(E11:AA11) -> 0
B12: 原価 | E12: =UAL常駐!L252 -> 676199 | G12: =UAL常駐!M252 -> 678473 | I12: =UAL常駐!N252 -> 684536 | K12: =UAL常駐!O252 -> 673926 | M12: =UAL常駐!P252 -> 0 | O12: =UAL常駐!Q252 -> 0 | Q12: =UAL常駐!R252 -> 0 | S12: =UAL常駐!S252 -> 0 | U12: =UAL常駐!T252 -> 0 | W12: =UAL常駐!U252 -> 0 | Y12: =UAL常駐!V252 -> 0 | AA12: =UAL常駐!W252 -> 0 | AC12: =SUM(E12:AA12) -> 2713134
B13: 粗利 | E13: =E11-E12 -> -676199 | G13: =G11-G12 -> -678473 | I13: =I11-I12 -> -684536 | K13: =K11-K12 -> -673926 | M13: =M11-M12 -> 0 | O13: =O11-O12 -> 0 | Q13: =Q11-Q12 -> 0 | S13: =S11-S12 -> 0 | U13: =U11-U12 -> 0 | W13: =W11-W12 -> 0 | Y13: =Y11-Y12 -> 0 | AA13: =AA11-AA12 -> 0 | AC13: =SUM(E13:AA13) -> -2713134
B14: 常駐 | E14: =UAL常駐!L2 -> 6629295 | G14: =UAL常駐!M2 -> 7361140 | I14: =UAL常駐!N2 -> 7632975 | K14: =UAL常駐!O2 -> 7466430 | M14: =UAL常駐!P2 -> 7304380 | O14: =UAL常駐!Q2 -> 7065585 | Q14: =UAL常駐!R2 -> 6276225 | S14: =UAL常駐!S2 -> 5387205 | U14: =UAL常駐!T2 -> 5674540 | W14: =UAL常駐!U2 -> 6119195 | Y14: =UAL常駐!V2 -> 5902185 | AA14: =UAL常駐!W2 -> 6198000 | AC14: =SUM(E14:AA14) -> 79017155
B15: 原価 | E15: =UAL常駐!L3 -> 4849295 | G15: =UAL常駐!M3 -> 5064747 | I15: =UAL常駐!N3 -> 5168234 | K15: =UAL常駐!O3 -> 5146603 | M15: =UAL常駐!P3 -> 5421520 | O15: =UAL常駐!Q3 -> 5369514 | Q15: =UAL常駐!R3 -> 4371086 | S15: =UAL常駐!S3 -> 4008642 | U15: =UAL常駐!T3 -> 4051923 | W15: =UAL常駐!U3 -> 4511464 | Y15: =UAL常駐!V3 -> 4499650 | AA15: =UAL常駐!W3 -> 4389137 | AC15: =SUM(E15:AA15) -> 56851815
B16: 粗利 | E16: =E14-E15 -> 1780000 | G16: =G14-G15 -> 2296393 | I16: =I14-I15 -> 2464741 | K16: =K14-K15 -> 2319827 | M16: =M14-M15 -> 1882860 | O16: =O14-O15 -> 1696071 | Q16: =Q14-Q15 -> 1905139 | S16: =S14-S15 -> 1378563 | U16: =U14-U15 -> 1622617 | W16: =W14-W15 -> 1607731 | Y16: =Y14-Y15 -> 1402535 | AA16: =AA14-AA15 -> 1808863 | AC16: =SUM(E16:AA16) -> 22165340
B19: その他
B20: 売上合計 | E20: =E23+E26 -> 4344000 | G20: =G23+G26 -> 1758500 | I20: =I23+I26 -> 3990000 | K20: =K23+K26 -> 0 | M20: =M23+M26 -> 9612750 | O20: =O23+O26 -> 3673250 | Q20: =Q23+Q26 -> 866250 | S20: =S23+S26 -> 0 | U20: =U23+U26 -> 8253000 | W20: =W23+W26 -> 27425364 | Y20: =Y23+Y26 -> 2604000 | AA20: =AA23+AA26 -> 15758000 | AC20: =SUM(E20:AA20) -> 78285114
B21: 原価 | E21: =E24+E27 -> 4000000 | G21: =G24+G27 -> 1650000 | I21: =I24+I27 -> 3800000 | K21: =K24+K27 -> 0 | M21: =M24+M27 -> 9155000 | O21: =O24+O27 -> 3445000 | Q21: =Q24+Q27 -> 825000 | S21: =S24+S27 -> 0 | U21: =U24+U27 -> 7860000 | W21: =W24+W27 -> 25979661 | Y21: =Y24+Y27 -> 2250000 | AA21: =AA24+AA27 -> 14900000 | AC21: =SUM(E21:AA21) -> 73864661
B22: 粗利 | E22: =E20-E21 -> 344000 | G22: =G20-G21 -> 108500 | I22: =I20-I21 -> 190000 | K22: =K20-K21 -> 0 | M22: =M20-M21 -> 457750 | O22: =O20-O21 -> 228250 | Q22: =Q20-Q21 -> 41250 | S22: =S20-S21 -> 0 | U22: =U20-U21 -> 393000 | W22: =W20-W21 -> 1445703 | Y22: =Y20-Y21 -> 354000 | AA22: =AA20-AA21 -> 858000 | AC22: =SUM(E22:AA22) -> 4420453
B23: 受託 | E23: =その他受託!L2 -> 4344000 | G23: =その他受託!M2 -> 1758500 | I23: =その他受託!N2 -> 3990000 | K23: =その他受託!O2 -> 0 | M23: =その他受託!P2 -> 9612750 | O23: =その他受託!Q2 -> 3673250 | Q23: =その他受託!R2 -> 866250 | S23: =その他受託!S2 -> 0 | U23: =その他受託!T2 -> 8253000 | W23: =その他受託!U2 -> 27425364 | Y23: =その他受託!V2 -> 2604000 | AA23: =その他受託!W2 -> 15758000 | AC23: =SUM(E23:AA23) -> 78285114
B24: 原価 | E24: =その他受託!L3 -> 4000000 | G24: =その他受託!M3 -> 1650000 | I24: =その他受託!N3 -> 3800000 | K24: =その他受託!O3 -> 0 | M24: =その他受託!P3 -> 9155000 | O24: =その他受託!Q3 -> 3445000 | Q24: =その他受託!R3 -> 825000 | S24: =その他受託!S3 -> 0 | U24: =その他受託!T3 -> 7860000 | W24: =その他受託!U3 -> 25979661 | Y24: =その他受託!V3 -> 2250000 | AA24: =その他受託!W3 -> 14900000 | AC24: =SUM(E24:AA24) -> 73864661
B25: 粗利 | E25: =E23-E24 -> 344000 | G25: =G23-G24 -> 108500 | I25: =I23-I24 -> 190000 | K25: =K23-K24 -> 0 | M25: =M23-M24 -> 457750 | O25: =O23-O24 -> 228250 | Q25: =Q23-Q24 -> 41250 | S25: =S23-S24 -> 0 | U25: =U23-U24 -> 393000 | W25: =W23-W24 -> 1445703 | Y25: =Y23-Y24 -> 354000 | AA25: =AA23-AA24 -> 858000 | AC25: =SUM(E25:AA25) -> 4420453
B26: 常駐 | E26: =その他常駐!L2 -> 0 | G26: =その他常駐!M2 -> 0 | I26: =その他常駐!N2 -> 0 | K26: =その他常駐!O2 -> 0 | M26: =その他常駐!P2 -> 0 | O26: =その他常駐!Q2 -> 0 | Q26: =その他常駐!R2 -> 0 | S26: =その他常駐!S2 -> 0 | U26: =その他常駐!T2 -> 0 | W26: =その他常駐!U2 -> 0 | Y26: =その他常駐!V2 -> 0 | AA26: =その他常駐!W2 -> 0 | AC26: =SUM(E26:AA26) -> 0
B27: 原価 | E27: =その他常駐!L3 -> 0 | G27: =その他常駐!M3 -> 0 | I27: =その他常駐!N3 -> 0 | K27: =その他常駐!O3 -> 0 | M27: =その他常駐!P3 -> 0 | O27: =その他常駐!Q3 -> 0 | Q27: =その他常駐!R3 -> 0 | S27: =その他常駐!S3 -> 0 | U27: =その他常駐!T3 -> 0 | W27: =その他常駐!U3 -> 0 | Y27: =その他常駐!V3 -> 0 | AA27: =その他常駐!W3 -> 0 | AC27: =SUM(E27:AA27) -> 0
B28: 粗利 | E28: =E26-E27 -> 0 | G28: =G26-G27 -> 0 | I28: =I26-I27 -> 0 | K28: =K26-K27 -> 0 | M28: =M26-M27 -> 0 | O28: =O26-O27 -> 0 | Q28: =Q26-Q27 -> 0 | S28: =S26-S27 -> 0 | U28: =U26-U27 -> 0 | W28: =W26-W27 -> 0 | Y28: =Y26-Y27 -> 0 | AA28: =AA26-AA27 -> 0 | AC28: =SUM(E28:AA28) -> 0

Sheet UAL常駐
B1: 氏名 | C1: No | D1: 派遣/請負 | E1: 担当 | F1: 氏名 | G1: 派遣先部署 | H1: 作業名 | I1: 契約先 | J1: 外注会社 | K1: 売上単価 (支払単価） 【≒粗利】 | L1: 4月 | M1: 5月 | N1: 6月 | O1: 7月 | P1: 8月 | Q1: 9月 | R1: 10月 | S1: 11月 | T1: 12月 | U1: 1月 | V1: 2月 | W1: 3月 | X1: 合計
K2: 売上 | L2: =L233 -> 6629295 | M2: =M233 -> 7361140 | N2: =N233 -> 7632975 | O2: =O233 -> 7466430 | P2: =P233 -> 7304380 | Q2: =Q233 -> 7065585 | R2: =R233 -> 6276225 | S2: =S233 -> 5387205 | ... W2: =W233 -> 6198000 | X2: =SUM(L2:W2) -> 79017155
K3: 仕入 | L3: =L234 -> 4849295 | M3: =M234 -> 5064747 | N3: =N234 -> 5168234 | O3: =O234 -> 5146603 | P3: =P234 -> 5421520 | Q3: =Q234 -> 5369514 | R3: =R234 -> 4371086 | S3: =S234 -> 4008642 | ... W3: =W234 -> 4389137 | X3: =SUM(L3:W3) -> 56851815
K4: 粗利 | L4: =L2-L3 -> 1780000 | M4: =M2-M3 -> 2296393 | N4: =N2-N3 -> 2464741 | O4: =O2-O3 -> 2319827 | P4: =P2-P3 -> 1882860 | Q4: =Q2-Q3 -> 1696071 | R4: =R2-R3 -> 1905139 | S4: =S2-S3 -> 1378563 | ... W4: =W2-W3 -> 1808863 | X4: =SUM(L4:W4) -> 22165340
A5: 2015009 | C5: 1 | D5: 派遣 | E5: 転出 | J5: 社員 | K5: 総受注金額 | L5: =L6+L7 -> 880000 | M5: =M6+M7 -> 880000 | N5: =N6+N7 -> 880000 | O5: =O6+O7 -> 771600 | P5: =P6+P7 -> 586030 | Q5: =Q6+Q7 -> 441430 | R5: =R6+R7 -> 0 | S5: =S6+S7 -> 0 | ... W5: =W6+W7 -> 0 | X5: =SUM(L5:W5) -> 4439060
A6: =+A5 -> 2015009 | K6: 派遣金額 | L6: 880000 | M6: 880000 | N6: 880000 | O6: 771600 | P6: 586030 | Q6: 441430 | X6: =SUM(L6:W6) -> 4439060
A7: =+A6 -> 2015009 | K7: 交通費 | X7: 0
A8: =+A7 -> 2015009 | K8: 総経費 | L8: =SUM(L9:L15) -> 464749 | M8: =SUM(M9:M15) -> 465962 | N8: =SUM(N9:N15) -> 469202 | O8: =SUM(O9:O15) -> 475265 | P8: =SUM(P9:P15) -> 480240 | Q8: =SUM(Q9:Q15) -> 478623 | R8: =SUM(R9:R15) -> 0 | S8: =SUM(S9:S15) -> 0 | ... W8: =SUM(W9:W15) -> 0 | X8: =SUM(L8:W8) -> 2834041
A9: =+A8 -> 2015009 | K9: 賃金 | L9: 410400 | M9: 411600 | N9: 411600 | O9: 417600 | P9: 415200 | Q9: 413600 | X9: =SUM(L9:W9) -> 2480000
A10: =+A9 -> 2015009 | K10: 交通費その他 | X10: =SUM(L10:W10) -> 0
A11: =+A10 -> 2015009 | K11: 通勤定期代 | L11: 0 | M11: 0 | N11: 0 | O11: \0 | P11: \0 | Q11: 0 | X11: =SUM(L11:W11) -> 0
A12: =+A11 -> 2015009 | K12: 健康保険 | L12: 17100 | M12: 17100 | N12: 20340 | O12: 20340 | P12: 23165 | Q12: 23165 | X12: =SUM(L12:W12) -> 121210
A13: =+A12 -> 2015009 | K13: 厚生年金 | L13: 32940 | M13: 32940 | N13: 32940 | O13: 32940 | P13: 37515 | Q13: 37515 | X13: =SUM(L13:W13) -> 206790
A14: =+A13 -> 2015009 | K14: 労災保険 | L14: 2052 | M14: 2058 | N14: 2058 | O14: 2088 | P14: 2076 | Q14: 2068 | X14: =SUM(L14:W14) -> 12400
A15: =+A14 -> 2015009 | K15: 雇用保険 | L15: 2257 | M15: 2264 | N15: 2264 | O15: 2297 | P15: 2284 | Q15: 2275 | X15: =SUM(L15:W15) -> 13641
A16: =+A15 -> 2015009 | K16: 粗利 | L16: =L5-L8 -> 415251 | M16: =M5-M8 -> 414038 | N16: =N5-N8 -> 410798 | O16: =O5-O8 -> 296335 | P16: =P5-P8 -> 105790 | Q16: =Q5-Q8 -> -37193 | R16: =R5-R8 -> 0 | S16: =S5-S8 -> 0 | ... X16: =X5-X8 -> 1605019
A17: 2022035 | C17: =C5+1 -> 2 | D17: 派遣 | J17: 社員 | K17: 総受注金額 | L17: =L18+L19 -> 450000 | M17: =M18+M19 -> 450000 | N17: =N18+N19 -> 450000 | O17: =O18+O19 -> 495000 | P17: =P18+P19 -> 450000 | Q17: =Q18+Q19 -> 450000 | R17: =R18+R19 -> 450000 | S17: =S18+S19 -> 405000 | ... W17: =W18+W19 -> 432000 | X17: =SUM(L17:W17) -> 5281500
A18: =+A17 -> 2022035 | K18: 派遣金額 | L18: 450000 | M18: 450000 | N18: 450000 | O18: 495000 | P18: 450000 | Q18: 450000 | R18: 450000 | S18: 405000 | T18: 439500 | U18: 427500 | V18: 382500 | W18: =2880*150 -> 432000 | X18: =SUM(L18:W18) -> 5281500
A19: =+A18 -> 2022035 | K19: 交通費 | X19: 0
A20: =+A19 -> 2022035 | K20: 総経費 | L20: =SUM(L21:L27) -> 283344 | M20: =SUM(M21:M27) -> 293058 | N20: =SUM(N21:N27) -> 296595 | O20: =SUM(O21:O27) -> 296090 | P20: =SUM(P21:P27) -> 298616 | Q20: =SUM(Q21:Q27) -> 297605 | R20: =SUM(R21:R27) -> 289269 | S20: =SUM(S21:S27) -> 292300 | ... W20: =SUM(W21:W27) -> 277260 | X20: =SUM(L20:W20) -> 3500800
A21: =+A20 -> 2022035 | K21: 賃金 | L21: 247396 | M21: 257000 | N21: 260500 | O21: 260000 | P21: 262500 | Q21: 261500 | R21: 253250 | S21: 256250 | T21: 246500 | U21: 275500 | V21: 246334 | W21: 240611 | X21: =SUM(L21:W21) -> 3067341
A22: =+A21 -> 2022035 | K22: 交通費その他 | X22: =SUM(L22:W22) -> 0
A23: =+A22 -> 2022035 | K23: 通勤定期代 | L23: 0 | M23: 0 | N23: 0 | O23: \0 | P23: \0 | Q23: 0 | R23: 0 | S23: 0 | T23: 0 | U23: 0 | V23: 0 | W23: 1563 | X23: =SUM(L23:W23) -> 1563
A24: =+A23 -> 2022035 | K24: 健康保険 | L24: 11400 | M24: 11400 | N24: 11400 | O24: 11400 | P24: 11400 | Q24: 11400 | R24: 11400 | S24: 11400 | T24: 11400 | U24: 11400 | V24: 11400 | W24: 10200 | X24: =SUM(L24:W24) -> 135600
A25: =+A24 -> 2022035 | K25: 厚生年金 | L25: 21960 | M25: 21960 | N25: 21960 | O25: 21960 | P25: 21960 | Q25: 21960 | R25: 21960 | S25: 21960 | T25: 21960 | U25: 21960 | V25: 21960 | W25: 21960 | X25: =SUM(L25:W25) -> 263520
A26: =+A25 -> 2022035 | K26: 労災保険 | L26: 1232 | M26: 1285 | N26: 1302 | O26: 1300 | P26: 1312 | Q26: 1307 | R26: 1266 | S26: 1281 | T26: 1232 | U26: 1377 | V26: 1319 | W26: 1182 | X26: =SUM(L26:W26) -> 15395
A27: =+A26 -> 2022035 | K27: 雇用保険 | L27: 1356 | M27: 1413 | N27: 1433 | O27: 1430 | P27: 1444 | Q27: 1438 | R27: 1393 | S27: 1409 | T27: 1356 | U27: 1515 | V27: 1450 | W27: 1744 | X27: =SUM(L27:W27) -> 17381
A28: =+A27 -> 2022035 | K28: 粗利 | L28: =L17-L20 -> 166656 | M28: =M17-M20 -> 156942 | N28: =N17-N20 -> 153405 | O28: =O17-O20 -> 198910 | P28: =P17-P20 -> 151384 | Q28: =Q17-Q20 -> 152395 | R28: =R17-R20 -> 160731 | S28: =S17-S20 -> 112700 | ... X28: =X17-X20 -> 1780700
A29: 2023033 | C29: =C17+1 -> 3 | D29: 派遣 | E29: 転出 | H29: 休職中 | J29: 社員 | K29: 総受注金額 | L29: =L30+L31 -> 450000 | M29: =M30+M31 -> 414000 | N29: =N30+N31 -> 315000 | O29: =O30+O31 -> 247500 | P29: =P30+P31 -> 0 | Q29: =Q30+Q31 -> 0 | R29: =R30+R31 -> 0 | S29: =S30+S31 -> 0 | ... W29: =W30+W31 -> 0 | X29: =SUM(L29:W29) -> 1426500
A30: =+A29 -> 2023033 | K30: 派遣金額 | L30: 450000 | M30: 414000 | N30: 315000 | O30: 247500 | X30: =SUM(L30:W30) -> 1426500
A31: =+A30 -> 2023033 | K31: 交通費 | X31: 0
A32: =+A31 -> 2023033 | K32: 総経費 | L32: =SUM(L33:L39) -> 308157 | M32: =SUM(M33:M39) -> 308561 | N32: =SUM(N33:N39) -> 302088 | O32: =SUM(O33:O39) -> 215373 | P32: =SUM(P33:P39) -> 0 | Q32: =SUM(Q33:Q39) -> 0 | R32: =SUM(R33:R39) -> 0 | S32: =SUM(S33:S39) -> 0 | ... W32: =SUM(W33:W39) -> 0 | X32: =SUM(L32:W32) -> 1134179
A33: =+A32 -> 2023033 | K33: 賃金 | L33: 245400 | M33: 245800 | N33: 245400 | O33: 168812 | X33: =SUM(L33:W33) -> 905412
A34: =+A33 -> 2023033 | K34: 交通費その他 | X34: =SUM(L34:W34) -> 0
A35: =+A34 -> 2023033 | K35: 通勤定期代 | L35: 23790 | M35: 23790 | N35: 17784 | O35: 8558 | X35: =SUM(L35:W35) -> 73922
A36: =+A35 -> 2023033 | K36: 健康保険 | L36: 12350 | M36: 12350 | N36: 12350 | O36: 12350 | X36: =SUM(L36:W36) -> 49400
A37: =+A36 -> 2023033 | K37: 厚生年金 | L37: 23790 | M37: 23790 | N37: 23790 | O37: 23790 | X37: =SUM(L37:W37) -> 95160
A38: =+A37 -> 2023033 | K38: 労災保険 | L38: 1346 | M38: 1348 | N38: 1316 | O38: 887 | X38: =SUM(L38:W38) -> 4897
A39: =+A38 -> 2023033 | K39: 雇用保険 | L39: 1481 | M39: 1483 | N39: 1448 | O39: 976 | X39: =SUM(L39:W39) -> 5388
A40: =+A39 -> 2023033 | K40: 粗利 | L40: =L29-L32 -> 141843 | M40: =M29-M32 -> 105439 | N40: =N29-N32 -> 12912 | O40: =O29-O32 -> 32127 | P40: =P29-P32 -> 0 | Q40: =Q29-Q32 -> 0 | R40: =R29-R32 -> 0 | S40: =S29-S32 -> 0 | ... X40: =X29-X32 -> 292321
A41: 2023019 | C41: =C29+1 -> 4 | D41: 派遣 | E41: 転出 | J41: 社員 | K41: 総受注金額 | L41: =L42+L43 -> 450000 | M41: =M42+M43 -> 427500 | N41: =N42+N43 -> 472500 | O41: =O42+O43 -> 496500 | P41: =P42+P43 -> 405000 | Q41: =Q42+Q43 -> 427500 | R41: =R42+R43 -> 486000 | S41: =S42+S43 -> 427500 | ... W41: =W42+W43 -> 0 | X41: =SUM(L41:W41) -> 4018500
A42: =+A41 -> 2023019 | K42: 派遣金額 | L42: 450000 | M42: 427500 | N42: 472500 | O42: 496500 | P42: 405000 | Q42: 427500 | R42: 486000 | S42: 427500 | T42: 426000 | X42: =SUM(L42:W42) -> 4018500
A43: =+A42 -> 2023019 | K43: 交通費 | X43: 0
A44: =+A43 -> 2023019 | K44: 総経費 | L44: =SUM(L45:L51) -> 324729 | M44: =SUM(M45:M51) -> 324729 | N44: =SUM(N45:N51) -> 324729 | O44: =SUM(O45:O51) -> 324729 | P44: =SUM(P45:P51) -> 324729 | Q44: =SUM(Q45:Q51) -> 327509 | R44: =SUM(R45:R51) -> 327509 | S44: =SUM(S45:S51) -> 327509 | ... W44: =SUM(W45:W51) -> 0 | X44: =SUM(L44:W44) -> 2934143
A45: =+A44 -> 2023019 | K45: 賃金 | L45: 256000 | M45: 256000 | N45: 256000 | O45: 256000 | P45: 256000 | Q45: 256000 | R45: 256000 | S45: 256000 | T45: 256000 | X45: =SUM(L45:W45) -> 2304000
A46: =+A45 -> 2023019 | K46: 交通費その他 | X46: =SUM(L46:W46) -> 0
A47: =+A46 -> 2023019 | K47: 通勤定期代 | L47: 29590 | M47: 29590 | N47: 29590 | O47: 29590 | P47: 29590 | Q47: 29590 | R47: 29590 | S47: 29590 | T47: 29590 | X47: =SUM(L47:W47) -> 266310
A48: =+A47 -> 2023019 | K48: 健康保険 | L48: 12350 | M48: 12350 | N48: 12350 | O48: 12350 | P48: 12350 | Q48: 13300 | R48: 13300 | S48: 13300 | T48: 13300 | X48: =SUM(L48:W48) -> 114950
A49: =+A48 -> 2023019 | K49: 厚生年金 | L49: 23790 | M49: 23790 | N49: 23790 | O49: 23790 | P49: 23790 | Q49: 25620 | R49: 25620 | S49: 25620 | T49: 25620 | X49: =SUM(L49:W49) -> 221430
A50: =+A49 -> 2023019 | K50: 労災保険 | L50: 1428 | M50: 1428 | N50: 1428 | O50: 1428 | P50: 1428 | Q50: 1428 | R50: 1428 | S50: 1428 | T50: 1648 | X50: =SUM(L50:W50) -> 13072
A51: =+A50 -> 2023019 | K51: 雇用保険 | L51: 1571 | M51: 1571 | N51: 1571 | O51: 1571 | P51: 1571 | Q51: 1571 | R51: 1571 | S51: 1571 | T51: 1813 | X51: =SUM(L51:W51) -> 14381
A52: =+A51 -> 2023019 | K52: 粗利 | L52: =L41-L44 -> 125271 | M52: =M41-M44 -> 102771 | N52: =N41-N44 -> 147771 | O52: =O41-O44 -> 171771 | P52: =P41-P44 -> 80271 | Q52: =Q41-Q44 -> 99991 | R52: =R41-R44 -> 158491 | S52: =S41-S44 -> 99991 | ... X52: =X41-X44 -> 1084357
A53: 2024007 | C53: =C41+1 -> 5 | D53: 派遣 | J53: 社員 | K53: 総受注金額 | L53: =L54+L55 -> 450000 | M53: =M54+M55 -> 382500 | N53: =N54+N55 -> 472500 | O53: =O54+O55 -> 505500 | P53: =P54+P55 -> 450000 | Q53: =Q54+Q55 -> 432000 | R53: =R54+R55 -> 499500 | S53: =S54+S55 -> 414000 | ... W53: =W54+W55 -> 432000 | X53: =SUM(L53:W53) -> 5313000
A54: =+A53 -> 2024007 | K54: 派遣金額 | L54: 450000 | M54: 382500 | N54: 472500 | O54: 505500 | P54: 450000 | Q54: 432000 | R54: 499500 | S54: 414000 | T54: 456000 | U54: 405000 | V54: 414000 | W54: =2880*150 -> 432000 | X54: =SUM(L54:W54) -> 5313000
A55: =+A54 -> 2024007 | K55: 交通費 | X55: 0
A56: =+A55 -> 2024007 | K56: 総経費 | L56: =SUM(L57:L63) -> 298565 | M56: =SUM(M57:M63) -> 298161 | N56: =SUM(N57:N63) -> 300950 | O56: =SUM(O57:O63) -> 300486 | P56: =SUM(P57:P63) -> 300486 | Q56: =SUM(Q57:Q63) -> 303670 | R56: =SUM(R57:R63) -> 303266 | S56: =SUM(S57:S63) -> 303266 | ... W56: =SUM(W57:W63) -> 310687 | X56: =SUM(L56:W56) -> 3630730
A57: =+A56 -> 2024007 | K57: 賃金 | L57: 245400 | M57: 245000 | N57: 245000 | O57: 245000 | P57: 245000 | Q57: 245400 | R57: 245000 | S57: 245000 | T57: 245400 | U57: 245000 | V57: 245800 | W57: 237975 | X57: =SUM(L57:W57) -> 2934975
A58: =+A57 -> 2024007 | K58: 交通費その他 | X58: =SUM(L58:W58) -> 0
A59: =+A58 -> 2024007 | K59: 通勤定期代 | L59: 17050 | M59: 17050 | N59: 19810 | O59: 19350 | P59: 19350 | Q59: 19350 | R59: 19350 | S59: 19350 | T59: 19350 | U59: 19350 | V59: 19350 | W59: 37626 | X59: =SUM(L59:W59) -> 246336
A60: =+A59 -> 2024007 | K60: 健康保険 | L60: 11400 | M60: 11400 | N60: 11400 | O60: 11400 | P60: 11400 | Q60: 12350 | R60: 12350 | S60: 12350 | T60: 12350 | U60: 12350 | V60: 12350 | W60: 10200 | X60: =SUM(L60:W60) -> 141300
A61: =+A60 -> 2024007 | K61: 厚生年金 | L61: 21960 | M61: 21960 | N61: 21960 | O61: 21960 | P61: 21960 | Q61: 23790 | R61: 23790 | S61: 23790 | T61: 23790 | U61: 23790 | V61: 23790 | W61: 21960 | X61: =SUM(L61:W61) -> 274500
A62: =+A61 -> 2024007 | K62: 労災保険 | L62: 1312 | M62: 1310 | N62: 1324 | O62: 1322 | P62: 1322 | Q62: 1324 | R62: 1322 | S62: 1322 | T62: 1324 | U62: 1322 | V62: 1413 | W62: 1182 | X62: =SUM(L62:W62) -> 15799
A63: =+A62 -> 2024007 | K63: 雇用保険 | L63: 1443 | M63: 1441 | N63: 1456 | O63: 1454 | P63: 1454 | Q63: 1456 | R63: 1454 | S63: 1454 | T63: 1456 | U63: 1454 | V63: 1554 | W63: 1744 | X63: =SUM(L63:W63) -> 17820
A64: =+A63 -> 2024007 | K64: 粗利 | L64: =L53-L56 -> 151435 | M64: =M53-M56 -> 84339 | N64: =N53-N56 -> 171550 | O64: =O53-O56 -> 205014 | P64: =P53-P56 -> 149514 | Q64: =Q53-Q56 -> 128330 | R64: =R53-R56 -> 196234 | S64: =S53-S56 -> 110734 | ... X64: =X53-X56 -> 1682270
A65: 2024046 | C65: =C53+1 -> 6 | D65: 派遣 | J65: 社員 | K65: 総受注金額 | L65: =L66+L67 -> 550000 | M65: =M66+M67 -> 550000 | N65: =N66+N67 -> 550000 | O65: =O66+O67 -> 550000 | P65: =P66+P67 -> 550000 | Q65: =Q66+Q67 -> 550000 | R65: =R66+R67 -> 550000 | S65: =S66+S67 -> 550000 | ... W65: =W66+W67 -> 550000 | X65: =SUM(L65:W65) -> 6600000
A66: =+A65 -> 2024046 | K66: 派遣金額 | L66: 550000 | M66: 550000 | N66: 550000 | O66: 550000 | P66: 550000 | Q66: 550000 | R66: 550000 | S66: 550000 | T66: 550000 | U66: 550000 | V66: 550000 | W66: 550000 | X66: =SUM(L66:W66) -> 6600000
A67: =+A66 -> 2024046 | K67: 交通費 | X67: 0
A68: =+A67 -> 2024046 | K68: 総経費 | L68: =SUM(L69:L75) -> 390830 | M68: =SUM(M69:M75) -> 390830 | N68: =SUM(N69:N75) -> 390830 | O68: =SUM(O69:O75) -> 393890 | P68: =SUM(P69:P75) -> 393890 | Q68: =SUM(Q69:Q75) -> 393890 | R68: =SUM(R69:R75) -> 393890 | S68: =SUM(S69:S75) -> 393890 | ... W68: =SUM(W69:W75) -> 390320 | X68: =SUM(L68:W68) -> 4714113
A69: =+A68 -> 2024046 | K69: 賃金 | L69: 320000 | M69: 320000 | N69: 320000 | O69: 320000 | P69: 320000 | Q69: 320000 | R69: 320000 | S69: 320000 | T69: 320000 | U69: 320000 | V69: 320000 | W69: 320000 | X69: =SUM(L69:W69) -> 3840000
A70: =+A69 -> 2024046 | K70: 交通費その他 | X70: =SUM(L70:W70) -> 0
A71: =+A70 -> 2024046 | K71: 通勤定期代 | L71: 20000 | M71: 20000 | N71: 20000 | O71: 20000 | P71: 20000 | Q71: 20000 | R71: 20000 | S71: 20000 | T71: 20000 | U71: 20000 | V71: 20000 | W71: 20000 | X71: =SUM(L71:W71) -> 240000
A72: =+A71 -> 2024046 | K72: 健康保険 | L72: 16150 | M72: 16150 | N72: 16150 | O72: 19210 | P72: 19210 | Q72: 19210 | R72: 19210 | S72: 19210 | T72: 19210 | U72: 19210 | V72: 19210 | W72: 16150 | X72: =SUM(L72:W72) -> 218280
A73: =+A72 -> 2024046 | K73: 厚生年金 | L73: 31110 | M73: 31110 | N73: 31110 | O73: 31110 | P73: 31110 | Q73: 31110 | R73: 31110 | S73: 31110 | T73: 31110 | U73: 31110 | V73: 31110 | W73: 31110 | X73: =SUM(L73:W73) -> 373320
A74: =+A73 -> 2024046 | K74: 労災保険 | L74: 1700 | M74: 1700 | N74: 1700 | O74: 1700 | P74: 1700 | Q74: 1700 | R74: 1700 | S74: 1700 | T74: 1700 | U74: 1700 | V74: 1787 | W74: 1020 | X74: =SUM(L74:W74) -> 19807
A75: =+A74 -> 2024046 | K75: 雇用保険 | L75: 1870 | M75: 1870 | N75: 1870 | O75: 1870 | P75: 1870 | Q75: 1870 | R75: 1870 | S75: 1870 | T75: 1870 | U75: 1870 | V75: 1966 | W75: 2040 | X75: =SUM(L75:W75) -> 22706
A76: =+A75 -> 2024046 | K76: 粗利 | L76: =L65-L68 -> 159170 | M76: =M65-M68 -> 159170 | N76: =N65-N68 -> 159170 | O76: =O65-O68 -> 156110 | P76: =P65-P68 -> 156110 | Q76: =Q65-Q68 -> 156110 | R76: =R65-R68 -> 156110 | S76: =S65-S68 -> 156110 | ... X76: =X65-X68 -> 1885887
A77: 2025001 | C77: =C65+1 -> 7 | D77: 派遣 | J77: 社員 | K77: 総受注金額 | L77: =L78+L79 -> 0 | M77: =M78+M79 -> 368550 | N77: =N78+N79 -> 496125 | O77: =O78+O79 -> 526050 | P77: =P78+P79 -> 434700 | Q77: =Q78+Q79 -> 456750 | R77: =R78+R79 -> 526050 | S77: =S78+S79 -> 474075 | ... W77: =W78+W79 -> 500000 | X77: =SUM(L77:W77) -> 5089550
A78: =+A77 -> 2025001 | K78: 派遣金額 | M78: 368550 | N78: 496125 | O78: 526050 | P78: 434700 | Q78: 456750 | R78: 526050 | S78: 474075 | T78: 453600 | U78: 425250 | V78: 428400 | W78: 500000 | X78: =SUM(L78:W78) -> 5089550
A79: =+A78 -> 2025001 | K79: 交通費 | X79: 0
A80: =+A79 -> 2025001 | K80: 総経費 | L80: =SUM(L81:L87) -> 0 | M80: =SUM(M81:M87) -> 353380 | N80: =SUM(N81:N87) -> 361051 | O80: =SUM(O81:O87) -> 360615 | P80: =SUM(P81:P87) -> 360615 | Q80: =SUM(Q81:Q87) -> 357655 | R80: =SUM(R81:R87) -> 357655 | S80: =SUM(S81:S87) -> 357655 | ... W80: =SUM(W81:W87) -> 360571 | X80: =SUM(L80:W80) -> 3940364
A81: =+A80 -> 2025001 | K81: 賃金 | M81: 290800 | N81: 292000 | O81: 290000 | P81: 290000 | Q81: 290000 | R81: 290000 | S81: 290000 | T81: 288040 | U81: 290000 | V81: 290000 | W81: 290000 | X81: =SUM(L81:W81) -> 3190840
A82: =+A81 -> 2025001 | K82: 交通費その他 | X82: =SUM(L82:W82) -> 0
A83: =+A82 -> 2025001 | K83: 通勤定期代 | M83: 12040 | N83: 18432 | O83: 20000 | P83: 20000 | Q83: 20000 | R83: 20000 | S83: 20000 | T83: 20000 | U83: 20000 | V83: 20000 | W83: 20000 | X83: =SUM(L83:W83) -> 210472
A84: =+A83 -> 2025001 | K84: 健康保険 | M84: 18080 | N84: 18080 | O84: 18080 | P84: 18080 | Q84: 16950 | R84: 16950 | S84: 16950 | T84: 16950 | U84: 16950 | V84: 16950 | W84: 18080 | X84: =SUM(L84:W84) -> 192100
A85: =+A84 -> 2025001 | K85: 厚生年金 | M85: 29280 | N85: 29280 | O85: 29280 | P85: 29280 | Q85: 27450 | R85: 27450 | S85: 27450 | T85: 27450 | U85: 27450 | V85: 27450 | W85: 29280 | X85: =SUM(L85:W85) -> 311100
A86: =+A85 -> 2025001 | K86: 労災保険 | M86: 1514 | N86: 1552 | O86: 1550 | P86: 1550 | Q86: 1550 | R86: 1550 | S86: 1550 | T86: 1540 | U86: 1550 | V86: 1637 | W86: 1529 | X86: =SUM(L86:W86) -> 17072
A87: =+A86 -> 2025001 | K87: 雇用保険 | M87: 1666 | N87: 1707 | O87: 1705 | P87: 1705 | Q87: 1705 | R87: 1705 | S87: 1705 | T87: 1694 | U87: 1705 | V87: 1801 | W87: 1682 | X87: =SUM(L87:W87) -> 18780
A88: =+A87 -> 2025001 | K88: 粗利 | L88: =L77-L80 -> 0 | M88: =M77-M80 -> 15170 | N88: =N77-N80 -> 135074 | O88: =O77-O80 -> 165435 | P88: =P77-P80 -> 74085 | Q88: =Q77-Q80 -> 99095 | R88: =R77-R80 -> 168395 | S88: =S77-S80 -> 116420 | ... X88: =X77-X80 -> 1149186
A89: 2024049 | C89: =C77+1 -> 8 | D89: 派遣 | J89: 社員 | K89: 総受注金額 | L89: =L90+L91 -> 0 | M89: =M90+M91 -> 0 | N89: =N90+N91 -> 0 | O89: =O90+O91 -> 0 | P89: =P90+P91 -> 432000 | Q89: =Q90+Q91 -> 367200 | R89: =R90+R91 -> 478080 | S89: =S90+S91 -> 367200 | ... W89: =W90+W91 -> 432000 | X89: =SUM(L89:W89) -> 3309120
A90: =+A89 -> 2024049 | K90: 派遣金額 | P90: 432000 | Q90: 367200 | R90: 478080 | S90: 367200 | T90: 429120 | U90: 407520 | V90: 396000 | W90: 432000 | X90: =SUM(L90:W90) -> 3309120
A91: =+A90 -> 2024049 | K91: 交通費 | X91: 0
A92: =+A91 -> 2024049 | K92: 総経費 | L92: =SUM(L93:L99) -> 0 | M92: =SUM(M93:M99) -> 0 | N92: =SUM(N93:N99) -> 0 | O92: =SUM(O93:O99) -> 0 | P92: =SUM(P93:P99) -> 298870 | Q92: =SUM(Q93:Q99) -> 298870 | R92: =SUM(R93:R99) -> 298870 | S92: =SUM(S93:S99) -> 298870 | ... W92: =SUM(W93:W99) -> 298870 | X92: =SUM(L92:W92) -> 2390322
A93: =+A92 -> 2024049 | K93: 賃金 | P93: 240000 | Q93: 240000 | R93: 240000 | S93: 240000 | T93: 240000 | U93: 240000 | V93: 239188 | W93: 240000 | X93: =SUM(L93:W93) -> 1919188
A94: =+A93 -> 2024049 | K94: 交通費その他 | X94: =SUM(L94:W94) -> 0
A95: =+A94 -> 2024049 | K95: 通勤定期代 | P95: 20000 | Q95: 20000 | R95: 20000 | S95: 20000 | T95: 20000 | U95: 20000 | V95: 20000 | W95: 20000 | X95: =SUM(L95:W95) -> 160000
A96: =+A95 -> 2024049 | K96: 健康保険 | P96: 12350 | Q96: 12350 | R96: 12350 | S96: 12350 | T96: 12350 | U96: 12350 | V96: 12350 | W96: 12350 | X96: =SUM(L96:W96) -> 98800
A97: =+A96 -> 2024049 | K97: 厚生年金 | P97: 23790 | Q97: 23790 | R97: 23790 | S97: 23790 | T97: 23790 | U97: 23790 | V97: 23790 | W97: 23790 | X97: =SUM(L97:W97) -> 190320
A98: =+A97 -> 2024049 | K98: 労災保険 | P98: 1300 | Q98: 1300 | R98: 1300 | S98: 1300 | T98: 1300 | U98: 1300 | V98: 1383 | W98: 1300 | X98: =SUM(L98:W98) -> 10483
A99: =+A98 -> 2024049 | K99: 雇用保険 | P99: 1430 | Q99: 1430 | R99: 1430 | S99: 1430 | T99: 1430 | U99: 1430 | V99: 1521 | W99: 1430 | X99: =SUM(L99:W99) -> 11531
A100: =+A99 -> 2024049 | K100: 粗利 | L100: =L89-L92 -> 0 | M100: =M89-M92 -> 0 | N100: =N89-N92 -> 0 | O100: =O89-O92 -> 0 | P100: =P89-P92 -> 133130 | Q100: =Q89-Q92 -> 68330 | R100: =R89-R92 -> 179210 | S100: =S89-S92 -> 68330 | ... X100: =X89-X92 -> 918798
...

Sheet その他受託
A1: 社員番号 | B1: 氏名 | C1: No | D1: 派遣/請負 | E1: 担当 | F1: 氏名 | G1: 派遣先部署 | H1: 作業名 | I1: 契約先 | J1: 外注会社 | K1: 売上単価 (支払単価） 【≒粗利】 | L1: 4月 | M1: 5月 | N1: 6月 | O1: 7月 | P1: 8月 | Q1: 9月 | R1: 10月 | S1: 11月 | T1: 12月 | U1: 1月 | V1: 2月 | W1: 3月 | X1: 合計
C2: その他受託 | K2: 売上 | L2: =L54 -> 4344000 | M2: =M54 -> 1758500 | N2: =N54 -> 3990000 | O2: =O54 -> 0 | P2: =P54 -> 9612750 | Q2: =Q54 -> 3673250 | R2: =R54 -> 866250 | S2: =S54 -> 0 | ... W2: =W54 -> 15758000 | X2: =SUM(L2:W2) -> 78285114
K3: 仕入 | L3: =L55 -> 4000000 | M3: =M55 -> 1650000 | N3: =N55 -> 3800000 | O3: =O55 -> 0 | P3: =P55 -> 9155000 | Q3: =Q55 -> 3445000 | R3: =R55 -> 825000 | S3: =S55 -> 0 | ... W3: =W55 -> 14900000 | X3: =SUM(L3:W3) -> 73864661
K4: 粗利 | L4: =L2-L3 -> 344000 | M4: =M2-M3 -> 108500 | N4: =N2-N3 -> 190000 | O4: =O2-O3 -> 0 | P4: =P2-P3 -> 457750 | Q4: =Q2-Q3 -> 228250 | R4: =R2-R3 -> 41250 | S4: =S2-S3 -> 0 | ... W4: =W2-W3 -> 858000 | X4: =SUM(L4:W4) -> 4420453
C5: 1 | D5: 委任 | K5: 総受注金額 | L5: =SUM(L6:L8) -> 4200000 | M5: =SUM(M6:M8) -> 1732500 | N5: =SUM(N6:N8) -> 3990000 | O5: =SUM(O6:O8) -> 0 | P5: =SUM(P6:P8) -> 9612750 | Q5: =SUM(Q6:Q8) -> 3617250 | R5: =SUM(R6:R8) -> 866250 | S5: =SUM(S6:S8) -> 0 | ... W5: =SUM(W6:W8) -> 10080000 | X5: =SUM(L5:W5) -> 42351750
A6: =+A5 -> 0 | B6: =+B5 -> 0 | K6: 委任金額 | L6: 4200000 | M6: 1732500 | N6: 3990000 | O6: 0 | P6: 9612750 | Q6: 3617250 | R6: =R10*1.05 -> 866250 | S6: 0 | T6: 2268000 | U6: 0 | W6: =W10*1.05 -> 10080000 | X6: =SUM(L6:W6) -> 36366750
A7: =+A6 -> 0 | B7: =+B6 -> 0 | T7: 5985000 | X7: =SUM(L7:W7) -> 5985000
X8: =SUM(L8:W8) -> 0
A9: =+A7 -> 0 | B9: =+B7 -> 0 | K9: 総経費 | L9: =SUM(L10:L16) -> 4000000 | M9: =SUM(M10:M16) -> 1650000 | N9: =SUM(N10:N16) -> 3800000 | O9: =SUM(O10:O16) -> 0 | P9: =SUM(P10:P16) -> 9155000 | Q9: =SUM(Q10:Q16) -> 3445000 | R9: =SUM(R10:R16) -> 825000 | S9: =SUM(S10:S16) -> 0 | ... W9: =SUM(W10:W16) -> 9600000 | X9: =SUM(L9:W9) -> 40335000
A10: =+A9 -> 0 | B10: =+B9 -> 0 | K10: 外注費 | L10: 4000000 | M10: 1650000 | N10: 3800000 | O10: 0 | P10: =3800000+2475000+2880000 -> 9155000 | Q10: =825000+1900000+720000 -> 3445000 | R10: 825000 | S10: 0 | T10: 2160000 | U10: 0 | W10: 9600000 | X10: =SUM(L10:W10) -> 34635000
A11: =+A10 -> 0 | B11: =+B10 -> 0 | T11: 5700000 | X11: =SUM(L11:W11) -> 5700000
A12: =+A11 -> 0 | B12: =+B11 -> 0 | X12: =SUM(L12:W12) -> 0
A13: =+A12 -> 0 | B13: =+B12 -> 0 | X13: =SUM(L13:W13) -> 0
A14: =+A13 -> 0 | B14: =+B13 -> 0 | X14: =SUM(L14:W14) -> 0
A15: =+A14 -> 0 | B15: =+B14 -> 0 | X15: =SUM(L15:W15) -> 0
A16: =+A15 -> 0 | B16: =+B15 -> 0 | X16: =SUM(L16:W16) -> 0
A17: =+A16 -> 0 | B17: =+B16 -> 0 | K17: 粗利 | L17: =L5-L9 -> 200000 | M17: =M5-M9 -> 82500 | N17: =N5-N9 -> 190000 | O17: =O5-O9 -> 0 | P17: =P5-P9 -> 457750 | Q17: =Q5-Q9 -> 172250 | R17: =R5-R9 -> 41250 | S17: =S5-S9 -> 0 | ... X17: =X5-X9 -> 2016750
C18: =C5+1 -> 2 | D18: 委任 | K18: 総受注金額 | L18: =L19+L20 -> 144000 | M18: =M19+M20 -> 26000 | N18: =N19+N20 -> 0 | O18: =O19+O20 -> 0 | P18: =P19+P20 -> 0 | Q18: =Q19+Q20 -> 56000 | R18: =R19+R20 -> 0 | S18: =S19+S20 -> 0 | ... W18: =W19+W20 -> 78000 | X18: =SUM(L18:W18) -> 554750
A19: =+A18 -> 0 | B19: =+B18 -> 0 | K19: 委任金額 | L19: 144000 | M19: 26000 | N19: 0 | O19: 0 | P19: 0 | Q19: 56000 | R19: 0 | S19: 0 | T19: 0 | U19: 146750 | V19: 104000 | W19: 78000 | X19: =SUM(L19:W19) -> 554750
A20: =+A19 -> 0 | B20: =+B19 -> 0 | X20: 0
A21: =+A20 -> 0 | B21: =+B20 -> 0 | K21: 総経費 | L21: =SUM(L22:L28) -> 0 | M21: =SUM(M22:M28) -> 0 | N21: =SUM(N22:N28) -> 0 | O21: =SUM(O22:O28) -> 0 | P21: =SUM(P22:P28) -> 0 | Q21: =SUM(Q22:Q28) -> 0 | R21: =SUM(R22:R28) -> 0 | S21: =SUM(S22:S28) -> 0 | ... W21: =SUM(W22:W28) -> 0 | X21: =SUM(L21:W21) -> 0
A22: =+A21 -> 0 | B22: =+B21 -> 0 | K22: 外注費 | X22: =SUM(L22:W22) -> 0
A23: =+A22 -> 0 | B23: =+B22 -> 0 | X23: =SUM(L23:W23) -> 0
A24: =+A23 -> 0 | B24: =+B23 -> 0 | X24: =SUM(L24:W24) -> 0
A25: =+A24 -> 0 | B25: =+B24 -> 0 | X25: =SUM(L25:W25) -> 0
A26: =+A25 -> 0 | B26: =+B25 -> 0 | X26: =SUM(L26:W26) -> 0
A27: =+A26 -> 0 | B27: =+B26 -> 0 | X27: =SUM(L27:W27) -> 0
A28: =+A27 -> 0 | B28: =+B27 -> 0 | X28: =SUM(L28:W28) -> 0
A29: =+A28 -> 0 | B29: =+B28 -> 0 | K29: 粗利 | L29: =L18-L21 -> 144000 | M29: =M18-M21 -> 26000 | N29: =N18-N21 -> 0 | O29: =O18-O21 -> 0 | P29: =P18-P21 -> 0 | Q29: =Q18-Q21 -> 56000 | R29: =R18-R21 -> 0 | S29: =S18-S21 -> 0 | ... X29: =X18-X21 -> 554750
C30: =C18+1 -> 3 | K30: 総受注金額 | L30: =L31+L32 -> 0 | M30: =M31+M32 -> 0 | N30: =N31+N32 -> 0 | O30: =O31+O32 -> 0 | P30: =P31+P32 -> 0 | Q30: =Q31+Q32 -> 0 | R30: =R31+R32 -> 0 | S30: =S31+S32 -> 0 | ... W30: =W31+W32 -> 0 | X30: =SUM(L30:W30) -> 27278614
A31: =+A30 -> 0 | B31: =+B30 -> 0 | K31: 委任金額 | U31: 27278614 | X31: =SUM(L31:W31) -> 27278614
A32: =+A31 -> 0 | B32: =+B31 -> 0 | X32: 0
A33: =+A32 -> 0 | B33: =+B32 -> 0 | K33: 総経費 | L33: =SUM(L34:L40) -> 0 | M33: =SUM(M34:M40) -> 0 | N33: =SUM(N34:N40) -> 0 | O33: =SUM(O34:O40) -> 0 | P33: =SUM(P34:P40) -> 0 | Q33: =SUM(Q34:Q40) -> 0 | R33: =SUM(R34:R40) -> 0 | S33: =SUM(S34:S40) -> 0 | ... W33: =SUM(W34:W40) -> 0 | X33: =SUM(L33:W33) -> 25979661
A34: =+A33 -> 0 | B34: =+B33 -> 0 | K34: 外注費 | U34: 25979661 | X34: =SUM(L34:W34) -> 25979661
A35: =+A34 -> 0 | B35: =+B34 -> 0 | X35: =SUM(L35:W35) -> 0
A36: =+A35 -> 0 | B36: =+B35 -> 0 | X36: =SUM(L36:W36) -> 0
A37: =+A36 -> 0 | B37: =+B36 -> 0 | X37: =SUM(L37:W37) -> 0
A38: =+A37 -> 0 | B38: =+B37 -> 0 | X38: =SUM(L38:W38) -> 0
A39: =+A38 -> 0 | B39: =+B38 -> 0 | X39: =SUM(L39:W39) -> 0
A40: =+A39 -> 0 | B40: =+B39 -> 0 | X40: =SUM(L40:W40) -> 0
A41: =+A40 -> 0 | B41: =+B40 -> 0 | K41: 粗利 | L41: =L30-L33 -> 0 | M41: =M30-M33 -> 0 | N41: =N30-N33 -> 0 | O41: =O30-O33 -> 0 | P41: =P30-P33 -> 0 | Q41: =Q30-Q33 -> 0 | R41: =R30-R33 -> 0 | S41: =S30-S33 -> 0 | ... X41: =X30-X33 -> 1298953
C42: =C30+1 -> 4 | K42: 総受注金額 | L42: =L43+L44 -> 0 | M42: =M43+M44 -> 0 | N42: =N43+N44 -> 0 | O42: =O43+O44 -> 0 | P42: =P43+P44 -> 0 | Q42: =Q43+Q44 -> 0 | R42: =R43+R44 -> 0 | S42: =S43+S44 -> 0 | ... W42: =W43+W44 -> 5600000 | X42: =SUM(L42:W42) -> 8100000
A43: =+A42 -> 0 | B43: =+B42 -> 0 | K43: 委任金額 | V43: 2500000 | W43: 2500000 | X43: =SUM(L43:W43) -> 5000000
A44: =+A43 -> 0 | B44: =+B43 -> 0 | W44: 3100000 | X44: =SUM(L44:W44) -> 3100000
A45: =+A44 -> 0 | B45: =+B44 -> 0 | K45: 総経費 | L45: =SUM(L46:L52) -> 0 | M45: =SUM(M46:M52) -> 0 | N45: =SUM(N46:N52) -> 0 | O45: =SUM(O46:O52) -> 0 | P45: =SUM(P46:P52) -> 0 | Q45: =SUM(Q46:Q52) -> 0 | R45: =SUM(R46:R52) -> 0 | S45: =SUM(S46:S52) -> 0 | ... W45: =SUM(W46:W52) -> 5300000 | X45: =SUM(L45:W45) -> 7550000
A46: =+A45 -> 0 | B46: =+B45 -> 0 | K46: 外注費 | V46: =V43*0.9 -> 2250000 | W46: =W43*0.9 -> 2250000 | X46: =SUM(L46:W46) -> 4500000
A47: =+A46 -> 0 | B47: =+B46 -> 0 | W47: 3050000 | X47: =SUM(L47:W47) -> 3050000
A48: =+A47 -> 0 | B48: =+B47 -> 0 | X48: =SUM(L48:W48) -> 0
A49: =+A48 -> 0 | B49: =+B48 -> 0 | X49: =SUM(L49:W49) -> 0
A50: =+A49 -> 0 | B50: =+B49 -> 0 | X50: =SUM(L50:W50) -> 0
A51: =+A50 -> 0 | B51: =+B50 -> 0 | X51: =SUM(L51:W51) -> 0
A52: =+A51 -> 0 | B52: =+B51 -> 0 | X52: =SUM(L52:W52) -> 0
A53: =+A52 -> 0 | B53: =+B52 -> 0 | K53: 粗利 | L53: =L42-L45 -> 0 | M53: =M42-M45 -> 0 | N53: =N42-N45 -> 0 | O53: =O42-O45 -> 0 | P53: =P42-P45 -> 0 | Q53: =Q42-Q45 -> 0 | R53: =R42-R45 -> 0 | S53: =S42-S45 -> 0 | ... X53: =X42-X45 -> 550000
C54: =C2 -> その他受託 | K54: 売上 | L54: =L5+L18+L30+L42 -> 4344000 | M54: =M5+M18+M30+M42 -> 1758500 | N54: =N5+N18+N30+N42 -> 3990000 | O54: =O5+O18+O30+O42 -> 0 | P54: =P5+P18+P30+P42 -> 9612750 | Q54: =Q5+Q18+Q30+Q42 -> 3673250 | R54: =R5+R18+R30+R42 -> 866250 | S54: =S5+S18+S30+S42 -> 0 | ... W54: =W5+W18+W30+W42 -> 15758000 | X54: =SUM(L54:W54) -> 78285114
K55: 仕入 | L55: =L9+L21+L33+L45 -> 4000000 | M55: =M9+M21+M33+M45 -> 1650000 | N55: =N9+N21+N33+N45 -> 3800000 | O55: =O9+O21+O33+O45 -> 0 | P55: =P9+P21+P33+P45 -> 9155000 | Q55: =Q9+Q21+Q33+Q45 -> 3445000 | R55: =R9+R21+R33+R45 -> 825000 | S55: =S9+S21+S33+S45 -> 0 | ... W55: =W9+W21+W33+W45 -> 14900000 | X55: =SUM(L55:W55) -> 73864661
K56: 粗利 | L56: =L54-L55 -> 344000 | M56: =M54-M55 -> 108500 | N56: =N54-N55 -> 190000 | O56: =O54-O55 -> 0 | P56: =P54-P55 -> 457750 | Q56: =Q54-Q55 -> 228250 | R56: =R54-R55 -> 41250 | S56: =S54-S55 -> 0 | ... W56: =W54-W55 -> 858000 | X56: =SUM(L56:W56) -> 4420453
K57: Q売上 | L57: =SUM(L54:N54) -> 10092500 | O57: =SUM(O54:Q54) -> 13286000 | R57: =SUM(R54:T54) -> 9119250 | U57: =SUM(U54:W54) -> 45787364 | X57: =SUM(L57:W57) -> 78285114
K58: Q粗利 | L58: =SUM(L56:N56) -> 642500 | O58: =SUM(O56:Q56) -> 686000 | R58: =SUM(R56:T56) -> 434250 | U58: =SUM(U56:W56) -> 2657703 | X58: =SUM(L58:W58) -> 4420453

Sheet その他常駐
A1: 社員番号 | B1: 氏名 | C1: No | D1: 派遣/請負 | E1: 担当 | F1: 氏名 | G1: 派遣先部署 | H1: 作業名 | I1: 契約先 | J1: 外注会社 | K1: 売上単価 (支払単価） 【≒粗利】 | L1: 4月 | M1: 5月 | N1: 6月 | O1: 7月 | P1: 8月 | Q1: 9月 | R1: 10月 | S1: 11月 | T1: 12月 | U1: 1月 | V1: 2月 | W1: 3月 | X1: 合計
C2: その他常駐 | K2: 売上 | L2: =L53 -> 0 | M2: =M53 -> 0 | N2: =N53 -> 0 | O2: =O53 -> 0 | P2: =P53 -> 0 | Q2: =Q53 -> 0 | R2: =R53 -> 0 | S2: =S53 -> 0 | ... W2: =W53 -> 0 | X2: =SUM(L2:W2) -> 0
K3: 仕入 | L3: =L54 -> 0 | M3: =M54 -> 0 | N3: =N54 -> 0 | O3: =O54 -> 0 | P3: =P54 -> 0 | Q3: =Q54 -> 0 | R3: =R54 -> 0 | S3: =S54 -> 0 | ... W3: =W54 -> 0 | X3: =SUM(L3:W3) -> 0
K4: 粗利 | L4: =L2-L3 -> 0 | M4: =M2-M3 -> 0 | N4: =N2-N3 -> 0 | O4: =O2-O3 -> 0 | P4: =P2-P3 -> 0 | Q4: =Q2-Q3 -> 0 | R4: =R2-R3 -> 0 | S4: =S2-S3 -> 0 | ... W4: =W2-W3 -> 0 | X4: =SUM(L4:W4) -> 0
C5: 1 | K5: 総受注金額 | L5: =L6+L7 -> 0 | M5: =M6+M7 -> 0 | N5: =N6+N7 -> 0 | O5: =O6+O7 -> 0 | P5: =P6+P7 -> 0 | Q5: =Q6+Q7 -> 0 | R5: =R6+R7 -> 0 | S5: =S6+S7 -> 0 | ... W5: =W6+W7 -> 0 | X5: =SUM(L5:W5) -> 0
A6: =+A5 -> 0 | B6: =+B5 -> 0 | K6: 派遣金額 | X6: =SUM(L6:W6) -> 0
A7: =+A6 -> 0 | B7: =+B6 -> 0 | K7: 交通費 | X7: 0
A8: =+A7 -> 0 | B8: =+B7 -> 0 | K8: 総経費 | L8: =SUM(L9:L15) -> 0 | M8: =SUM(M9:M15) -> 0 | N8: =SUM(N9:N15) -> 0 | O8: =SUM(O9:O15) -> 0 | P8: =SUM(P9:P15) -> 0 | Q8: =SUM(Q9:Q15) -> 0 | R8: =SUM(R9:R15) -> 0 | S8: =SUM(S9:S15) -> 0 | ... W8: =SUM(W9:W15) -> 0 | X8: =SUM(L8:W8) -> 0
A9: =+A8 -> 0 | B9: =+B8 -> 0 | K9: 賃金 | X9: =SUM(L9:W9) -> 0
A10: =+A9 -> 0 | B10: =+B9 -> 0 | K10: 交通費その他 | X10: =SUM(L10:W10) -> 0
A11: =+A10 -> 0 | B11: =+B10 -> 0 | K11: 通勤定期代 | X11: =SUM(L11:W11) -> 0
A12: =+A11 -> 0 | B12: =+B11 -> 0 | K12: 健康保険 | X12: =SUM(L12:W12) -> 0
A13: =+A12 -> 0 | B13: =+B12 -> 0 | K13: 厚生年金 | X13: =SUM(L13:W13) -> 0
A14: =+A13 -> 0 | B14: =+B13 -> 0 | K14: 労災保険 | X14: =SUM(L14:W14) -> 0
A15: =+A14 -> 0 | B15: =+B14 -> 0 | K15: 雇用保険 | X15: =SUM(L15:W15) -> 0
A16: =+A15 -> 0 | B16: =+B15 -> 0 | K16: 粗利 | L16: =L5-L8 -> 0 | M16: =M5-M8 -> 0 | N16: =N5-N8 -> 0 | O16: =O5-O8 -> 0 | P16: =P5-P8 -> 0 | Q16: =Q5-Q8 -> 0 | R16: =R5-R8 -> 0 | S16: =S5-S8 -> 0 | ... X16: =X5-X8 -> 0
C17: =C5+1 -> 2 | K17: 総受注金額 | L17: =L18+L19 -> 0 | M17: =M18+M19 -> 0 | N17: =N18+N19 -> 0 | O17: =O18+O19 -> 0 | P17: =P18+P19 -> 0 | Q17: =Q18+Q19 -> 0 | R17: =R18+R19 -> 0 | S17: =S18+S19 -> 0 | ... W17: =W18+W19 -> 0 | X17: =SUM(L17:W17) -> 0
A18: =+A17 -> 0 | B18: =+B17 -> 0 | K18: 派遣金額 | X18: =SUM(L18:W18) -> 0
A19: =+A18 -> 0 | B19: =+B18 -> 0 | K19: 交通費 | X19: 0
A20: =+A19 -> 0 | B20: =+B19 -> 0 | K20: 総経費 | L20: =SUM(L21:L27) -> 0 | M20: =SUM(M21:M27) -> 0 | N20: =SUM(N21:N27) -> 0 | O20: =SUM(O21:O27) -> 0 | P20: =SUM(P21:P27) -> 0 | Q20: =SUM(Q21:Q27) -> 0 | R20: =SUM(R21:R27) -> 0 | S20: =SUM(S21:S27) -> 0 | ... W20: =SUM(W21:W27) -> 0 | X20: =SUM(L20:W20) -> 0
A21: =+A20 -> 0 | B21: =+B20 -> 0 | K21: 賃金 | X21: =SUM(L21:W21) -> 0
A22: =+A21 -> 0 | B22: =+B21 -> 0 | K22: 交通費その他 | X22: =SUM(L22:W22) -> 0
A23: =+A22 -> 0 | B23: =+B22 -> 0 | K23: 通勤定期代 | X23: =SUM(L23:W23) -> 0
A24: =+A23 -> 0 | B24: =+B23 -> 0 | K24: 健康保険 | X24: =SUM(L24:W24) -> 0
A25: =+A24 -> 0 | B25: =+B24 -> 0 | K25: 厚生年金 | X25: =SUM(L25:W25) -> 0
A26: =+A25 -> 0 | B26: =+B25 -> 0 | K26: 労災保険 | X26: =SUM(L26:W26) -> 0
A27: =+A26 -> 0 | B27: =+B26 -> 0 | K27: 雇用保険 | X27: =SUM(L27:W27) -> 0
A28: =+A27 -> 0 | B28: =+B27 -> 0 | K28: 粗利 | L28: =L17-L20 -> 0 | M28: =M17-M20 -> 0 | N28: =N17-N20 -> 0 | O28: =O17-O20 -> 0 | P28: =P17-P20 -> 0 | Q28: =Q17-Q20 -> 0 | R28: =R17-R20 -> 0 | S28: =S17-S20 -> 0 | ... X28: =X17-X20 -> 0
C29: =C17+1 -> 3 | K29: 総受注金額 | L29: =L30+L31 -> 0 | M29: =M30+M31 -> 0 | N29: =N30+N31 -> 0 | O29: =O30+O31 -> 0 | P29: =P30+P31 -> 0 | Q29: =Q30+Q31 -> 0 | R29: =R30+R31 -> 0 | S29: =S30+S31 -> 0 | ... W29: =W30+W31 -> 0 | X29: =SUM(L29:W29) -> 0
A30: =+A29 -> 0 | B30: =+B29 -> 0 | K30: 派遣金額 | X30: =SUM(L30:W30) -> 0
A31: =+A30 -> 0 | B31: =+B30 -> 0 | K31: 交通費 | X31: 0
A32: =+A31 -> 0 | B32: =+B31 -> 0 | K32: 総経費 | L32: =SUM(L33:L39) -> 0 | M32: =SUM(M33:M39) -> 0 | N32: =SUM(N33:N39) -> 0 | O32: =SUM(O33:O39) -> 0 | P32: =SUM(P33:P39) -> 0 | Q32: =SUM(Q33:Q39) -> 0 | R32: =SUM(R33:R39) -> 0 | S32: =SUM(S33:S39) -> 0 | ... W32: =SUM(W33:W39) -> 0 | X32: =SUM(L32:W32) -> 0
A33: =+A32 -> 0 | B33: =+B32 -> 0 | K33: 賃金 | X33: =SUM(L33:W33) -> 0
A34: =+A33 -> 0 | B34: =+B33 -> 0 | K34: 交通費その他 | X34: =SUM(L34:W34) -> 0
A35: =+A34 -> 0 | B35: =+B34 -> 0 | K35: 通勤定期代 | X35: =SUM(L35:W35) -> 0
A36: =+A35 -> 0 | B36: =+B35 -> 0 | K36: 健康保険 | X36: =SUM(L36:W36) -> 0
A37: =+A36 -> 0 | B37: =+B36 -> 0 | K37: 厚生年金 | X37: =SUM(L37:W37) -> 0
A38: =+A37 -> 0 | B38: =+B37 -> 0 | K38: 労災保険 | X38: =SUM(L38:W38) -> 0
A39: =+A38 -> 0 | B39: =+B38 -> 0 | K39: 雇用保険 | X39: =SUM(L39:W39) -> 0
A40: =+A39 -> 0 | B40: =+B39 -> 0 | K40: 粗利 | L40: =L29-L32 -> 0 | M40: =M29-M32 -> 0 | N40: =N29-N32 -> 0 | O40: =O29-O32 -> 0 | P40: =P29-P32 -> 0 | Q40: =Q29-Q32 -> 0 | R40: =R29-R32 -> 0 | S40: =S29-S32 -> 0 | ... X40: =X29-X32 -> 0
C41: =C29+1 -> 4 | K41: 総受注金額 | L41: =L42+L43 -> 0 | M41: =M42+M43 -> 0 | N41: =N42+N43 -> 0 | O41: =O42+O43 -> 0 | P41: =P42+P43 -> 0 | Q41: =Q42+Q43 -> 0 | R41: =R42+R43 -> 0 | S41: =S42+S43 -> 0 | ... W41: =W42+W43 -> 0 | X41: =SUM(L41:W41) -> 0
A42: =+A41 -> 0 | B42: =+B41 -> 0 | K42: 派遣金額 | X42: =SUM(L42:W42) -> 0
A43: =+A42 -> 0 | B43: =+B42 -> 0 | K43: 交通費 | X43: 0
A44: =+A43 -> 0 | B44: =+B43 -> 0 | K44: 総経費 | L44: =SUM(L45:L51) -> 0 | M44: =SUM(M45:M51) -> 0 | N44: =SUM(N45:N51) -> 0 | O44: =SUM(O45:O51) -> 0 | P44: =SUM(P45:P51) -> 0 | Q44: =SUM(Q45:Q51) -> 0 | R44: =SUM(R45:R51) -> 0 | S44: =SUM(S45:S51) -> 0 | ... W44: =SUM(W45:W51) -> 0 | X44: =SUM(L44:W44) -> 0
A45: =+A44 -> 0 | B45: =+B44 -> 0 | K45: 賃金 | X45: =SUM(L45:W45) -> 0
A46: =+A45 -> 0 | B46: =+B45 -> 0 | K46: 交通費その他 | X46: =SUM(L46:W46) -> 0
A47: =+A46 -> 0 | B47: =+B46 -> 0 | K47: 通勤定期代 | X47: =SUM(L47:W47) -> 0
A48: =+A47 -> 0 | B48: =+B47 -> 0 | K48: 健康保険 | X48: =SUM(L48:W48) -> 0
A49: =+A48 -> 0 | B49: =+B48 -> 0 | K49: 厚生年金 | X49: =SUM(L49:W49) -> 0
A50: =+A49 -> 0 | B50: =+B49 -> 0 | K50: 労災保険 | X50: =SUM(L50:W50) -> 0
A51: =+A50 -> 0 | B51: =+B50 -> 0 | K51: 雇用保険 | X51: =SUM(L51:W51) -> 0
A52: =+A51 -> 0 | B52: =+B51 -> 0 | K52: 粗利 | L52: =L41-L44 -> 0 | M52: =M41-M44 -> 0 | N52: =N41-N44 -> 0 | O52: =O41-O44 -> 0 | P52: =P41-P44 -> 0 | Q52: =Q41-Q44 -> 0 | R52: =R41-R44 -> 0 | S52: =S41-S44 -> 0 | ... X52: =X41-X44 -> 0
C53: =C2 -> その他常駐 | K53: 売上 | L53: =L5+L17+L29+L41 -> 0 | M53: =M5+M17+M29+M41 -> 0 | N53: =N5+N17+N29+N41 -> 0 | O53: =O5+O17+O29+O41 -> 0 | P53: =P5+P17+P29+P41 -> 0 | Q53: =Q5+Q17+Q29+Q41 -> 0 | R53: =R5+R17+R29+R41 -> 0 | S53: =S5+S17+S29+S41 -> 0 | ... W53: =W5+W17+W29+W41 -> 0 | X53: =SUM(L53:W53) -> 0
K54: 仕入 | L54: =L8+L20+L32+L44 -> 0 | M54: =M8+M20+M32+M44 -> 0 | N54: =N8+N20+N32+N44 -> 0 | O54: =O8+O20+O32+O44 -> 0 | P54: =P8+P20+P32+P44 -> 0 | Q54: =Q8+Q20+Q32+Q44 -> 0 | R54: =R8+R20+R32+R44 -> 0 | S54: =S8+S20+S32+S44 -> 0 | ... W54: =W8+W20+W32+W44 -> 0 | X54: =SUM(L54:W54) -> 0
K55: 粗利 | L55: =L53-L54 -> 0 | M55: =M53-M54 -> 0 | N55: =N53-N54 -> 0 | O55: =O53-O54 -> 0 | P55: =P53-P54 -> 0 | Q55: =Q53-Q54 -> 0 | R55: =R53-R54 -> 0 | S55: =S53-S54 -> 0 | ... W55: =W53-W54 -> 0 | X55: =SUM(L55:W55) -> 0
K56: Q売上 | L56: =SUM(L53:N53) -> 0 | O56: =SUM(O53:Q53) -> 0 | R56: =SUM(R53:T53) -> 0 | U56: =SUM(U53:W53) -> 0 | X56: =SUM(L56:W56) -> 0
K57: Q粗利 | L57: =SUM(L55:N55) -> 0 | O57: =SUM(O55:Q55) -> 0 | R57: =SUM(R55:T55) -> 0 | U57: =SUM(U55:W55) -> 0 | X57: =SUM(L57:W57) -> 0
