Workbook

Sheet まとめ
B1: FS/首都圏合計 | D1: 4月 | F1: 5月 | H1: 6月 | J1: 7月 | L1: 8月 | N1: 9月 | P1: 10月 | R1: 11月 | T1: 12月 | V1: 1月 | X1: 2月 | Z1: 3月 | AB1: 通期合計
B2: 首都圏売上合計 | E2: =E8 -> 20269500 | G2: =G8 -> 20606000 | I2: =I8 -> 19251500 | K2: =K8 -> 19450500 | M2: =M8 -> 17507500 | O2: =O8 -> 17644500 | Q2: =Q8 -> 17396500 | S2: =S8 -> 17075000 | U2: =U8 -> 17845500 | W2: =W8 -> 15680500 | Y2: =Y8 -> 14660000 | AA2: =AA8 -> 16704000 | AC2: =SUM(E2:AA2) -> 214091000
B3: 原価 | E3: =E14 -> 13542758 | G3: =G14 -> 12925580 | I3: =I14 -> 12936353 | K3: =K14 -> 13029791 | M3: =M14 -> 12910002 | O3: =O14 -> 12999923 | Q3: =Q14 -> 12386306 | S3: =S14 -> 12251513 | U3: =U14 -> 12373396 | W3: =W14 -> 11623373 | Y3: =Y14 -> 11686532 | AA3: =AA14 -> 8945842 | AC3: =SUM(E3:AA3) -> 1.4761137e+08
B4: 粗利 | E4: =E2-E3 -> 6726742 | G4: =G2-G3 -> 7680420 | I4: =I2-I3 -> 6315147 | K4: =K2-K3 -> 6420709 | M4: =M2-M3 -> 4597498 | O4: =O2-O3 -> 4644577 | Q4: =Q2-Q3 -> 5010194 | S4: =S2-S3 -> 4823487 | U4: =U2-U3 -> 5472103.6 | W4: =W2-W3 -> 4057127 | Y4: =Y2-Y3 -> 2973468 | AA4: =AA2-AA3 -> 7758158 | AC4: =SUM(E4:AA4) -> 66479631
R5: =AVERAGE(D12,F12,H12,J12,L12,N12,P12,R12) -> 1
B6: インシデント対応
B7: 区分 | C7: 単価 | D7: 件数 | E7: 金額 | F7: 件数 | G7: 金額 | H7: 件数 | I7: 金額 | J7: 件数 | K7: 金額 | L7: 件数 | M7: 金額 | N7: 件数 | O7: 金額 | P7: 件数 | Q7: 金額 | R7: 件数 | S7: 金額 | T7: 件数 | U7: 金額 | V7: 件数 | W7: 金額 | X7: 件数 | Y7: 金額 | Z7: 件数 | AA7: 金額 | AB7: 件数 | AC7: 金額
B8: 売上合計 | D8: =SUM(D9:D13) -> 525.5 | E8: =SUM(E9:E13) -> 20269500 | F8: =SUM(F9:F13) -> 535 | G8: =SUM(G9:G13) -> 20606000 | H8: =SUM(H9:H13) -> 495.5 | I8: =SUM(I9:I13) -> 19251500 | J8: =SUM(J9:J13) -> 500.5 | K8: =SUM(K9:K13) -> 19450500 | L8: =SUM(L9:L13) -> 445.5 | M8: 17507500 | N8: =SUM(N9:N13) -> 450.5 | O8: =SUM(O9:O13) -> 17644500 | P8: =SUM(P9:P13) -> 442.5 | Q8: =SUM(Q9:Q13) -> 17396500 | R8: =SUM(R9:R13) -> 434 | S8: =SUM(S9:S13) -> 17075000 | T8: =SUM(T9:T13) -> 455.5 | U8: =SUM(U9:U13) -> 17845500 | ... AA8: =SUM(AA9:AA13) -> 16704000 | AB8: =D8+F8+H8+J8+L8+N8+P8+R8+T8+V8+X8+Z8 -> 5467 | AC8: =E8+G8+I8+K8+M8+O8+Q8+S8+U8+W8+Y8+AA8 -> 214091000
B9: ｻﾎﾟｰﾄｻｰﾋﾞｽ | C9: 35000 | D9: 496 | E9: =$C9*D9 -> 17360000 | F9: 515 | G9: =$C9*F9 -> 18025000 | H9: 482.5 | I9: =$C9*H9 -> 16887500 | J9: 490.5 | K9: =$C9*J9 -> 17167500 | L9: 434 | M9: =$C9*L9 -> 15190000 | N9: 429.5 | O9: =$C9*N9 -> 15032500 | P9: 430.5 | Q9: =$C9*P9 -> 15067500 | R9: 413 | S9: =$C9*R9 -> 14455000 | T9: 437.5 | U9: =$C9*T9 -> 15312500 | V9: 372.5 | W9: =$C9*V9 -> 13037500 | X9: 337.5 | Y9: =$C9*X9 -> 11812500 | Z9: 402 | AA9: =$C9*Z9 -> 14070000 | AB9: =D9+F9+H9+J9+L9+N9+P9+R9+T9+V9+X9+Z9 -> 5240.5 | AC9: =E9+G9+I9+K9+M9+O9+Q9+S9+U9+W9+Y9+AA9 -> 183417500
B10: OPEN | C10: 35000 | D10: 11.5 | E10: =$C10*D10 -> 402500 | F10: 3 | G10: =$C10*F10 -> 105000 | H10: 3 | I10: =$C10*H10 -> 105000 | J10: 6 | K10: =$C10*J10 -> 210000 | L10: 3 | M10: =$C10*L10 -> 105000 | N10: 3 | O10: =$C10*N10 -> 105000 | P10: 2 | Q10: =$C10*P10 -> 70000 | R10: 5 | S10: =$C10*R10 -> 175000 | T10: 6.5 | U10: =$C10*T10 -> 227500 | V10: 3 | W10: =$C10*V10 -> 105000 | X10: 11.5 | Y10: =$C10*X10 -> 402500 | Z10: 4 | AA10: =$C10*Z10 -> 140000 | AB10: =D10+F10+H10+J10+L10+N10+P10+R10+T10+V10+X10+Z10 -> 61.5 | AC10: =E10+G10+I10+K10+M10+O10+Q10+S10+U10+W10+Y10+AA10 -> 2152500
B12: ｻﾎﾟｰﾄｻｰﾋﾞｽ山梨 | C12: 1980000 | D12: 1 | E12: =$C12*D12 -> 1980000 | F12: 1 | G12: =$C12*F12 -> 1980000 | H12: 1 | I12: =$C12*H12 -> 1980000 | J12: 1 | K12: =$C12*J12 -> 1980000 | L12: 1 | M12: =$C12*L12 -> 1980000 | N12: 1 | O12: =$C12*N12 -> 1980000 | P12: 1 | Q12: =$C12*P12 -> 1980000 | R12: 1 | S12: =$C12*R12 -> 1980000 | T12: 1 | U12: =$C12*T12 -> 1980000 | V12: 1 | W12: =$C12*V12 -> 1980000 | X12: 1 | Y12: =$C12*X12 -> 1980000 | Z12: 1 | AA12: =$C12*Z12+18000 -> 1998000 | AB12: =D12+F12+H12+J12+L12+N12+P12+R12+T12+V12+X12+Z12 -> 12 | AC12: =E12+G12+I12+K12+M12+O12+Q12+S12+U12+W12+Y12+AA12 -> 23778000
B13: 山梨ｴﾘｱ | C13: 31000 | D13: 17 | E13: =$C13*D13 -> 527000 | F13: 16 | G13: =$C13*F13 -> 496000 | H13: 9 | I13: =$C13*H13 -> 279000 | J13: 3 | K13: =$C13*J13 -> 93000 | L13: 7.5 | M13: =$C13*L13 -> 232500 | N13: 17 | O13: =$C13*N13 -> 527000 | P13: 9 | Q13: =$C13*P13 -> 279000 | R13: 15 | S13: =$C13*R13 -> 465000 | T13: 10.5 | U13: =$C13*T13 -> 325500 | V13: 18 | W13: =$C13*V13 -> 558000 | X13: 15 | Y13: =$C13*X13 -> 465000 | Z13: 16 | AA13: =$C13*Z13 -> 496000 | AB13: =D13+F13+H13+J13+L13+N13+P13+R13+T13+V13+X13+Z13 -> 153 | AC13: =E13+G13+I13+K13+M13+O13+Q13+S13+U13+W13+Y13+AA13 -> 4743000
B14: 原価合計 | E14: =SUM(E15:E16) -> 13542758 | G14: =SUM(G15:G16) -> 12925580 | I14: =SUM(I15:I16) -> 12936353 | K14: =SUM(K15:K16) -> 13029791 | M14: =SUM(M15:M16) -> 12910002 | O14: =SUM(O15:O16) -> 12999923 | Q14: =SUM(Q15:Q16) -> 12386306 | S14: =SUM(S15:S16) -> 12251513 | U14: =SUM(U15:U16) -> 12373396 | W14: =SUM(W15:W16) -> 11623373 | Y14: =SUM(Y15:Y16) -> 11686532 | AA14: =SUM(AA15:AA16) -> 8945842 | AC14: =SUM(E14:AA14) -> 1.4761137e+08
B15: ディスパッチ | E15: ='DELL委託人件費(DPT)'!$K$2 -> 1403131 | G15: ='DELL委託人件費(DPT)'!$L$2 -> 1083072 | I15: ='DELL委託人件費(DPT)'!M2 -> 1257464 | K15: ='DELL委託人件費(DPT)'!N2 -> 1230021 | M15: ='DELL委託人件費(DPT)'!O2 -> 1260996 | O15: ='DELL委託人件費(DPT)'!P2 -> 1371268 | Q15: ='DELL委託人件費(DPT)'!Q2 -> 1311807 | S15: ='DELL委託人件費(DPT)'!R2 -> 1412148 | U15: ='DELL委託人件費(DPT)'!S2 -> 1466527 | W15: ='DELL委託人件費(DPT)'!T2 -> 1076402 | Y15: ='DELL委託人件費(DPT)'!U2 -> 1058198 | AA15: ='DELL委託人件費(DPT)'!V2 -> 581530 | AC15: =SUM(E15:AA15) -> 14512564
B16: FS技術部 | E16: ='DELL委託人件費(FS）'!K2 -> 12139627 | G16: ='DELL委託人件費(FS）'!L2 -> 11842508 | I16: ='DELL委託人件費(FS）'!M2 -> 11678889 | K16: ='DELL委託人件費(FS）'!N2 -> 11799770 | M16: ='DELL委託人件費(FS）'!O2 -> 11649006 | O16: ='DELL委託人件費(FS）'!P2 -> 11628655 | Q16: ='DELL委託人件費(FS）'!Q2 -> 11074499 | S16: ='DELL委託人件費(FS）'!R2 -> 10839365 | U16: ='DELL委託人件費(FS）'!S2 -> 10906869 | W16: ='DELL委託人件費(FS）'!T2 -> 10546971 | Y16: ='DELL委託人件費(FS）'!U2 -> 10628334 | AA16: ='DELL委託人件費(FS）'!V2 -> 8364312 | AC16: =SUM(E16:AA16) -> 1.3309881e+08
B17: 粗利 | E17: =E8-E14 -> 6726742 | G17: =G8-G14 -> 7680420 | I17: =I8-I14 -> 6315147 | K17: =K8-K14 -> 6420709 | M17: =M8-M14 -> 4597498 | O17: =O8-O14 -> 4644577 | Q17: =Q8-Q14 -> 5010194 | S17: =S8-S14 -> 4823487 | U17: =U8-U14 -> 5472103.6 | W17: =W8-W14 -> 4057127 | Y17: =Y8-Y14 -> 2973468 | AA17: =AA8-AA14 -> 7758158 | AC17: =SUM(E17:AA17) -> 66479631
B19: UAL常駐
B20: 売上合計 | E20: =E21+E22 -> 3822500 | G20: =G21+G22 -> 3822500 | I20: =I21+I22 -> 3817500 | K20: =K21+K22 -> 3819455 | M20: =M21+M22 -> 3602025 | O20: =O21+O22 -> 3687320 | Q20: =Q21+Q22 -> 3302435 | S20: =S21+S22 -> 3179855 | U20: =U21+U22 -> 3718440 | W20: =W21+W22 -> 4025275 | Y20: =Y21+Y22 -> 4082725 | AA20: =AA21+AA22 -> 4140000 | AC20: =SUM(E20:AA20) -> 45020030
B21: DSD | E21: =UAL常駐!L2 -> 3822500 | G21: =UAL常駐!M2 -> 3822500 | I21: =UAL常駐!N2 -> 3817500 | K21: =UAL常駐!O2 -> 3819455 | M21: =UAL常駐!P2 -> 3602025 | O21: =UAL常駐!Q2 -> 3687320 | Q21: =UAL常駐!R2 -> 3302435 | S21: =UAL常駐!S2 -> 3179855 | U21: =UAL常駐!T2 -> 3718440 | W21: =UAL常駐!U2 -> 4025275 | Y21: =UAL常駐!V2 -> 4082725 | AA21: =UAL常駐!W2 -> 4140000 | AC21: =SUM(E21:AA21) -> 45020030
B22: UALスポット | AC22: =SUM(E22:AA22) -> 0
B23: 原価 | E23: =UAL常駐!L3 -> 2573624 | G23: =UAL常駐!M3 -> 2556425 | I23: =UAL常駐!N3 -> 2555803 | K23: =UAL常駐!O3 -> 2555021 | M23: =UAL常駐!P3 -> 2540089 | O23: =UAL常駐!Q3 -> 2588419 | Q23: =UAL常駐!R3 -> 2305130 | S23: =UAL常駐!S3 -> 2286257 | U23: =UAL常駐!T3 -> 2619829 | W23: =UAL常駐!U3 -> 2956040 | Y23: =UAL常駐!V3 -> 2914638 | AA23: =UAL常駐!W3 -> 2911560.4 | AC23: =SUM(E23:AA23) -> 31362835
B24: 粗利 | E24: =E20-E23 -> 1248876 | G24: =G20-G23 -> 1266075 | I24: =I20-I23 -> 1261697 | K24: =K20-K23 -> 1264434 | M24: =M20-M23 -> 1061936 | O24: =O20-O23 -> 1098901 | Q24: =Q20-Q23 -> 997305 | S24: =S20-S23 -> 893598 | U24: =U20-U23 -> 1098611 | W24: =W20-W23 -> 1069235 | Y24: =Y20-Y23 -> 1168087 | AA24: =AA20-AA23 -> 1228439.6 | AC24: =SUM(E24:AA24) -> 13657195
B26: FS/その他
B27: 売上合計 | E27: =E28+E29 -> 780000 | G27: =G28+G29 -> 780000 | I27: =I28+I29 -> 780000 | K27: =K28+K29 -> 810000 | M27: =M28+M29 -> 954000 | O27: =O28+O29 -> 993125 | Q27: =Q28+Q29 -> 1207500 | S27: =S28+S29 -> 1255775 | U27: =U28+U29 -> 1282350 | W27: =W28+W29 -> 974650 | Y27: =Y28+Y29 -> 1503175 | AA27: =AA28+AA29 -> 2407080 | AC27: =SUM(E27:AA27) -> 13727655
B28: NDICS | E28: =その他業務!L2 -> 780000 | G28: =その他業務!M2 -> 780000 | I28: =その他業務!N2 -> 780000 | K28: =その他業務!O2 -> 810000 | M28: =その他業務!P2 -> 954000 | O28: =その他業務!Q2 -> 993125 | Q28: =その他業務!R2 -> 1207500 | S28: =その他業務!S2 -> 1255775 | U28: =その他業務!T2 -> 1282350 | W28: =その他業務!U2 -> 974650 | Y28: =その他業務!V2 -> 1503175 | AA28: =その他業務!W2 -> 2407080 | AC28: =SUM(E28:AA28) -> 13727655
B29: スポット | AC29: =SUM(E29:AA29) -> 0
B30: 原価 | E30: =その他業務!L3 -> 22000 | G30: =その他業務!M3 -> 24000 | I30: =その他業務!N3 -> 25000 | K30: =その他業務!O3 -> 24000 | M30: =その他業務!P3 -> 23000 | O30: =その他業務!Q3 -> 23000 | Q30: =その他業務!R3 -> 24000 | S30: =その他業務!S3 -> 24000 | U30: =その他業務!T3 -> 25000 | W30: =その他業務!U3 -> 26000 | Y30: =その他業務!V3 -> 23000 | AA30: =その他業務!W3 -> 30000 | AC30: =SUM(E30:AA30) -> 293000
B31: 粗利 | E31: =E27-E30 -> 758000 | G31: =G27-G30 -> 756000 | I31: =I27-I30 -> 755000 | K31: =K27-K30 -> 786000 | M31: =M27-M30 -> 931000 | O31: =O27-O30 -> 970125 | Q31: =Q27-Q30 -> 1183500 | S31: =S27-S30 -> 1231775 | U31: =U27-U30 -> 1257350 | W31: =W27-W30 -> 948650 | Y31: =Y27-Y30 -> 1480175 | AA31: =AA27-AA30 -> 2377080 | AC31: =SUM(E31:AA31) -> 13434655
D34: 4月 | F34: 5月 | H34: 6月 | J34: 7月 | L34: 8月 | N34: 9月 | P34: 10月 | R34: 11月 | T34: 12月 | V34: 1月 | X34: 2月 | Z34: 3月 | AB34: 通期総計
C35: 総計売上 | D35: =E8+E20+E27 -> 24872000 | F35: =G8+G20+G27 -> 25208500 | H35: =I8+I20+I27 -> 23849000 | J35: =K8+K20+K27 -> 24079955 | L35: =M8+M20+M27 -> 22063525 | N35: =O8+O20+O27 -> 22324945 | P35: =Q8+Q20+Q27 -> 21906435 | R35: =S8+S20+S27 -> 21510630 | T35: =U8+U20+U27 -> 22846290 | V35: =W8+W20+W27 -> 20680425 | X35: =Y8+Y20+Y27 -> 20245900 | Z35: =AA8+AA20+AA27 -> 23251080 | AB35: =SUM(D35:Z35) -> 272838685
C36: 原価 | D36: =E14+E23+E30 -> 16138382 | F36: =G14+G23+G30 -> 15506005 | H36: =I14+I23+I30 -> 15517156 | J36: =K14+K23+K30 -> 15608812 | L36: =M14+M23+M30 -> 15473091 | N36: =O14+O23+O30 -> 15611342 | P36: =Q14+Q23+Q30 -> 14715436 | R36: =S14+S23+S30 -> 14561770 | T36: =U14+U23+U30 -> 15018225 | V36: =W14+W23+W30 -> 14605413 | X36: =Y14+Y23+Y30 -> 14624170 | Z36: =AA14+AA23+AA30 -> 11887402 | AB36: =SUM(D36:Z36) -> 1.792672e+08
C37: 粗利 | D37: =D35-D36 -> 8733618 | F37: =F35-F36 -> 9702495 | H37: =H35-H36 -> 8331844 | J37: =J35-J36 -> 8471143 | L37: =L35-L36 -> 6590434 | N37: =N35-N36 -> 6713603 | P37: =P35-P36 -> 7190999 | R37: =R35-R36 -> 6948860 | T37: =T35-T36 -> 7828064.6 | V37: =V35-V36 -> 6075012 | X37: =X35-X36 -> 5621730 | Z37: =Z35-Z36 -> 11363678 | AB37: =SUM(D37:Z37) -> 93571480
B39: 甲府SS案件
B40: 売上合計 | E40: =E41 -> 1980000 | G40: =G41 -> 1980000 | I40: =I41 -> 1980000 | K40: =K41 -> 1980000 | M40: =M41 -> 1980000 | O40: =O41 -> 1980000 | Q40: =Q41 -> 1980000 | S40: =S41 -> 1980000 | U40: =U41 -> 1980000 | W40: =W41 -> 1980000 | Y40: =Y41 -> 1980000 | AA40: =AA41 -> 1980000 | AC40: =SUM(E40:AA40) -> 23760000
B41: 甲府SS | E41: 1980000 | G41: 1980000 | I41: 1980000 | K41: 1980000 | M41: 1980000 | O41: 1980000 | Q41: 1980000 | S41: 1980000 | U41: 1980000 | W41: 1980000 | Y41: 1980000 | AA41: 1980000 | AC41: =SUM(E41:AA41) -> 23760000
B42: 原価 | AC42: =SUM(E42:AA42) -> 0
B43: 粗利 | E43: =E40-E42 -> 1980000 | G43: =G40-G42 -> 1980000 | I43: =I40-I42 -> 1980000 | K43: =K40-K42 -> 1980000 | M43: =M40-M42 -> 1980000 | O43: =O40-O42 -> 1980000 | Q43: =Q40-Q42 -> 1980000 | S43: =S40-S42 -> 1980000 | U43: =U40-U42 -> 1980000 | W43: =W40-W42 -> 1980000 | Y43: =Y40-Y42 -> 1980000 | AA43: =AA40-AA42 -> 1980000 | AC43: =SUM(E43:AA43) -> 23760000

Sheet DELL委託人件費(DPT)
A1: 社員番号 | B1: 氏名 | C1: No | D1: 派遣/請負 | E1: 担当 | F1: 氏名 | G1: 作業名 | H1: 契約先 | I1: 外注会社 | J1: 売上単価 (支払単価） 【≒粗利】 | K1: 4月 | L1: 5月 | M1: 6月 | N1: 7月 | O1: 8月 | P1: 9月 | Q1: 10月 | R1: 11月 | S1: 12月 | T1: 1月 | U1: 2月 | V1: 3月 | W1: 合計
C2: DELL委託（DPT） | J2: 人件費合計 | K2: =K51 -> 1403131 | L2: =L51 -> 1083072 | M2: =M51 -> 1257464 | N2: =N51 -> 1230021 | O2: =O51 -> 1260996 | P2: =P51 -> 1371268 | Q2: =Q51 -> 1311807 | R2: =R51 -> 1412148 | ... V2: =V51 -> 581530 | W2: =SUM(K2:V2) -> 14512564 | Y2: =AVERAGE(K2:V2) -> 1209380.3
A3: 2018041 | C3: 1 | I3: 社員 | J3: 総経費 | K3: =SUM(K4:K10) -> 345054 | L3: =SUM(L4:L10) -> 345054 | M3: =SUM(M4:M10) -> 345054 | N3: =SUM(N4:N10) -> 345054 | O3: =SUM(O4:O10) -> 345054 | P3: =SUM(P4:P10) -> 345054 | Q3: =SUM(Q4:Q10) -> 345054 | R3: =SUM(R4:R10) -> 345054 | ... V3: =SUM(V4:V10) -> 306237 | W3: =SUM(K3:V3) -> 4102014
A4: =A3 -> 2018041 | J4: 賃金 | K4: 288560 | L4: 288560 | M4: 288560 | N4: 288560 | O4: 288560 | P4: 288560 | Q4: 288560 | R4: 288560 | S4: 288560 | T4: 288560 | U4: 288560 | V4: 249560 | W4: =SUM(K4:V4) -> 3423720
A5: =A4 -> 2018041 | J5: 顧客対応当番 | V5: ￥0 | W5: =SUM(K5:V5) -> 0
A6: =A5 -> 2018041 | J6: 交通費 | K6: 8970 | L6: 8970 | M6: 8970 | N6: 8970 | O6: 8970 | P6: 8970 | Q6: 8970 | R6: 8970 | S6: 8970 | T6: 8970 | U6: 8970 | V6: 8970 | W6: =SUM(K6:V6) -> 107640
A7: =A6 -> 2018041 | J7: 健康保険 | K7: 16950 | L7: 16950 | M7: 16950 | N7: 16950 | O7: 16950 | P7: 16950 | Q7: 16950 | R7: 16950 | S7: 16950 | T7: 16950 | U7: 16950 | V7: 16950 | W7: =SUM(K7:V7) -> 203400
A8: =A7 -> 2018041 | J8: 厚生年金 | K8: 27450 | L8: 27450 | M8: 27450 | N8: 27450 | O8: 27450 | P8: 27450 | Q8: 27450 | R8: 27450 | S8: 27450 | T8: 27450 | U8: 27450 | V8: 27450 | W8: =SUM(K8:V8) -> 329400
A9: =A8 -> 2018041 | J9: 労災保険 | K9: 1488 | L9: 1488 | M9: 1488 | N9: 1488 | O9: 1488 | P9: 1488 | Q9: 1488 | R9: 1488 | S9: 1488 | T9: 1488 | U9: 1575 | V9: 1575 | W9: =SUM(K9:V9) -> 18030
A10: =A9 -> 2018041 | J10: 雇用保険 | K10: 1636 | L10: 1636 | M10: 1636 | N10: 1636 | O10: 1636 | P10: 1636 | Q10: 1636 | R10: 1636 | S10: 1636 | T10: 1636 | U10: 1732 | V10: 1732 | W10: =SUM(K10:V10) -> 19824
A11: 2022027 | C11: =C3+1 -> 2 | E11: 転出 | H11: 1月～営業部移動、本社付け | I11: 社員 | J11: 総経費 | K11: =SUM(K12:K18) -> 405516 | L11: =SUM(L12:L18) -> 403505 | M11: =SUM(M12:M18) -> 412050 | N11: =SUM(N12:N18) -> 405547 | O11: =SUM(O12:O18) -> 407084 | P11: =SUM(P12:P18) -> 400502 | Q11: =SUM(Q12:Q18) -> 368115 | R11: =SUM(R12:R18) -> 384431 | ... V11: =SUM(V12:V18) -> 0 | W11: =SUM(K11:V11) -> 3575289
A12: =A11 -> 2022027 | J12: 賃金 | K12: 299630 | L12: 298630 | M12: 302880 | N12: 302630 | O12: 305630 | P12: 302430 | Q12: 270380 | R12: 291130 | S12: 294130 | W12: =SUM(K12:V12) -> 2667470
A13: =A12 -> 2022027 | J13: 顧客対応当番 | K13: 29250 | L13: 28250 | M13: 32500 | N13: 26250 | O13: 31250 | P13: 29250 | Q13: 29250 | R13: 20750 | S13: 23750 | W13: =SUM(K13:V13) -> 250500
A14: =A13 -> 2022027 | J14: 交通費 | K14: 20000 | L14: 20000 | M14: 20000 | N14: 20000 | O14: 13572 | P14: 18096 | Q14: 18096 | R14: 21904 | S14: 20000 | W14: =SUM(K14:V14) -> 171668
A15: =A14 -> 2022027 | J15: 健康保険 | K15: 20340 | L15: 20340 | M15: 20340 | N15: 20340 | O15: 20340 | P15: 18080 | Q15: 18080 | R15: 18080 | S15: 18080 | W15: =SUM(K15:V15) -> 174020
A16: =A15 -> 2022027 | J16: 厚生年金 | K16: 32940 | L16: 32940 | M16: 32940 | N16: 32940 | O16: 32940 | P16: 29280 | Q16: 29280 | R16: 29280 | S16: 29280 | W16: =SUM(K16:V16) -> 281820
A17: =A16 -> 2022027 | J17: 労災保険 | K17: 1598 | L17: 1593 | M17: 1614 | N17: 1613 | O17: 1596 | P17: 1603 | Q17: 1442 | R17: 1565 | S17: 1571 | W17: =SUM(K17:V17) -> 14195
A18: =A17 -> 2022027 | J18: 雇用保険 | K18: 1758 | L18: 1752 | M18: 1776 | N18: 1774 | O18: 1756 | P18: 1763 | Q18: 1587 | R18: 1722 | S18: 1728 | W18: =SUM(K18:V18) -> 15616
A19: 2018037 | C19: =C11+1 -> 3 | I19: 社員 | J19: 総経費 | K19: =SUM(K20:K26) -> 334513 | L19: =SUM(L20:L26) -> 334513 | M19: =SUM(M20:M26) -> 334513 | N19: =SUM(N20:N26) -> 323700 | O19: =SUM(O20:O26) -> 329983 | P19: =SUM(P20:P26) -> 327145 | Q19: =SUM(Q20:Q26) -> 324053 | R19: =SUM(R20:R26) -> 321091 | ... V19: =SUM(V20:V26) -> 275293 | W19: =SUM(K19:V19) -> 3958534
A20: =A19 -> 2018037 | J20: 賃金 | K20: 269450 | L20: 269450 | M20: 269450 | N20: 269450 | O20: 269450 | P20: 269450 | Q20: 269450 | R20: 268539 | S20: 278548 | T20: 309450 | U20: 301450 | V20: 233025 | W20: =SUM(K20:V20) -> 3277162
A21: =A20 -> 2018037 | J21: 顧客対応当番 | V21: ￥0 | W21: =SUM(K21:V21) -> 0
A22: =A21 -> 2018037 | J22: 交通費 | K22: 20320 | L22: 20320 | M22: 20320 | N22: 9620 | O22: 16004 | P22: 15946 | Q22: 12720 | R22: 10812 | S22: 14290 | T22: 12262 | U22: 11448 | V22: ￥0 | W22: =SUM(K22:V22) -> 164062
A23: =A22 -> 2018037 | J23: 健康保険 | K23: 14250 | L23: 14250 | M23: 14250 | N23: 14250 | O23: 14250 | P23: 13300 | Q23: 13300 | R23: 13300 | S23: 13300 | T23: 13300 | U23: 13300 | V23: 13300 | W23: =SUM(K23:V23) -> 164350
A24: =A23 -> 2018037 | J24: 厚生年金 | K24: 27450 | L24: 27450 | M24: 27450 | N24: 27450 | O24: 27450 | P24: 25620 | Q24: 25620 | R24: 25620 | S24: 25620 | T24: 25620 | U24: 25620 | V24: 25620 | W24: =SUM(K24:V24) -> 316590
A25: =A24 -> 2018037 | J25: 労災保険 | K25: 1449 | L25: 1449 | M25: 1449 | N25: 1395 | O25: 1347 | P25: 1347 | Q25: 1411 | R25: 1343 | S25: 1393 | T25: 1547 | U25: 1594 | V25: 1594 | W25: =SUM(K25:V25) -> 17318
A26: =A25 -> 2018037 | J26: 雇用保険 | K26: 1594 | L26: 1594 | M26: 1594 | N26: 1535 | O26: 1482 | P26: 1482 | Q26: 1552 | R26: 1477 | S26: 1532 | T26: 1702 | U26: 1754 | V26: 1754 | W26: =SUM(K26:V26) -> 19052
A27: 2020024 | C27: =C19+1 -> 4 | E27: 転出 | I27: 社員 | J27: 総経費 | K27: =SUM(K28:K34) -> 318048 | L27: =SUM(L28:L34) -> 0 | M27: =SUM(M28:M34) -> 165847 | N27: =SUM(N28:N34) -> 155720 | O27: =SUM(O28:O34) -> 0 | P27: =SUM(P28:P34) -> 0 | Q27: =SUM(Q28:Q34) -> 0 | R27: =SUM(R28:R34) -> 0 | ... V27: =SUM(V28:V34) -> 0 | W27: =SUM(K27:V27) -> 639615
A28: =A27 -> 2020024 | J28: 賃金 | K28: 247025 | M28: 120105 | N28: 110085 | W28: =SUM(K28:V28) -> 477215
A29: =A28 -> 2020024 | J29: 顧客対応当番 | W29: =SUM(K29:V29) -> 0
A30: =A29 -> 2020024 | J30: 交通費 | K30: 23700 | M30: 0 | N30: 0 | W30: =SUM(K30:V30) -> 23700
A31: =A30 -> 2020024 | J31: 健康保険 | K31: 15200 | M31: 15200 | N31: 15200 | W31: =SUM(K31:V31) -> 45600
A32: =A31 -> 2020024 | J32: 厚生年金 | K32: 29280 | M32: 29280 | N32: 29280 | W32: =SUM(K32:V32) -> 87840
A33: =A32 -> 2020024 | J33: 労災保険 | K33: 1354 | M33: 601 | N33: 550 | W33: =SUM(K33:V33) -> 2505
A34: =A33 -> 2020024 | J34: 雇用保険 | K34: 1489 | M34: 661 | N34: 605 | W34: =SUM(K34:V34) -> 2755
C35: =C27+1 -> 5 | E35: 転出 | I35: 派遣 | J35: 総経費 | K35: =SUM(K36:K42) -> 0 | L35: =SUM(L36:L42) -> 0 | M35: =SUM(M36:M42) -> 0 | N35: =SUM(N36:N42) -> 0 | O35: =SUM(O36:O42) -> 178875 | P35: =SUM(P36:P42) -> 298567 | Q35: =SUM(Q36:Q42) -> 274585 | R35: =SUM(R36:R42) -> 0 | ... V35: =SUM(V36:V42) -> 0 | W35: =SUM(K35:V35) -> 752027
A36: =A35 -> 0 | J36: 派遣料金 | O36: 178875 | P36: 298567 | Q36: 274585 | W36: =SUM(K36:V36) -> 752027
A37: =A36 -> 0 | W37: =SUM(K37:V37) -> 0
A38: =A37 -> 0 | W38: =SUM(K38:V38) -> 0
A39: =A38 -> 0 | W39: =SUM(K39:V39) -> 0
A40: =A39 -> 0 | W40: =SUM(K40:V40) -> 0
A41: =A40 -> 0 | W41: =SUM(K41:V41) -> 0
A42: =A41 -> 0 | W42: =SUM(K42:V42) -> 0
C43: =C35+1 -> 6 | I43: 派遣 | J43: 総経費 | K43: =SUM(K44:K50) -> 0 | L43: =SUM(L44:L50) -> 0 | M43: =SUM(M44:M50) -> 0 | N43: =SUM(N44:N50) -> 0 | O43: =SUM(O44:O50) -> 0 | P43: =SUM(P44:P50) -> 0 | Q43: =SUM(Q44:Q50) -> 0 | R43: =SUM(R44:R50) -> 361572 | ... V43: =SUM(V44:V50) -> 0 | W43: =SUM(K43:V43) -> 1485085
A44: =A43 -> 0 | J44: 派遣料金 | R44: 361572 | S44: 398251 | T44: 367467 | U44: 357795 | V44: ￥0 | W44: =SUM(K44:V44) -> 1485085
A45: =A44 -> 0 | V45: ￥0 | W45: =SUM(K45:V45) -> 0
A46: =A45 -> 0 | V46: ￥0 | W46: =SUM(K46:V46) -> 0
A47: =A46 -> 0 | V47: ￥0 | W47: =SUM(K47:V47) -> 0
A48: =A47 -> 0 | V48: ￥0 | W48: =SUM(K48:V48) -> 0
A49: =A48 -> 0 | V49: ￥0 | W49: =SUM(K49:V49) -> 0
A50: =A49 -> 0 | V50: ￥0 | W50: =SUM(K50:V50) -> 0
J51: =J2 -> 人件費合計 | K51: =K3+K11+K19+K27+K35+K43 -> 1403131 | L51: =L3+L11+L19+L27+L35+L43 -> 1083072 | M51: =M3+M11+M19+M27+M35+M43 -> 1257464 | N51: =N3+N11+N19+N27+N35+N43 -> 1230021 | O51: =O3+O11+O19+O27+O35+O43 -> 1260996 | P51: =P3+P11+P19+P27+P35+P43 -> 1371268 | Q51: =Q3+Q11+Q19+Q27+Q35+Q43 -> 1311807 | R51: =R3+R11+R19+R27+R35+R43 -> 1412148 | ... V51: =V3+V11+V19+V27+V35+V43 -> 581530 | W51: =SUM(K51:V51) -> 14512564

Sheet DELL委託人件費(FS）
A1: 社員番号 | B1: 氏名 | C1: No | D1: 派遣/請負 | E1: 担当 | F1: 氏名 | G1: 作業名 | H1: 契約先 | I1: 外注会社 | J1: 売上単価 (支払単価） 【≒粗利】 | K1: 4月 | L1: 5月 | M1: 6月 | N1: 7月 | O1: 8月 | P1: 9月 | Q1: 10月 | R1: 11月 | S1: 12月 | T1: 1月 | U1: 2月 | V1: 3月 | W1: 合計
C2: DELL委託（八丁堀） | J2: 人件費合計 | K2: =K275 -> 12139627 | L2: =L275 -> 11842508 | M2: =M275 -> 11678889 | N2: =N275 -> 11799770 | O2: =O275 -> 11649006 | P2: =P275 -> 11628655 | Q2: =Q275 -> 11074499 | R2: =R275 -> 10839365 | ... V2: =V275 -> 8364312 | W2: =SUM(K2:V2) -> 1.3309881e+08 | Y2: =AVERAGE(K2:V2) -> 11091567
A3: 2018038 | C3: =1 -> 1 | I3: 社員 | J3: 総経費 | K3: =SUM(K4:K10) -> 462265 | L3: =SUM(L4:L10) -> 469467 | M3: =SUM(M4:M10) -> 463908 | N3: =SUM(N4:N10) -> 465676 | O3: =SUM(O4:O10) -> 478614 | P3: =SUM(P4:P10) -> 479900 | Q3: =SUM(Q4:Q10) -> 474338 | R3: =SUM(R4:R10) -> 493762 | ... V3: =SUM(V4:V10) -> 382270 | W3: =SUM(K3:V3) -> 5632713
A4: =A3 -> 2018038 | J4: 賃金 | K4: 372680 | L4: 372680 | M4: 372680 | N4: 372680 | O4: 387680 | P4: 372680 | Q4: 372680 | R4: 397680 | S4: 377680 | T4: 377680 | U4: 377680 | V4: 321630 | W4: =SUM(K4:V4) -> 4476110
A5: =A4 -> 2018038 | J5: 顧客対応当番 | K5: 12500 | L5: 15000 | M5: 10000 | N5: 15000 | O5: 15000 | P5: 15000 | Q5: 15000 | R5: 15000 | S5: 36000 | T5: 24000 | U5: 24000 | V5: ￥0 | W5: =SUM(K5:V5) -> 196500
A6: =A5 -> 2018038 | J6: 交通費 | K6: 20221 | L6: 24897 | M6: 24390 | N6: 17686 | O6: 15624 | P6: 31910 | Q6: 26073 | R6: 20509 | S6: 21663 | T6: 19461 | U6: 22669 | V6: ￥0 | W6: =SUM(K6:V6) -> 245103
A7: =A6 -> 2018038 | J7: 健康保険 | K7: 18050 | L7: 18050 | M7: 18050 | N7: 21470 | O7: 21470 | P7: 21470 | Q7: 21470 | R7: 21470 | S7: 21470 | T7: 21470 | U7: 21470 | V7: 21470 | W7: =SUM(K7:V7) -> 247380
A8: =A7 -> 2018038 | J8: 厚生年金 | K8: 34770 | L8: 34770 | M8: 34770 | N8: 34770 | O8: 34770 | P8: 34770 | Q8: 34770 | R8: 34770 | S8: 34770 | T8: 34770 | U8: 34770 | V8: 34770 | W8: =SUM(K8:V8) -> 417240
A9: =A8 -> 2018038 | J9: 労災保険 | K9: 1926 | L9: 1938 | M9: 1913 | N9: 1938 | O9: 1938 | P9: 1938 | Q9: 2069 | R9: 2063 | S9: 2068 | T9: 2008 | U9: 2095 | V9: 2095 | W9: =SUM(K9:V9) -> 23989
A10: =A9 -> 2018038 | J10: 雇用保険 | K10: 2118 | L10: 2132 | M10: 2105 | N10: 2132 | O10: 2132 | P10: 2132 | Q10: 2276 | R10: 2270 | S10: 2275 | T10: 2209 | U10: 2305 | V10: 2305 | W10: =SUM(K10:V10) -> 26391
A11: 2019002 | C11: =C3+1 -> 2 | I11: 社員 | J11: 総経費 | K11: =SUM(K12:K18) -> 632826 | L11: =SUM(L12:L18) -> 561913 | M11: =SUM(M12:M18) -> 561524 | N11: =SUM(N12:N18) -> 682605 | O11: =SUM(O12:O18) -> 576315 | P11: =SUM(P12:P18) -> 608651 | Q11: =SUM(Q12:Q18) -> 622908 | R11: =SUM(R12:R18) -> 576131 | ... V11: =SUM(V12:V18) -> 422244 | W11: =SUM(K11:V11) -> 6923923
A12: =A11 -> 2019002 | J12: 賃金 | K12: 525281 | L12: 453125 | M12: 448125 | N12: 574063 | O12: 464688 | P12: 486563 | Q12: 495938 | R12: 448125 | S12: 501250 | T12: 400625 | U12: 389531 | V12: 343750 | W12: =SUM(K12:V12) -> 5531064
A13: =A12 -> 2019002 | J13: 顧客対応当番 | K13: 12500 | L13: 12500 | M13: 12500 | N13: 12500 | O13: 15000 | P13: 15000 | Q13: 15000 | R13: 17500 | S13: 33000 | T13: 33000 | U13: 21000 | V13: ￥0 | W13: =SUM(K13:V13) -> 199500
A14: =A13 -> 2019002 | J14: 交通費 | K14: 19838 | L14: 21839 | M14: 26778 | N14: 20323 | O14: 22031 | P14: 27821 | Q14: 32266 | R14: 31617 | S14: 23322 | T14: 22317 | U14: 18105 | V14: ￥0 | W14: =SUM(K14:V14) -> 266257
A15: =A14 -> 2019002 | J15: 健康保険 | K15: 26555 | L15: 26555 | M15: 26555 | N15: 26555 | O15: 26555 | P15: 28250 | Q15: 28250 | R15: 28250 | S15: 28250 | T15: 28250 | U15: 28250 | V15: 28250 | W15: =SUM(K15:V15) -> 330525
A16: =A15 -> 2019002 | J16: 厚生年金 | K16: 43005 | L16: 43005 | M16: 43005 | N16: 43005 | O16: 43005 | P16: 45750 | Q16: 45750 | R16: 45750 | S16: 45750 | T16: 45750 | U16: 45750 | V16: 45750 | W16: =SUM(K16:V16) -> 535275
A17: =A16 -> 2019002 | J17: 労災保険 | K17: 2689 | L17: 2328 | M17: 2172 | N17: 2933 | O17: 2398 | P17: 2508 | Q17: 2716 | R17: 2328 | S17: 2671 | T17: 2168 | U17: 2140 | V17: 2140 | W17: =SUM(K17:V17) -> 29191
A18: =A17 -> 2019002 | J18: 雇用保険 | K18: 2958 | L18: 2561 | M18: 2389 | N18: 3226 | O18: 2638 | P18: 2759 | Q18: 2988 | R18: 2561 | S18: 2938 | T18: 2385 | U18: 2354 | V18: 2354 | W18: =SUM(K18:V18) -> 32111
A19: 2019024 | C19: =C11+1 -> 3 | I19: 社員 | J19: 総経費 | K19: =SUM(K20:K26) -> 479285 | L19: =SUM(L20:L26) -> 468150 | M19: =SUM(M20:M26) -> 463422 | N19: =SUM(N20:N26) -> 447922 | O19: =SUM(O20:O26) -> 428927 | P19: =SUM(P20:P26) -> 450525 | Q19: =SUM(Q20:Q26) -> 444950 | R19: =SUM(R20:R26) -> 432055 | ... V19: =SUM(V20:V26) -> 349768 | W19: =SUM(K19:V19) -> 5334076
A20: =A19 -> 2019024 | J20: 賃金 | K20: 338300 | L20: 338300 | M20: 338300 | N20: 342072 | O20: 338300 | P20: 338300 | Q20: 338300 | R20: 338300 | S20: 338300 | T20: 340586 | U20: 338300 | V20: 292575 | W20: =SUM(K20:V20) -> 4019933
A21: =A20 -> 2019024 | J21: 顧客対応当番 | K21: 15000 | L21: 12500 | M21: 15000 | N21: 12500 | O21: 12500 | P21: 15000 | Q21: 15000 | R21: 12500 | S21: 25000 | T21: 29000 | U21: 17000 | V21: ￥0 | W21: =SUM(K21:V21) -> 181000
A22: =A21 -> 2019024 | J22: 交通費 | K22: 71956 | L22: 63347 | M22: 56093 | N22: 39307 | O22: 24124 | P22: 40236 | Q22: 34300 | R22: 24292 | S22: 38309 | T22: 34195 | U22: 36934 | V22: ￥0 | W22: =SUM(K22:V22) -> 463093
A23: =A22 -> 2019024 | J23: 健康保険 | K23: 19210 | L23: 19210 | M23: 19210 | N23: 19210 | O23: 19210 | P23: 20340 | Q23: 20340 | R23: 20340 | S23: 20340 | T23: 20340 | U23: 20340 | V23: 20340 | W23: =SUM(K23:V23) -> 238430
A24: =A23 -> 2019024 | J24: 厚生年金 | K24: 31110 | L24: 31110 | M24: 31110 | N24: 31110 | O24: 31110 | P24: 32940 | Q24: 32940 | R24: 32940 | S24: 32940 | T24: 32940 | U24: 32940 | V24: 32940 | W24: =SUM(K24:V24) -> 386130
A25: =A24 -> 2019024 | J25: 労災保険 | K25: 1766 | L25: 1754 | M25: 1766 | N25: 1773 | O25: 1754 | P25: 1766 | Q25: 1938 | R25: 1754 | S25: 1816 | T25: 1848 | U25: 1863 | V25: 1863 | W25: =SUM(K25:V25) -> 21661
A26: =A25 -> 2019024 | J26: 雇用保険 | K26: 1943 | L26: 1929 | M26: 1943 | N26: 1950 | O26: 1929 | P26: 1943 | Q26: 2132 | R26: 1929 | S26: 1998 | T26: 2033 | U26: 2050 | V26: 2050 | W26: =SUM(K26:V26) -> 23829
A27: 2018024 | C27: =C19+1 -> 4 | I27: 社員 | J27: 総経費 | K27: =SUM(K28:K34) -> 430584 | L27: =SUM(L28:L34) -> 401326 | M27: =SUM(M28:M34) -> 387759 | N27: =SUM(N28:N34) -> 404699 | O27: =SUM(O28:O34) -> 464834 | P27: =SUM(P28:P34) -> 413919 | Q27: =SUM(Q28:Q34) -> 418244 | R27: =SUM(R28:R34) -> 410986 | ... V27: =SUM(V28:V34) -> 318677 | W27: =SUM(K27:V27) -> 4937410
A28: =A27 -> 2018024 | J28: 賃金 | K28: 346612 | L28: 315000 | M28: 315000 | N28: 315000 | O28: 372370 | P28: 315000 | Q28: 320748 | R28: 315000 | S28: 315000 | T28: 315000 | U28: 315000 | V28: 267425 | W28: =SUM(K28:V28) -> 3827155
A29: =A28 -> 2018024 | J29: 顧客対応当番 | K29: 24500 | L29: 27250 | M29: 17500 | N29: 30500 | O29: 21250 | P29: 27250 | Q29: 27250 | R29: 25500 | S29: 38000 | T29: 49250 | U29: 47750 | V29: ￥0 | W29: =SUM(K29:V29) -> 336000
A30: =A29 -> 2018024 | J30: 交通費 | K30: 16655 | L30: 16563 | M30: 12848 | N30: 16652 | O30: 19821 | P30: 20816 | Q30: 19131 | R30: 19651 | S30: 17594 | T30: 19311 | U30: 16175 | V30: ￥0 | W30: =SUM(K30:V30) -> 195217
A31: =A30 -> 2018024 | J31: 健康保険 | K31: 13300 | L31: 13300 | M31: 13300 | N31: 13300 | O31: 16150 | P31: 16150 | Q31: 16150 | R31: 16150 | S31: 16150 | T31: 16150 | U31: 16150 | V31: 16150 | W31: =SUM(K31:V31) -> 182400
A32: =A31 -> 2018024 | J32: 厚生年金 | K32: 25620 | L32: 25620 | M32: 25620 | N32: 25620 | O32: 31110 | P32: 31110 | Q32: 31110 | R32: 31110 | S32: 31110 | T32: 31110 | U32: 31110 | V32: 31110 | W32: =SUM(K32:V32) -> 351360
A33: =A32 -> 2018024 | J33: 労災保険 | K33: 1856 | L33: 1711 | M33: 1662 | N33: 1727 | O33: 1968 | P33: 1711 | Q33: 1836 | R33: 1702 | S33: 1765 | T33: 1821 | U33: 1901 | V33: 1901 | W33: =SUM(K33:V33) -> 21561
A34: =A33 -> 2018024 | J34: 雇用保険 | K34: 2041 | L34: 1882 | M34: 1829 | N34: 1900 | O34: 2165 | P34: 1882 | Q34: 2019 | R34: 1873 | S34: 1941 | T34: 2003 | U34: 2091 | V34: 2091 | W34: =SUM(K34:V34) -> 23717
A35: 2018032 | C35: =C27+1 -> 5 | E35: 転出 | I35: 社員 | J35: 総経費 | K35: =SUM(K36:K42) -> 471508 | L35: =SUM(L36:L42) -> 457739 | M35: =SUM(M36:M42) -> 472452 | N35: =SUM(N36:N42) -> 441123 | O35: =SUM(O36:O42) -> 384804 | P35: =SUM(P36:P42) -> 351291 | Q35: =SUM(Q36:Q42) -> 0 | R35: =SUM(R36:R42) -> 0 | ... V35: =SUM(V36:V42) -> 0 | W35: =SUM(K35:V35) -> 2578917
A36: =A35 -> 2018032 | J36: 賃金 | K36: 373085 | L36: 356443 | M36: 371977 | N36: 339314 | O36: 305620 | P36: 298120 | W36: =SUM(K36:V36) -> 2044559
A37: =A36 -> 2018032 | J37: 顧客対応当番 | K37: 12500 | L37: 15000 | M37: 12500 | N37: 12500 | O37: 7500 | P37: 0 | W37: =SUM(K37:V37) -> 60000
A38: =A37 -> 2018032 | J38: 交通費 | K38: 29186 | L38: 29734 | M38: 31249 | N38: 32926 | O38: 15655 | P38: 0 | W38: =SUM(K38:V38) -> 138750
A39: =A38 -> 2018032 | J39: 健康保険 | K39: 18050 | L39: 18050 | M39: 18050 | N39: 18050 | O39: 18050 | P39: 17100 | W39: =SUM(K39:V39) -> 107350
A40: =A39 -> 2018032 | J40: 厚生年金 | K40: 34770 | L40: 34770 | M40: 34770 | N40: 34770 | O40: 34770 | P40: 32940 | W40: =SUM(K40:V40) -> 206790
A41: =A40 -> 2018032 | J41: 労災保険 | K41: 1865 | L41: 1782 | M41: 1860 | N41: 1697 | O41: 1528 | P41: 1491 | W41: =SUM(K41:V41) -> 10223
A42: =A41 -> 2018032 | J42: 雇用保険 | K42: 2052 | L42: 1960 | M42: 2046 | N42: 1866 | O42: 1681 | P42: 1640 | W42: =SUM(K42:V42) -> 11245
A43: 2018040 | C43: =C35+1 -> 6 | I43: 社員 | J43: 総経費 | K43: =SUM(K44:K50) -> 500334 | L43: =SUM(L44:L50) -> 487621 | M43: =SUM(M44:M50) -> 485475 | N43: =SUM(N44:N50) -> 530188 | O43: =SUM(O44:O50) -> 483465 | P43: =SUM(P44:P50) -> 466065 | Q43: =SUM(Q44:Q50) -> 541093 | R43: =SUM(R44:R50) -> 469339 | ... V43: =SUM(V44:V50) -> 356560 | W43: =SUM(K43:V43) -> 5805312
A44: =A43 -> 2018040 | J44: 賃金 | K44: 404710 | L44: 375000 | M44: 392238 | N44: 420833 | O44: 375000 | P44: 375000 | Q44: 439896 | R44: 375000 | S44: 417081 | T44: 375000 | U44: 375000 | V44: 299300 | W44: =SUM(K44:V44) -> 4624058
A45: =A44 -> 2018040 | J45: 顧客対応当番 | K45: 25000 | L45: 21250 | M45: 17500 | N45: 29000 | O45: 28500 | P45: 19250 | Q45: 19250 | R45: 23750 | S45: 33250 | T45: 17500 | U45: 30500 | V45: ￥0 | W45: =SUM(K45:V45) -> 264750
A46: =A45 -> 2018040 | J46: 交通費 | K46: 13292 | L46: 34391 | M46: 18614 | N46: 22812 | O46: 22909 | P46: 14856 | Q46: 24053 | R46: 13582 | S46: 27281 | T46: 19034 | U46: 18776 | V46: ￥0 | W46: =SUM(K46:V46) -> 229600
A47: =A46 -> 2018040 | J47: 健康保険 | K47: 18050 | L47: 18050 | M47: 18050 | N47: 18050 | O47: 18050 | P47: 18050 | Q47: 18050 | R47: 18050 | S47: 18050 | T47: 18050 | U47: 18050 | V47: 18050 | W47: =SUM(K47:V47) -> 216600
A48: =A47 -> 2018040 | J48: 厚生年金 | K48: 34770 | L48: 34770 | M48: 34770 | N48: 34770 | O48: 34770 | P48: 34770 | Q48: 34770 | R48: 34770 | S48: 34770 | T48: 34770 | U48: 34770 | V48: 34770 | W48: =SUM(K48:V48) -> 417240
A49: =A48 -> 2018040 | J49: 労災保険 | K49: 2149 | L49: 1981 | M49: 2049 | N49: 2249 | O49: 2017 | P49: 1971 | Q49: 2416 | R49: 1994 | S49: 2252 | T49: 1962 | U49: 2114 | V49: 2114 | W49: =SUM(K49:V49) -> 25268
A50: =A49 -> 2018040 | J50: 雇用保険 | K50: 2363 | L50: 2179 | M50: 2254 | N50: 2474 | O50: 2219 | P50: 2168 | Q50: 2658 | R50: 2193 | S50: 2477 | T50: 2159 | U50: 2326 | V50: 2326 | W50: =SUM(K50:V50) -> 27796
A51: 2018047 | C51: =C43+1 -> 7 | I51: 社員 | J51: 総経費 | K51: =SUM(K52:K58) -> 393667 | L51: =SUM(L52:L58) -> 439442 | M51: =SUM(M52:M58) -> 383452 | N51: =SUM(N52:N58) -> 378399 | O51: =SUM(O52:O58) -> 418803 | P51: =SUM(P52:P58) -> 403511 | Q51: =SUM(Q52:Q58) -> 394548 | R51: =SUM(R52:R58) -> 406905 | ... V51: =SUM(V52:V58) -> 294367 | W51: =SUM(K51:V51) -> 4793996
A52: =A51 -> 2018047 | J52: 賃金 | K52: 288058 | L52: 325858 | M52: 277950 | N52: 277950 | O52: 299931 | P52: 277950 | Q52: 298428 | R52: 277950 | S52: 277950 | T52: 277950 | U52: 277950 | V52: 240375 | W52: =SUM(K52:V52) -> 3398300
A53: =A52 -> 2018047 | J53: 顧客対応当番 | K53: 57500 | L53: 65000 | M53: 57500 | N53: 52500 | O53: 65000 | P53: 60000 | Q53: 42500 | R53: 65000 | S53: 88000 | T53: 116000 | U53: 81000 | V53: ￥0 | W53: =SUM(K53:V53) -> 750000
A54: =A53 -> 2018047 | J54: 交通費 | K54: 0 | L54: 0 | M54: 0 | N54: 0 | O54: 0 | P54: 11972 | Q54: 0 | R54: 10314 | S54: 0 | T54: 0 | U54: 0 | V54: ￥0 | W54: =SUM(K54:V54) -> 22286
A55: =A54 -> 2018047 | J55: 健康保険 | K55: 15200 | L55: 15200 | M55: 15200 | N55: 15200 | O55: 17100 | P55: 17100 | Q55: 17100 | R55: 17100 | S55: 17100 | T55: 17100 | U55: 17100 | V55: 17100 | W55: =SUM(K55:V55) -> 197600
A56: =A55 -> 2018047 | J56: 厚生年金 | K56: 29280 | L56: 29280 | M56: 29280 | N56: 29280 | O56: 32940 | P56: 32940 | Q56: 32940 | R56: 32940 | S56: 32940 | T56: 32940 | U56: 32940 | V56: 32940 | W56: =SUM(K56:V56) -> 380640
A57: =A56 -> 2018047 | J57: 労災保険 | K57: 1728 | L57: 1954 | M57: 1677 | N57: 1652 | O57: 1825 | P57: 1690 | Q57: 1705 | R57: 1715 | S57: 1830 | T57: 1970 | U57: 1882 | V57: 1882 | W57: =SUM(K57:V57) -> 21510
A58: =A57 -> 2018047 | J58: 雇用保険 | K58: 1901 | L58: 2150 | M58: 1845 | N58: 1817 | O58: 2007 | P58: 1859 | Q58: 1875 | R58: 1886 | S58: 2013 | T58: 2167 | U58: 2070 | V58: 2070 | W58: =SUM(K58:V58) -> 23660
A59: 2019020 | C59: =C51+1 -> 8 | E59: 転出 | I59: 社員 | J59: 総経費 | K59: =SUM(K60:K66) -> 400577 | L59: =SUM(L60:L66) -> 400797 | M59: =SUM(M60:M66) -> 391857 | N59: =SUM(N60:N66) -> 398674 | O59: =SUM(O60:O66) -> 383736 | P59: =SUM(P60:P66) -> 376244 | Q59: =SUM(Q60:Q66) -> 379507 | R59: =SUM(R60:R66) -> 364731 | ... V59: =SUM(V60:V66) -> 0 | W59: =SUM(K59:V59) -> 3221403
A60: =A59 -> 2019020 | J60: 賃金 | K60: 313108 | L60: 297680 | M60: 299435 | N60: 297680 | O60: 290180 | P60: 290180 | Q60: 292680 | R60: 287680 | S60: 29000 | W60: =SUM(K60:V60) -> 2397623
A61: =A60 -> 2019020 | J61: 顧客対応当番 | K61: 12500 | L61: 20000 | M61: 15000 | N61: 20000 | O61: 12500 | P61: 12500 | Q61: 15000 | R61: 10000 | S61: 29000 | W61: =SUM(K61:V61) -> 146500
A62: =A61 -> 2019020 | J62: 交通費 | K62: 24421 | L62: 32732 | M62: 27018 | N62: 30609 | O62: 30749 | P62: 28817 | Q62: 26773 | R62: 22331 | S62: 25276 | W62: =SUM(K62:V62) -> 248726
A63: =A62 -> 2019020 | J63: 健康保険 | K63: 16150 | L63: 16150 | M63: 16150 | N63: 16150 | O63: 16150 | P63: 14250 | Q63: 14250 | R63: 14250 | S63: 14250 | W63: =SUM(K63:V63) -> 137750
A64: =A63 -> 2019020 | J64: 厚生年金 | K64: 31110 | L64: 31110 | M64: 31110 | N64: 31110 | O64: 31110 | P64: 27450 | Q64: 27450 | R64: 27450 | S64: 27450 | W64: =SUM(K64:V64) -> 265350
A65: =A64 -> 2019020 | J65: 労災保険 | K65: 1566 | L65: 1488 | M65: 1497 | N65: 1488 | O65: 1451 | P65: 1451 | Q65: 1597 | R65: 1438 | S65: 145 | W65: =SUM(K65:V65) -> 12121
A66: =A65 -> 2019020 | J66: 雇用保険 | K66: 1722 | L66: 1637 | M66: 1647 | N66: 1637 | O66: 1596 | P66: 1596 | Q66: 1757 | R66: 1582 | S66: 159 | W66: =SUM(K66:V66) -> 13333
A67: 2019027 | C67: =C59+1 -> 9 | I67: 社員 | J67: 総経費 | K67: =SUM(K68:K74) -> 430314 | L67: =SUM(L68:L74) -> 428809 | M67: =SUM(M68:M74) -> 429820 | N67: =SUM(N68:N74) -> 441974 | O67: =SUM(O68:O74) -> 423357 | P67: =SUM(P68:P74) -> 419352 | Q67: =SUM(Q68:Q74) -> 467904 | R67: =SUM(R68:R74) -> 435982 | ... V67: =SUM(V68:V74) -> 318551 | W67: =SUM(K67:V67) -> 5101112
A68: =A67 -> 2019027 | J68: 賃金 | K68: 330050 | L68: 328624 | M68: 321812 | N68: 329901 | O68: 315000 | P68: 315000 | Q68: 343951 | R68: 315000 | S68: 315000 | T68: 315000 | U68: 315000 | V68: 267425 | W68: =SUM(K68:V68) -> 3811763
A69: =A68 -> 2019027 | J69: 顧客対応当番 | K69: 17500 | L69: 15000 | M69: 15000 | N69: 12500 | O69: 15000 | P69: 26750 | Q69: 23750 | R69: 25000 | S69: 15500 | T69: 23500 | U69: 35750 | V69: ￥0 | W69: =SUM(K69:V69) -> 225250
A70: =A69 -> 2019027 | J70: 交通費 | K70: 37414 | L70: 39877 | M70: 47772 | N70: 54278 | O70: 42632 | P70: 26753 | Q70: 48572 | R70: 45152 | S70: 49952 | T70: 43066 | U70: 39611 | V70: ￥0 | W70: =SUM(K70:V70) -> 475079
A71: =A70 -> 2019027 | J71: 健康保険 | K71: 14250 | L71: 14250 | M71: 14250 | N71: 14250 | O71: 16150 | P71: 16150 | Q71: 16150 | R71: 16150 | S71: 16150 | T71: 16150 | U71: 16150 | V71: 16150 | W71: =SUM(K71:V71) -> 186200
A72: =A71 -> 2019027 | J72: 厚生年金 | K72: 27450 | L72: 27450 | M72: 27450 | N72: 27450 | O72: 31110 | P72: 31110 | Q72: 31110 | R72: 31110 | S72: 31110 | T72: 31110 | U72: 31110 | V72: 31110 | W72: =SUM(K72:V72) -> 358680
A73: =A72 -> 2019027 | J73: 労災保険 | K73: 1738 | L73: 1718 | M73: 1684 | N73: 1712 | O73: 1650 | P73: 1709 | Q73: 2081 | R73: 1700 | S73: 1652 | T73: 1692 | U73: 1841 | V73: 1841 | W73: =SUM(K73:V73) -> 21018
A74: =A73 -> 2019027 | J74: 雇用保険 | K74: 1912 | L74: 1890 | M74: 1852 | N74: 1883 | O74: 1815 | P74: 1880 | Q74: 2290 | R74: 1870 | S74: 1818 | T74: 1862 | U74: 2025 | V74: 2025 | W74: =SUM(K74:V74) -> 23122
A75: 2019023 | C75: =C67+1 -> 10 | I75: 社員 | J75: 総経費 | K75: =SUM(K76:K82) -> 422680 | L75: =SUM(L76:L82) -> 365687 | M75: =SUM(M76:M82) -> 405840 | N75: =SUM(N76:N82) -> 382415 | O75: =SUM(O76:O82) -> 377044 | P75: =SUM(P76:P82) -> 377909 | Q75: =SUM(Q76:Q82) -> 358093 | R75: =SUM(R76:R82) -> 365245 | ... V75: =SUM(V76:V82) -> 285384 | W75: =SUM(K75:V75) -> 4548158
A76: =A75 -> 2019023 | J76: 賃金 | K76: 308094 | L76: 274700 | M76: 301504 | N76: 286209 | O76: 274700 | P76: 274700 | Q76: 274700 | R76: 274700 | S76: 301523 | T76: 274700 | U76: 274700 | V76: 237575 | W76: =SUM(K76:V76) -> 3357805
A77: =A76 -> 2019023 | J77: 顧客対応当番 | K77: 25000 | L77: 10000 | M77: 17500 | N77: 17500 | O77: 15000 | P77: 17500 | Q77: 10000 | R77: 12500 | S77: 34000 | T77: 39000 | U77: 25000 | V77: ￥0 | W77: =SUM(K77:V77) -> 223000
A78: =A77 -> 2019023 | J78: 交通費 | K78: 47169 | L78: 39078 | M78: 44566 | N78: 36597 | O78: 39823 | P78: 38161 | Q78: 25654 | R78: 30549 | S78: 32799 | T78: 45395 | U78: 37159 | V78: ￥0 | W78: =SUM(K78:V78) -> 416950
A79: =A78 -> 2019023 | J79: 健康保険 | K79: 13300 | L79: 13300 | M79: 13300 | N79: 13300 | O79: 15200 | P79: 15200 | Q79: 15200 | R79: 15200 | S79: 15200 | T79: 15200 | U79: 15200 | V79: 15200 | W79: =SUM(K79:V79) -> 174800
A80: =A79 -> 2019023 | J80: 厚生年金 | K80: 25620 | L80: 25620 | M80: 25620 | N80: 25620 | O80: 29280 | P80: 29280 | Q80: 29280 | R80: 29280 | S80: 29280 | T80: 29280 | U80: 29280 | V80: 29280 | W80: =SUM(K80:V80) -> 336720
A81: =A80 -> 2019023 | J81: 労災保険 | K81: 1665 | L81: 1423 | M81: 1595 | N81: 1519 | O81: 1448 | P81: 1461 | Q81: 1552 | R81: 1436 | S81: 1678 | T81: 1568 | U81: 1585 | V81: 1585 | W81: =SUM(K81:V81) -> 18515
A82: =A81 -> 2019023 | J82: 雇用保険 | K82: 1832 | L82: 1566 | M82: 1755 | N82: 1670 | O82: 1593 | P82: 1607 | Q82: 1707 | R82: 1580 | S82: 1845 | T82: 1725 | U82: 1744 | V82: 1744 | W82: =SUM(K82:V82) -> 20368
A83: 2020008 | C83: =C75+1 -> 11 | I83: 社員 | J83: 総経費 | K83: =SUM(K84:K90) -> 481606 | L83: =SUM(L84:L90) -> 475085 | M83: =SUM(M84:M90) -> 465817 | N83: =SUM(N84:N90) -> 443702 | O83: =SUM(O84:O90) -> 443211 | P83: =SUM(P84:P90) -> 444235 | Q83: =SUM(Q84:Q90) -> 448538 | R83: =SUM(R84:R90) -> 445174 | ... V83: =SUM(V84:V90) -> 366011 | W83: =SUM(K83:V83) -> 5354765
A84: =A83 -> 2020008 | J84: 賃金 | K84: 360354 | L84: 353730 | M84: 353730 | N84: 353730 | O84: 353730 | P84: 353730 | Q84: 353730 | R84: 353730 | S84: 353730 | T84: 353730 | U84: 350740 | V84: 305905 | W84: =SUM(K84:V84) -> 4200569
A85: =A84 -> 2020008 | J85: 顧客対応当番 | K85: 25000 | L85: 27500 | M85: 20000 | N85: 2500 | O85: 0 | P85: 0 | Q85: 0 | R85: 0 | S85: 0 | T85: 14000 | U85: 0 | V85: ￥0 | W85: =SUM(K85:V85) -> 89000
A86: =A85 -> 2020008 | J86: 交通費 | K86: 31526 | L86: 29172 | M86: 27482 | N86: 23052 | O86: 25086 | P86: 30550 | Q86: 34492 | R86: 31489 | S86: 0 | T86: 62054 | U86: 26969 | V86: ￥0 | W86: =SUM(K86:V86) -> 321872
A87: =A86 -> 2020008 | J87: 健康保険 | K87: 23165 | L87: 23165 | M87: 23165 | N87: 23165 | O87: 23165 | P87: 21470 | Q87: 21470 | R87: 21470 | S87: 21470 | T87: 21470 | U87: 21470 | V87: 21470 | W87: =SUM(K87:V87) -> 266115
A88: =A87 -> 2020008 | J88: 厚生年金 | K88: 37515 | L88: 37515 | M88: 37515 | N88: 37515 | O88: 37515 | P88: 34770 | Q88: 34770 | R88: 34770 | S88: 34770 | T88: 34770 | U88: 34770 | V88: 34770 | W88: =SUM(K88:V88) -> 430965
A89: =A88 -> 2020008 | J89: 労災保険 | K89: 1927 | L89: 1906 | M89: 1869 | N89: 1781 | O89: 1769 | P89: 1769 | Q89: 1941 | R89: 1769 | S89: 1769 | T89: 1839 | U89: 1841 | V89: 1841 | W89: =SUM(K89:V89) -> 22021
A90: =A89 -> 2020008 | J90: 雇用保険 | K90: 2119 | L90: 2097 | M90: 2056 | N90: 1959 | O90: 1946 | P90: 1946 | Q90: 2135 | R90: 1946 | S90: 1946 | T90: 2023 | U90: 2025 | V90: 2025 | W90: =SUM(K90:V90) -> 24223
A91: 2020006 | C91: =C83+1 -> 12 | E91: 転出 | I91: 社員 | J91: 総経費 | K91: =SUM(K92:K98) -> 486463 | L91: =SUM(L92:L98) -> 424752 | M91: =SUM(M92:M98) -> 393755 | N91: =SUM(N92:N98) -> 417534 | O91: =SUM(O92:O98) -> 390105 | P91: =SUM(P92:P98) -> 382099 | Q91: =SUM(Q92:Q98) -> 404946 | R91: =SUM(R92:R98) -> 377007 | ... V91: =SUM(V92:V98) -> 0 | W91: =SUM(K91:V91) -> 3597868
A92: =A91 -> 2020006 | J92: 賃金 | K92: 371093 | L92: 306810 | M92: 301037 | N92: 318907 | O92: 294310 | P92: 294310 | Q92: 318132 | R92: 294310 | S92: 274310 | W92: =SUM(K92:V92) -> 2773219
A93: =A92 -> 2020006 | J93: 顧客対応当番 | K93: 20000 | L93: 22500 | M93: 12500 | N93: 15000 | O93: 10000 | P93: 10000 | Q93: 7500 | R93: 10000 | S93: 0 | W93: =SUM(K93:V93) -> 107500
A94: =A93 -> 2020006 | J94: 交通費 | K94: 41434 | L94: 42181 | M94: 27017 | N94: 30238 | O94: 32664 | P94: 30218 | Q94: 31167 | R94: 25126 | S94: 0 | W94: =SUM(K94:V94) -> 260045
A95: =A94 -> 2020006 | J95: 健康保険 | K95: 17100 | L95: 17100 | M95: 17100 | N95: 17100 | O95: 17100 | P95: 15200 | Q95: 15200 | R95: 15200 | S95: 15200 | W95: =SUM(K95:V95) -> 146300
A96: =A95 -> 2020006 | J96: 厚生年金 | K96: 32940 | L96: 32940 | M96: 32940 | N96: 32940 | O96: 32940 | P96: 29280 | Q96: 29280 | R96: 29280 | S96: 29280 | W96: =SUM(K96:V96) -> 281820
A97: =A96 -> 2020006 | J97: 労災保険 | K97: 1855 | L97: 1534 | M97: 1505 | N97: 1595 | O97: 1472 | P97: 1472 | Q97: 1746 | R97: 1472 | S97: 1422 | W97: =SUM(K97:V97) -> 14073
A98: =A97 -> 2020006 | J98: 雇用保険 | K98: 2041 | L98: 1687 | M98: 1656 | N98: 1754 | O98: 1619 | P98: 1619 | Q98: 1921 | R98: 1619 | S98: 995 | W98: =SUM(K98:V98) -> 14911
A99: 2020021 | C99: =C91+1 -> 13 | I99: 社員 | J99: 総経費 | K99: =SUM(K100:K106) -> 388509 | L99: =SUM(L100:L106) -> 351680 | M99: =SUM(M100:M106) -> 370925 | N99: =SUM(N100:N106) -> 376542 | O99: =SUM(O100:O106) -> 369518 | P99: =SUM(P100:P106) -> 375362 | Q99: =SUM(Q100:Q106) -> 377508 | R99: =SUM(R100:R106) -> 368973 | ... V99: =SUM(V100:V106) -> 286929 | W99: =SUM(K99:V99) -> 4416093
A100: =A99 -> 2020021 | J100: 賃金 | K100: 298678 | L100: 279700 | M100: 279700 | N100: 284425 | O100: 279700 | P100: 279700 | Q100: 290095 | R100: 279700 | S100: 279700 | T100: 279700 | U100: 299700 | V100: 241900 | W100: =SUM(K100:V100) -> 3372698
...

Sheet UAL常駐
A1: 社員番号 | B1: 氏名 | C1: No | D1: 派遣/請負 | E1: 担当 | F1: 氏名 | G1: 派遣先部署 | H1: 作業名 | I1: 契約先 | J1: 外注会社 | K1: 売上単価 (支払単価） 【≒粗利】 | L1: 4月 | M1: 5月 | N1: 6月 | O1: 7月 | P1: 8月 | Q1: 9月 | R1: 10月 | S1: 11月 | T1: 12月 | U1: 1月 | V1: 2月 | W1: 3月 | X1: 合計
C2: UAL常駐 | K2: 売上 | L2: =L125 -> 3822500 | M2: =M125 -> 3822500 | N2: =N125 -> 3817500 | O2: =O125 -> 3819455 | P2: =P125 -> 3602025 | Q2: =Q125 -> 3687320 | R2: =R125 -> 3302435 | S2: =S125 -> 3179855 | ... W2: =W125 -> 4140000 | X2: =SUM(L2:W2) -> 45020030
K3: 仕入 | L3: =L126 -> 2573624 | M3: =M126 -> 2556425 | N3: =N126 -> 2555803 | O3: =O126 -> 2555021 | P3: =P126 -> 2540089 | Q3: =Q126 -> 2588419 | R3: =R126 -> 2305130 | S3: =S126 -> 2286257 | ... W3: =W126 -> 2911560.4 | X3: =SUM(L3:W3) -> 31362835
K4: 粗利 | L4: =L2-L3 -> 1248876 | M4: =M2-M3 -> 1266075 | N4: =N2-N3 -> 1261697 | O4: =O2-O3 -> 1264434 | P4: =P2-P3 -> 1061936 | Q4: =Q2-Q3 -> 1098901 | R4: =R2-R3 -> 997305 | S4: =S2-S3 -> 893598 | ... W4: =W2-W3 -> 1228439.6 | X4: =SUM(L4:W4) -> 13657195
A5: 2020031 | C5: 1 | D5: 派遣 | G5: DSD/KDX | J5: 社員 | K5: 総受注金額 | L5: =L6+L7 -> 600000 | M5: =M6+M7 -> 600000 | N5: =N6+N7 -> 600000 | O5: =O6+O7 -> 600000 | P5: =P6+P7 -> 600000 | Q5: =Q6+Q7 -> 600000 | R5: =R6+R7 -> 607500 | S5: =S6+S7 -> 570000 | ... W5: =W6+W7 -> 580000 | X5: =SUM(L5:W5) -> 7157500
A6: =+A5 -> 2020031 | K6: 派遣金額 | L6: 600000 | M6: 600000 | N6: 600000 | O6: 600000 | P6: 600000 | Q6: 600000 | R6: 607500 | S6: 570000 | T6: 600000 | U6: 600000 | V6: 600000 | W6: 580000 | X6: =SUM(L6:W6) -> 7157500
A7: =+A6 -> 2020031 | K7: 交通費 | X7: 0
A8: =+A7 -> 2020031 | K8: 総経費 | L8: =SUM(L9:L15) -> 418728 | M8: =SUM(M9:M15) -> 417920 | N8: =SUM(N9:N15) -> 418768 | O8: =SUM(O9:O15) -> 420132 | P8: =SUM(P9:P15) -> 419173 | Q8: =SUM(Q9:Q15) -> 422941 | R8: =SUM(R9:R15) -> 439048 | S8: =SUM(S9:S15) -> 422016 | ... W8: =SUM(W9:W15) -> 421052 | X8: =SUM(L8:W8) -> 5075322
A9: =+A8 -> 2020031 | K9: 賃金 | L9: 343640 | M9: 342840 | N9: 342840 | O9: 344040 | P9: 343240 | Q9: 344040 | R9: 359979 | S9: 343124 | T9: 352510 | U9: 343240 | V9: 342840 | W9: 342840 | X9: =SUM(L9:W9) -> 4145173
A10: =+A9 -> 2020031 | K10: 交通費その他 | X10: =SUM(L10:W10) -> 0
A11: =+A10 -> 2020031 | K11: 通勤定期代 | L11: 20940 | M11: 20940 | N11: 21780 | O11: 21780 | P11: 21780 | Q11: 21780 | R11: 21780 | S11: 21780 | T11: 21780 | U11: 21780 | V11: 21780 | W11: 20940 | X11: =SUM(L11:W11) -> 258840
A12: =+A11 -> 2020031 | K12: 健康保険 | L12: 19210 | M12: 19210 | N12: 19210 | O12: 19210 | P12: 19210 | Q12: 20340 | R12: 20340 | S12: 20340 | T12: 20340 | U12: 20340 | V12: 20340 | W12: 20340 | X12: =SUM(L12:W12) -> 238430
A13: =+A12 -> 2020031 | K13: 厚生年金 | L13: 31110 | M13: 31110 | N13: 31110 | O13: 31110 | P13: 31110 | Q13: 32940 | R13: 32940 | S13: 32940 | T13: 32940 | U13: 32940 | V13: 32940 | W13: 32940 | X13: =SUM(L13:W13) -> 386130
A14: =+A13 -> 2020031 | K14: 労災保険 | L14: 1823 | M14: 1819 | N14: 1823 | O14: 1711 | P14: 1825 | Q14: 1829 | R14: 1909 | S14: 1825 | T14: 1871 | U14: 1825 | V14: 1910 | W14: 1711 | X14: =SUM(L14:W14) -> 21881
A15: =+A14 -> 2020031 | K15: 雇用保険 | L15: 2005 | M15: 2001 | N15: 2005 | O15: 2281 | P15: 2008 | Q15: 2012 | R15: 2100 | S15: 2007 | T15: 2059 | U15: 2008 | V15: 2101 | W15: 2281 | X15: =SUM(L15:W15) -> 24868
A16: =+A15 -> 2020031 | K16: 粗利 | L16: =L5-L8 -> 181272 | M16: =M5-M8 -> 182080 | N16: =N5-N8 -> 181232 | O16: =O5-O8 -> 179868 | P16: =P5-P8 -> 180827 | Q16: =Q5-Q8 -> 177059 | R16: =R5-R8 -> 168452 | S16: =S5-S8 -> 147984 | ... X16: =X5-X8 -> 2082178
A17: 2022014 | C17: =C5+1 -> 2 | D17: 派遣 | G17: DSD/KDX | J17: 社員 | K17: 総受注金額 | L17: =L18+L19 -> 460000 | M17: =M18+M19 -> 460000 | N17: =N18+N19 -> 460000 | O17: =O18+O19 -> 460000 | P17: =P18+P19 -> 447040 | Q17: =Q18+Q19 -> 460000 | R17: =R18+R19 -> 460000 | S17: =S18+S19 -> 403840 | ... W17: =W18+W19 -> 430000 | X17: =SUM(L17:W17) -> 5407920
A18: =+A17 -> 2022014 | K18: 派遣金額 | L18: 460000 | M18: 460000 | N18: 460000 | O18: 460000 | P18: 447040 | Q18: 460000 | R18: 460000 | S18: 403840 | T18: 460000 | U18: 460000 | V18: 447040 | W18: 430000 | X18: =SUM(L18:W18) -> 5407920
A19: =+A18 -> 2022014 | K19: 交通費 | X19: 0
A20: =+A19 -> 2022014 | K20: 総経費 | L20: =SUM(L21:L27) -> 310095 | M20: =SUM(M21:M27) -> 309287 | N20: =SUM(N21:N27) -> 310452 | O20: =SUM(O21:O27) -> 308404 | P20: =SUM(P21:P27) -> 306146 | Q20: =SUM(Q21:Q27) -> 309287 | R20: =SUM(R21:R27) -> 310846 | S20: =SUM(S21:S27) -> 308273 | ... W20: =SUM(W21:W27) -> 311345.44 | X20: =SUM(L20:W20) -> 3699501.4
A21: =+A20 -> 2022014 | K21: 賃金 | L21: 268000 | M21: 267200 | N21: 266800 | O21: 267200 | P21: 267200 | Q21: 267200 | R21: 267200 | S21: 256873 | T21: 267200 | U21: 267200 | V21: 260873 | W21: 260000 | X21: =SUM(L21:W21) -> 3182946
A22: =+A21 -> 2022014 | K22: 交通費その他 | X22: =SUM(L22:W22) -> 0
A23: =+A22 -> 2022014 | K23: 通勤定期代 | L23: 3108 | M23: 3108 | N23: 4662 | O23: 1554 | P23: 0 | Q23: 3108 | R23: 4652 | S23: 12432 | T23: 1554 | U23: 1554 | V23: 0 | W23: 11695.444 | X23: =SUM(L23:W23) -> 47427.444
A24: =+A23 -> 2022014 | K24: 健康保険 | L24: 12350 | M24: 12350 | N24: 12350 | O24: 12350 | P24: 12350 | Q24: 12350 | R24: 12350 | S24: 12350 | T24: 12350 | U24: 12350 | V24: 12350 | W24: 12350 | X24: =SUM(L24:W24) -> 148200
A25: =+A24 -> 2022014 | K25: 厚生年金 | L25: 23790 | M25: 23790 | N25: 23790 | O25: 23790 | P25: 23790 | Q25: 23790 | R25: 23790 | S25: 23790 | T25: 23790 | U25: 23790 | V25: 23790 | W25: 23790 | X25: =SUM(L25:W25) -> 285480
A26: =+A25 -> 2022014 | K26: 労災保険 | L26: 1356 | M26: 1352 | N26: 1357 | O26: 1300 | P26: 1336 | Q26: 1352 | R26: 1359 | S26: 1347 | T26: 1344 | U26: 1344 | V26: 1391 | W26: 1300 | X26: =SUM(L26:W26) -> 16138
A27: =+A26 -> 2022014 | K27: 雇用保険 | L27: 1491 | M27: 1487 | N27: 1493 | O27: 2210 | P27: 1470 | Q27: 1487 | R27: 1495 | S27: 1481 | T27: 1478 | U27: 1478 | V27: 1530 | W27: 2210 | X27: =SUM(L27:W27) -> 19310
A28: =+A27 -> 2022014 | K28: 粗利 | L28: =L17-L20 -> 149905 | M28: =M17-M20 -> 150713 | N28: =N17-N20 -> 149548 | O28: =O17-O20 -> 151596 | P28: =P17-P20 -> 140894 | Q28: =Q17-Q20 -> 150713 | R28: =R17-R20 -> 149154 | S28: =S17-S20 -> 95567 | ... X28: =X17-X20 -> 1708418.6
A29: 2023021 | C29: =C17+1 -> 3 | D29: 派遣 | I29: 有楽町/国際ビル | J29: 社員 | K29: 総受注金額 | L29: =L30+L31 -> 462500 | M29: =M30+M31 -> 462500 | N29: =N30+N31 -> 465000 | O29: =O30+O31 -> 462500 | P29: =P30+P31 -> 465000 | Q29: =Q30+Q31 -> 462500 | R29: =R30+R31 -> 462500 | S29: =S30+S31 -> 458270 | ... W29: =W30+W31 -> 450000 | X29: =SUM(L29:W29) -> 5508660
A30: =+A29 -> 2023021 | K30: 派遣金額 | L30: 450000 | M30: 450000 | N30: 450000 | O30: 450000 | P30: 450000 | Q30: 450000 | R30: 450000 | S30: 445770 | T30: 450000 | U30: 450000 | V30: 420390 | W30: 450000 | X30: =SUM(L30:W30) -> 5366160
A31: =+A30 -> 2023021 | K31: 顧客対応当番 | L31: 12500 | M31: 12500 | N31: 15000 | O31: 12500 | P31: 15000 | Q31: 12500 | R31: 12500 | S31: 12500 | T31: 12500 | U31: 12500 | V31: 12500 | W31: 0 | X31: =SUM(L31:W31) -> 142500
A32: =+A31 -> 2023021 | K32: 総経費 | L32: =SUM(L33:L39) -> 320999 | M32: =SUM(M33:M39) -> 321808 | N32: =SUM(N33:N39) -> 324335 | O32: =SUM(O33:O39) -> 321990 | P32: =SUM(P33:P39) -> 324335 | Q32: =SUM(Q33:Q39) -> 323779 | R32: =SUM(R33:R39) -> 324588 | S32: =SUM(S33:S39) -> 321968 | ... W32: =SUM(W33:W39) -> 306670 | X32: =SUM(L32:W32) -> 3864014
A33: =+A32 -> 2023021 | K33: 賃金 | L33: 261900 | M33: 262700 | N33: 265200 | O33: 263100 | P33: 265200 | Q33: 261900 | R33: 262700 | S33: 260106 | T33: 263100 | U33: 262700 | V33: 261900 | W33: 245000 | X33: =SUM(L33:W33) -> 3135506
A34: =+A33 -> 2023021 | K34: 交通費その他 | X34: =SUM(L34:W34) -> 0
A35: =+A34 -> 2023021 | K35: 通勤定期代 | L35: 20000 | M35: 20000 | N35: 20000 | O35: 20000 | P35: 20000 | Q35: 20000 | R35: 20000 | S35: 20000 | T35: 20000 | U35: 20000 | V35: 20000 | W35: 20000 | X35: =SUM(L35:W35) -> 240000
A36: =+A35 -> 2023021 | K36: 健康保険 | L36: 12350 | M36: 12350 | N36: 12350 | O36: 12350 | P36: 12350 | Q36: 13300 | R36: 13300 | S36: 13300 | T36: 13300 | U36: 13300 | V36: 13300 | W36: 13300 | X36: =SUM(L36:W36) -> 154850
A37: =+A36 -> 2023021 | K37: 厚生年金 | L37: 23790 | M37: 23790 | N37: 23790 | O37: 23790 | P37: 23790 | Q37: 25620 | R37: 25620 | S37: 25620 | T37: 25620 | U37: 25620 | V37: 25620 | W37: 25620 | X37: =SUM(L37:W37) -> 298290
A38: =+A37 -> 2023021 | K38: 労災保険 | L38: 1409 | M38: 1413 | N38: 1426 | O38: 1250 | P38: 1426 | Q38: 1409 | R38: 1413 | S38: 1401 | T38: 1415 | U38: 1413 | V38: 1496 | W38: 1250 | X38: =SUM(L38:W38) -> 16721
A39: =+A38 -> 2023021 | K39: 雇用保険 | L39: 1550 | M39: 1555 | N39: 1569 | O39: 1500 | P39: 1569 | Q39: 1550 | R39: 1555 | S39: 1541 | T39: 1557 | U39: 1555 | V39: 1646 | W39: 1500 | X39: =SUM(L39:W39) -> 18647
A40: =+A39 -> 2023021 | K40: 粗利 | L40: =L29-L32 -> 141501 | M40: =M29-M32 -> 140692 | N40: =N29-N32 -> 140665 | O40: =O29-O32 -> 140510 | P40: =P29-P32 -> 140665 | Q40: =Q29-Q32 -> 138721 | R40: =R29-R32 -> 137912 | S40: =S29-S32 -> 136302 | ... X40: =X29-X32 -> 1644646
A41: 2023024 | C41: =C29+1 -> 4 | D41: 派遣 | I41: 横浜SS | J41: 社員 | K41: 総受注金額 | L41: =L42+L43 -> 487500 | M41: =M42+M43 -> 485000 | N41: =N42+N43 -> 482500 | O41: =O42+O43 -> 485000 | P41: =P42+P43 -> 391650 | Q41: =Q42+Q43 -> 439430 | R41: =R42+R43 -> 480000 | S41: =S42+S43 -> 490000 | ... W41: =W42+W43 -> 450000 | X41: =SUM(L41:W41) -> 5653580
A42: =+A41 -> 2023024 | K42: 派遣金額 | L42: 470000 | M42: 470000 | N42: 470000 | O42: 470000 | P42: 389150 | Q42: 424430 | R42: 470000 | S42: 470000 | T42: 470000 | U42: 470000 | V42: 470000 | W42: 450000 | X42: =SUM(L42:W42) -> 5493580
A43: =+A42 -> 2023024 | K43: 顧客対応当番 | L43: 17500 | M43: 15000 | N43: 12500 | O43: 15000 | P43: 2500 | Q43: 15000 | R43: 10000 | S43: 20000 | T43: 17500 | U43: 20000 | V43: 15000 | W43: 0 | X43: 0
A44: =+A43 -> 2023024 | K44: 総経費 | L44: =SUM(L45:L51) -> 312965 | M44: =SUM(M45:M51) -> 311550 | N44: =SUM(N45:N51) -> 307458 | O44: =SUM(O45:O51) -> 313263 | P44: =SUM(P45:P51) -> 294530 | Q44: =SUM(Q45:Q51) -> 313700 | R44: =SUM(R45:R51) -> 311603 | S44: =SUM(S45:S51) -> 321464 | ... W44: =SUM(W45:W51) -> 306584 | X44: =SUM(L44:W44) -> 3748267
A45: =+A44 -> 2023024 | K45: 賃金 | L45: 262500 | M45: 260000 | N45: 257500 | O45: 260000 | P45: 247500 | Q45: 260000 | R45: 255000 | S45: 265000 | T45: 262500 | U45: 265000 | V45: 260000 | W45: 245000 | X45: =SUM(L45:W45) -> 3100000
A46: =+A45 -> 2023024 | K46: 交通費その他 | X46: =SUM(L46:W46) -> 0
A47: =+A46 -> 2023024 | K47: 通勤定期代 | L47: 14200 | M47: 15300 | N47: 13750 | O47: 17666 | P47: 10956 | Q47: 11924 | R47: 14850 | S47: 14608 | T47: 16016 | U47: 14894 | V47: 11088 | W47: 20427 | X47: =SUM(L47:W47) -> 175679
A48: =+A47 -> 2023024 | K48: 健康保険 | L48: 11400 | M48: 11400 | N48: 11400 | O48: 11400 | P48: 11400 | Q48: 13300 | R48: 13300 | S48: 13300 | T48: 13300 | U48: 13300 | V48: 13300 | W48: 13300 | X48: =SUM(L48:W48) -> 150100
A49: =+A48 -> 2023024 | K49: 厚生年金 | L49: 21960 | M49: 21960 | N49: 21960 | O49: 21960 | P49: 21960 | Q49: 25620 | R49: 25620 | S49: 25620 | T49: 25620 | U49: 25620 | V49: 25620 | W49: 25620 | X49: =SUM(L49:W49) -> 289140
A50: =+A49 -> 2023024 | K50: 労災保険 | L50: 1383 | M50: 1376 | N50: 1356 | O50: 746 | P50: 1292 | Q50: 1360 | R50: 1349 | S50: 1398 | T50: 1393 | U50: 1399 | V50: 1442 | W50: 746 | X50: =SUM(L50:W50) -> 15240
A51: =+A50 -> 2023024 | K51: 雇用保険 | L51: 1522 | M51: 1514 | N51: 1492 | O51: 1491 | P51: 1422 | Q51: 1496 | R51: 1484 | S51: 1538 | T51: 1532 | U51: 1539 | V51: 1587 | W51: 1491 | X51: =SUM(L51:W51) -> 18108
A52: =+A51 -> 2023024 | K52: 粗利 | L52: =L41-L44 -> 174535 | M52: =M41-M44 -> 173450 | N52: =N41-N44 -> 175042 | O52: =O41-O44 -> 171737 | P52: =P41-P44 -> 97120 | Q52: =Q41-Q44 -> 125730 | R52: =R41-R44 -> 168397 | S52: =S41-S44 -> 168536 | ... X52: =X41-X44 -> 1905313
A53: 2025021 | C53: =C41+1 -> 5 | D53: 派遣 | I53: 横浜SS | J53: 社員 | K53: 総受注金額 | L53: =L54+L55 -> 0 | M53: =M54+M55 -> 0 | N53: =N54+N55 -> 0 | O53: =O54+O55 -> 0 | P53: =P54+P55 -> 0 | Q53: =Q54+Q55 -> 0 | R53: =R54+R55 -> 0 | S53: =S54+S55 -> 0 | ... W53: =W54+W55 -> 480000 | X53: =SUM(L53:W53) -> 1228900
A54: =+A53 -> 2025021 | K54: 派遣金額 | U54: 277900 | V54: 471000 | W54: 480000 | X54: =SUM(L54:W54) -> 1228900
A55: =+A54 -> 2025021 | K55: 顧客対応当番 | X55: 0
A56: =+A55 -> 2025021 | K56: 総経費 | L56: =SUM(L57:L63) -> 0 | M56: =SUM(M57:M63) -> 0 | N56: =SUM(N57:N63) -> 0 | O56: =SUM(O57:O63) -> 0 | P56: =SUM(P57:P63) -> 0 | Q56: =SUM(Q57:Q63) -> 0 | R56: =SUM(R57:R63) -> 0 | S56: =SUM(S57:S63) -> 0 | ... W56: =SUM(W57:W63) -> 365897 | X56: =SUM(L56:W56) -> 1105239
A57: =+A56 -> 2025021 | K57: 賃金 | U57: 300000 | V57: 300000 | W57: 300000 | X57: =SUM(L57:W57) -> 900000
A58: =+A57 -> 2025021 | K58: 交通費その他 | X58: =SUM(L58:W58) -> 0
A59: =+A58 -> 2025021 | K59: 通勤定期代 | U59: 21694 | V59: 21750 | W59: 21750 | X59: =SUM(L59:W59) -> 65194
A60: =+A59 -> 2025021 | K60: 健康保険 | U60: 15200 | V60: 15200 | W60: 14250 | X60: =SUM(L60:W60) -> 44650
A61: =+A60 -> 2025021 | K61: 厚生年金 | U61: 29280 | V61: 29280 | W61: 27450 | X61: =SUM(L61:W61) -> 86010
A62: =+A61 -> 2025021 | K62: 労災保険 | U62: 1608 | V62: 1696 | W62: 816 | X62: =SUM(L62:W62) -> 4120
A63: =+A62 -> 2025021 | K63: 雇用保険 | U63: 1769 | V63: 1865 | W63: 1631 | X63: =SUM(L63:W63) -> 5265
A64: =+A63 -> 2025021 | K64: 粗利 | L64: =L53-L56 -> 0 | M64: =M53-M56 -> 0 | N64: =N53-N56 -> 0 | O64: =O53-O56 -> 0 | P64: =P53-P56 -> 0 | Q64: =Q53-Q56 -> 0 | R64: =R53-R56 -> 0 | S64: =S53-S56 -> 0 | ... X64: =X53-X56 -> 123661
A65: 2024008 | C65: =C41+1 -> 5 | D65: 派遣 | I65: 立川SS | J65: 社員 | K65: 総受注金額 | L65: =L66+L67 -> 492500 | M65: =M66+M67 -> 495000 | N65: =N66+N67 -> 490000 | O65: =O66+O67 -> 491955 | P65: =P66+P67 -> 490000 | Q65: =Q66+Q67 -> 492500 | R65: =R66+R67 -> 495000 | S65: =S66+S67 -> 401445 | ... W65: =W66+W67 -> 460000 | X65: =SUM(L65:W65) -> 5769020
A66: =+A65 -> 2024008 | K66: 派遣金額 | L66: 475000 | M66: 475000 | N66: 475000 | O66: 479455 | P66: 475000 | Q66: 475000 | R66: 475000 | S66: 381445 | T66: 480940 | U66: 475000 | V66: 457180 | W66: 460000 | X66: =SUM(L66:W66) -> 5584020
A67: =+A66 -> 2024008 | K67: 顧客対応当番 | L67: 17500 | M67: 20000 | N67: 15000 | O67: 12500 | P67: 15000 | Q67: 17500 | R67: 20000 | S67: 20000 | T67: 17500 | U67: 25000 | V67: 5000 | W67: 0 | X67: 0
A68: =+A67 -> 2024008 | K68: 総経費 | L68: =SUM(L69:L75) -> 307590 | M68: =SUM(M69:M75) -> 312136 | N68: =SUM(N69:N75) -> 303062 | O68: =SUM(O69:O75) -> 299141 | P68: =SUM(P69:P75) -> 301203 | Q68: =SUM(Q69:Q75) -> 309298 | R68: =SUM(R69:R75) -> 311249 | S68: =SUM(S69:S75) -> 310158 | ... W68: =SUM(W69:W75) -> 298890 | X68: =SUM(L68:W68) -> 3682150
A69: =+A68 -> 2024008 | K69: 賃金 | L69: 266100 | M69: 270600 | N69: 265200 | O69: 262466 | P69: 262000 | Q69: 266900 | R69: 267800 | S69: 267400 | T69: 270325 | U69: 274800 | V69: 253200 | W69: 245000 | X69: =SUM(L69:W69) -> 3171791
A70: =+A69 -> 2024008 | K70: 交通費その他 | X70: =SUM(L70:W70) -> 0
A71: =+A70 -> 2024008 | K71: 通勤定期代 | L71: 5280 | M71: 5280 | N71: 1700 | O71: 1020 | P71: 3060 | Q71: 668 | R71: 1700 | S71: 1020 | T71: 2040 | U71: 2004 | V71: 1670 | W71: 12675 | X71: =SUM(L71:W71) -> 38117
A72: =+A71 -> 2024008 | K72: 健康保険 | L72: 11400 | M72: 11400 | N72: 11400 | O72: 11400 | P72: 11400 | Q72: 13300 | R72: 13300 | S72: 13300 | T72: 13300 | U72: 13300 | V72: 13300 | W72: 13300 | X72: =SUM(L72:W72) -> 150100
A73: =+A72 -> 2024008 | K73: 厚生年金 | L73: 21960 | M73: 21960 | N73: 21960 | O73: 21960 | P73: 21960 | Q73: 25620 | R73: 25620 | S73: 25620 | T73: 25620 | U73: 25620 | V73: 25620 | W73: 25620 | X73: =SUM(L73:W73) -> 289140
A74: =+A73 -> 2024008 | K74: 労災保険 | L74: 1357 | M74: 1379 | N74: 1334 | O74: 765 | P74: 1325 | Q74: 1338 | R74: 1347 | S74: 1342 | T74: 1362 | U74: 1384 | V74: 1361 | W74: 765 | X74: =SUM(L74:W74) -> 15059
A75: =+A74 -> 2024008 | K75: 雇用保険 | L75: 1493 | M75: 1517 | N75: 1468 | O75: 1530 | P75: 1458 | Q75: 1472 | R75: 1482 | S75: 1476 | T75: 1498 | U75: 1522 | V75: 1497 | W75: 1530 | X75: =SUM(L75:W75) -> 17943
A76: =+A75 -> 2024008 | K76: 粗利 | L76: =L65-L68 -> 184910 | M76: =M65-M68 -> 182864 | N76: =N65-N68 -> 186938 | O76: =O65-O68 -> 192814 | P76: =P65-P68 -> 188797 | Q76: =Q65-Q68 -> 183202 | R76: =R65-R68 -> 183751 | S76: =S65-S68 -> 91287 | ... X76: =X65-X68 -> 2086870
A77: 2024012 | C77: =C65+1 -> 6 | D77: 派遣 | E77: 転出 | I77: KDX | J77: 社員 | K77: 総受注金額 | L77: =L78+L79 -> 420000 | M77: =M78+M79 -> 420000 | N77: =N78+N79 -> 420000 | O77: =O78+O79 -> 420000 | P77: =P78+P79 -> 347675 | Q77: =Q78+Q79 -> 420000 | R77: =R78+R79 -> 0 | S77: =S78+S79 -> 0 | ... W77: =W78+W79 -> 0 | X77: =SUM(L77:W77) -> 2447675
A78: =+A77 -> 2024012 | K78: 派遣金額 | L78: 420000 | M78: 420000 | N78: 420000 | O78: 420000 | P78: 347675 | Q78: 420000 | X78: =SUM(L78:W78) -> 2447675
A79: =+A78 -> 2024012 | K79: 交通費 | X79: 0
A80: =+A79 -> 2024012 | K80: 総経費 | L80: =SUM(L81:L87) -> 303922 | M80: =SUM(M81:M87) -> 303922 | N80: =SUM(N81:N87) -> 303922 | O80: =SUM(O81:O87) -> 303922 | P80: =SUM(P81:P87) -> 298242 | Q80: =SUM(Q81:Q87) -> 303922 | R80: =SUM(R81:R87) -> 0 | S80: =SUM(S81:S87) -> 0 | ... W80: =SUM(W81:W87) -> 0 | X80: =SUM(L80:W80) -> 1817852
A81: =+A80 -> 2024012 | K81: 賃金 | L81: 245000 | M81: 245000 | N81: 245000 | O81: 245000 | P81: 245000 | Q81: 245000 | X81: =SUM(L81:W81) -> 1470000
A82: =+A81 -> 2024012 | K82: 交通費その他 | X82: =SUM(L82:W82) -> 0
A83: =+A82 -> 2024012 | K83: 通勤定期代 | L83: 20000 | M83: 20000 | N83: 20000 | O83: 20000 | P83: 14320 | Q83: 20000 | X83: =SUM(L83:W83) -> 114320
A84: =+A83 -> 2024012 | K84: 健康保険 | L84: 12350 | M84: 12350 | N84: 12350 | O84: 12350 | P84: 12350 | Q84: 12350 | X84: =SUM(L84:W84) -> 74100
A85: =+A84 -> 2024012 | K85: 厚生年金 | L85: 23790 | M85: 23790 | N85: 23790 | O85: 23790 | P85: 23790 | Q85: 23790 | X85: =SUM(L85:W85) -> 142740
A86: =+A85 -> 2024012 | K86: 労災保険 | L86: 1325 | M86: 1325 | N86: 1325 | O86: 1325 | P86: 1325 | Q86: 1325 | X86: =SUM(L86:W86) -> 7950
A87: =+A86 -> 2024012 | K87: 雇用保険 | L87: 1457 | M87: 1457 | N87: 1457 | O87: 1457 | P87: 1457 | Q87: 1457 | X87: =SUM(L87:W87) -> 8742
A88: =+A87 -> 2024012 | K88: 粗利 | L88: =L77-L80 -> 116078 | M88: =M77-M80 -> 116078 | N88: =N77-N80 -> 116078 | O88: =O77-O80 -> 116078 | P88: =P77-P80 -> 49433 | Q88: =Q77-Q80 -> 116078 | R88: =R77-R80 -> 0 | S88: =S77-S80 -> 0 | ... X88: =X77-X80 -> 629823
A89: 2024010 | C89: =C77+1 -> 7 | D89: 派遣 | G89: DSD/KDX/FS | J89: 社員 | K89: 総受注金額 | L89: =L90+L91 -> 450000 | M89: =M90+M91 -> 450000 | N89: =N90+N91 -> 450000 | O89: =O90+O91 -> 450000 | P89: =P90+P91 -> 410660 | Q89: =Q90+Q91 -> 435950 | R89: =R90+R91 -> 347435 | S89: =S90+S91 -> 434545 | ... W89: =W90+W91 -> 440000 | X89: =SUM(L89:W89) -> 5151150
A90: =+A89 -> 2024010 | K90: 派遣金額 | L90: 450000 | M90: 450000 | N90: 450000 | O90: 450000 | P90: 410660 | Q90: 435950 | R90: 347435 | S90: 434545 | T90: 450000 | U90: 414875 | V90: 417685 | W90: 440000 | X90: =SUM(L90:W90) -> 5151150
A91: =+A90 -> 2024010 | K91: 交通費 | X91: 0
A92: =+A91 -> 2024010 | K92: 総経費 | L92: =SUM(L93:L99) -> 303922 | M92: =SUM(M93:M99) -> 303922 | N92: =SUM(N93:N99) -> 303922 | O92: =SUM(O93:O99) -> 303922 | P92: =SUM(P93:P99) -> 311122 | Q92: =SUM(Q93:Q99) -> 302822 | R92: =SUM(R93:R99) -> 296699 | S92: =SUM(S93:S99) -> 296293 | ... W92: =SUM(W93:W99) -> 303922 | X92: =SUM(L92:W92) -> 3603058
A93: =+A92 -> 2024010 | K93: 賃金 | L93: 245000 | M93: 245000 | N93: 245000 | O93: 245000 | P93: 252200 | Q93: 245000 | R93: 245000 | S93: 238540 | T93: 245000 | U93: 230425 | V93: 227775 | W93: 245000 | X93: =SUM(L93:W93) -> 2908940
A94: =+A93 -> 2024010 | K94: 交通費その他 | X94: =SUM(L94:W94) -> 0
A95: =+A94 -> 2024010 | K95: 通勤定期代 | L95: 20000 | M95: 20000 | N95: 20000 | O95: 20000 | P95: 20000 | Q95: 18910 | R95: 12852 | S95: 18910 | T95: 18910 | U95: 18910 | V95: 18910 | W95: 20000 | X95: =SUM(L95:W95) -> 227402
A96: =+A95 -> 2024010 | K96: 健康保険 | L96: 12350 | M96: 12350 | N96: 12350 | O96: 12350 | P96: 12350 | Q96: 12350 | R96: 12350 | S96: 12350 | T96: 12350 | U96: 12350 | V96: 12350 | W96: 12350 | X96: =SUM(L96:W96) -> 148200
A97: =+A96 -> 2024010 | K97: 厚生年金 | L97: 23790 | M97: 23790 | N97: 23790 | O97: 23790 | P97: 23790 | Q97: 23790 | R97: 23790 | S97: 23790 | T97: 23790 | U97: 23790 | V97: 23790 | W97: 23790 | X97: =SUM(L97:W97) -> 285480
A98: =+A97 -> 2024010 | K98: 労災保険 | L98: 1325 | M98: 1325 | N98: 1325 | O98: 1325 | P98: 1325 | Q98: 1320 | R98: 1289 | S98: 1287 | T98: 1320 | U98: 1247 | V98: 1320 | W98: 1325 | X98: =SUM(L98:W98) -> 15733
A99: =+A98 -> 2024010 | K99: 雇用保険 | L99: 1457 | M99: 1457 | N99: 1457 | O99: 1457 | P99: 1457 | Q99: 1452 | R99: 1418 | S99: 1416 | T99: 1452 | U99: 1371 | V99: 1452 | W99: 1457 | X99: =SUM(L99:W99) -> 17303
A100: =+A99 -> 2024010 | K100: 粗利 | L100: =L89-L92 -> 146078 | M100: =M89-M92 -> 146078 | N100: =N89-N92 -> 146078 | O100: =O89-O92 -> 146078 | P100: =P89-P92 -> 99538 | Q100: =Q89-Q92 -> 133128 | R100: =R89-R92 -> 50736 | S100: =S89-S92 -> 138252 | ... X100: =X89-X92 -> 1548092
...

Sheet その他業務
A1: 社員番号 | B1: 氏名 | C1: No | D1: 派遣/請負 | E1: 担当 | F1: 氏名 | G1: 派遣先部署 | H1: 作業名 | I1: 契約先 | J1: 外注会社 | K1: 売上単価 (支払単価） 【≒粗利】 | L1: 4月 | M1: 5月 | N1: 6月 | O1: 7月 | P1: 8月 | Q1: 9月 | R1: 10月 | S1: 11月 | T1: 12月 | U1: 1月 | V1: 2月 | W1: 3月 | X1: 合計
C2: その他常駐 | K2: 売上 | L2: =L89 -> 780000 | M2: =M89 -> 780000 | N2: =N89 -> 780000 | O2: =O89 -> 810000 | P2: =P89 -> 954000 | Q2: =Q89 -> 993125 | R2: =R89 -> 1207500 | S2: =S89 -> 1255775 | ... W2: =W89 -> 2407080 | X2: =SUM(L2:W2) -> 13727655
K3: 仕入 | L3: =L90 -> 22000 | M3: =M90 -> 24000 | N3: =N90 -> 25000 | O3: =O90 -> 24000 | P3: =P90 -> 23000 | Q3: =Q90 -> 23000 | R3: =R90 -> 24000 | S3: =S90 -> 24000 | ... W3: =W90 -> 30000 | X3: =SUM(L3:W3) -> 293000
K4: 粗利 | L4: =L2-L3 -> 758000 | M4: =M2-M3 -> 756000 | N4: =N2-N3 -> 755000 | O4: =O2-O3 -> 786000 | P4: =P2-P3 -> 931000 | Q4: =Q2-Q3 -> 970125 | R4: =R2-R3 -> 1183500 | S4: =S2-S3 -> 1231775 | ... W4: =W2-W3 -> 2377080 | X4: =SUM(L4:W4) -> 13434655
C5: 1 | D5: 請負 | H5: 夜間、土日祭 対応当番手当 | I5: NDICS RINK保守業務 | J5: エム・ジー・エー | K5: 総受注金額 | L5: =L6+L7 -> 780000 | M5: =M6+M7 -> 780000 | N5: =N6+N7 -> 780000 | O5: =O6+O7 -> 810000 | P5: =P6+P7 -> 810000 | Q5: =Q6+Q7 -> 810000 | R5: =R6+R7 -> 810000 | S5: =S6+S7 -> 810000 | ... W5: =W6+W7 -> 810000 | X5: =SUM(L5:W5) -> 9630000
A6: =+A5 -> 0 | B6: =+B5 -> 0 | K6: 派遣金額 | L6: 780000 | M6: 780000 | N6: 780000 | O6: 810000 | P6: 810000 | Q6: 810000 | R6: 810000 | S6: 810000 | T6: 810000 | U6: 810000 | V6: 810000 | W6: 810000 | X6: =SUM(L6:W6) -> 9630000
A7: =+A6 -> 0 | B7: =+B6 -> 0 | K7: 交通費 | X7: 0
A8: =+A7 -> 0 | B8: =+B7 -> 0 | K8: 総経費 | L8: =SUM(L9:L15) -> 22000 | M8: =SUM(M9:M15) -> 24000 | N8: =SUM(N9:N15) -> 25000 | O8: =SUM(O9:O15) -> 24000 | P8: =SUM(P9:P15) -> 23000 | Q8: =SUM(Q9:Q15) -> 23000 | R8: =SUM(R9:R15) -> 24000 | S8: =SUM(S9:S15) -> 24000 | ... W8: =SUM(W9:W15) -> 30000 | X8: =SUM(L8:W8) -> 293000
A9: =+A8 -> 0 | B9: =+B8 -> 0 | K9: 賃金 | L9: 22000 | M9: 24000 | N9: 25000 | O9: 24000 | P9: 23000 | Q9: 23000 | R9: 24000 | S9: 24000 | T9: 25000 | U9: 26000 | V9: 23000 | W9: 30000 | X9: =SUM(L9:W9) -> 293000
A10: =+A9 -> 0 | B10: =+B9 -> 0 | K10: 交通費その他 | X10: =SUM(L10:W10) -> 0
A11: =+A10 -> 0 | B11: =+B10 -> 0 | K11: 通勤定期代 | X11: =SUM(L11:W11) -> 0
A12: =+A11 -> 0 | B12: =+B11 -> 0 | K12: 健康保険 | X12: =SUM(L12:W12) -> 0
A13: =+A12 -> 0 | B13: =+B12 -> 0 | K13: 厚生年金 | X13: =SUM(L13:W13) -> 0
A14: =+A13 -> 0 | B14: =+B13 -> 0 | K14: 労災保険 | X14: =SUM(L14:W14) -> 0
A15: =+A14 -> 0 | B15: =+B14 -> 0 | K15: 雇用保険 | X15: =SUM(L15:W15) -> 0
A16: =+A15 -> 0 | B16: =+B15 -> 0 | K16: 粗利 | L16: =L5-L8 -> 758000 | M16: =M5-M8 -> 756000 | N16: =N5-N8 -> 755000 | O16: =O5-O8 -> 786000 | P16: =P5-P8 -> 787000 | Q16: =Q5-Q8 -> 787000 | R16: =R5-R8 -> 786000 | S16: =S5-S8 -> 786000 | ... X16: =X5-X8 -> 9337000
C17: =C5+1 -> 2 | D17: 委託 | H17: PC展開業務(旧機器撤去および新機器設置) | I17: UBS | K17: 総受注金額 | L17: =L18+L19 -> 0 | M17: =M18+M19 -> 0 | N17: =N18+N19 -> 0 | O17: =O18+O19 -> 0 | P17: =P18+P19 -> 144000 | Q17: =Q18+Q19 -> 150000 | R17: =R18+R19 -> 72000 | S17: =S18+S19 -> 0 | ... W17: =W18+W19 -> 0 | X17: =SUM(L17:W17) -> 366000
A18: =+A17 -> 0 | B18: =+B17 -> 0 | K18: 派遣金額 | P18: 144000 | Q18: 150000 | R18: 72000 | S18: 0 | X18: =SUM(L18:W18) -> 366000
A19: =+A18 -> 0 | B19: =+B18 -> 0 | K19: 交通費 | X19: 0
A20: =+A19 -> 0 | B20: =+B19 -> 0 | K20: 総経費 | L20: =SUM(L21:L27) -> 0 | M20: =SUM(M21:M27) -> 0 | N20: =SUM(N21:N27) -> 0 | O20: =SUM(O21:O27) -> 0 | P20: =SUM(P21:P27) -> 0 | Q20: =SUM(Q21:Q27) -> 0 | R20: =SUM(R21:R27) -> 0 | S20: =SUM(S21:S27) -> 0 | ... W20: =SUM(W21:W27) -> 0 | X20: =SUM(L20:W20) -> 0
A21: =+A20 -> 0 | B21: =+B20 -> 0 | K21: 賃金 | X21: =SUM(L21:W21) -> 0
A22: =+A21 -> 0 | B22: =+B21 -> 0 | K22: 交通費その他 | X22: =SUM(L22:W22) -> 0
A23: =+A22 -> 0 | B23: =+B22 -> 0 | K23: 通勤定期代 | X23: =SUM(L23:W23) -> 0
A24: =+A23 -> 0 | B24: =+B23 -> 0 | K24: 健康保険 | X24: =SUM(L24:W24) -> 0
A25: =+A24 -> 0 | B25: =+B24 -> 0 | K25: 厚生年金 | X25: =SUM(L25:W25) -> 0
A26: =+A25 -> 0 | B26: =+B25 -> 0 | K26: 労災保険 | X26: =SUM(L26:W26) -> 0
A27: =+A26 -> 0 | B27: =+B26 -> 0 | K27: 雇用保険 | X27: =SUM(L27:W27) -> 0
A28: =+A27 -> 0 | B28: =+B27 -> 0 | K28: 粗利 | L28: =L17-L20 -> 0 | M28: =M17-M20 -> 0 | N28: =N17-N20 -> 0 | O28: =O17-O20 -> 0 | P28: =P17-P20 -> 144000 | Q28: =Q17-Q20 -> 150000 | R28: =R17-R20 -> 72000 | S28: =S17-S20 -> 0 | ... X28: =X17-X20 -> 366000
C29: =C17+1 -> 3 | D29: 委託 | H29: Ciscoﾙｰﾀｰ 導入・撤去作業 | I29: UAL - NRI | K29: 総受注金額 | L29: =L30+L31 -> 0 | M29: =M30+M31 -> 0 | N29: =N30+N31 -> 0 | O29: =O30+O31 -> 0 | P29: =P30+P31 -> 0 | Q29: =Q30+Q31 -> 33125 | R29: =R30+R31 -> 0 | S29: =S30+S31 -> 445775 | ... W29: =W30+W31 -> 645800 | X29: =SUM(L29:W29) -> 2454875
A30: =+A29 -> 0 | B30: =+B29 -> 0 | K30: 1名/4時間パック | Q30: 33125 | R30: 0 | S30: 255300 | T30: 170300 | U30: 164650 | V30: 315875 | W30: 557900 | X30: =SUM(L30:W30) -> 1497150
A31: =+A30 -> 0 | B31: =+B30 -> 0 | K31: 2名/4時間パック | S31: 190475 | T31: 302050 | V31: 377300 | W31: 87900 | X31: =SUM(L31:W31) -> 957725
A32: =+A31 -> 0 | B32: =+B31 -> 0 | K32: 総経費 | L32: =SUM(L33:L39) -> 0 | M32: =SUM(M33:M39) -> 0 | N32: =SUM(N33:N39) -> 0 | O32: =SUM(O33:O39) -> 0 | P32: =SUM(P33:P39) -> 0 | Q32: =SUM(Q33:Q39) -> 0 | R32: =SUM(R33:R39) -> 0 | S32: =SUM(S33:S39) -> 0 | ... W32: =SUM(W33:W39) -> 0 | X32: =SUM(L32:W32) -> 0
A33: =+A32 -> 0 | B33: =+B32 -> 0 | K33: 賃金 | X33: =SUM(L33:W33) -> 0
A34: =+A33 -> 0 | B34: =+B33 -> 0 | K34: 交通費その他 | X34: =SUM(L34:W34) -> 0
A35: =+A34 -> 0 | B35: =+B34 -> 0 | K35: 通勤定期代 | X35: =SUM(L35:W35) -> 0
A36: =+A35 -> 0 | B36: =+B35 -> 0 | K36: 健康保険 | X36: =SUM(L36:W36) -> 0
A37: =+A36 -> 0 | B37: =+B36 -> 0 | K37: 厚生年金 | X37: =SUM(L37:W37) -> 0
A38: =+A37 -> 0 | B38: =+B37 -> 0 | K38: 労災保険 | X38: =SUM(L38:W38) -> 0
A39: =+A38 -> 0 | B39: =+B38 -> 0 | K39: 雇用保険 | X39: =SUM(L39:W39) -> 0
A40: =+A39 -> 0 | B40: =+B39 -> 0 | K40: 粗利 | L40: =L29-L32 -> 0 | M40: =M29-M32 -> 0 | N40: =N29-N32 -> 0 | O40: =O29-O32 -> 0 | P40: =P29-P32 -> 0 | Q40: =Q29-Q32 -> 33125 | R40: =R29-R32 -> 0 | S40: =S29-S32 -> 445775 | ... X40: =X29-X32 -> 2454875
C41: =C29+1 -> 4 | D41: 委託 | H41: Cisco製品導入作業/横浜 | I41: UAL - NRI | K41: 総受注金額 | L41: =L42+L43 -> 0 | M41: =M42+M43 -> 0 | N41: =N42+N43 -> 0 | O41: =O42+O43 -> 0 | P41: =P42+P43 -> 0 | Q41: =Q42+Q43 -> 0 | R41: =R42+R43 -> 325500 | S41: =S42+S43 -> 0 | ... W41: =W42+W43 -> 247500 | X41: =SUM(L41:W41) -> 573000
A42: =+A41 -> 0 | B42: =+B41 -> 0 | K42: 派遣金額 | R42: 325500 | W42: 247500 | X42: =SUM(L42:W42) -> 573000
A43: =+A42 -> 0 | B43: =+B42 -> 0 | K43: 交通費 | X43: 0
A44: =+A43 -> 0 | B44: =+B43 -> 0 | K44: 総経費 | L44: =SUM(L45:L51) -> 0 | M44: =SUM(M45:M51) -> 0 | N44: =SUM(N45:N51) -> 0 | O44: =SUM(O45:O51) -> 0 | P44: =SUM(P45:P51) -> 0 | Q44: =SUM(Q45:Q51) -> 0 | R44: =SUM(R45:R51) -> 0 | S44: =SUM(S45:S51) -> 0 | ... W44: =SUM(W45:W51) -> 0 | X44: =SUM(L44:W44) -> 0
A45: =+A44 -> 0 | B45: =+B44 -> 0 | K45: 賃金 | X45: =SUM(L45:W45) -> 0
A46: =+A45 -> 0 | B46: =+B45 -> 0 | K46: 交通費その他 | X46: =SUM(L46:W46) -> 0
A47: =+A46 -> 0 | B47: =+B46 -> 0 | K47: 通勤定期代 | X47: =SUM(L47:W47) -> 0
A48: =+A47 -> 0 | B48: =+B47 -> 0 | K48: 健康保険 | X48: =SUM(L48:W48) -> 0
A49: =+A48 -> 0 | B49: =+B48 -> 0 | K49: 厚生年金 | X49: =SUM(L49:W49) -> 0
A50: =+A49 -> 0 | B50: =+B49 -> 0 | K50: 労災保険 | X50: =SUM(L50:W50) -> 0
A51: =+A50 -> 0 | B51: =+B50 -> 0 | K51: 雇用保険 | X51: =SUM(L51:W51) -> 0
A52: =+A51 -> 0 | B52: =+B51 -> 0 | K52: 粗利 | L52: =L41-L44 -> 0 | M52: =M41-M44 -> 0 | N52: =N41-N44 -> 0 | O52: =O41-O44 -> 0 | P52: =P41-P44 -> 0 | Q52: =Q41-Q44 -> 0 | R52: =R41-R44 -> 325500 | S52: =S41-S44 -> 0 | ... X52: =X41-X44 -> 573000
C53: =C41+1 -> 5 | D53: 委託 | H53: Cisco製品導入作業/大阪 | I53: UAL - NRI | K53: 総受注金額 | L53: =L54+L55 -> 0 | M53: =M54+M55 -> 0 | N53: =N54+N55 -> 0 | O53: =O54+O55 -> 0 | P53: =P54+P55 -> 0 | Q53: =Q54+Q55 -> 0 | R53: =R54+R55 -> 0 | S53: =S54+S55 -> 0 | ... W53: =W54+W55 -> 105280 | X53: =SUM(L53:W53) -> 105280
K54: 派遣金額 | W54: 105280 | X54: =SUM(L54:W54) -> 105280
K55: 交通費 | X55: 0
K56: 総経費 | L56: =SUM(L57:L63) -> 0 | M56: =SUM(M57:M63) -> 0 | N56: =SUM(N57:N63) -> 0 | O56: =SUM(O57:O63) -> 0 | P56: =SUM(P57:P63) -> 0 | Q56: =SUM(Q57:Q63) -> 0 | R56: =SUM(R57:R63) -> 0 | S56: =SUM(S57:S63) -> 0 | ... W56: =SUM(W57:W63) -> 0 | X56: =SUM(L56:W56) -> 0
K57: 賃金 | X57: =SUM(L57:W57) -> 0
K58: 交通費その他 | X58: =SUM(L58:W58) -> 0
K59: 通勤定期代 | X59: =SUM(L59:W59) -> 0
K60: 健康保険 | X60: =SUM(L60:W60) -> 0
K61: 厚生年金 | X61: =SUM(L61:W61) -> 0
K62: 労災保険 | X62: =SUM(L62:W62) -> 0
K63: 雇用保険 | X63: =SUM(L63:W63) -> 0
K64: 粗利 | L64: =L53-L56 -> 0 | M64: =M53-M56 -> 0 | N64: =N53-N56 -> 0 | O64: =O53-O56 -> 0 | P64: =P53-P56 -> 0 | Q64: =Q53-Q56 -> 0 | R64: =R53-R56 -> 0 | S64: =S53-S56 -> 0 | ... X64: =X53-X56 -> 105280
C65: =C53+1 -> 6 | D65: 委託 | H65: Fortigate FW更新作業 | I65: NDICS Fortigate | K65: 総受注金額 | L65: =L66+L67 -> 0 | M65: =M66+M67 -> 0 | N65: =N66+N67 -> 0 | O65: =O66+O67 -> 0 | P65: =P66+P67 -> 0 | Q65: =Q66+Q67 -> 0 | R65: =R66+R67 -> 0 | S65: =S66+S67 -> 0 | ... W65: =W66+W67 -> 472500 | X65: =SUM(L65:W65) -> 472500
K66: 派遣金額 | W66: 472500 | X66: =SUM(L66:W66) -> 472500
K67: 交通費 | X67: 0
K68: 総経費 | L68: =SUM(L69:L75) -> 0 | M68: =SUM(M69:M75) -> 0 | N68: =SUM(N69:N75) -> 0 | O68: =SUM(O69:O75) -> 0 | P68: =SUM(P69:P75) -> 0 | Q68: =SUM(Q69:Q75) -> 0 | R68: =SUM(R69:R75) -> 0 | S68: =SUM(S69:S75) -> 0 | ... W68: =SUM(W69:W75) -> 0 | X68: =SUM(L68:W68) -> 0
K69: 賃金 | X69: =SUM(L69:W69) -> 0
K70: 交通費その他 | X70: =SUM(L70:W70) -> 0
K71: 通勤定期代 | X71: =SUM(L71:W71) -> 0
K72: 健康保険 | X72: =SUM(L72:W72) -> 0
K73: 厚生年金 | X73: =SUM(L73:W73) -> 0
K74: 労災保険 | X74: =SUM(L74:W74) -> 0
K75: 雇用保険 | X75: =SUM(L75:W75) -> 0
K76: 粗利 | L76: =L65-L68 -> 0 | M76: =M65-M68 -> 0 | N76: =N65-N68 -> 0 | O76: =O65-O68 -> 0 | P76: =P65-P68 -> 0 | Q76: =Q65-Q68 -> 0 | R76: =R65-R68 -> 0 | S76: =S65-S68 -> 0 | ... X76: =X65-X68 -> 472500
C77: =C65+1 -> 7 | D77: 委託 | H77: PC展開業務(新機器設置および初期セットアップ) | I77: Route | K77: 総受注金額 | L77: =L78+L79 -> 0 | M77: =M78+M79 -> 0 | N77: =N78+N79 -> 0 | O77: =O78+O79 -> 0 | P77: =P78+P79 -> 0 | Q77: =Q78+Q79 -> 0 | R77: =R78+R79 -> 0 | S77: =S78+S79 -> 0 | ... W77: =W78+W79 -> 126000 | X77: =SUM(L77:W77) -> 126000
K78: 派遣金額 | W78: 126000 | X78: =SUM(L78:W78) -> 126000
K79: 交通費 | X79: 0
K80: 総経費 | L80: =SUM(L81:L87) -> 0 | M80: =SUM(M81:M87) -> 0 | N80: =SUM(N81:N87) -> 0 | O80: =SUM(O81:O87) -> 0 | P80: =SUM(P81:P87) -> 0 | Q80: =SUM(Q81:Q87) -> 0 | R80: =SUM(R81:R87) -> 0 | S80: =SUM(S81:S87) -> 0 | ... W80: =SUM(W81:W87) -> 0 | X80: =SUM(L80:W80) -> 0
K81: 賃金 | X81: =SUM(L81:W81) -> 0
K82: 交通費その他 | X82: =SUM(L82:W82) -> 0
K83: 通勤定期代 | X83: =SUM(L83:W83) -> 0
K84: 健康保険 | X84: =SUM(L84:W84) -> 0
K85: 厚生年金 | X85: =SUM(L85:W85) -> 0
K86: 労災保険 | X86: =SUM(L86:W86) -> 0
K87: 雇用保険 | X87: =SUM(L87:W87) -> 0
K88: 粗利 | L88: =L77-L80 -> 0 | M88: =M77-M80 -> 0 | N88: =N77-N80 -> 0 | O88: =O77-O80 -> 0 | P88: =P77-P80 -> 0 | Q88: =Q77-Q80 -> 0 | R88: =R77-R80 -> 0 | S88: =S77-S80 -> 0 | ... X88: =X77-X80 -> 126000
C89: =C2 -> その他常駐 | K89: 売上 | L89: =L5+L17+L29+L41+L77 -> 780000 | M89: =M5+M17+M29+M41+M77 -> 780000 | N89: =N5+N17+N29+N41+N77 -> 780000 | O89: =O5+O17+O29+O41+O77 -> 810000 | P89: =P5+P17+P29+P41+P77 -> 954000 | Q89: =Q5+Q17+Q29+Q41+Q77 -> 993125 | R89: =R5+R17+R29+R41+R77 -> 1207500 | S89: =S5+S17+S29+S41+S77 -> 1255775 | ... V89: =V5+V17+V29+V41+V77 -> 1503175 | W89: =W5+W17+W29+W41+W53+W65+W77 -> 2407080 | X89: =SUM(L89:W89) -> 13727655
K90: 仕入 | L90: =L8+L20+L32+L44+L80 -> 22000 | M90: =M8+M20+M32+M44+M80 -> 24000 | N90: =N8+N20+N32+N44+N80 -> 25000 | O90: =O8+O20+O32+O44+O80 -> 24000 | P90: =P8+P20+P32+P44+P80 -> 23000 | Q90: =Q8+Q20+Q32+Q44+Q80 -> 23000 | R90: =R8+R20+R32+R44+R80 -> 24000 | S90: =S8+S20+S32+S44+S80 -> 24000 | ... V90: =V8+V20+V32+V44+V80 -> 23000 | W90: =W8+W20+W32+W44+W56+W68+W80 -> 30000 | X90: =SUM(L90:W90) -> 293000
K91: 粗利 | L91: =L89-L90 -> 758000 | M91: =M89-M90 -> 756000 | N91: =N89-N90 -> 755000 | O91: =O89-O90 -> 786000 | P91: =P89-P90 -> 931000 | Q91: =Q89-Q90 -> 970125 | R91: =R89-R90 -> 1183500 | S91: =S89-S90 -> 1231775 | ... W91: =W89-W90 -> 2377080 | X91: =SUM(L91:W91) -> 13434655
K92: Q売上 | L92: =SUM(L89:N89) -> 2340000 | O92: =SUM(O89:Q89) -> 2757125 | R92: =SUM(R89:T89) -> 3745625 | U92: =SUM(U89:W89) -> 4884905 | X92: =SUM(L92:W92) -> 13727655
K93: Q粗利 | L93: =SUM(L91:N91) -> 2269000 | O93: =SUM(O91:Q91) -> 2687125 | R93: =SUM(R91:T91) -> 3672625 | U93: =SUM(U91:W91) -> 4805905 | X93: =SUM(L93:W93) -> 13434655
